Workbook

Sheet IT Working sheet 
A1: S.No | B1: Policy Number | E1: Policy Issuance Date | F1: Customer Name | G1: Contact Number | H1: VehicleNumber | I1: Make | J1: Model | K1: Value | L1: Up Front Charges | M1: Rates | N1: Sales Date | O1: Gross Cont | P1: Net Cont | Q1: Gross Cont (Fresh *2) | R1: Deferred Commission | S1: Commission % | T1: Agency | U1: Tagging | V1: Commission Status | W1: Custodian Name | X1: Category | Y1: Channel | Z1: Sub Channel
A2: 1 | B2: KHI/HO/D/MO/PC COMP/P/110102/06/2025 | E2: 45827 | F2: Zain ul abidin | G2: 0300 2348932 | H2: BVB-723 | I2: ALTO VXR | J2: 2021 | K2: 2500000 | L2: 37500 | M2: 0.015 | N2: 45827 | O2: 31897 | P2: 37500 | Q2: =O2*2 -> 63794 | R2: 573 | S2: 0 | T2: 09000870/Digital sales - DA | U2: FRE | W2: Hamna Ali | X2: Comprehensive | Y2: Other | Z2: Other
A3: 2 | B3: KHI/HO/D/MO/PC COMP/P/110104/06/2025 | E3: 45827 | F3: Zain ul abidin | G3: 0300 2348932 | H3: BTY-041 | I3: ALTO VXR | J3: 2021 | K3: 2500000 | L3: 37500 | M3: 0.015 | N3: 45827 | O3: 31897 | P3: 37500 | Q3: =O3*2 -> 63794 | R3: 563 | S3: 0 | T3: 09000870/Digital sales - DA | U3: FRE | W3: Hamna Ali | X3: Comprehensive | Y3: Other | Z3: Other
A4: 3 | B4: KHI/HO/D/MO/PC COMP/P/110238/06/2025 | E4: 45834 | F4: Zain ul abidin | G4: 0300 2348932 | H4: BWX-068 | I4: ALTO VXR | J4: 2022 | K4: 2500000 | L4: 37500 | M4: 0.015 | N4: 45834 | O4: 31897 | P4: 37500 | Q4: =O4*2 -> 63794 | R4: 563 | S4: 0 | T4: 09000870/Digital sales - DA | U4: FRE | W4: Hamna Ali | X4: Comprehensive | Y4: Other | Z4: Other
A5: 4 | B5: KHI/HO/D/MO/PC COMP/P/110441/07/2025 | C5: =VLOOKUP('IT Working sheet '!B5,'09000210'!B:C,2,0) -> 040000200398 | D5: ="Update ins_assorted_clients set commission_amount = '"&R5&"' where assorted_code = '"&C5&"' and agency_code = '09000870';" -> Update ins_assorted_clients set commission_amount = '563' where assorted_code = '040000200398' and agency_code = '09000870'; | E5: 45846 | F5: Mohammad Tariq Deen | G5: 0333-3618220 | H5: BYT-442 | I5: EK Wagon | J5: 2023 | K5: 2500000 | L5: 35000 | M5: 0.014 | N5: 45846 | O5: 29742 | P5: 35000 | Q5: 29742 | R5: 563 | S5: 0 | T5: 09000870/Digital sales - DA | U5: REN | W5: Hamna Ali | X5: Comprehensive | Y5: Retail Renewal | Z5: Retail Renewal (July-2025)
A6: 5 | B6: LHR/LHR/D/MO/PC COMP/P/110475/07/2025 | C6: =VLOOKUP('IT Working sheet '!B6,'09000210'!B:C,2,0) -> 040000200465 | D6: ="Update ins_assorted_clients set commission_amount = '"&R6&"' where assorted_code = '"&C6&"' and agency_code = '09000870';" -> Update ins_assorted_clients set commission_amount = '563' where assorted_code = '040000200465' and agency_code = '09000870'; | E6: 45847 | F6: Shoaib Nazir | G6: 0307-9379517 | H6: RIC 19 450 | I6: ALTO VXR | J6: 2019 | K6: 2300000 | L6: 46000 | M6: 0.02 | N6: 45847 | O6: 39299 | P6: 46000 | Q6: 39299 | R6: 563 | S6: 0 | T6: 09000870/Digital sales - DA | U6: REN | W6: Hamna Ali | X6: Comprehensive | Y6: Retail Renewal | Z6: Retail Renewal (July-2025)
A7: 6 | B7: LHR/LHR/D/MO/PC COMP/P/110352/07/2025 | C7: =VLOOKUP('IT Working sheet '!B7,'09000210'!B:C,2,0) -> 040000200132 | D7: ="Update ins_assorted_clients set commission_amount = '"&R7&"' where assorted_code = '"&C7&"' and agency_code = '09000870';" -> Update ins_assorted_clients set commission_amount = '563' where assorted_code = '040000200132' and agency_code = '09000870'; | E7: 45841 | F7: Rasul Bakhsh Siraj | G7: 0320-4800112 | H7: LE-18-8813 | I7: CITY 1.5 ASPIRE | J7: 2017 | K7: 3300000 | L7: 49500 | M7: 0.015 | N7: 45841 | O7: 42291 | P7: 49500 | Q7: 42291 | R7: 563 | S7: 0 | T7: 09000870/Digital sales - DA | U7: REN | W7: Hamna Ali | X7: Comprehensive | Y7: Retail Renewal | Z7: Retail Renewal (July-2025)
A8: 7 | B8: KHI/HO/D/MO/PC COMP/P/110480/07/2025 | C8: =VLOOKUP('IT Working sheet '!B8,'09000210'!B:C,2,0) -> 040000200474 | D8: ="Update ins_assorted_clients set commission_amount = '"&R8&"' where assorted_code = '"&C8&"' and agency_code = '09000870';" -> Update ins_assorted_clients set commission_amount = '563' where assorted_code = '040000200474' and agency_code = '09000870'; | E8: 45848 | F8: Mukhtar Ahmed | G8: 0333-2286698 | H8: BXF-950 | I8: SAGA | J8: 2022 | K8: 2519200 | L8: 50384 | M8: 0.02 | N8: 45848 | O8: 43003 | P8: 50384 | Q8: 43003 | R8: 563 | S8: 0 | T8: 09000870/Digital sales - DA | U8: REN | W8: Hamna Ali | X8: Comprehensive | Y8: Retail Renewal | Z8: Retail Renewal (July-2025)
A9: 8 | B9: KHI/HO/D/MO/PC COMP/P/110452/07/2025 | C9: =VLOOKUP('IT Working sheet '!B9,'09000210'!B:C,2,0) -> 040000200415 | D9: ="Update ins_assorted_clients set commission_amount = '"&R9&"' where assorted_code = '"&C9&"' and agency_code = '09000870';" -> Update ins_assorted_clients set commission_amount = '563' where assorted_code = '040000200415' and agency_code = '09000870'; | E9: 45846 | F9: Nida Hussain | G9: 0321-2029596 | I9: DAYZ | J9: 2022 | K9: 3500000 | L9: 52500 | M9: 0.015 | N9: 45846 | O9: 44828 | P9: 52500 | Q9: 44828 | R9: 563 | S9: 0 | T9: 09000870/Digital sales - DA | U9: REN | W9: Hamna Ali | X9: Comprehensive | Y9: Retail Renewal | Z9: Retail Renewal (June-2025)
A10: 9 | B10: KHI/HO/D/MO/PC COMP/P/110537/07/2025 | C10: =VLOOKUP('IT Working sheet '!B10,'09000210'!B:C,2,0) -> 040000200563 | D10: ="Update ins_assorted_clients set commission_amount = '"&R10&"' where assorted_code = '"&C10&"' and agency_code = '09000870';" -> Update ins_assorted_clients set commission_amount = '563' where assorted_code = '040000200563' and agency_code = '09000870'; | E10: 45852 | F10: Muhammad Asif | G10: 0336-0001977 | H10: CAC-708 | I10: ALTO VXL AGS | J10: 2024 | K10: 3045000 | L10: 53288 | M10: 0.0175 | N10: 45852 | O10: 45507 | P10: 53288 | Q10: 45507 | R10: 563 | S10: 0 | T10: 09000870/Digital sales - DA | U10: REN | W10: Hamna Ali | X10: Comprehensive | Y10: Retail Renewal | Z10: Retail Renewal (July-2025)
A11: 10 | B11: KHI/HO/D/MO/PC COMP/P/110478/07/2025 | C11: =VLOOKUP('IT Working sheet '!B11,'09000210'!B:C,2,0) -> 040000200469 | D11: ="Update ins_assorted_clients set commission_amount = '"&R11&"' where assorted_code = '"&C11&"' and agency_code = '09000870';" -> Update ins_assorted_clients set commission_amount = '563' where assorted_code = '040000200469' and agency_code = '09000870'; | E11: 45847 | F11: Sameer Ul Haq | G11: 0323-2035147 | H11: BXE-201 | I11: YARIS CVT | J11: 2022 | K11: 4000000 | L11: 60000 | M11: 0.015 | N11: 45847 | O11: 51293 | P11: 60000 | Q11: 51293 | R11: 563 | S11: 0 | T11: 09000870/Digital sales - DA | U11: REN | W11: Hamna Ali | X11: Comprehensive | Y11: Retail Renewal | Z11: Retail Renewal (July-2025)
A12: 11 | B12: KHI/HO/D/MO/PC COMP/P/110449/07/2025 | C12: =VLOOKUP('IT Working sheet '!B12,'09000210'!B:C,2,0) -> 040000200409 | D12: ="Update ins_assorted_clients set commission_amount = '"&R12&"' where assorted_code = '"&C12&"' and agency_code = '09000870';" -> Update ins_assorted_clients set commission_amount = '563' where assorted_code = '040000200409' and agency_code = '09000870'; | E12: 45846 | F12: Tariq Altaf | G12: 0321-2587658 | H12: BP-0274 | I12: RAIZE | J12: 2021 | K12: 6000000 | L12: 84000 | M12: 0.014 | N12: 45846 | O12: 71983 | P12: 84000 | Q12: 71983 | R12: 563 | S12: 0 | T12: 09000870/Digital sales - DA | U12: REN | W12: Hamna Ali | X12: Comprehensive | Y12: Retail Renewal | Z12: Retail Renewal (July-2025)
A13: 12 | B13: KHI/HO/D/MO/PC COMP/P/110540/07/2025 | C13: =VLOOKUP('IT Working sheet '!B13,'09000210'!B:C,2,0) -> 040000200568 | D13: ="Update ins_assorted_clients set commission_amount = '"&R13&"' where assorted_code = '"&C13&"' and agency_code = '09000870';" -> Update ins_assorted_clients set commission_amount = '563' where assorted_code = '040000200568' and agency_code = '09000870'; | E13: 45852 | F13: Topline Securities Limited | G13: 0331-3219274 | H13: BK-1720 | I13: SPORTAGE | J13: 2022 | K13: 6000000 | L13: 90000 | M13: 0.015 | N13: 45852 | O13: 77155 | P13: 90000 | Q13: 77155 | R13: 563 | S13: 0 | T13: 09000870/Digital sales - DA | U13: REN | W13: Hamna Ali | X13: Comprehensive | Y13: Retail Renewal | Z13: Retail Renewal (July-2025)
A14: 13 | B14: KHI/HO/D/MO/PC COMP/P/110512/07/2025 | C14: =VLOOKUP('IT Working sheet '!B14,'09000210'!B:C,2,0) -> 040000200522 | D14: ="Update ins_assorted_clients set commission_amount = '"&R14&"' where assorted_code = '"&C14&"' and agency_code = '09000870';" -> Update ins_assorted_clients set commission_amount = '563' where assorted_code = '040000200522' and agency_code = '09000870'; | E14: 45849 | F14: Sheikh Mansoor Ali Masood | G14: 0300-8271290 | H14: BM-7300 | I14: PROTON X70 EXECUTIVE AWD | J14: .. | K14: 6500000 | L14: 110500 | M14: 0.017 | N14: 45849 | O14: 94828 | P14: 110500 | Q14: 94828 | R14: 563 | S14: 0 | T14: 09000870/Digital sales - DA | U14: REN | W14: Hamna Ali | X14: Comprehensive | Y14: Retail Renewal | Z14: Retail Renewal (July-2025)
A15: 14 | B15: KHI/HO/D/MO/PC COMP/P/110516/07/2025 | C15: =VLOOKUP('IT Working sheet '!B15,'09000210'!B:C,2,0) -> #N/A | E15: 45849 | F15: Muhammad Yaseen Baloch | G15: 0300-2025750 | H15: BVT-719 | I15: ALTO VXL AGS | J15: 2022 | K15: 3000000 | L15: 51000 | M15: 0.017 | N15: 45849 | O15: 43535 | P15: 51000 | Q15: 43535 | R15: 563 | S15: 0 | T15: 09000870/Digital sales - DA | U15: REN | W15: Hamna Ali | X15: Comprehensive | Y15: Other | Z15: Other
A16: 15 | B16: LHR/LHR/D/MO/PC COMP/P/110338/07/2025 | C16: =VLOOKUP('IT Working sheet '!B16,'09000210'!B:C,2,0) -> 040000200105 | D16: ="Update ins_assorted_clients set commission_amount = '"&R16&"' where assorted_code = '"&C16&"' and agency_code = '09000870';" -> Update ins_assorted_clients set commission_amount = '563' where assorted_code = '040000200105' and agency_code = '09000870'; | E16: 45840 | F16: Muhammad Ammad Sohail Bhopal | G16: 0333-4352333 | H16: BDW-457 | I16: SANTA FE AWD | J16: 2024 | K16: 14780000 | L16: 206920 | M16: 0.014 | N16: 45840 | O16: 176838 | P16: 206920 | Q16: 176838 | R16: 563 | S16: 0 | T16: 09000870/Digital sales - DA | U16: REN | W16: Hamna Ali | X16: Comprehensive | Y16: Retail Renewal | Z16: Retail Renewal (July-2025)
A17: 16 | B17: KHI/HO/D/MO/PC COMP/P/110240/06/2025 | E17: 45835 | F17: Roshna Razzaq | G17: 0331-9747508 | H17: ABQ-082 | I17: PICANTO A/T | J17: 2021 | K17: 3200000 | L17: 48000 | M17: 0.015 | N17: 45835 | O17: 40949 | P17: 48000 | Q17: 40949 | R17: 563 | S17: 0 | T17: 09000870/Digital sales - DA | U17: REN | W17: Hamna Ali | X17: Comprehensive | Y17: Retail Renewal | Z17: Retail Renewal (June-2025)
A18: 17 | B18: LHR/LHR/D/MO/PC COMP/P/109750/06/2025 | E18: 45810 | F18: Zulfiqar Ali | G18: 0322-4081828 | H18: ADC-197 | I18: WAGON R VXL | J18: 2021 | K18: 2800000 | L18: 55720 | M18: 0.0199 | N18: 45809 | O18: 47607 | P18: 55720 | Q18: 47607 | R18: 563 | S18: 0 | T18: 09000870/Digital sales - DA | U18: REN | W18: Hamna Ali | X18: Comprehensive | Y18: Retail Renewal | Z18: Retail Renewal (June-2025)
A19: 18 | B19: LHR/LHR/D/MO/PC COMP/P/110250/06/2025 | E19: 45835 | F19: Tariq Mehmood | G19: 0334-5282712 | H19: AED-513 | I19: BRV I-VTEC | J19: 2024 | K19: 3700000 | L19: 62900 | M19: 0.017 | N19: 45824 | O19: 53744 | P19: 62900 | Q19: 53744 | R19: 563 | S19: 0 | T19: 09000870/Digital sales - DA | U19: REN | W19: Hamna Ali | X19: Comprehensive | Y19: Retail Renewal | Z19: Retail Renewal (June-2025)
A20: 19 | B20: LHR/LHR/D/MO/PC COMP/P/110111/06/2025 | E20: 45827 | F20: Progressive Textile | G20: 0300-8661774 | H20: AKN-625 | I20: Swift GLX CVT | J20: 2022 | K20: 4300000 | L20: 64500 | M20: 0.015 | N20: 45827 | O20: 55111 | P20: 64500 | Q20: 55111 | R20: 563 | S20: 0 | T20: 09000870/Digital sales - DA | U20: REN | W20: Hamna Ali | X20: Comprehensive | Y20: Retail Renewal | Z20: Retail Renewal (June-2025)
A21: 20 | B21: KHI/HO/D/MO/PC COMP/P/110021/06/2025 | E21: 45824 | F21: Haris Anwaar | G21: 0300-3252100 | H21: AKR-897 | I21: FORTUNER 645B 4X4 AT V | J21: 2022 | K21: 10000000 | L21: 150000 | M21: 0.015 | N21: 45822 | O21: 128879 | P21: 150000 | Q21: 128879 | R21: 563 | S21: 0 | T21: 09000870/Digital sales - DA | U21: REN | W21: Hamna Ali | X21: Comprehensive | Y21: Retail Renewal | Z21: Retail Renewal (June-2025)
A22: 21 | B22: KHI/HO/D/MO/PC COMP/P/109994/06/2025 | E22: 45821 | F22: Saima Irfan | G22: 0321-2766331 | H22: ATD-461 | I22: COROLLA GLI M/T 1.3 | J22: 2010 | K22: 2000000 | L22: 35000 | M22: 0.0175 | N22: 45821 | O22: 29742 | P22: 35000 | Q22: 29742 | R22: 563 | S22: 0 | T22: 09000870/Digital sales - DA | U22: REN | W22: Hamna Ali | X22: Comprehensive | Y22: Retail Renewal | Z22: Retail Renewal (June-2025)
A23: 22 | B23: LHR/LHR/D/MO/PC COMP/P/109996/06/2025 | E23: 45821 | F23: Furqan Muhammad Khan | G23: 0331-5569874 | H23: AZF-967 | I23: ALSVIN | J23: 2022 | K23: 4000000 | L23: 60000 | M23: 0.015 | N23: 45821 | O23: 51265 | P23: 60000 | Q23: 51265 | R23: 563 | S23: 0 | T23: 09000870/Digital sales - DA | U23: REN | W23: Hamna Ali | X23: Comprehensive | Y23: Retail Renewal | Z23: Retail Renewal (June-2025)
A24: 23 | B24: KHI/HO/D/MO/PC COMP/P/110182/06/2025 | E24: 45832 | F24: Khalid Deen | G24: 0334-2904798 | H24: BK-5923 | I24: KIA SPORTAGE | J24: 2022 | K24: 6500000 | L24: 94250 | M24: 0.0145 | N24: 45831 | O24: 80819 | P24: 94250 | Q24: 80819 | R24: 563 | S24: 0 | T24: 09000870/Digital sales - DA | U24: REN | W24: Hamna Ali | X24: Comprehensive | Y24: Retail Renewal | Z24: Retail Renewal (June-2025)
A25: 24 | B25: KHI/HO/D/MO/PC COMP/P/109991/06/2025 | E25: 45821 | F25: Saima Bano | G25: 0331-2198961 | H25: BK-6225 | I25: HS | J25: 2022 | K25: 10000000 | L25: 150000 | M25: 0.015 | N25: 45819 | O25: 128879 | P25: 150000 | Q25: 128879 | R25: 563 | S25: 0 | T25: 09000870/Digital sales - DA | U25: REN | W25: Hamna Ali | X25: Comprehensive | Y25: Retail Renewal | Z25: Retail Renewal (June-2025)
A26: 25 | B26: KHI/HO/D/MO/PC COMP/P/109939/06/2025 | E26: 45819 | F26: Harris Bin Shakir | G26: 0345-2145480 | H26: BML-992 | I26: PASSO A/T | J26: 2015 | K26: 2500000 | L26: 32500 | M26: 0.013 | N26: 45819 | O26: 27586 | P26: 32500 | Q26: 27586 | R26: 563 | S26: 0 | T26: 09000870/Digital sales - DA | U26: REN | W26: Hamna Ali | X26: Comprehensive | Y26: Direct Renewal | Z26: (Direct Renewal June-2025)
A27: 26 | B27: KHI/HO/D/MO/PC COMP/P/109930/06/2025 | E27: 45818 | F27: Faiq Ali HPA Meezan Bank Staff | G27: 0302-3935860 | H27: BMZ-608 | I27: WAGON-R | J27: 2018 | K27: 2400000 | L27: 33600 | M27: 0.014 | N27: 45818 | O27: 28535 | P27: 33600 | Q27: 28535 | R27: 563 | S27: 0 | T27: 09000870/Digital sales - DA | U27: REN | W27: Hamna Ali | X27: Comprehensive | Y27: Direct Renewal | Z27: (Direct Renewal June-2025)
A28: 27 | B28: KHI/HO/D/MO/PC COMP/P/109882/06/2025 | E28: 45813 | F28: Muhammad Waqas | G28: 0333-3455790 | H28: BWV-941 | I28: WAGON-R | J28: 2022 | K28: 3200000 | L28: 57600 | M28: 0.018 | N28: 45813 | O28: 49224 | P28: 57600 | Q28: 49224 | R28: 563 | S28: 0 | T28: 09000870/Digital sales - DA | U28: REN | W28: Hamna Ali | X28: Comprehensive | Y28: Retail Renewal | Z28: Retail Renewal (June-2025)
... A32: 31 | B32: LHR/LHR/D/MO/PC COMP/P/109860/06/2025 | E32: 45813 | F32: Kashif Iqbal Malik | G32: 0333-4242848 | H32: APL-4 | I32: Swift GLX CVT | J32: 2024 | K32: 4744000 | L32: 71160 | M32: 0.015 | N32: 45813 | O32: 60803 | P32: 71160 | Q32: 60803 | R32: 563 | S32: 0 | T32: 09000870/Digital sales - DA | U32: REN | W32: Hamna Ali | X32: Comprehensive | Y32: Retail Renewal | Z32: Retail Renewal (May-2025)
A33: 32 | B33: KHI/HO/D/MO/PD COMP/P/110175/06/2025 | E33: 45832 | F33: Muhammad Tayyab | G33: 0323-4179417 | H33: ALP-818 | I33: Suzuki Swift GL CVT | J33: 2022 | K33: 4800000 | L33: 10000 | M33: 0.025 | N33: 45829 | O33: 8190 | P33: 10000 | Q33: 8190 | R33: 563 | S33: - | T33: 09000870/Digital sales - DA | U33: REN | W33: Hamna Ali | X33: Pay As You Drive | Y33: Direct Renewal | Z33: (Direct Renewal June-2025)
A34: 33 | B34: KHI/HO/D/MO/PC COMP/P/109768/06/2025 | E34: 45810 | F34: ZAREEN GUL | G34: 0333-3638261 | H34: BRT-723 | I34: ALTO VXR | J34: 2020 | K34: 2000000 | L34: 36000 | M34: 0.018 | N34: 45810 | O34: 31535 | P34: 36000 | Q34: 31535 | R34: 563 | S34: 0 | T34: 09000870/Digital sales - DA | U34: REN | W34: Hamna Ali | X34: Comprehensive | Y34: Retail Renewal | Z34: Retail Renewal (June-2025)
A35: 34 | B35: LHR/LHR/D/MO/PC COMP/P/110518/07/2025 | C35: =VLOOKUP('IT Working sheet '!B35,'09000210'!B:C,2,0) -> 040000200531 | D35: ="Update ins_assorted_clients set commission_amount = '"&R35&"' where assorted_code = '"&C35&"' and agency_code = '09000870';" -> Update ins_assorted_clients set commission_amount = '563' where assorted_code = '040000200531' and agency_code = '09000870'; | E35: 45849 | F35: Shehar Bano | G35: 0332-9253454 | H35: AYW-172 | I35: ALTO | J35: 2022 | K35: 2000000 | L35: 30000 | M35: 0.015 | N35: 45811 | O35: 25624 | P35: 30000 | Q35: 25624 | R35: 563 | S35: 0 | T35: 09000870/Digital sales - DA | U35: REN | W35: Hamna Ali | X35: Comprehensive | Y35: Retail Renewal | Z35: Retail Renewal (May-2025)
A36: 35 | B36: KHI/HO/D/MO/MC COMP/P/110077/06/2025 | E36: 45826 | F36: Mr. Muhammad Hassan Raza | G36: 3412914850 | H36: KTD-2229 | I36: HONDA - Prider 100 | J36: 2025 | K36: 208900 | L36: 8356 | M36: 4 | N36: 45825 | O36: 6772 | P36: 8356 | Q36: 13544 | R36: 0 | S36: 0 | T36: 09000870/Digital sales - DA | U36: FRE | V36: 0 | W36: Syed Waqas Shah | X36: Comprehensive | Y36: Other | Z36: Other
A37: 36 | B37: KHI/HO/D/MO/PD COMP/P/109905/06/2025 | E37: 45814 | F37: Shakeel Ahmed | G37: 3343451716 | H37: CBR-607 | I37: Suzuki ALTO | J37: 2025 | K37: 3080000 | L37: 10000 | M37: 0.025 | N37: 45813 | O37: 8190 | P37: 10000 | Q37: 16380 | R37: 0 | S37: 0 | T37: 09000870/Digital sales - DA | U37: FRE | V37: 0 | W37: Syed Waqas Shah | X37: Pay As You Drive | Y37: Other | Z37: Other
A38: 37 | B38: KHI/HO/D/MO/PC COMP/P/110275/06/2025 | E38: 45838 | F38: Muhammad Noor Kamran | G38: 3072942941 | H38: BRT-862 | I38: Suzuki ALTO | J38: 2020 | K38: 2200000 | L38: 45500 | M38: 2 | N38: 45838 | O38: 38793 | P38: 45500 | Q38: 77586 | R38: 0 | S38: 0 | T38: 09000870/Digital sales - DA | U38: Fresh | W38: Syed Waqas Shah | X38: Comprehensive | Y38: Other | Z38: 0
A39: 38 | B39: KHI/HO/D/MO/PC COMP/P/110348/07/2025 | C39: =VLOOKUP('IT Working sheet '!B39,'09000210'!B:C,2,0) -> #N/A | E39: 45841 | F39: Mr. Mufti Ehsan Waquar Ahmed | G39: 3008286191 | H39: CAB-064 | I39: SUZUKI - ALTO VXR | J39: 2024 | K39: 3175000 | L39: 55563 | M39: 1.75 | N39: 45861 | O39: 47468 | P39: 55563 | Q39: 47468 | R39: 0 | S39: 0 | T39: 09000870/Digital sales - DA | U39: REN | V39: 0 | W39: Syed Waqas Shah | X39: Comprehensive | Y39: PAYD Renewal | Z39: PAYD Renewal (July-2025)
A40: 39 | B40: KHI/HO/D/MO/PC COMP/P/110556/07/2025 | C40: =VLOOKUP('IT Working sheet '!B40,'09000210'!B:C,2,0) -> #N/A | E40: 45853 | F40: Mr. Muhammad Moez Syed | G40: 3413832018 | H40: BVL-164 | I40: SUZUKI ALTO VXR | J40: 2021 | K40: 2300000 | L40: 39100 | M40: 1.7 | N40: 45853 | O40: 33276 | P40: 39100 | Q40: 33276 | R40: 0 | S40: 0 | T40: 09000870/Digital sales - DA | U40: REN | V40: 0 | W40: Syed Waqas Shah | X40: Comprehensive | Y40: Direct Renewal | Z40: Direct Renewal (July-2025)
A41: 40 | B41: KHI/HO/D/MO/PC COMP/P/110520/07/2025 | C41: =VLOOKUP('IT Working sheet '!B41,'09000210'!B:C,2,0) -> #N/A | E41: 45849 | F41: Mr. Adil Hussain | G41: 3212311508 | H41: BMV-766 | I41: SUZUKI CULTUS | J41: 2018 | K41: 2300000 | L41: 40250 | M41: 1.75 | N41: 45849 | O41: 34267 | P41: 40250 | Q41: 34267 | R41: 0 | S41: 0 | T41: 09000870/Digital sales - DA | U41: REN | V41: 0 | W41: Syed Waqas Shah | X41: Comprehensive | Y41: Direct Renewal | Z41: Direct Renewal (July-2025)
A42: 41 | B42: KHI/HO/D/MO/PC COMP/P/110425/07/2025 | C42: =VLOOKUP('IT Working sheet '!B42,'09000210'!B:C,2,0) -> #N/A | E42: 45845 | F42: Mr. Israr Ahmed Khan | G42: 3008940171 | H42: BXB-104 | I42: Suzuki ALTO | J42: 2021 | K42: 2500000 | L42: 41250 | M42: 1.65 | N42: 45845 | O42: 35130 | P42: 41250 | Q42: 35130 | R42: 0 | S42: 0 | T42: 09000870/Digital sales - DA | U42: REN | V42: 0 | W42: Syed Waqas Shah | X42: Comprehensive | Y42: Direct Renewal | Z42: Direct Renewal (July-2025)
A43: 42 | B43: KHI/HO/D/MO/CV/P/110054/06/2025 | E43: 45825 | F43: M.R Industries | G43: 3132816156 | H43: JZ-2455 | I43: MASTER - FORLAND | J43: 2016 | K43: 1000000 | L43: 15000 | M43: 1.5 | N43: 45807 | O43: 12500 | P43: 17500 | Q43: 12500 | R43: 0 | S43: 0 | T43: 09000870/Digital sales - DA | U43: REN | V43: 0 | W43: Syed Waqas Shah | X43: Comprehensive | Y43: Retail Renewal | Z43: Retail Renewal (May-2025)
A44: 43 | B44: LHR/LHR/D/MO/PC COMP/P/109970/06/2025 | E44: 45820 | F44: Ms. Firdose Sultana | G44: 3334273529 | H44: APG-310 | I44: SUZUKI - ALTO VXL | J44: 2023 | K44: 2935000 | L44: 58407 | M44: 1.99 | N44: 45820 | O44: 49903 | P44: 58407 | Q44: 49903 | R44: 0 | S44: 0 | T44: 09000870/Digital sales - DA | U44: REN | V44: 0 | W44: Syed Waqas Shah | X44: Comprehensive | Y44: Retail Renewal | Z44: Retail Renewal (June-2025)
A45: 44 | B45: LHR/LHR/D/MO/PC COMP/P/109899/06/2025 | E45: 45813 | F45: Ms. Ammara Lodhi | G45: 3334253418 | H45: APG-338 | I45: SUZUKI - ALTO VXL | J45: 2023 | K45: 2935000 | L45: 58407 | M45: 1.99 | N45: 45813 | O45: 49903 | P45: 58407 | Q45: 49903 | R45: 0 | S45: 0 | T45: 09000870/Digital sales - DA | U45: REN | V45: 0 | W45: Syed Waqas Shah | X45: Comprehensive | Y45: Retail Renewal | Z45: Retail Renewal (June-2025)
A46: 45 | B46: LHR/LHR/D/MO/PC COMP/P/109781/06/2025 | E46: 45811 | F46: Mrs. Mohsina Azhar | G46: 3214888830 | H46: ARY-319 | I46: SUZUKI - Suzuki Swift | J46: 2024 | K46: 4719000 | L46: 82583 | M46: 1.75 | N46: 45810 | O46: 70566 | P46: 82583 | Q46: 70566 | R46: 0 | S46: 0 | T46: 09000870/Digital sales - DA | U46: REN | V46: 0 | W46: Syed Waqas Shah | X46: Comprehensive | Y46: Retail Renewal | Z46: Retail Renewal (June-2025)
A47: 46 | B47: LHR/LHR/D/MO/PC COMP/P/110032/06/2025 | E47: 45824 | F47: Mr. Muhammad Mubeen Arif | G47: 3214151659 | H47: ASB-753 | I47: SUZUKI - Swift GLX CVT | J47: 2024 | K47: 4794000 | L47: 83895 | M47: 1.75 | N47: 45824 | O47: 71688 | P47: 83895 | Q47: 71688 | R47: 0 | S47: 0 | T47: 09000870/Digital sales - DA | U47: REN | V47: 0 | W47: Syed Waqas Shah | X47: Comprehensive | Y47: Retail Renewal | Z47: Retail Renewal (June-2025)
A48: 47 | B48: KHI/HO/D/MO/PC COMP/P/110092/06/2025 | E48: 45826 | F48: Mr. Osman Saeed Khan | G48: 3008284228 | H48: AZG-116 | I48: FORTUNER 4X4 AT LEGENDER | J48: 2022 | K48: 17000000 | L48: 221000 | M48: 1.3 | N48: 45826 | O48: 190086 | P48: 221000 | Q48: 190086 | R48: 0 | S48: 0 | T48: 09000870/Digital sales - DA | U48: REN | V48: 0 | W48: Syed Waqas Shah | X48: Comprehensive | Y48: Retail Renewal | Z48: Retail Renewal (June-2025)
A49: 48 | B49: KHI/HO/D/MO/PC COMP/P/109921/06/2025 | E49: 45818 | F49: Mr. Raja Atif Shabbir HPA Meezan Bank (Staff) | G49: 3343000034 | H49: BBB-420 | I49: SUZUKI - ALTO VXR | J49: 2022 | K49: 2200000 | L49: 30800 | M49: 1.4 | N49: 45818 | O49: 26121 | P49: 30800 | Q49: 26121 | R49: 0 | S49: 0 | T49: 09000870/Digital sales - DA | U49: REN | V49: 0 | W49: Syed Waqas Shah | X49: Comprehensive | Y49: Direct Renewal | Z49: (Direct Renewal June-2025)
A50: 49 | B50: LHR/LHR/D/MO/PC COMP/P/110094/06/2025 | E50: 45826 | F50: Mr. Habib Ullah Khan | G50: 3305485656 | H50: BCG-115 | I50: SUZUKI - CULTUS AGS | J50: 2023 | K50: 3800000 | L50: 64600 | M50: 1.7 | N50: 45826 | O50: 55197 | P50: 64600 | Q50: 55197 | R50: 0 | S50: 0 | T50: 09000870/Digital sales - DA | U50: REN | V50: 0 | W50: Syed Waqas Shah | X50: Comprehensive | Y50: Retail Renewal | Z50: Retail Renewal (June-2025)
A51: 50 | B51: KHI/HO/D/MO/PC COMP/P/110242/06/2025 | E51: 45835 | F51: Ms. Mehak Naz HPA Meezan Bank (Staff) | G51: 3040920464 | H51: BFC-768 | I51: SUZUKI - MEHRAN VXR | J51: 2016 | K51: 1050000 | L51: 14700 | M51: 1.4 | N51: 45835 | O51: 12242 | P51: 14700 | Q51: 12242 | R51: 0 | S51: 0 | T51: 09000870/Digital sales - DA | U51: REN | V51: 0 | W51: Syed Waqas Shah | X51: Comprehensive | Y51: Direct Renewal | Z51: (Direct Renewal June-2025)
A52: 51 | B52: KHI/HO/D/MO/PC COMP/P/109896/06/2025 | E52: 45813 | F52: Mr. Junaid Ahmed HPA M/s. Meezan Bank Limited Staff Loan | G52: 3172128640 | H52: BGW-557 | I52: SUZUKI - MEHRAN VXR CNG | J52: 2016 | K52: 1100000 | L52: 15400 | M52: 1.4 | N52: 45813 | O52: 12845 | P52: 15400 | Q52: 12845 | R52: 0 | S52: 0 | T52: 09000870/Digital sales - DA | U52: REN | V52: 0 | W52: Syed Waqas Shah | X52: Comprehensive | Y52: Direct Renewal | Z52: (Direct Renewal June-2025)
A53: 52 | B53: KHI/HO/D/MO/PC COMP/P/110034/06/2025 | E53: 45825 | F53: Mr. Muhammad Umer Farooq | G53: 3333559921 | H53: BH-1755 | I53: HONDA - VEZEL HYBRID A/T | J53: 2014 | K53: 4500000 | L53: 99000 | M53: 2.2 | N53: 45824 | O53: 84914 | P53: 99000 | Q53: 84914 | R53: 0 | S53: 0 | T53: 09000870/Digital sales - DA | U53: REN | V53: 0 | W53: Syed Waqas Shah | X53: Comprehensive | Y53: Direct Renewal | Z53: (Direct Renewal June-2025)
A54: 53 | B54: KHI/HO/D/MO/PC COMP/P/109908/06/2025 | E54: 45818 | F54: Mr. Imran | G54: 3342428111 | H54: BQH-884 | I54: TOYOTA PASSO | J54: 2015 | K54: 2500000 | L54: 37500 | M54: 1.5 | N54: 45821 | O54: 31897 | P54: 37500 | Q54: 31897 | R54: 0 | S54: 0 | T54: 09000870/Digital sales - DA | U54: REN | V54: 0 | W54: Syed Waqas Shah | X54: Comprehensive | Y54: Direct Renewal | Z54: (Direct Renewal June-2025)
... A56: 55 | B56: KHI/HO/D/MO/PC COMP/P/110060/06/2025 | E56: 45825 | F56: Mr. Mohsin Mobeen | G56: 3152870400 | H56: BWR-208 | I56: CHANGAN - ALSVIN LUMEIRE | J56: 2022 | K56: 3500000 | L56: 52500 | M56: 1.5 | N56: 45824 | O56: 44828 | P56: 52500 | Q56: 44828 | R56: 0 | S56: 0 | T56: 09000870/Digital sales - DA | U56: REN | V56: 0 | W56: Syed Waqas Shah | X56: Comprehensive | Y56: Retail Renewal | Z56: Retail Renewal (June-2025)
A57: 56 | B57: KHI/HO/D/MO/PC COMP/P/109983/06/2025 | E57: 45821 | F57: Mr. Fahad Suria | G57: 0323-2828955 / 03212411377 | H57: BXU-357 | I57: SUZUKI - ALTO VXL | J57: 2022 | K57: 3200000 | L57: 51200 | M57: 1.6 | N57: 45821 | O57: 43707 | P57: 51200 | Q57: 43707 | R57: 0 | S57: 0 | T57: 09000870/Digital sales - DA | U57: REN | V57: 0 | W57: Syed Waqas Shah | X57: Comprehensive | Y57: Direct Renewal | Z57: (Direct Renewal June-2025)
A58: 57 | B58: KHI/HO/D/MO/PC COMP/P/109830/06/2025 | E58: 45812 | F58: Javeriah | G58: 3462771423 | H58: BZX-595 | I58: SUZUKI - ALTO AGS A/T | J58: 2024 | K58: 3055000 | L58: 53463 | M58: 1.75 | N58: 45812 | O58: 45657 | P58: 53463 | Q58: 45657 | R58: 0 | S58: 0 | T58: 09000870/Digital sales - DA | U58: REN | V58: 0 | W58: Syed Waqas Shah | X58: Comprehensive | Y58: Retail Renewal | Z58: Retail Renewal (June-2025)
A59: 58 | B59: KHI/HO/D/MO/PC COMP/P/110272/06/2025 | E59: 45838 | F59: Maha Wadood | G59: 3260247077 | H59: CAA-952 | I59: SUZUKI - ALTO VXL AGS | J59: 2024 | K59: 3045000 | L59: 54810 | M59: 1.8 | N59: 45838 | O59: 46819 | P59: 54810 | Q59: 46819 | R59: 0 | S59: 0 | T59: 09000870/Digital sales - DA | U59: REN | V59: 0 | W59: Syed Waqas Shah | X59: Comprehensive | Y59: Retail Renewal | Z59: Retail Renewal (June-2025)
A60: 59 | B60: KHI/HO/D/MO/PD COMP/P/109803/06/2025 | E60: 45811 | F60: Mr. Touseef Khan | G60: 0300-3588375 | H60: BJ-4733 | I60: MG ZS | J60: 2021 | K60: 4000000 | L60: 10000 | M60: 0.025 | N60: 45811 | O60: 8190 | P60: 10000 | Q60: 8190 | R60: 0 | S60: 0 | T60: 09000870/Digital sales - DA | U60: REN | V60: 0 | W60: Syed Waqas Shah | X60: Pay As You Drive | Y60: Direct Renewal | Z60: (Direct Renewal June-2025)
A61: 60 | B61: KHI/HO/D/MO/PD COMP/P/109863/06/2025 | E61: 45813 | F61: Mr. Abdul Rehman | G61: 3362553895 | H61: BZW-873 | I61: SUZUKI - ALTO VXL | J61: 2024 | K61: 2900000 | L61: 10000 | M61: 0.025 | N61: 45813 | O61: 8190 | P61: 10000 | Q61: 8190 | R61: 0 | S61: 0 | T61: 09000870/Digital sales - DA | U61: REN | V61: 0 | W61: Syed Waqas Shah | X61: Pay As You Drive | Y61: PAYD Renewal | Z61: PAYD Renewal (June-2025)
A62: 61 | B62: KHI/HO/D/MO/PC COMP/P/110043/06/2025 | E62: 45825 | F62: Haleem Ul Hassan | G62: 0300 8733901 | H62: AGM-496 | I62: Honda Civic | J62: 2021 | K62: 7000000 | L62: 119000 | M62: 0.017 | N62: 45825 | O62: 102155 | P62: 119000 | Q62: 204310 | R62: 1299 | S62: - | T62: 09000870/Digital sales - DA | U62: FRE | V62: 0 | W62: Muhammad Danish Azhar | X62: Comprehensive | Y62: Facebook | Z62: Facebook
A63: 62 | B63: KHI/HO/D/MO/PC COMP/P/110088/06/2025 | E63: 45826 | F63: Steve Simon | G63: 0327-2835001 | H63: Un-Reg | I63: JAC T9 Hunter | J63: 2025 | K63: 10600000 | L63: 159000 | M63: 0.015 | N63: 45825 | O63: 136638 | P63: 159000 | Q63: 273276 | R63: 1299 | S63: - | T63: 09000870/Digital sales - DA | U63: FRE | V63: 0 | W63: Muhammad Danish Azhar | X63: Comprehensive | Y63: Facebook | Z63: Facebook
A64: 63 | B64: KHI/HO/D/MO/PC COMP/P/110264/06/2025 | E64: 45836 | F64: Muhammad Fahad Khalid Rathore | G64: 0345 3274286 | H64: BWD-410 | I64: Hyundai Elentra | J64: 2022 | K64: 5000000 | L64: 90000 | M64: 0.018 | N64: 45834 | O64: 77155 | P64: 90000 | Q64: 154310 | R64: 1299 | S64: - | T64: 09000870/Digital sales - DA | U64: FRE | V64: 0 | W64: Muhammad Danish Azhar | X64: Comprehensive | Y64: Facebook | Z64: Facebook
A65: 64 | B65: KHI/HO/D/MO/PC COMP/P/110559/07/2025 | C65: =VLOOKUP('IT Working sheet '!B65,'09000210'!B:C,2,0) -> 040000200596 | D65: ="Update ins_assorted_clients set commission_amount = '"&R65&"' where assorted_code = '"&C65&"' and agency_code = '09000870';" -> Update ins_assorted_clients set commission_amount = '1299' where assorted_code = '040000200596' and agency_code = '09000870'; | E65: 45853 | F65: Kamran Ali | G65: 0300-0122937 | H65: BRM-579 | I65: SUZUKI - ALTO VXR | J65: 2020 | K65: 2000000 | L65: 30000 | M65: 0.015 | N65: 45853 | O65: 25431 | P65: 30000 | Q65: 25431 | R65: 1299 | S65: - | T65: 09000870/Digital sales - DA | U65: REN | V65: 0 | W65: Muhammad Danish Azhar | X65: Comprehensive | Y65: Retail Renewal | Z65: Retail Renewal (July-2025)
A66: 65 | B66: KHI/HO/D/MO/PC COMP/P/110465/07/2025 | C66: =VLOOKUP('IT Working sheet '!B66,'09000210'!B:C,2,0) -> 040000200430 | D66: ="Update ins_assorted_clients set commission_amount = '"&R66&"' where assorted_code = '"&C66&"' and agency_code = '09000870';" -> Update ins_assorted_clients set commission_amount = '1299' where assorted_code = '040000200430' and agency_code = '09000870'; | E66: 45846 | F66: Muhammed Mohsin | G66: 0305-9450243 | H66: BBR-625 | I66: HONDA - CITY I-VTEC | J66: 2014 | K66: 2650000 | L66: 42400 | M66: 0.016 | N66: 45846 | O66: 36121 | P66: 42400 | Q66: 36121 | R66: 1299 | S66: - | T66: 09000870/Digital sales - DA | U66: REN | V66: 0 | W66: Muhammad Danish Azhar | X66: Comprehensive | Y66: Retail Renewal | Z66: Retail Renewal (July-2025)
A67: 66 | B67: KHI/HO/D/MO/PC COMP/P/110527/07/2025 | C67: =VLOOKUP('IT Working sheet '!B67,'09000210'!B:C,2,0) -> 040000200547 | D67: ="Update ins_assorted_clients set commission_amount = '"&R67&"' where assorted_code = '"&C67&"' and agency_code = '09000870';" -> Update ins_assorted_clients set commission_amount = '1299' where assorted_code = '040000200547' and agency_code = '09000870'; | E67: 45852 | F67: Latif Akbar | G67: 0331-8976727 | H67: SA-6822 | I67: NISSAN - CLIPPER A/T | J67: 2019 | K67: 2600000 | L67: 44252 | M67: 0.017 | N67: 45852 | O67: 37717 | P67: 44252 | Q67: 37717 | R67: 1299 | S67: - | T67: 09000870/Digital sales - DA | U67: REN | V67: 0 | W67: Muhammad Danish Azhar | X67: Comprehensive | Y67: Retail Renewal | Z67: Retail Renewal (July-2025)
A68: 67 | B68: KHI/HO/D/MO/PC COMP/P/110553/07/2025 | C68: =VLOOKUP('IT Working sheet '!B68,'09000210'!B:C,2,0) -> 040000200588 | D68: ="Update ins_assorted_clients set commission_amount = '"&R68&"' where assorted_code = '"&C68&"' and agency_code = '09000870';" -> Update ins_assorted_clients set commission_amount = '1299' where assorted_code = '040000200588' and agency_code = '09000870'; | E68: 45853 | F68: Jamil Ahmed Siddiqui | G68: 0333-3454948 | H68: BWY-049 | I68: SUZUKI - ALTO | J68: 2022 | K68: 2250000 | L68: 45000 | M68: 0.02 | N68: 45853 | O68: 38362 | P68: 45000 | Q68: 38362 | R68: 1299 | S68: - | T68: 09000870/Digital sales - DA | U68: REN | V68: 0 | W68: Muhammad Danish Azhar | X68: Comprehensive | Y68: Retail Renewal | Z68: Retail Renewal (July-2025)
A69: 68 | B69: KHI/HO/D/MO/CV/P/110552/07/2025 | C69: =VLOOKUP('IT Working sheet '!B69,'09000210'!B:C,2,0) -> 040000200587 | D69: ="Update ins_assorted_clients set commission_amount = '"&R69&"' where assorted_code = '"&C69&"' and agency_code = '09000870';" -> Update ins_assorted_clients set commission_amount = '1299' where assorted_code = '040000200587' and agency_code = '09000870'; | E69: 45853 | F69: Muhammad Irfan | G69: 0313-2273281 | I69: SUZUKI - RAVI PICK UP | J69: 2024 | K69: 1856000 | L69: 46400 | M69: 0.025 | N69: 45853 | O69: 39569 | P69: 46400 | Q69: 39569 | R69: 1299 | S69: - | T69: 09000870/Digital sales - DA | U69: REN | V69: 0 | W69: Muhammad Danish Azhar | X69: Comprehensive | Y69: Retail Renewal | Z69: Retail Renewal (July-2025)
A70: 69 | B70: KHI/HO/D/MO/PC COMP/P/110306/07/2025 | C70: =VLOOKUP('IT Working sheet '!B70,'09000210'!B:C,2,0) -> 040000200036 | D70: ="Update ins_assorted_clients set commission_amount = '"&R70&"' where assorted_code = '"&C70&"' and agency_code = '09000870';" -> Update ins_assorted_clients set commission_amount = '1299' where assorted_code = '040000200036' and agency_code = '09000870'; | E70: 45839 | F70: Fizza Mashhood Jafri | G70: 0313-0442760 | H70: BXF-201 | I70: PROTON - SAGA | J70: 2022 | K70: 2519200 | L70: 50384 | M70: 0.02 | N70: 45839 | O70: 43003 | P70: 50384 | Q70: 43003 | R70: 1299 | S70: - | T70: 09000870/Digital sales - DA | U70: REN | V70: 0 | W70: Muhammad Danish Azhar | X70: Comprehensive | Y70: Retail Renewal | Z70: Retail Renewal (July-2025)
A71: 70 | B71: LHR/LHR/D/MO/PC COMP/P/110481/07/2025 | C71: =VLOOKUP('IT Working sheet '!B71,'09000210'!B:C,2,0) -> 040000200475 | D71: ="Update ins_assorted_clients set commission_amount = '"&R71&"' where assorted_code = '"&C71&"' and agency_code = '09000870';" -> Update ins_assorted_clients set commission_amount = '1299' where assorted_code = '040000200475' and agency_code = '09000870'; | E71: 45848 | F71: Zain Ul Abideen | G71: 0334-7193808 | H71: ASJ-819 | I71: SUZUKI - Swift GLX CVT | J71: 2024 | K71: 4766160 | L71: 76259 | M71: 0.016 | N71: 45848 | O71: 65161 | P71: 76259 | Q71: 65161 | R71: 1299 | S71: - | T71: 09000870/Digital sales - DA | U71: REN | V71: 0 | W71: Muhammad Danish Azhar | X71: Comprehensive | Y71: Retail Renewal | Z71: Retail Renewal (July-2025)
A72: 71 | B72: LHR/LHR/D/MO/PC COMP/P/110305/07/2025 | C72: =VLOOKUP('IT Working sheet '!B72,'09000210'!B:C,2,0) -> 040000200033 | D72: ="Update ins_assorted_clients set commission_amount = '"&R72&"' where assorted_code = '"&C72&"' and agency_code = '09000870';" -> Update ins_assorted_clients set commission_amount = '1299' where assorted_code = '040000200033' and agency_code = '09000870'; | E72: 45839 | F72: Mona Imran CNIC # 37405-61817 | G72: 0321-5365055 | H72: AZT-172 | I72: HONDA - BRV I-VTEC | J72: 2022 | K72: 4200000 | L72: 84000 | M72: 0.02 | N72: 45839 | O72: 71778 | P72: 84000 | Q72: 71778 | R72: 1299 | S72: - | T72: 09000870/Digital sales - DA | U72: REN | V72: 0 | W72: Muhammad Danish Azhar | X72: Comprehensive | Y72: Retail Renewal | Z72: Retail Renewal (July-2025)
A73: 72 | B73: KHI/HO/D/MO/PC COMP/P/110549/07/2025 | C73: =VLOOKUP('IT Working sheet '!B73,'09000210'!B:C,2,0) -> 040000200584 | D73: ="Update ins_assorted_clients set commission_amount = '"&R73&"' where assorted_code = '"&C73&"' and agency_code = '09000870';" -> Update ins_assorted_clients set commission_amount = '1299' where assorted_code = '040000200584' and agency_code = '09000870'; | E73: 45853 | F73: Kiran | G73: 0300-8250056 | H73: BRM-832 | I73: HONDA - CIVIC I-VTEC ORIEL | J73: 2019 | K73: 5640000 | L73: 84600 | M73: 0.015 | N73: 45853 | O73: 72500 | P73: 84600 | Q73: 72500 | R73: 1299 | S73: - | T73: 09000870/Digital sales - DA | U73: REN | V73: 0 | W73: Muhammad Danish Azhar | X73: Comprehensive | Y73: Retail Renewal | Z73: Retail Renewal (July-2025)
A74: 73 | B74: LHR/LHR/D/MO/PC COMP/P/110411/07/2025 | C74: =VLOOKUP('IT Working sheet '!B74,'09000210'!B:C,2,0) -> 040000200297 | D74: ="Update ins_assorted_clients set commission_amount = '"&R74&"' where assorted_code = '"&C74&"' and agency_code = '09000870';" -> Update ins_assorted_clients set commission_amount = '1299' where assorted_code = '040000200297' and agency_code = '09000870'; | E74: 45845 | F74: Samia Altaf Hussain | G74: 0332-3010097 | I74: HONDA - CITY 1.2 LS CVT | J74: 2024 | K74: 4864500 | L74: 85129 | M74: 0.0175 | N74: 45845 | O74: 72743 | P74: 85129 | Q74: 72743 | R74: 1299 | S74: - | T74: 09000870/Digital sales - DA | U74: REN | V74: 0 | W74: Muhammad Danish Azhar | X74: Comprehensive | Y74: Retail Renewal | Z74: Retail Renewal (July-2025)
A75: 74 | B75: KHI/HO/D/MO/PC COMP/P/110508/07/2025 | C75: =VLOOKUP('IT Working sheet '!B75,'09000210'!B:C,2,0) -> 040000200516 | D75: ="Update ins_assorted_clients set commission_amount = '"&R75&"' where assorted_code = '"&C75&"' and agency_code = '09000870';" -> Update ins_assorted_clients set commission_amount = '1299' where assorted_code = '040000200516' and agency_code = '09000870'; | E75: 45849 | F75: Hussain Ac Ressichem Pvt Ltd | G75: 0300-8266063 | H75: BK-6702 | I75: KIA - SPORTAGE AWD | J75: 2022 | K75: 7000000 | L75: 112000 | M75: 0.016 | N75: 45849 | O75: 96121 | P75: 112000 | Q75: 96121 | R75: 1299 | S75: - | T75: 09000870/Digital sales - DA | U75: REN | V75: 0 | W75: Muhammad Danish Azhar | X75: Comprehensive | Y75: Retail Renewal | Z75: Retail Renewal (July-2025)
A76: 75 | B76: LHR/LHR/D/MO/PC COMP/P/110558/07/2025 | C76: =VLOOKUP('IT Working sheet '!B76,'09000210'!B:C,2,0) -> 040000200595 | D76: ="Update ins_assorted_clients set commission_amount = '"&R76&"' where assorted_code = '"&C76&"' and agency_code = '09000870';" -> Update ins_assorted_clients set commission_amount = '1299' where assorted_code = '040000200595' and agency_code = '09000870'; | E76: 45853 | F76: Muhammad Rashid Butt | G76: 0323-6108108 | H76: BEC-108 | I76: HAVAL - Haval Jolion Turbo 1.5L AT | J76: 2024 | K76: 8300000 | L76: 116200 | M76: 0.014 | N76: 45853 | O76: 99299 | P76: 116200 | Q76: 99299 | R76: 1299 | S76: - | T76: 09000870/Digital sales - DA | U76: REN | V76: 0 | W76: Muhammad Danish Azhar | X76: Comprehensive | Y76: Retail Renewal | Z76: Retail Renewal (July-2025)
A77: 76 | B77: KHI/HO/D/MO/PC COMP/P/110445/07/2025 | C77: =VLOOKUP('IT Working sheet '!B77,'09000210'!B:C,2,0) -> 040000200405 | D77: ="Update ins_assorted_clients set commission_amount = '"&R77&"' where assorted_code = '"&C77&"' and agency_code = '09000870';" -> Update ins_assorted_clients set commission_amount = '1299' where assorted_code = '040000200405' and agency_code = '09000870'; | E77: 45846 | F77: Asfara Tariq | G77: 0333-3618220 | H77: BG-6037 | I77: TOYOTA - FORTUNER | J77: 2017 | K77: 9000000 | L77: 121500 | M77: 0.0135 | N77: 45846 | O77: 104310 | P77: 121500 | Q77: 104310 | R77: 1299 | S77: - | T77: 09000870/Digital sales - DA | U77: REN | V77: 0 | W77: Muhammad Danish Azhar | X77: Comprehensive | Y77: Retail Renewal | Z77: Retail Renewal (July-2025)
A78: 77 | B78: LHR/LHR/D/MO/PC COMP/P/110413/07/2025 | C78: =VLOOKUP('IT Working sheet '!B78,'09000210'!B:C,2,0) -> 040000200301 | D78: ="Update ins_assorted_clients set commission_amount = '"&R78&"' where assorted_code = '"&C78&"' and agency_code = '09000870';" -> Update ins_assorted_clients set commission_amount = '1299' where assorted_code = '040000200301' and agency_code = '09000870'; | E78: 45845 | F78: Fazal Ali | G78: 0333-5423421 | H78: BEC-720 | I78: HAVAL - Haval Jolion Turbo 1.5L AT | J78: 2024 | K78: 9631850 | L78: 144478 | M78: 0.015 | N78: 45845 | O78: 123468 | P78: 144478 | Q78: 123468 | R78: 1299 | S78: - | T78: 09000870/Digital sales - DA | U78: REN | V78: 0 | W78: Muhammad Danish Azhar | X78: Comprehensive | Y78: Retail Renewal | Z78: Retail Renewal (July-2025)
A79: 78 | B79: KHI/HO/D/MO/PC COMP/P/109884/06/2025 | E79: 45813 | F79: Toyota Central Motors User Iqbal Fareed | G79: 0346-8222391 | H79: BPX-355 | I79: SUZUKI - WAGON R VXL | J79: 2019 | K79: 2000000 | L79: 30000 | M79: 0.015 | N79: 45812 | O79: 25431 | P79: 30000 | Q79: 25431 | R79: 1299 | S79: - | T79: 09000870/Digital sales - DA | U79: REN | V79: 0 | W79: Muhammad Danish Azhar | X79: Comprehensive | Y79: Retail Renewal | Z79: Retail Renewal (May-2025)
A80: 79 | B80: KHI/HO/D/MO/PC COMP/P/109885/06/2025 | E80: 45813 | F80: Toyota Central Motors User Shahid Ilyas | G80: 0300-2953245 | H80: BKU-806 | I80: SUZUKI - CULTUS | J80: 2017 | K80: 2000000 | L80: 30000 | M80: 0.015 | N80: 45812 | O80: 25431 | P80: 30000 | Q80: 25431 | R80: 1299 | S80: - | T80: 09000870/Digital sales - DA | U80: REN | V80: 0 | W80: Muhammad Danish Azhar | X80: Comprehensive | Y80: Retail Renewal | Z80: Retail Renewal (May-2025)
A81: 80 | B81: KHI/HO/D/MO/PC COMP/P/109903/06/2025 | E81: 45813 | F81: Gul Faraz Khan | G81: 0300-2647043 | H81: BWC-254 | I81: SUZUKI - ALTO | J81: 2022 | K81: 2200000 | L81: 33000 | M81: 0.015 | N81: 45813 | O81: 28017 | P81: 33000 | Q81: 28017 | R81: 1299 | S81: - | T81: 09000870/Digital sales - DA | U81: REN | V81: 0 | W81: Muhammad Danish Azhar | X81: Comprehensive | Y81: Direct Renewal | Z81: Direct Renewal (May-2025)
A82: 81 | B82: LHR/LHR/D/MO/PC COMP/P/109982/06/2025 | E82: 45821 | F82: Nasir Wakeel | G82: 0308-6110710 | H82: ARW 722 | I82: SUZUKI - ALTO AGS A/T | J82: 2024 | K82: 3055000 | L82: 60795 | M82: 0.0199 | N82: 45821 | O82: 51945 | P82: 60795 | Q82: 51945 | R82: 1299 | S82: - | T82: 09000870/Digital sales - DA | U82: REN | V82: 0 | W82: Muhammad Danish Azhar | X82: Comprehensive | Y82: Retail Renewal | Z82: Retail Renewal (June-2025)
A83: 82 | B83: LHR/LHR/D/MO/PC COMP/P/109800/06/2025 | E83: 45811 | F83: Farhana Gulshan | G83: 0331-8686243 | H83: ASE-528 | I83: SUZUKI - ALTO VXL AGS | J83: 2024 | K83: 3045000 | L83: 60596 | M83: 0.0199 | N83: 45811 | O83: 51774 | P83: 60596 | Q83: 51774 | R83: 1299 | S83: - | T83: 09000870/Digital sales - DA | U83: REN | V83: 0 | W83: Muhammad Danish Azhar | X83: Comprehensive | Y83: Retail Renewal | Z83: Retail Renewal (June-2025)
A84: 83 | B84: KHI/HO/D/MO/PC COMP/P/110081/06/2025 | E84: 45826 | F84: Sheerin Ashhar | G84: 0321-4421065 | H84: ATX-577 | I84: HONDA - CITY I-VTEC | J84: 2022 | K84: 4000000 | L84: 56000 | M84: 0.014 | N84: 45826 | O84: 47845 | P84: 56000 | Q84: 47845 | R84: 1299 | S84: - | T84: 09000870/Digital sales - DA | U84: REN | V84: 0 | W84: Muhammad Danish Azhar | X84: Comprehensive | Y84: Retail Renewal | Z84: Retail Renewal (June-2025)
A85: 84 | B85: LHR/LHR/D/MO/PC COMP/P/110093/06/2025 | E85: 45826 | F85: Habib Ullah Khan | G85: 0330-5485656 | H85: AVU-378 | I85: TOYOTA COROLLA GRAND X | J85: 2021 | K85: 5900000 | L85: 100300 | M85: 0.017 | N85: 45826 | O85: 85709 | P85: 100300 | Q85: 85709 | R85: 1299 | S85: - | T85: 09000870/Digital sales - DA | U85: REN | V85: 0 | W85: Muhammad Danish Azhar | X85: Comprehensive | Y85: Retail Renewal | Z85: Retail Renewal (June-2025)
A86: 85 | B86: KHI/HO/D/MO/PC COMP/P/109801/06/2025 | E86: 45811 | F86: Sohail Ahmed | G86: 3312611101 | H86: BBF-140 | I86: TOYOTA - COROLLA | J86: 2014 | K86: 2400000 | L86: 36000 | M86: 0.015 | N86: 45811 | O86: 31535 | P86: 36000 | Q86: 31535 | R86: 1299 | S86: - | T86: 09000870/Digital sales - DA | U86: REN | V86: 0 | W86: Muhammad Danish Azhar | X86: Comprehensive | Y86: Retail Renewal | Z86: Retail Renewal (June-2025)
A87: 86 | B87: KHI/HO/D/MO/PC COMP/P/109977/06/2025 | E87: 45821 | F87: Sehr Pirzada | G87: 0306-2740771 | H87: BD-3565 | I87: TOYOTA - LAND CRUISER PRADO TZ | J87: 2003 | K87: 4000000 | L87: 70000 | M87: 0.0175 | N87: 45820 | O87: 59914 | P87: 70000 | Q87: 59914 | R87: 1299 | S87: - | T87: 09000870/Digital sales - DA | U87: REN | V87: 0 | W87: Muhammad Danish Azhar | X87: Comprehensive | Y87: Direct Renewal | Z87: (Direct Renewal June-2025)
A88: 87 | B88: KHI/HO/D/MO/PC COMP/P/109767/06/2025 | E88: 45810 | F88: Muzafar Hussain Talpur | G88: 0333-7141203 | H88: BQR-347 | I88: TOYOTA COROLLA GLI | J88: 2019 | K88: 4000000 | L88: 60000 | M88: 0.015 | N88: 45810 | O88: 51293 | P88: 60000 | Q88: 51293 | R88: 1299 | S88: - | T88: 09000870/Digital sales - DA | U88: REN | V88: 0 | W88: Muhammad Danish Azhar | X88: Comprehensive | Y88: Retail Renewal | Z88: Retail Renewal (June-2025)
A89: 88 | B89: KHI/HO/D/MO/PC COMP/P/110148/06/2025 | E89: 45831 | F89: Talat Abbasi | G89: 0333-2112311 | H89: BTT-649 | I89: SUZUKI - ALTO VXR E-2 | J89: 2021 | K89: 1400000 | L89: 23800 | M89: 0.017 | N89: 45831 | O89: 20086 | P89: 23800 | Q89: 20086 | R89: 1299 | S89: - | T89: 09000870/Digital sales - DA | U89: REN | V89: 0 | W89: Muhammad Danish Azhar | X89: Comprehensive | Y89: Retail Renewal | Z89: Retail Renewal (June-2025)
A90: 89 | B90: KHI/HO/D/MO/PC COMP/P/110132/06/2025 | E90: 45828 | F90: Muhammad Waqar Shaikh | G90: 0333-2168273 | H90: BWG-868 | I90: SUZUKI - ALTO | J90: 2022 | K90: 2200000 | L90: 33000 | M90: 0.015 | N90: 45828 | O90: 28017 | P90: 33000 | Q90: 28017 | R90: 1299 | S90: - | T90: 09000870/Digital sales - DA | U90: REN | V90: 0 | W90: Muhammad Danish Azhar | X90: Comprehensive | Y90: Retail Renewal | Z90: Retail Renewal (June-2025)
A91: 90 | B91: KHI/HO/D/MO/PC COMP/P/109975/06/2025 | E91: 45820 | F91: Nidae Fatima Asim | G91: 0315-2100200 | H91: BZZ-719 | I91: SUZUKI - ALTO VXL AGS 2024 | J91: 2024 | K91: 3045000 | L91: 45675 | M91: 0.015 | N91: 45820 | O91: 38944 | P91: 45675 | Q91: 38944 | R91: 1299 | S91: - | T91: 09000870/Digital sales - DA | U91: REN | V91: 0 | W91: Muhammad Danish Azhar | X91: Comprehensive | Y91: Retail Renewal | Z91: Retail Renewal (June-2025)
A92: 91 | B92: KHI/HO/D/MO/PC COMP/P/110243/06/2025 | E92: 45835 | F92: Misbah Rizwan | G92: 3332148080 | H92: CZ-7583 | I92: SUZUKI - BOLAN | J92: 2022 | K92: 1800000 | L92: 22500 | M92: 0.0125 | N92: 45834 | O92: 18965 | P92: 22500 | Q92: 18965 | R92: 1299 | S92: - | T92: 09000870/Digital sales - DA | U92: REN | V92: 0 | W92: Muhammad Danish Azhar | X92: Comprehensive | Y92: Direct Renewal | Z92: (Direct Renewal June-2025)
A93: 92 | B93: LHR/LHR/D/MO/PC COMP/P/109849/06/2025 | E93: 45812 | F93: Muhammad Arif Qazi | G93: 0321-5005529 | H93: EF-263 | I93: HONDA - CITY ASPIRE M/T | J93: 2015 | K93: 2500000 | L93: 40000 | M93: 0.016 | N93: 45812 | O93: 34171 | P93: 40000 | Q93: 34171 | R93: 1299 | S93: - | T93: 09000870/Digital sales - DA | U93: REN | V93: 0 | W93: Muhammad Danish Azhar | X93: Comprehensive | Y93: Retail Renewal | Z93: Retail Renewal (June-2025)
A94: 93 | B94: KHI/HO/D/MO/PC COMP/P/110146/06/2025 | E94: 45831 | F94: Muhammad Bin Majid | G94: 0332-8911128 | H94: FG-499 | I94: TOYOTA - COROLLA ALTIS 1.6 | J94: 2015 | K94: 3000000 | L94: 51000 | M94: 0.017 | N94: 45831 | O94: 43535 | P94: 51000 | Q94: 43535 | R94: 1299 | S94: - | T94: 09000870/Digital sales - DA | U94: REN | V94: 0 | W94: Muhammad Danish Azhar | X94: Comprehensive | Y94: Retail Renewal | Z94: Retail Renewal (June-2025)
A95: 94 | B95: KHI/HO/D/MO/PD COMP/P/110147/06/2025 | E95: 45831 | F95: Younus Abdul Hameed | G95: 0333-3256182 | H95: CZ-2002 | I95: DAIHATSU - HIJET VAN A/T | J95: 2015 | K95: 1500000 | L95: 10000 | M95: 0.025 | N95: 45831 | O95: 8190 | P95: 10000 | Q95: 8190 | R95: 1299 | S95: - | T95: 09000870/Digital sales - DA | U95: REN | V95: 0 | W95: Muhammad Danish Azhar | X95: Pay As You Drive | Y95: Direct Renewal | Z95: (Direct Renewal June-2025)
A96: 95 | B96: KHI/HO/D/MO/PC COMP/P/109894/06/2025 | E96: 45813 | F96: Syed Musharraf Ali | G96: 0333-3431015 | H96: BRC-309 | I96: SUZUKI ALTO VXL | J96: 2019 | K96: 2300000 | L96: 40250 | M96: 0.0175 | N96: 45807 | O96: 34267 | P96: 40250 | Q96: 68534 | R96: 1270 | S96: 0 | T96: 09000870/Digital sales - DA | U96: FRE | V96: 0 | W96: Moied Shamoon | X96: Comprehensive | Y96: Facebook | Z96: Facebook
A97: 96 | B97: KHI/HO/D/MO/PC COMP/P/110095/06/2025 | E97: 45826 | F97: Ahmad Shoukat | G97: 0306-1981111 | H97: LEA-18A-4082 | I97: Suzuki Wagon R | J97: 2018 | K97: 2000000 | L97: 35000 | M97: 0.0175 | N97: 45825 | O97: 29742 | P97: 35000 | Q97: 59484 | R97: 1270 | S97: 0 | T97: 09000870/Digital sales - DA | U97: FRE | V97: 0 | W97: Moied Shamoon | X97: Comprehensive | Y97: Facebook | Z97: Facebook
A98: 97 | B98: KHI/HO/D/MO/PC COMP/P/110456/07/2025 | C98: =VLOOKUP('IT Working sheet '!B98,'09000210'!B:C,2,0) -> 040000200421 | D98: ="Update ins_assorted_clients set commission_amount = '"&R98&"' where assorted_code = '"&C98&"' and agency_code = '09000870';" -> Update ins_assorted_clients set commission_amount = '1270' where assorted_code = '040000200421' and agency_code = '09000870'; | E98: 45846 | F98: Mr. Shahid Ahmed | G98: 0333-2053266 | H98: CAB-252 | I98: SUZUKI - ALTO VX | J98: 2024 | K98: 2331000 | L98: 40793 | M98: 0.0175 | N98: 45846 | O98: 34736 | P98: 40793 | Q98: 34736 | R98: 1270 | S98: 0 | T98: 09000870/Digital sales - DA | U98: REN | V98: 0 | W98: Moied Shamoon | X98: Comprehensive | Y98: Retail Renewal | Z98: Retail Renewal (July-2025)
A99: 98 | B99: KHI/HO/D/MO/PC COMP/P/110522/07/2025 | C99: =VLOOKUP('IT Working sheet '!B99,'09000210'!B:C,2,0) -> 040000200538 | D99: ="Update ins_assorted_clients set commission_amount = '"&R99&"' where assorted_code = '"&C99&"' and agency_code = '09000870';" -> Update ins_assorted_clients set commission_amount = '1269' where assorted_code = '040000200538' and agency_code = '09000870'; | E99: 45849 | F99: Mr. Muhammad Shahbaz | G99: 0303-2966004 | H99: BXH-847 | I99: SUZUKI - ALTO VXL | J99: 2022 | K99: 2800000 | L99: 42000 | M99: 0.015 | N99: 45849 | O99: 35776 | P99: 42000 | Q99: 35776 | R99: 1269 | S99: 0 | T99: 09000870/Digital sales - DA | U99: REN | V99: 0 | W99: Moied Shamoon | X99: Comprehensive | Y99: Retail Renewal | Z99: Retail Renewal (July-2025)
A100: 99 | B100: KHI/HO/D/MO/PC COMP/P/110563/07/2025 | C100: =VLOOKUP('IT Working sheet '!B100,'09000210'!B:C,2,0) -> 040000200601 | D100: ="Update ins_assorted_clients set commission_amount = '"&R100&"' where assorted_code = '"&C100&"' and agency_code = '09000870';" -> Update ins_assorted_clients set commission_amount = '1269' where assorted_code = '040000200601' and agency_code = '09000870'; | E100: 45853 | F100: SUZUKI - ALTO VXL | G100: 3452229464 | H100: BXC-293 | I100: SUZUKI - ALTO VXL | J100: 2022 | K100: 2800000 | L100: 42000 | M100: 0.015 | N100: 45853 | O100: 35776 | P100: 42000 | Q100: 35776 | R100: 1269 | S100: 0 | T100: 09000870/Digital sales - DA | U100: REN | V100: 0 | W100: Moied Shamoon | X100: Comprehensive | Y100: Retail Renewal | Z100: Retail Renewal (July-2025)
A101: 100 | B101: KHI/HO/D/MO/PC COMP/P/110354/07/2025 | C101: =VLOOKUP('IT Working sheet '!B101,'09000210'!B:C,2,0) -> 040000200134 | D101: ="Update ins_assorted_clients set commission_amount = '"&R101&"' where assorted_code = '"&C101&"' and agency_code = '09000870';" -> Update ins_assorted_clients set commission_amount = '1269' where assorted_code = '040000200134' and agency_code = '09000870'; | E101: 45841 | F101: Mr. Raza Ali | G101: 0336-8473291 | H101: BXD-164 | I101: SUZUKI - ALTO | J101: 2022 | K101: 2500000 | L101: 47500 | M101: 0.019 | N101: 45841 | O101: 40517 | P101: 47500 | Q101: 40517 | R101: 1269 | S101: 0 | T101: 09000870/Digital sales - DA | U101: REN | V101: 0 | W101: Moied Shamoon | X101: Comprehensive | Y101: Retail Renewal | Z101: Retail Renewal (July-2025)
A102: 101 | B102: LHR/LHR/D/MO/PC COMP/P/110307/07/2025 | C102: =VLOOKUP('IT Working sheet '!B102,'09000210'!B:C,2,0) -> 040000200037 | D102: ="Update ins_assorted_clients set commission_amount = '"&R102&"' where assorted_code = '"&C102&"' and agency_code = '09000870';" -> Update ins_assorted_clients set commission_amount = '1269' where assorted_code = '040000200037' and agency_code = '09000870'; | E102: 45839 | F102: Mr. Arsalan Ahmad | G102: 0309-9333297 | H102: ADX 998 | I102: SUZUKI - CULTUS VXL | J102: 2021 | K102: 3000000 | L102: 59700 | M102: 0.0199 | N102: 45839 | O102: 51009 | P102: 59700 | Q102: 51009 | R102: 1269 | S102: 0 | T102: 09000870/Digital sales - DA | U102: REN | V102: 0 | W102: Moied Shamoon | X102: Comprehensive | Y102: Retail Renewal | Z102: Retail Renewal (July-2025)
A103: 102 | B103: LHR/LHR/D/MO/PC COMP/P/110408/07/2025 | C103: =VLOOKUP('IT Working sheet '!B103,'09000210'!B:C,2,0) -> 040000200283 | D103: ="Update ins_assorted_clients set commission_amount = '"&R103&"' where assorted_code = '"&C103&"' and agency_code = '09000870';" -> Update ins_assorted_clients set commission_amount = '1270' where assorted_code = '040000200283' and agency_code = '09000870'; | E103: 45845 | F103: Mr. Irfan Ahmad | G103: 0334-9986690 | H103: ASG-601 | I103: SUZUKI - Swift GLX VVT | J103: 2024 | K103: 4719000 | L103: 70785 | M103: 0.015 | N103: 45845 | O103: 60483 | P103: 70785 | Q103: 60483 | R103: 1270 | S103: 0 | T103: 09000870/Digital sales - DA | U103: REN | V103: 0 | W103: Moied Shamoon | X103: Comprehensive | Y103: Retail Renewal | Z103: Retail Renewal (July-2025)
A104: 103 | B104: KHI/HO/D/MO/PC COMP/P/110551/07/2025 | C104: =VLOOKUP('IT Working sheet '!B104,'09000210'!B:C,2,0) -> 040000200586 | D104: ="Update ins_assorted_clients set commission_amount = '"&R104&"' where assorted_code = '"&C104&"' and agency_code = '09000870';" -> Update ins_assorted_clients set commission_amount = '1270' where assorted_code = '040000200586' and agency_code = '09000870'; | E104: 45853 | F104: Mr. Shaoor Nafees | G104: 0347-2240087 | H104: BSX-142 | I104: TOYOTA - COROLLA ALTIS 1.5 | J104: 2021 | K104: 4500000 | L104: 83250 | M104: 0.0185 | N104: 45853 | O104: 71337 | P104: 83250 | Q104: 71337 | R104: 1270 | S104: 0 | T104: 09000870/Digital sales - DA | U104: REN | V104: 0 | W104: Moied Shamoon | X104: Comprehensive | Y104: Retail Renewal | Z104: Retail Renewal (July-2025)
...

Sheet 09000210
B1: POLICY | C1: ASSORTED_CODE
A2: 1 | B2: LHR/LHR/D/MO/PC COMP/P/110294/07/2025 | C2: 040000200020
A3: 2 | B3: LHR/LHR/D/MO/PC COMP/P/110296/07/2025 | C3: 040000200023
A4: 3 | B4: KHI/HO/D/MO/PC COMP/P/110297/07/2025 | C4: 040000200024
A5: 4 | B5: LHR/LHR/D/MO/PC COMP/P/110305/07/2025 | C5: 040000200033
A6: 5 | B6: KHI/HO/D/MO/PC COMP/P/110306/07/2025 | C6: 040000200036
A7: 6 | B7: LHR/LHR/D/MO/PC COMP/P/110307/07/2025 | C7: 040000200037
A8: 7 | B8: KHI/HO/D/MO/PC COMP/P/110334/07/2025 | C8: 040000200091
A9: 8 | B9: LHR/LHR/D/MO/PC COMP/P/110335/07/2025 | C9: 040000200092
A10: 9 | B10: KHI/HO/D/MO/PC COMP/P/110336/07/2025 | C10: 040000200103
A11: 10 | B11: LHR/LHR/D/MO/PC COMP/P/110338/07/2025 | C11: 040000200105
A12: 11 | B12: LHR/LHR/D/MO/PC COMP/P/110352/07/2025 | C12: 040000200132
A13: 12 | B13: KHI/HO/D/MO/PC COMP/P/110354/07/2025 | C13: 040000200134
... A51: 50 | B51: KHI/HO/D/MO/PC COMP/P/110563/07/2025 | C51: 040000200601

Sheet Already Marked Digital
B1: POLICY | C1: ASSORTED_CODE | D1: AGENCY_CODE
A2: 1 | B2: KHI/HO/D/MO/PC COMP/P/110301/07/2025 | C2: 040000200029 | D2: 09000870
A3: 2 | B3: KHI/HO/D/MO/PD COMP/P/110344/07/2025 | C3: 040000200115 | D3: 09000870
A4: 3 | B4: KHI/HO/D/MO/PD COMP/P/110345/07/2025 | C4: 040000200116 | D4: 09000870
A5: 4 | B5: KHI/HO/D/MO/PC COMP/P/110348/07/2025 | C5: 040000200128 | D5: 09000870
A6: 5 | B6: KHI/HO/D/MO/PC COMP/P/110425/07/2025 | C6: 040000200340 | D6: 09000870
A7: 6 | B7: KHI/HO/D/MO/PC COMP/P/110427/07/2025 | C7: 040000200342 | D7: 09000870
A8: 7 | B8: KHI/HO/D/MO/PD COMP/P/110437/07/2025 | C8: 040000200392 | D8: 09000870
A9: 8 | B9: KHI/HO/D/MO/PD COMP/P/110472/07/2025 | C9: 040000200444 | D9: 09000870
A10: 9 | B10: KHI/HO/D/MO/PC COMP/P/110479/07/2025 | C10: 040000200471 | D10: 09000870
A11: 10 | B11: KHI/HO/D/MO/PC COMP/P/110497/07/2025 | C11: 040000200500 | D11: 09000870
A12: 11 | B12: KHI/HO/D/MO/PC COMP/P/110499/07/2025 | C12: 040000200504 | D12: 09000870
A13: 12 | B13: KHI/HO/D/MO/PC COMP/P/110507/07/2025 | C13: 040000200513 | D13: 09000870
... A21: 20 | B21: KHI/HO/D/MO/PC COMP/P/110556/07/2025 | C21: 040000200592 | D21: 09000870

Sheet Sheet1
B1: POLICY | C1: ASSORTED_CODE
A2: 1 | B2: KHI/HO/D/MO/PC COMP/P/110080/06/2025 | C2: 040000199699
A3: 2 | B3: KHI/HO/D/MO/PC COMP/P/110121/06/2025 | C3: 040000199767
A4: 3 | B4: KHI/HO/D/MO/PC COMP/P/110075/06/2025 | C4: 040000199691
A5: 4 | B5: KHI/HO/D/MO/PC COMP/P/110334/07/2025 | C5: 040000200091
A6: 5 | B6: KHI/HO/D/MO/PC COMP/P/110132/06/2025 | C6: 040000199795
A7: 6 | B7: KHI/HO/D/MO/PC COMP/P/110164/06/2025 | C7: 040000199833
A8: 7 | B8: KHI/HO/D/MO/PD COMP/P/109863/06/2025 | C8: 040000199386
A9: 8 | B9: KHI/HO/D/MO/PC COMP/P/110002/06/2025 | C9: 040000199602
A10: 9 | B10: KHI/HO/D/MO/PC COMP/P/110060/06/2025 | C10: 040000199666
A11: 10 | B11: KHI/HO/D/MO/MC COMP/P/110077/06/2025 | C11: 040000199694
A12: 11 | B12: LHR/LHR/D/MO/PC COMP/P/109780/06/2025 | C12: 040000199289
A13: 12 | B13: KHI/HO/D/MO/PC COMP/P/109801/06/2025 | C13: 040000199314
... A220: 219 | B220: KHI/HO/D/MO/PC COMP/P/110143/06/2025 | C220: 040000199806
