Workbook

Sheet T-PAK
A1: Sr. | B1: Status | C1: Contract No. | D1: Class Code | E1: Contract Status | F1: Insurance Agency | G1: Dealer Name | H1: App ID | I1: CIF # | J1: Insurance Rate | K1: Profit Rate | L1: ISI Account No. | M1: Customer Name | N1: City | O1: CNIC No. | P1: Home Phone# | Q1: Mobile Number | R1: Business Phone# | S1: Mail Address | T1: Finance Amount | U1: Car Price | V1: Ins. Policy | W1: Ins. Expiry Date | X1: Engine No. | Y1: Chassis No. | Z1: Car Category | AA1: Reg. No. | AB1: Car Name | AC1: Model | AD1: Contract Booking Date | AE1: Contract Value Date | AF1: Contract Maturity Date | AG1: Purchase Order No. | AH1: Tenor#2 | AI1: Tracker Company | AJ1: Tracker Reference Number | AK1: Tracker Installation Date | AL1: Contract No.2 | AM1: Rate | AN1: Sum Insured | AO1: Premium | AP1: OLD Contract Ref | AQ1: Remarks-I | AR1: Remarks-II
A2: 1 | B2: CLOSED | C2: 9976AD1210740004 | D2: 6AD1 | E2: A | F2: T-PAK | G2: TOYOTA LAYALPUR MOTOR | H2: 643165 | I2: 0679228 | J2: 2 | K2: 25.45 | L2: 0679228001 | M2: MURAD SALEEM | N2: Faisalabad | O2: 33102-9076864-7 | P2: 03216664328 | Q2: 03216664328, 03216664328 | R2: 0418860340 | S2: P-4041 MAIN SHEIKHUPURA ROAD HAJI A BAD FAISALABAD PK | T2: 2746100 | U2: 3923000 | V2: 55601/00054/09/2021 | W2: 29-SEP-2022 | X2: Q0352444 | Y2: 7051600 | Z2: NEW | AB2: TOYOTA COROLLA ALTIS GRANDE CVT | AC2: 2021 | AD2: 15-MAR-2021 | AE2: 03-OCT-2021 | AF2: 03-Oct-2024 | AG2: OLAFSD300066742 | AH2: 3 | AI2: ITFT | AJ2: 5442/09/2021/ITFM | AK2: 30-SEP-2021 | AM2: 2% | AN2: 0 | AO2: 0
A3: 2 | B3: CLOSED | C3: 9976AP1222730064 | D3: 6AP1 | E3: A | F3: T-PAK | G3: NEW CAR COMPLEX | H3: 1200610 | I3: 0074972 | J3: 1.75 | K3: 25.2 | L3: 0074972005 | M3: MUSHTAQ HAROON | N3: Karachi | O3: 42201-4972674-3 | P3: 32256416 | Q3: 03002369446 | R3: 35216213 | S3: FLAT NO A 2 SOUTHERN COPERATIVE SOCIETY 106 DEPOT LINE RIZVI SHAHEED ROAD PLOT 106 FIRST FLOOR KARACHI | T3: 1300000 | U3: 2000000 | V3: 63286/00098/09/2022 | W3: 29-SEP-2023 | X3: 13041512 | Y3: 10041514 | Z3: USD | AA3: BMT-564 | AB3: SUZUKI SWIFT A/T NAVIGATION | AC3: 2018 | AD3: 30-SEP-2022 | AE3: 03-OCT-2022 | AF3: 03-Oct-2024 | AG3: OLUKHI300090209 | AH3: 2 | AI3: ITFM | AJ3: 8911/09/2022/ITFM | AK3: 30-SEP-2022 | AM3: 1.75% | AN3: 0 | AO3: 0
A4: 3 | B4: CLOSED | C4: 9976AD1211830084 | D4: 6AD1 | E4: A | F4: T-PAK | G4: KIA CLIFTON | H4: 1091257 | I4: 0462522 | J4: 1.75 | K4: 25.95 | L4: 0462522002 | M4: ANIL KUMAR | N4: Karachi | O4: 42301-1102183-1 | Q4: 03333430536 | R4: 32786657 | S4: KARACHI CHEMIST AND DRUGGIEST SHOP NO 1 SHABAZ PLAZA OPPOSITE CIVIL HOSPITAL BABA E URDU ROAD KARACHI | T4: 3386349 | U4: 5275999 | V4: DIB/T/BT/33727/KHI/0921 | W4: 29-SEP-2022 | X4: 315536 | Y4: 512969 | Z4: NEW | AB4: KIA SPORTAGE AWD | AC4: 2021 | AD4: 02-JUL-2021 | AE4: 03-OCT-2021 | AF4: 03-Oct-2024 | AG4: OLAKHI300070365 | AH4: 3 | AM4: 1.75% | AN4: 0 | AO4: 0
A5: 4 | B5: CLOSED | C5: 9976AP1212740089 | D5: 6AP1 | E5: A | F5: T-PAK | G5: NEW S.S MOTORS | H5: 1099727 | I5: 0361983 | J5: 2 | K5: 25.69 | L5: 0361983002 | M5: ABID ALI | N5: Faisalabad | O5: 33100-6228369-3 | Q5: 03009653100 | S5: HOUSE NO 174 B D-GROUND MOHALA PEOPLES COLONY NO 1 FAISALABAD | T5: 2832500 | U5: 5150000 | V5: 56038/00001/10/2021 | W5: 29-SEP-2022 | X5: G4NALH3413439 | Y5: NNAQL51AZKP304712 | Z5: USD | AA5: ASH-882 | AB5: KIA SPORTAGE FWD | AC5: 2021 | AD5: 01-OCT-2021 | AE5: 03-OCT-2021 | AF5: 03-Oct-2024 | AG5: OLUFSD300074560 | AH5: 3 | AM5: 2% | AN5: 0 | AO5: 0
A6: 5 | B6: CLOSED | C6: 997AAD1202100014 | D6: AAD1 | E6: A | F6: T-PAK | G6: HONDA LYALLPUR | H6: 598281 | I6: 0075974 | J6: 1.5 | K6: 26.78 | L6: 0075974003 | M6: ADNAN ALI | N6: Faisalabad | O6: 33100-7791721-1 | P6: 8733900 | Q6: 03218733900 | S6: H NO P-990 RAJA GHULAM RASOOL NAGAR PEOPLES COLONY NO 2 FAISALABAD | T6: 2837450 | U6: 4053500 | V6: COMP/P/52740/09/2020 | W6: 29-SEP-2021 | X6: R18Z16913639 | Y6: NFBFC6661LR065434 | Z6: NEW | AB6: CIVIC VTI ORIEL P/T | AC6: 2020 | AD6: 28-JUL-2020 | AE6: 03-OCT-2020 | AF6: 03-Oct-2024 | AG6: POAFSD300055961 | AH6: 4 | AI6: ITFM | AJ6: 3117/09/2020/ITFM | AK6: 30-SEP-2020 | AM6: 1.5% | AN6: 0 | AO6: 0
A7: 6 | B7: CLOSED | C7: 9976AP1192730026 | D7: 6AP1 | E7: A | F7: T-PAK | G7: TOYOTA CAPITAL MOTORS | H7: 587018 | I7: 0562911 | J7: 2.5 | K7: 26.7 | L7: 0562911001 | M7: ASIF IQBAL | N7: Islamabad | O7: 61101-1847774-9 | P7: 03425474950 | R7: 0 | S7: H # 385 ST # 17 SECTOR I-10/2 ISLAMABAD PK | T7: 2198570 | U7: 2783000 | V7: 51132/00104/09/2019 | W7: 29-SEP-2020 | X7: Z566768 | Y7: 4192614 | Z7: NEW | AA7: APS-981 | AB7: COROLLA GLI | AC7: 2019 | AD7: 30-SEP-2019 | AE7: 03-OCT-2019 | AF7: 03-Oct-2024 | AG7: PODISD300049568 | AH7: 5 | AI7: ITFM | AJ7: 1824/09/2019/ITFM | AK7: 30-SEP-2019 | AM7: 2.5% | AN7: 0 | AO7: 0
A8: 7 | B8: CLOSED | C8: 9976AD1212120063 | D8: 6AD1 | E8: A | F8: T-PAK | G8: PAK SUZUKI MOTOR CO LTD | H8: 1097432 | I8: 0710135 | J8: 2 | K8: 25.61 | L8: 0710135001 | M8: ABDUL HASEEB AHMED | N8: Lahore | O8: 35202-2877846-9 | P8: 03004236503 | Q8: 03004236503 | R8: 35860721 | S8: 34/B MOH MILITARY ACCOUNTS SOCIETY COLLEGE LAHORE | T8: 915000 | U8: 1830000 | V8: 2524/02640/00133/09/2021 | W8: 29-SEP-2022 | X8: 185135 | Y8: 10085125 | Z8: NEW | AB8: SUZUKI CULTUS VXL EURO II | AC8: 2021 | AD8: 31-JUL-2021 | AE8: 03-OCT-2021 | AF8: 03-Oct-2024 | AG8: OLALHR300071392 | AH8: 3 | AI8: ITECL | AJ8: 5480/09/2021 | AK8: 30-SEP-2021 | AM8: 2% | AN8: 0 | AO8: 0
A9: 8 | B9: CLOSED | C9: 9976AD1210300090 | D9: 6AD1 | E9: A | F9: T-PAK | G9: CHANGAN AL NOOR MOTORS | H9: 637252 | I9: 0669115 | J9: 2 | K9: 25.45 | L9: 0669115001 | M9: FARMAN IDREES | N9: Faisalabad | O9: 33100-0715241-7 | P9: 03017051197 | Q9: 03017051197, 03017051197 | R9: 03017051197 | S9: H NO P-791 ST NO 06 NEW GARDEN TOWN MILLAT ROAD FAISALABAD PK | T9: 1077300 | U9: 1539000 | V9: 2021-09-205-V01501DP0002198 | W9: 28-SEP-2022 | X9: 504293 | Y9: 1008681 | Z9: NEW | AB9: CHANGAN KARVAAN PLUS | AC9: 2021 | AD9: 30-JAN-2021 | AE9: 11-OCT-2021 | AF9: 11-Oct-2024 | AG9: OLAFSD300064649 | AH9: 3 | AI9: ITFM | AJ9: 5453/09/2021 | AK9: 29-SEP-2021 | AM9: 2% | AN9: 0 | AO9: 0
A10: 9 | B10: CLOSED | C10: 9976AD1211670013 | D10: 6AD1 | E10: A | F10: T-PAK | G10: PRINCE PUNJAB MOTORS | H10: 1097740 | I10: 0264812 | J10: 1.5 | K10: 25.56 | L10: 0264812002 | M10: MUKHTAR AHMAD | N10: Faisalabad | O10: 33100-8231808-5 | Q10: 03009661442 | R10: 0412600992 | S10: ALIYAAN FABRICS SHOP NO 27 NEAR ANAYAT CLOTH MARKET RAIL BAZAR FAISALABAD 03009661442 | T10: 3200300 | U10: 4610000 | V10: 55601/00081/09/2021 | W10: 27-SEP-2022 | X10: SFG15T-2101391 | Y10: PDF580PALR21H1791 | Z10: NEW | AB10: PRINCE GLORY 580 PRO | AC10: 2021 | AD10: 16-JUN-2021 | AE10: 03-OCT-2021 | AF10: 03-Oct-2024 | AG10: OLAFSD300069478 | AH10: 3 | AI10: CTRK | AJ10: DIB0031802 | AK10: 28-SEP-2021 | AM10: 1.5% | AN10: 0 | AO10: 0
A11: 10 | B11: CLOSED | C11: 9976AD2212420005 | D11: 6AD2 | E11: A | F11: T-PAK | G11: TOYOTA CENTRAL MOTORS | H11: 1105528 | I11: 0717785 | J11: 2 | K11: 26.2 | L11: 0717785001 | M11: KULSOOM RAUF | N11: Karachi | O11: 42201-6322286-6 | P11: 03212888320 | Q11: 03212888320 | R11: 02134328787 | S11: A- 15 KDA SCH 1 EXT PIR PAGARA HOUS E KARACHI PK | T11: 2954600 | U11: 7386500 | V11: 2021/09/CLFTTPCDP01050 | W11: 27-SEP-2022 | X11: 1GD5058617 | Y11: GUN126R-5548153 | Z11: NEW | AB11: TOYOTA HILUX REVO V DC | AC11: 2021 | AD11: 30-AUG-2021 | AE11: 03-OCT-2021 | AF11: 03-Oct-2024 | AG11: OLAKHI300072646 | AH11: 3 | AI11: CTRK | AJ11: DIB0031835 | AK11: 24-SEP-2021 | AM11: 2% | AN11: 0 | AO11: 0
A12: 11 | B12: CLOSED | C12: 9976AD2212120055 | D12: 6AD2 | E12: A | F12: T-PAK | G12: SUZUKI ISLAMABAD MOTORS | H12: 639476 | I12: 0534737 | J12: 2 | K12: 26.11 | L12: 0534737003 | M12: ZEESHAN AHMED | N12: Rawalpindi | O12: 37405-3410919-5 | P12: 03365251627 | R12: 0512801311 | S12: H # BII 265 ST # 09 MUSLIM TOWN RAWALPINDI | T12: 1324000 | U12: 1655000 | V12: 01-2109-PO-MTR-PCCM-D001335 | W12: 27-SEP-2022 | X12: 186242 | Y12: 10086241 | Z12: NEW | AB12: CULTUS VXR EURO-II | AC12: 2021 | AD12: 31-JUL-2021 | AE12: 11-OCT-2021 | AF12: 11-Oct-2024 | AG12: OLARWP300071598 | AH12: 3 | AI12: ITECL | AJ12: 5472/09/2021 | AK12: 28-SEP-2021 | AM12: 2% | AN12: 0 | AO12: 0
A13: 12 | B13: CLOSED | C13: 9976AP2192730005 | D13: 6AP2 | E13: A | F13: T-PAK | G13: SUZUKI MUZAFARABAD MOTOR | H13: 602999 | I13: 0561735 | J13: 2.5 | K13: 25.2 | L13: 0561735001 | M13: SHAHID IFTIKHAR | N13: Islamabad | O13: 61101-4610207-1 | P13: 03135257237 | R13: 0514100311 | S13: H # 86 MAIN STREET ISLAMABAD HOMES PHASE-2 JHANGI SYEDAN NEAR MOTORWAY ISLAMABAD PK | T13: 1003100 | U13: 1433000 | V13: 51132/00084/09/2019 | W13: 27-SEP-2020 | X13: 110794 | Y13: 1010754 | Z13: NEW | AA13: ANZ-539 | AB13: ALTO VXL AGS EURO-II | AC13: 2019 | AD13: 30-SEP-2019 | AE13: 03-OCT-2019 | AF13: 03-Oct-2024 | AG13: PODISD300049427 | AH13: 5 | AI13: ITFM | AJ13: 1796/09/2019/ITFM | AK13: 28-SEP-2019 | AM13: 2.5% | AN13: 0 | AO13: 0
A14: 13 | B14: CLOSED | C14: 9976AP1212720027 | D14: 6AP1 | E14: A | F14: T-PAK | G14: SHAHNAWAZ PVT LTD | H14: 1102777 | I14: 0198992 | J14: 2 | K14: 25.69 | L14: 0198992003 | M14: MIAN HUMAYUN HASSAN | N14: Karachi | O14: 42201-9223228-5 | Q14: 03212447500 | R14: 0412612045 | S14: K A ENTERPRISES PVT LTD OFFICE NO 206 2ND FLOOR GUL TOWER II CHUNDRIGAR ROAD KARACHI | T14: 6925000 | U14: 13850000 | V14: 55601/00103/09/2021 | W14: 26-SEP-2022 | X14: 282914-80-613133 | Y14: W1K-177187-25-311776 | Z14: NEW | AB14: MERCEDES CLA 200 | AC14: 2021 | AD14: 29-SEP-2021 | AE14: 03-OCT-2021 | AF14: 03-Oct-2024 | AG14: OLDKHI300074131 | AH14: 3 | AM14: 2% | AN14: 0 | AO14: 0
A15: 14 | B15: CLOSED | C15: 9976AD2212250017 | D15: 6AD2 | E15: A | F15: T-PAK | G15: TOYOTA SOUTHERN MOTORS | H15: 1108028 | I15: 0127265 | J15: 2 | K15: 26.06 | L15: 0127265020 | M15: MUHAMMAD ALI SHAHZADA | N15: Karachi | O15: 42201-5958122-7 | P15: 34523930 | Q15: 03008278770 | R15: 356670609 35662609 | S15: H# R-87 ST# 20 KHAYABAN-E-ROOMI PHASE-8 NEAR KHAYABAN-E-TARIQ KARACHI | T15: 2006250 | U15: 2675000 | V15: 2524/02640/00113/09/2021 | W15: 26-SEP-2022 | X15: 2A36510 | Y15: 7022861 | Z15: NEW | AB15: TOYOTA YARIS ATIV CVT 1.3 | AC15: 2021 | AD15: 13-AUG-2021 | AE15: 03-OCT-2021 | AF15: 03-Oct-2024 | AG15: OLAKHI300071930 | AH15: 3 | AI15: ITECL | AJ15: 5441/09/2021 | AK15: 16-SEP-2021 | AM15: 2% | AN15: 0 | AO15: 0
A16: 15 | B16: CLOSED | C16: 9976AD1211790005 | D16: 6AD1 | E16: A | F16: T-PAK | G16: PAK SUZUKI MOTOR CO LTD | H16: 638979 | I16: 0545421 | J16: 2 | K16: 25.55 | L16: 0545421002 | M16: MUHAMMAD ZEESHAN HAMEED | N16: Lahore | O16: 33303-3677318-3 | Q16: 03312328682 | S16: HOUSE NO 87 MAIN STREET, ARSLAN TOWN MULTAN, MULTAN.0331-2328682 MULTAN | T16: 1704000 | U16: 2130000 | V16: 2021-09-205-V015010P0002294 | W16: 26-SEP-2022 | X16: 183379 | Y16: 10083374 | Z16: NEW | AB16: SUZUKI CULTUS VXL | AC16: 2021 | AD16: 28-JUN-2021 | AE16: 03-OCT-2021 | AF16: 03-Oct-2024 | AG16: OLALHR300069975 | AH16: 3 | AI16: CTRK | AJ16: DIB0031892 | AK16: 28-SEP-2021 | AM16: 2% | AN16: 0 | AO16: 0
A17: 16 | B17: CLOSED | C17: 9976AD2192120019 | D17: 6AD2 | E17: A | F17: T-PAK | G17: KIA MOTORS CANAL ROAD | H17: 594274 | I17: 0185121 | J17: 2.5 | K17: 26.2 | L17: 0185121003 | M17: FARAN AHMED | N17: Faisalabad | O17: 33100-1356810-7 | P17: 0333-6633311 | Q17: 03336633311 | R17: 041-8547511 | S17: H NO P-101 1ST FLOOR SHADMAN COLONY PEOPLES COLONY NO 1 NEAR ABU BAKAR MASJID FAISALABAD | T17: 2999400 | U17: 4999000 | V17: 51132/00065/09/2019 | W17: 24-SEP-2020 | X17: KH025588 | Y17: KP500548 | Z17: NEW | AA17: APJ-811 | AB17: KIA SPORTAGE | AC17: 2019 | AD17: 31-JUL-2019 | AE17: 03-OCT-2019 | AF17: 03-Oct-2024 | AG17: POAFSD300048094 | AH17: 5 | AI17: ITFM | AM17: 2.5% | AN17: 0 | AO17: 0
A18: 17 | B18: CLOSED | C18: 9976AD1210700029 | D18: 6AD1 | E18: A | F18: T-PAK | G18: TOYOTA AIRPORT MOTOR | H18: 654464 | I18: 0678803 | J18: 2 | K18: 25.45 | L18: 0678803001 | M18: SHAHID ALI | N18: Lahore | O18: 35201-6724429-1 | P18: 03214269841 | Q18: 03214269841 | R18: 03214269841 | S18: STREET NO 18 DILSHAD STREET SHALAMA R TOWN LAHORE | T18: 2041800 | U18: 3403000 | V18: DIB/T/BT/33692/0921 | W18: 23-SEP-2022 | X18: Q080853 | Y18: 6058309 | Z18: NEW | AB18: TOYOTA COROLLA ALTIS A/T | AC18: 2021 | AD18: 11-MAR-2021 | AE18: 03-OCT-2021 | AF18: 03-Oct-2024 | AG18: OLALHR300066679 | AH18: 3 | AI18: CTRK | AJ18: TDIDIB0029647 | AK18: 24-SEP-2021 | AM18: 2% | AN18: 0 | AO18: 0
A19: 18 | B19: CLOSED | C19: 9976AD2212500002 | D19: 6AD2 | E19: A | F19: T-PAK | G19: HYUNDAI D GROUND MOTORS | H19: 1103498 | I19: 0339233 | J19: 2 | K19: 26.19 | L19: 0339233005 | M19: MUHAMMAD ATTIQUE UR REHMAN | N19: Faisalabad | O19: 33100-2350567-5 | P19: 0418717495 | Q19: 03217835276 | R19: 2647349 | S19: H NO P-488 STREET NO 6 SARFRAZ COLONY FAISALABAD | T19: 2927250 | U19: 3903000 | V19: 2021-09-205-V01501OP0002187 | W19: 22-SEP-2022 | X19: G4NAMU877378 | Y19: PMHD841FMMN301545 | Z19: NEW | AB19: HYUNDAI ELANTRA | AC19: 2021 | AD19: 07-SEP-2021 | AE19: 27-SEP-2021 | AF19: 27-Sep-2024 | AG19: OLAFSD300073136 | AH19: 3 | AI19: CTRK | AJ19: DIB0031766 | AK19: 23-SEP-2021 | AM19: 2% | AN19: 0 | AO19: 0
A20: 19 | B20: CLOSED | C20: 9976AD1211730019 | D20: 6AD1 | E20: A | F20: T-PAK | G20: PAK SUZUKI MOTOR CO LTD | H20: 1097822 | I20: 0701206 | J20: 2 | K20: 25.56 | L20: 0701206001 | M20: NAJMA BEGUM | N20: Faisalabad | O20: 33100-0660926-0 | P20: 03007623818 | Q20: 03007623818, 03007623818 | R20: 03007623818 | S20: P- 528 ST NO 10 NAIMAT COLONY 1 FAISALABAD PK | T20: 993000 | U20: 1655000 | V20: 2021/09/CLFTTPCDP01011 | W20: 22-SEP-2022 | X20: 184610 | Y20: 10084587 | Z20: NEW | AB20: SUZUKI CULTUS VXR EURO II | AC20: 2021 | AD20: 22-JUN-2021 | AE20: 03-OCT-2021 | AF20: 03-Oct-2024 | AG20: OLAFSD300069682 | AH20: 3 | AI20: CTRK | AJ20: DIB0031656 | AK20: 23-SEP-2021 | AM20: 2% | AN20: 0 | AO20: 0
A21: 20 | B21: CLOSED | C21: 9976AP1232690003 | D21: 6AP1 | E21: A | F21: T-PAK | G21: MASTER MOTORS | H21: 23208170408861 | I21: 0618569 | J21: 1.4 | K21: 22.69 | L21: 0618569005 | M21: MOHAMMAD QASIM FAROOQI | N21: Lahore | O21: 61101-9156805-3 | P21: 03354552446 | Q21: 00971502319295 | R21: 0 | S21: VILLA 57 STREET 6C AL SATWA DUBAI UNITED ARAB EMIRATES | T21: 3720000 | U21: 4960000 | V21: 74853/00026/09/2023 | W21: 21-SEP-2024 | X21: 1016642 | Y21: 116646 | Z21: RDA | AB21: SUZUKI SWIFT GLX | AC21: 2023 | AD21: 45195 | AE21: 27-SEP-2023 | AF21: 27-Sep-2024 | AG21: OLDLHR300097243 | AH21: 1 | AI21: CTRK | AJ21: DIB0035322 | AK21: 25-SEP-2023 | AM21: 1.4% | AN21: 0 | AO21: 0
A22: 21 | B22: CLOSED | C22: 9976AD1211380004 | D22: 6AD1 | E22: A | F22: T-PAK | G22: KIA MOTORS MARSHALS | H22: 526643 | I22: 0688678 | J22: 1.75 | K22: 26.21 | L22: 0688678001 | M22: FIDA MUHAMMAD | N22: Islamabad | O22: 17301-1523055-9 | P22: 0512728354 | R22: 03429090337 | S22: UNDP (IFAD) LEVEL II SERENA BUSINES S COMPLEX SECTOR G-5 ISLAMABAD | T22: 4074750 | U22: 5433000 | V22: 2021/09/CLFTTPCDPO1029 | W22: 21-SEP-2022 | X22: 314372 | Y22: 512829 | Z22: NEW | AB22: SPORTAGE AWD | AC22: 2021 | AD22: 18-MAY-2021 | AE22: 03-OCT-2021 | AF22: 03-Oct-2024 | AG22: OLAISD300068749 | AH22: 3 | AM22: 1.75% | AN22: 0 | AO22: 0
A23: 22 | B23: CLOSED | C23: 9976AD1212560018 | D23: 6AD1 | E23: A | F23: T-PAK | G23: HYUNDAI D GROUND MOTORS | H23: 1100503 | I23: 0547484 | J23: 2 | K23: 25.68 | L23: 0547484003 | M23: NUMAN AFZAL | N23: Faisalabad | O23: 33102-1783712-5 | P23: 03018661999 | Q23: 03018661999, 03018661999 | R23: 0418724999 | S23: P-136-B LIAQUAT TOWN JHANG ROAD FS D FAISALABAD PK | T23: 1949500 | U23: 3899000 | V23: 2021-09-205-V01501OP0002195 | W23: 21-SEP-2022 | X23: G4NAM877342 | Y23: PMHD841FMMN301680 | Z23: NEW | AB23: HYUNDAI ELANTRA | AC23: 2021 | AD23: 13-SEP-2021 | AE23: 27-SEP-2021 | AF23: 27-Sep-2024 | AG23: OLAFSD300073444 | AH23: 3 | AI23: CTRK | AJ23: DIB0031790 | AK23: 22-SEP-2021 | AM23: 2% | AN23: 0 | AO23: 0
A24: 23 | B24: CLOSED | C24: 9976AD2212090010 | D24: 6AD2 | E24: A | F24: T-PAK | G24: SUZUKI RACECOURSE MOTORS | H24: 635669 | I24: 0704288 | J24: 2 | K24: 26.06 | L24: 0704288001 | M24: AAMER SHAHZAD | N24: Rawalpindi | O24: 13302-4178537-5 | P24: 03146262797 | R24: 0512724178 | S24: FLAT # 6 4TH FLOOR PLAZA # 14 CIVI C CENTRE BAHRIA TOWN PHASE 4 RAWALPINDI PK | T24: 1464000 | U24: 1830000 | V24: PL-0921-1101010102-V14-D-00435 | W24: 21-SEP-2022 | X24: 185155 | Y24: 10085145 | Z24: NEW | AB24: CULTUS VXL EURO-II | AC24: 2021 | AD24: 28-JUL-2021 | AE24: 03-OCT-2021 | AF24: 03-Oct-2024 | AG24: OLARWP300071014 | AH24: 3 | AI24: CTRK | AJ24: DIB0031789 | AK24: 23-SEP-2021 | AM24: 2% | AN24: 0 | AO24: 0
A25: 24 | B25: CLOSED | C25: 9976AP1172690005 | D25: 6AP1 | E25: A | F25: T-PAK | G25: NEW CAR COMPLEX | H25: 403169 | I25: 0421008 | J25: 3.2 | K25: 27.69 | L25: 0421008002 | M25: SAJJAD HAIDER | N25: Karachi | O25: 42201-0702394-3 | Q25: 03002115346 | S25: FLAT NO E01, GROUND FLOOR SAIMA HEAVEN , GULSHAN E IQBAL BLOCK 4 KARACHI PK | T25: 855000 | U25: 1140000 | V25: DIB/T/17887/KHI/0917 | W25: 21-SEP-2018 | X25: 13019609 | Y25: 10019608 | Z25: USD | AA25: AZR-987 | AB25: SWIFT DLX ABS WITH EBD | AC25: 2013 | AD25: 26-SEP-2017 | AE25: 27-SEP-2017 | AF25: 27-Sep-2024 | AG25: POUKHI300025782 | AH25: 7 | AI25: FLCN | AJ25: 13250/09/2017 | AK25: 23-SEP-2017 | AM25: 3.2% | AN25: 0 | AO25: 0
A26: 25 | B26: CLOSED | C26: 9976AP1222640006 | D26: 6AP1 | E26: A | F26: T-PAK | G26: FAROOQ MOTORS | H26: 1150447 | I26: 0295543 | J26: 1.75 | K26: 25.19 | L26: 0295543003 | M26: MUZAMAL ALI | N26: Lahore | O26: 35202-1486167-9 | Q26: 03204496693 | R26: 04235774125 | S26: H NO.190/D-2 GULSHAN E RAVI NEAR LAHORE PUBLIC SCHOOL LAHORE | T26: 1470000 | U26: 2100000 | V26: 63286/00047/09/2022 | W26: 20-SEP-2023 | X26: 6R210377 | Y26: 1110453 | Z26: USD | AA26: AJA-183 | AB26: SUZUKI ALTO VXL AGS EURO-II | AC26: 2022 | AD26: 21-SEP-2022 | AE26: 21-SEP-2022 | AF26: 21-Sep-2024 | AG26: OLULHR300089914 | AH26: 2 | AI26: ITFM | AJ26: 8712/09/2022/ITFM | AK26: 21-SEP-2022 | AM26: 1.75% | AN26: 0 | AO26: 0
A27: 26 | B27: CLOSED | C27: 9976AP2192660005 | D27: 6AP2 | E27: A | F27: T-PAK | G27: NEW S.S MOTORS | H27: 591073 | I27: 0560406 | J27: 2.5 | K27: 29.44 | L27: 0560406001 | M27: KHURAM ZIA | N27: Faisalabad | O27: 33100-6507523-5 | P27: 03216611003 | Q27: 03216611003, 03216611003 | R27: 0419200183 | S27: P-70 ST NO 01 EAST CANAL ROAD RAZA TOWN FSD FAISALABAD PK | T27: 1820000 | U27: 2600000 | V27: 51132/00045/09/2019 | W27: 20-SEP-2020 | X27: 1NZ-7995674 | Y27: NHP10-2558682 | Z27: RCN | AA27: APG-630 | AB27: AQUA | AC27: 2016 | AD27: 23-SEP-2019 | AE27: 21-SEP-2019 | AF27: 21-Sep-2024 | AG27: POUFSD300049274 | AH27: 5 | AI27: CTRK | AJ27: DIB0027845 | AK27: 21-SEP-2019 | AM27: 2.5% | AN27: 0 | AO27: 0
A28: 27 | B28: CLOSED | C28: 9976AP1222650011 | D28: 6AP1 | E28: A | F28: T-PAK | G28: NEW CAR COMPLEX | H28: 1197710 | I28: 0801675 | J28: 1.5 | K28: 26.19 | L28: 0801675001 | M28: ASIM MIRZA | N28: Karachi | O28: 42301-0262971-9 | P28: 03133803682 | Q28: 03133803682 | R28: 0 | S28: 402 FLAT 04 FLOOR CITY VIEW APPARTM ENT SADDAR KHI NEAR NMI HOSPITAL KARACHI PK | T28: 2968000 | U28: 5600000 | V28: 63286/00045/09/2022 | W28: 19-SEP-2023 | X28: 312210 | Y28: 302280 | Z28: USD | AA28: BH-6588 | AB28: KIA SPORTAGE FWD | AC28: 2020 | AD28: 22-SEP-2022 | AE28: 27-SEP-2022 | AF28: 27-Sep-2024 | AG28: OLUKHI300089980 | AH28: 2 | AI28: ITFM | AJ28: 8720/09/2022/ITFM | AK28: 21-SEP-2022 | AM28: 1.5% | AN28: 0 | AO28: 0
A29: 28 | B29: CLOSED | C29: 9976AD1210460011 | D29: 6AD1 | E29: A | F29: T-PAK | G29: JW SEZ (PVT) LTD | H29: 627518 | I29: 0671787 | J29: 1.75 | K29: 25.94 | L29: 0671787001 | M29: IMRAN SAJID | N29: Gujranwala | O29: 34101-6864800-1 | P29: 03228624200 | Q29: 03228624200 | R29: 03228624200 | S29: NEAR 132 KV GRID STATION CHANWALI G T ROAD GUJRANWALA | T29: 3814300 | U29: 5449000 | V29: 17578/00039/09/2021 | W29: 19-SEP-2022 | X29: 5MGM5180052 | Y29: MN093965 | Z29: NEW | AB29: MG HS TURBO | AC29: 2021 | AD29: 15-FEB-2021 | AE29: 27-SEP-2021 | AF29: 27-Sep-2024 | AG29: OLAGWL300065808 | AH29: 3 | AI29: CTRK | AJ29: TDIDIB0029545 | AK29: 28-AUG-2021 | AM29: 1.75% | AN29: 0 | AO29: 0
A30: 29 | B30: CLOSED | C30: 9976AD1210760016 | D30: 6AD1 | E30: A | F30: T-PAK | G30: JW SEZ (PVT) LTD | H30: 627595 | I30: 0680554 | J30: 1.75 | K30: 25.94 | L30: 0680554001 | M30: REHMAN UL HAQ | N30: Gujrat | O30: 34201-1842388-7 | P30: 03040554133 | Q30: 03040554133 | R30: 03040554133 | S30: OPP. ANMOL MARRIAGE HALL GT ROAD GUJRAT | T30: 3432870 | U30: 5449000 | V30: DIB/T/BT/33669/FSD/0921 | W30: 19-SEP-2022 | X30: MSM3080220 | Y30: LSJA24U93MN060005 | Z30: NEW | AB30: MG HS TURBO | AC30: 2021 | AD30: 17-MAR-2021 | AE30: 21-SEP-2021 | AF30: 21-Sep-2024 | AG30: OLAGJR300066793 | AH30: 3 | AI30: CTRK | AJ30: TDIDIB0029567 | AK30: 26-AUG-2021 | AM30: 1.75% | AN30: 0 | AO30: 0
A31: 30 | B31: CLOSED | C31: 9976AP2192660006 | D31: 6AP2 | E31: A | F31: T-PAK | G31: CAR CAPITAL | H31: 532106 | I31: 0559435 | J31: 2.5 | K31: 29.19 | L31: 0559435001 | M31: NAZISH FATIMA | N31: Karachi | O31: 42101-2290780-6 | P31: 03332301275 | Q31: 03332301275 | R31: 037130068 | S31: H.NO 148 BANGLOW TOWN TIPU SULTAN R OAD KCHS NEAR MACCA MASJID KARACHI PK | T31: 1200000 | U31: 1500000 | V31: 51132/00037/09/2019 | W31: 18-SEP-2020 | X31: 7423533 | Y31: 160728 | Z31: USD | AA31: BCX-524 | AB31: HONDA CITY M/T | AC31: 2015 | AD31: 23-SEP-2019 | AE31: 21-SEP-2019 | AF31: 21-Sep-2024 | AG31: POUKHI300049222 | AH31: 5 | AI31: ITFM | AJ31: 1765/09/2019/ITFM | AK31: 20-SEP-2019 | AM31: 2.5% | AN31: 0 | AO31: 0
A32: 31 | B32: CLOSED | C32: 9976AP1192660011 | D32: 6AP1 | E32: A | F32: T-PAK | G32: MINI MOTORS | H32: 589261 | I32: 0560108 | J32: 2.5 | K32: 25.19 | L32: 0560108001 | M32: MUHAMMAD ADREES | N32: Lahore | O32: 35202-8119531-3 | P32: 03127241094 | Q32: 03024719541, 03127241094 | R32: 03127241094 | S32: 47 MIAN BAZAR GAWALMANDI LAHORE | T32: 1137500 | U32: 1625000 | V32: 51132/00038/09/2019 | W32: 18-SEP-2020 | X32: 200197 | Y32: 10100189 | Z32: NEW | AA32: LE-19A-4552 | AB32: SUZUKI WAGONR VXL | AC32: 2019 | AD32: 23-SEP-2019 | AE32: 21-SEP-2019 | AF32: 21-Sep-2024 | AG32: PODLHR300049226 | AH32: 5 | AI32: CTRK | AJ32: DIB0027837 | AK32: 19-SEP-2019 | AM32: 2.5% | AN32: 0 | AO32: 0
A33: 32 | B33: CLOSED | C33: 9976AD2171180004 | D33: 6AD2 | E33: A | F33: T-PAK | G33: PAK SUZUKI MOTOR CO LTD | H33: 326088 | I33: 0405406 | J33: 3.1 | K33: 24.03 | L33: 0405406001 | M33: ATIF IQBAL | N33: Karachi | O33: 42201-0495130-1 | P33: N/A | Q33: 03405558394 | R33: 04685383 | S33: H#A39 1ST FLOOR GULSHAN E FATIMA KEHKASHAN SOCIETY MALIR HALT NEAR BISMILLAH BAKERY AFZAL HOTEL KARACHI | T33: 790500 | U33: 1054000 | V33: DIB/T/17847/KHI/0917 | W33: 18-SEP-2018 | X33: 139186 | Y33: 10039177 | Z33: NEW | AA33: BKJ-413 | AB33: WAGONR VXR | AC33: 2017 | AD33: 28-APR-2017 | AE33: 27-SEP-2017 | AF33: 27-Sep-2024 | AG33: POAKHI300021482 | AH33: 7 | AI33: CTRK | AJ33: TDIDIB0021047 | AK33: 11-SEP-2017 | AM33: 3.1% | AN33: 0 | AO33: 0
A34: 33 | B34: CLOSED | C34: 9976AP1212700025 | D34: 6AP1 | E34: A | F34: T-PAK | G34: FAROOQ MOTORS | H34: 1104880 | I34: 0719635 | J34: 2 | K34: 25.54 | L34: 0719635001 | M34: ADNAN SHAHZAD | N34: Lahore | O34: 35202-8493779-1 | P34: 03334286567 | Q34: 03334286567 | R34: 03334286567 | S34: KABIR STREET NO 2 URDU BAZAR LAHORE | T34: 1516500 | U34: 3033000 | V34: 55601/00062/09/2021 | W34: 16-SEP-2022 | X34: 2A30426 | Y34: NSP151R-9511635 | Z34: NEW | AB34: YARIS ATIV X CVT 1.5 | AC34: 2021 | AD34: 27-SEP-2021 | AE34: 27-SEP-2021 | AF34: 27-Sep-2024 | AG34: OLDLHR300073646 | AH34: 3 | AI34: CTRK | AJ34: DIB0031741 | AK34: 20-SEP-2021 | AM34: 2% | AN34: 0 | AO34: 0
A35: 34 | B35: CLOSED | C35: 9976AD1211970005 | D35: 6AD1 | E35: A | F35: T-PAK | G35: PAK SUZUKI MOTOR CO LTD | H35: 1098924 | I35: 0431603 | J35: 2 | K35: 25.6 | L35: 0431603003 | M35: MUHAMMAD IRFAN | N35: Faisalabad | O35: 33100-6988210-3 | P35: 03217843232 | Q35: 03217843232 | R35: 03217843232 | S35: P-28 BLOCK X ST NO 12 MADINA TOWN M USTFAI MASJID FAISALABAD PK | T35: 1372500 | U35: 1830000 | V35: DIB/T/BT/33652/LHR/0921 | W35: 15-SEP-2022 | X35: 185102 | Y35: 10085105 | Z35: NEW | AB35: SUZUKI CULTUS VXL EURO-II | AC35: 2021 | AD35: 16-JUL-2021 | AE35: 27-SEP-2021 | AF35: 27-Sep-2024 | AG35: OLAFSD300070802 | AH35: 3 | AI35: CTRK | AJ35: DIB0031709 | AK35: 16-SEP-2021 | AM35: 2% | AN35: 0 | AO35: 0
A36: 35 | B36: CLOSED | C36: 9976AD1211790003 | D36: 6AD1 | E36: A | F36: T-PAK | G36: KIA CLIFTON | H36: 575336 | I36: 0703739 | J36: 1.75 | K36: 25.94 | L36: 0703739001 | M36: KHURRAM | N36: Karachi | O36: 42301-0987315-5 | P36: 03222383101 | Q36: 03222383101 | R36: 0 | S36: MADINA HEIGHTS DHELI COLONY FLAT # 104 GALI # zero line clifotn near a KARACHI PK | T36: 3509350 | U36: 5399000 | V36: 2524/02640/00062/09/2021 | W36: 15-SEP-2022 | X36: G4NAMH313747 | Y36: NNAQL51AZKP513013 | Z36: NEW | AB36: KIA SPORTGE | AC36: 2021 | AD36: 28-JUN-2021 | AE36: 21-SEP-2021 | AF36: 21-Sep-2024 | AG36: OLAKHI300070009 | AH36: 3 | AM36: 1.75% | AN36: 0 | AO36: 0
A37: 36 | B37: CLOSED | C37: 9976AP1212650005 | D37: 6AP1 | E37: A | F37: T-PAK | G37: MUAZ MOTORS | H37: 1107932 | I37: 0720281 | J37: 1.75 | K37: 25.54 | L37: 0720281001 | M37: SHABNAM NIAZ | N37: Lahore | O37: 35202-2583875-4 | P37: 03344113234 | Q37: 03344113234 | R37: 03344113234 | S37: LAHORE COLLEGE FOR WOMEN UNIVERSITY JAIL ROAD LAHORE | T37: 1305500 | U37: 1865000 | V37: 55601/00056/09/2021 | W37: 15-SEP-2022 | X37: R06A-1857217 | Y37: DA17V-808397 | Z37: RCN | AB37: SUZUKI EVERY | AC37: 2016 | AD37: 22-SEP-2021 | AE37: 21-SEP-2021 | AF37: 21-Sep-2024 | AG37: OLULHR300073634 | AH37: 3 | AI37: CTRK | AJ37: DIB0031725 | AK37: 17-SEP-2021 | AM37: 1.75% | AN37: 0 | AO37: 0
A38: 37 | B38: CLOSED | C38: 9976AD1211120026 | D38: 6AD1 | E38: A | F38: T-PAK | G38: PRINCE PUNJAB MOTORS | H38: 643102 | I38: 0622692 | J38: 2 | K38: 25.45 | L38: 0622692003 | M38: MUHAMMAD SHAKIR | N38: Faisalabad | O38: 33100-0897584-5 | P38: 03007654806 | Q38: 03007654806, 03007654806 | R38: 2652220 | S38: H NO266 ST NO 14 AYUB COLONY JHANG ROAD FSD NEAR FAISAL BAKERY Faisalabad PK | T38: 712725 | U38: 1096500 | V38: 55601/00029/09/2021 | W38: 15-SEP-2022 | X38: M04603857W | Y38: RAILPPM21G02736 | Z38: NEW | AB38: PRINCE PEARL | AC38: 2021 | AD38: 22-APR-2021 | AE38: 03-OCT-2021 | AF38: 03-Oct-2024 | AG38: OLAFSD300068015 | AH38: 3 | AI38: CTRK | AJ38: DIB0031637 | AK38: 16-SEP-2021 | AM38: 2% | AN38: 0 | AO38: 0
A39: 38 | B39: CLOSED | C39: 9976AD1211960006 | D39: 6AD1 | E39: A | F39: T-PAK | G39: PAK SUZUKI MOTOR CO LTD | H39: 1098985 | I39: 0472807 | J39: 2 | K39: 25.55 | L39: 0472807004 | M39: MUHAMMAD TARIQ | N39: Faisalabad | O39: 90403-0108361-7 | P39: 03007204256 | Q39: 03007204256, 03007204256, 03411076986 | R39: 03007204256 | S39: 975-C QASIM PARK PEOPLES COLONY NO2 FAISALABAD | T39: 1555500 | U39: 1830000 | V39: 2021/09/CLFTTPCDP01002 | W39: 14-SEP-2022 | X39: 183231 | Y39: 10083200 | Z39: NEW | AB39: CULTUS VXL EURO II | AC39: 2021 | AD39: 15-JUL-2021 | AE39: 27-SEP-2021 | AF39: 27-Sep-2024 | AG39: OLAFSD300070688 | AH39: 3 | AI39: CTRK | AJ39: DIB0031629 | AK39: 15-SEP-2021 | AM39: 2% | AN39: 0 | AO39: 0
A40: 39 | B40: CLOSED | C40: 9976AD2212430057 | D40: 6AD2 | E40: A | F40: T-PAK | G40: PAK SUZUKI MOTOR CO LTD | H40: 6277755 | I40: 0718426 | J40: 2 | K40: 26.2 | L40: 0718426001 | M40: BILAL IQBAL | N40: Bahawalpur | O40: 31202-4467991-1 | P40: 03123456735 | Q40: 03123456735 | R40: 03123456735 | S40: H NO 269 BHATTA NO 01 GULBERG ROAD BAHAWALPUR PK | T40: 801000 | U40: 1335000 | V40: 2021-09-CLFTTPCDP01013 | W40: 13-SEP-2022 | X40: 6R183003 | Y40: H1082988 | Z40: NEW | AB40: SUZUKI ALTO VXR EURO II | AC40: 2021 | AD40: 31-AUG-2021 | AE40: 03-OCT-2021 | AF40: 03-Oct-2024 | AG40: OLABHP300072888 | AH40: 3 | AI40: ITECL | AJ40: 5430/09/2021 | AK40: 14-SEP-2021 | AM40: 2% | AN40: 0 | AO40: 0
A41: 40 | B41: CLOSED | C41: 9976AD1210780035 | D41: 6AD1 | E41: A | F41: T-PAK | G41: TOYOTA LAYALPUR MOTOR | H41: 631027 | I41: 0680473 | J41: 2 | K41: 25.55 | L41: 0680473001 | M41: HAFIZ NISAR AHMED | N41: Faisalabad | O41: 33100-8282363-1 | P41: 0418816509 | Q41: 03009666170, 03009666170 | R41: 03009666170 | S41: H NO 109 IRFA KAREEM BLOCK SARGODHA ROAD NEAR SUNDAR HOUSE JINNAH ROAD FAISALABAD PK | T41: 1805650 | U41: 3283000 | V41: DIB/T/BT/33630/LHR/0921 | W41: 13-SEP-2021 | X41: Q079792 | Y41: 6057282 | Z41: NEW | AB41: TOYOTA COROLLA ALTIS A/T | AC41: 2021 | AD41: 19-MAR-2021 | AE41: 03-OCT-2021 | AF41: 03-Oct-2024 | AG41: OLAFSD300066838 | AH41: 3 | AI41: CTRK | AJ41: DIB0031632 | AK41: 14-SEP-2021 | AM41: 2% | AN41: 0 | AO41: 0
A42: 41 | B42: CLOSED | C42: 9976AD2211610008 | D42: 6AD2 | E42: A | F42: T-PAK | G42: PAK SUZUKI MOTOR CO LTD | H42: 598772 | I42: 0621930 | J42: 2 | K42: 26.05 | L42: 0621930002 | M42: SHAHZORE KHAN | N42: Karachi | O42: 42101-6641304-7 | Q42: 03452993949 | S42: HOUSE NO-IV G,1/39, NAZIMABAD NO-4,KARACHI. NEAR MASJID KHARUL AMAL. KARACHI. 03452993949 | T42: 1074750 | U42: 1433000 | V42: 2021-09-205-V01501DP0002156 | W42: 13-SEP-2022 | X42: 6R181007 | Y42: NF1AET306H1081032 | Z42: NEW | AB42: ALTO VXR EURO II | AC42: 2021 | AD42: 10-JUN-2021 | AE42: 21-SEP-2021 | AF42: 21-Sep-2024 | AG42: OLAKHI300069409 | AH42: 3 | AI42: ITECL | AJ42: 5414/09/2021 | AK42: 07-SEP-2021 | AM42: 2% | AN42: 0 | AO42: 0
A43: 42 | B43: CLOSED | C43: 9976AP2192600001 | D43: 6AP2 | E43: A | F43: T-PAK | G43: NEW CAR COMPLEX | H43: 591921 | I43: 0155920 | J43: 2.5 | K43: 28.69 | L43: 0155920003 | M43: SAEED AHMED AGHA | N43: Karachi | O43: 42301-0704901-1 | P43: 0331-3934095 | Q43: 03313934095 | R43: 99243329 EXT 318 | S43: FLAT NO 6 3RD FLOOR PLOT NO 42/D 24TH COMMERCIAL STREET PHASE II EXT DHA OPP MASTER JUICE KARACHI | T43: 700000 | U43: 1400000 | V43: 51132/00028/09/2019 | W43: 13-SEP-2020 | X43: Y682613 | Y43: 2157599 | Z43: USD | AA43: AYW-909 | AB43: COROLLA GLI | AC43: 2013 | AD43: 17-SEP-2019 | AE43: 21-SEP-2019 | AF43: 21-Sep-2024 | AG43: POUKHI300049113 | AH43: 5 | AI43: ITFM | AJ43: 1746/09/2019/ITFM | AK43: 14-SEP-2019 | AM43: 2.5% | AN43: 0 | AO43: 0
A44: 43 | B44: CLOSED | C44: 9976AP1222570006 | D44: 6AP1 | E44: A | F44: T-PAK | G44: NASEER AUTOS | H44: 1196906 | I44: 0282018 | J44: 1.75 | K44: 25.69 | L44: 0282018007 | M44: HAFIZ SYED RASHID MUSTAFA | N44: Karachi | O44: 42201-5974988-9 | P44: N/A | Q44: 03426000004 | R44: N/A | S44: 18 BLOCK # 07 GULISTAN E JOHAR NEAR AYESHA MARKEET KARACHI | T44: 1615320 | U44: 2564000 | V44: 63286/00031/09/2022 | W44: 12-SEP-2023 | X44: 239575 | Y44: 10139593 | Z44: NEW | AB44: SUZUKI WAGONR VXL | AC44: 2022 | AD44: 14-SEP-2022 | AE44: 21-SEP-2022 | AF44: 21-Sep-2024 | AG44: OLDKHI300089794 | AH44: 2 | AI44: ITFT | AJ44: 8650/09/2022/ITFM | AK44: 14-SEP-2022 | AM44: 1.75% | AN44: 0 | AO44: 0
A45: 44 | B45: CLOSED | C45: 9976AD1212120120 | D45: 6AD1 | E45: A | F45: T-PAK | G45: KIA CLIFTON | H45: 1107145 | I45: 0070983 | J45: 1.75 | K45: 25.94 | L45: 0070983007 | M45: MUHAMMAD KHURRAM | N45: Karachi | O45: 42000-6191713-3 | Q45: 03008219958 | R45: 02132270661 | S45: FLAT NO FB 302 NEAR MOTI MASJID AL HABIB APPARTMENT BLOCK 8 KEHKASHAN CLIFTON | T45: 2898500 | U45: 5270000 | V45: DIB/T/BT/33638/KHI/0921 | W45: 12-SEP-2022 | X45: G4NAMH318581 | Y45: NNAQL51AZKP513411 | Z45: NEW | AB45: KIA SPORTAGE AWD | AC45: 2021 | AD45: 31-JUL-2021 | AE45: 21-SEP-2021 | AF45: 21-Sep-2024 | AG45: OLAKHI300071555 | AH45: 3 | AM45: 1.75% | AN45: 0 | AO45: 0
A46: 45 | B46: CLOSED | C46: 9976AD1212380011 | D46: 6AD1 | E46: A | F46: T-PAK | G46: HONDA UNITED | H46: 1095465 | I46: 0703374 | J46: 2 | K46: 25.55 | L46: 0703374001 | M46: ASYM MIRZA | N46: Karachi | O46: 42301-3412952-9 | P46: 03333211480 | Q46: 03333211480 | R46: 03333211480 | S46: HOUSE # 262-U BLOCK-6 MOHALLA PECHS NEAR MADINA MASJID KARACHI PK | T46: 2816800 | U46: 4024000 | V46: 2524/02640/00039/09/2021 | W46: 12-SEP-2022 | X46: 16925655 | Y46: 078182 | Z46: NEW | AB46: HONDA CIVIC VTI ORIEL | AC46: 2021 | AD46: 26-AUG-2021 | AE46: 21-SEP-2021 | AF46: 21-Sep-2024 | AG46: OLAKHI300072456 | AH46: 3 | AI46: CTRK | AJ46: DIB0031592 | AK46: 10-SEP-2021 | AM46: 2% | AN46: 0 | AO46: 0
A47: 46 | B47: CLOSED | C47: 9976AD1210280014 | D47: 6AD1 | E47: A | F47: T-PAK | G47: PRINCE SAJJAD MOTORS | H47: 532628 | I47: 0668346 | J47: 2 | K47: 25.44 | L47: 0668346001 | M47: REHMAN ALI | N47: Rawalpindi | O47: 14301-6180231-9 | P47: 03330674999 | Q47: 03339637221 | R47: 0515152086 | S47: H # 240 ST # 57 SECTOR 2 GULSHANABA D ADYALA ROAD RAWALPINDI PK | T47: 2800000 | U47: 4000000 | V47: 2524/02640/00041/09/2021 | W47: 12-SEP-2022 | X47: 21013206 | Y47: PDF580SALR21H1763 | Z47: NEW | AB47: PRINCE GLORY 580 SUV | AC47: 2021 | AD47: 28-JAN-2021 | AE47: 21-SEP-2021 | AF47: 21-Sep-2024 | AG47: OLARWP300065381 | AH47: 3 | AI47: ITFT | AJ47: 5428/09/2021 | AK47: 13-SEP-2021 | AM47: 2% | AN47: 0 | AO47: 0
A48: 47 | B48: CLOSED | C48: 9976AD1211400014 | D48: 6AD1 | E48: A | F48: T-PAK | G48: KIA MOTORS CROSSROAD | H48: 633565 | I48: 0690766 | J48: 2 | K48: 25.54 | L48: 0690766001 | M48: RIAZ ALI MOMIN | N48: Hyderabad | O48: 42101-1632581-3 | P48: 03003799086 | Q48: 03003799086 | R48: 03003799086 | S48: HOUSE # A-3 AMINABAD PHASE 2 KALI M ORI HYDERABAD PK | T48: 3239400 | U48: 5399000 | V48: UWT/D/T002/0000001065/0921/109-0 | W48: 10-SEP-2022 | X48: 315403 | Y48: 512839 | Z48: NEW | AB48: KIA SPORTAGE AWD | AC48: 2021 | AD48: 20-MAY-2021 | AE48: 21-SEP-2021 | AF48: 21-Sep-2024 | AG48: OLAHYD300068724 | AH48: 3 | AM48: 2% | AN48: 0 | AO48: 0
A49: 48 | B49: CLOSED | C49: 997APD1202670040 | D49: APD1 | E49: A | F49: T-PAK | G49: KIA MOTORS CHINAR | H49: 579378 | I49: 0632776 | J49: 1.5 | K49: 26.68 | L49: 0632776001 | M49: MUHAMMAD AZEEM RASHEED | N49: Gujranwala | O49: 34101-2452419-1 | P49: 03216443940 | Q49: 03216443940 | R49: 03216443940 | S49: KAGNI WALA BY PASS GT ROAD, GUJRANWALA | T49: 3453100 | U49: 4933000 | V49: 52740/00029/09/2020 | W49: 10-SEP-2021 | X49: G4NALH314347 | Y49: NNAQL51AZKP303239 | Z49: NEW | AB49: KIA SPORTAGE AWD | AC49: 2020 | AD49: 23-SEP-2020 | AE49: 27-SEP-2020 | AF49: 27-Sep-2024 | AG49: PODGWL300057255 | AH49: 4 | AM49: 1.5% | AN49: 0 | AO49: 0
A50: 49 | B50: CLOSED | C50: 9976AD1211590011 | D50: 6AD1 | E50: A | F50: T-PAK | G50: PAK SUZUKI MOTOR CO LTD | H50: 633387 | I50: 0224748 | J50: 2 | K50: 25.56 | L50: 0224748002 | M50: SYED AAMIR ALI | N50: SHEIKUPURA | O50: 35404-1577442-3 | P50: 0563781001 | Q50: 03338805999 03243781001 | S50: HOUSE NO 1 RASOOL NAGAR SHAH COLONY ROAD SHEIKHUPURA | T50: 890000 | U50: 1780000 | V50: UWT/D/T002/0000001064/0921/109-0 | W50: 10-SEP-2022 | X50: 183998 | Y50: 10084008 | Z50: NEW | AB50: SUZUKI CULTUS VXR | AC50: 2021 | AD50: 08-JUN-2021 | AE50: 03-OCT-2021 | AF50: 03-Oct-2024 | AG50: OLASHK300069351 | AH50: 3 | AI50: CTRK | AJ50: DIB0031642 | AK50: 13-SEP-2021 | AM50: 2% | AN50: 0 | AO50: 0
A51: 50 | B51: CLOSED | C51: 9976AD1192120012 | D51: 6AD1 | E51: A | F51: T-PAK | G51: SUZUKI ISLAMABAD MOTORS | H51: 576917 | I51: 0552380 | J51: 2.5 | K51: 24.69 | L51: 0552380001 | M51: AROOJ ANTHONEY | N51: Islamabad | O51: 35202-7783205-8 | P51: 03227601867 | R51: 0519107724 | S51: APARTMENT # F4 ISRA APARTMENTS NUST UNIVERSITY H - 12 ISLAMABAD PK | T51: 1036000 | U51: 1295000 | V51: 51132/00019/09/2019 | W51: 10-SEP-2020 | X51: 111925 | Y51: 1011915 | Z51: NEW | AA51: APE-851 | AB51: SUZUKI ALTO VXR AGS EURO II | AC51: 2019 | AD51: 31-JUL-2019 | AE51: 21-SEP-2019 | AF51: 21-Sep-2024 | AG51: POAISD300048036 | AH51: 5 | AI51: ITFM | AJ51: 1737/09/2019/ITFM | AK51: 11-SEP-2019 | AM51: 2.5% | AN51: 0 | AO51: 0
A52: 51 | B52: CLOSED | C52: 9976AP1212580028 | D52: 6AP1 | E52: A | F52: T-PAK | G52: S F MOTORS | H52: 1104379 | I52: 0720081 | J52: 2 | K52: 25.68 | L52: 0720081001 | M52: ZAHID WAQAR | N52: Lahore | O52: 35201-1387483-7 | P52: 03234646167 | Q52: 03234646167 | R52: 03234646167 | S52: MAIN GHAZI ROAD DEFENCE ROAD MILLAT CHOWK ASLAM STREET PURANI WAPDA TO WER WALI GALI ROAD NEAR OPPOSITE AL LAHORE | T52: 2732100 | U52: 3903000 | V52: 55601/00036/09/2021 | W52: 09-SEP-2022 | X52: Q351527 | Y52: 7050694 | Z52: NEW | AB52: TOYOTA COROLLA ALTIS GRANDE CVT | AC52: 2021 | AD52: 15-SEP-2021 | AE52: 21-SEP-2021 | AF52: 21-Sep-2026 | AG52: OLDLHR300073320 | AH52: 5 | AI52: CTRK | AJ52: DIB0031648 | AK52: 13-SEP-2021 | AM52: 2% | AN52: 0 | AO52: 0
A53: 52 | B53: CLOSED | C53: 9976AD1212110059 | D53: 6AD1 | E53: A | F53: T-PAK | G53: HYUNDAI SOUTH | H53: 599276 | I53: 0644061 | J53: 2 | K53: 25.54 | L53: 0644061003 | M53: PERVEZ RAUF | N53: Karachi | O53: 42201-1180685-1 | P53: 03458223366 | Q53: 03458223366 | R53: 0 | S53: A- 15 KDA SCHEEM 1 EXT NEAR KARSAZ ROAD PEER PAGARA HOUSE KARACHI PK | T53: 2559600 | U53: 6399000 | V53: DIB/T/BT/33629/KHI/0921 | W53: 09-SEP-2022 | X53: GAHAMU142125 | Y53: PMHL3416MMN400411 | Z53: NEW | AB53: SONATA A/T | AC53: 2021 | AD53: 30-JUL-2021 | AE53: 21-SEP-2021 | AF53: 21-Sep-2024 | AG53: OLAKHI300071426 | AH53: 3 | AI53: CTRK | AJ53: TDIDIB0029607 | AK53: 10-SEP-2021 | AM53: 2% | AN53: 0 | AO53: 0
A54: 53 | B54: CLOSED | C54: 9976AD1210900048 | D54: 6AD1 | E54: A | F54: T-PAK | G54: CHANGAN ADIL ASHRAF MOTORS | H54: 536261 | I54: 0657956 | J54: 2 | K54: 25.45 | L54: 0657956001 | M54: SOBIA MALIK | N54: SHEIKUPURA | O54: 35403-1097863-8 | P54: 03024432313 | Q54: 03024432313 | R54: 03024432313 | S54: EXCISE AND TAXATION DEPARTMENT LAHORE | T54: 1457500 | U54: 2650000 | V54: 01-2109-PO-MTR-PCCM-D-001197 | W54: 09-SEP-2022 | X54: 510898 | Y54: 1001658 | Z54: NEW | AB54: CHANGAN ALSVIN 1.5L LUMIERE | AC54: 2021 | AD54: 31-MAR-2021 | AE54: 03-OCT-2021 | AF54: 03-Oct-2026 | AG54: OLASHK300067311 | AH54: 5 | AI54: CTRK | AJ54: DIB0031642 | AK54: 10-SEP-2021 | AM54: 2% | AN54: 0 | AO54: 0
A55: 54 | B55: CLOSED | C55: 9976AD1212350015 | D55: 6AD1 | E55: A | F55: T-PAK | G55: KIA MOTORS 9TH AVENUE | H55: 1106671 | I55: 0295092 | J55: 2 | K55: 25.6 | L55: 0295092012 | M55: RABIA RIAZ | N55: Islamabad | O55: 37103-2499486-8 | P55: NA | Q55: 0302854859 | S55: AIR BLUE HEAD QUARTER CORPORATE ISLAMABAD | T55: 1515500 | U55: 4330000 | V55: 01-2109-PO-MTR-PCCM-D001189 | W55: 08-SEP-2022 | X55: G4NAMH314612 | Y55: P102115 | Z55: NEW | AB55: KIA SPORTGE ALPHA | AC55: 2021 | AD55: 23-AUG-2021 | AE55: 21-SEP-2021 | AF55: 21-Sep-2024 | AG55: OLAISD300072222 | AH55: 3 | AM55: 2% | AN55: 0 | AO55: 0
A56: 55 | B56: CLOSED | C56: 9976AD1211810052 | D56: 6AD1 | E56: A | F56: T-PAK | G56: TOYOTA SOUTHERN MOTORS | H56: 1107010 | I56: 0319218 | J56: 1.75 | K56: 26.05 | L56: 0319218007 | M56: ZULFIQAR ALI BEHAN | N56: Karachi | O56: 42000-4786158-3 | Q56: 0300-202225 | R56: N/A | S56: HOUSE # 109/1 KHAYABAN-E-TARIQ D.H.A KARACHI | T56: 4879225 | U56: 7506500 | V56: 2021/09/CLFTTPCDP00996 | W56: 07-SEP-2022 | X56: 5032948 | Y56: 5547720 | Z56: NEW | AB56: TOYOTA HILUX REVO V DC A/T 4X4 | AC56: 2021 | AD56: 30-JUN-2021 | AE56: 21-SEP-2021 | AF56: 21-Sep-2024 | AG56: OLAKHI300070301 | AH56: 3 | AI56: CTRK | AJ56: DIB0031528 | AK56: 03-SEP-2021 | AM56: 1.75% | AN56: 0 | AO56: 0
A57: 56 | B57: CLOSED | C57: 9976AD1211200029 | D57: 6AD1 | E57: A | F57: T-PAK | G57: SUZUKI MUZAFARABAD MOTOR | H57: 1090059 | I57: 0688294 | J57: 2 | K57: 25.54 | L57: 0688294001 | M57: MUHAMMAD TARIQ KHAN | N57: Muzaffarabad | O57: 82203-5846306-7 | P57: 03005568842 | R57: 0 | S57: TARIQABAD WARD NO 07 H # BI-1279 NE AR MDA OFFICE MUZAFFARABAD PK | T57: 1491000 | U57: 2130000 | V57: 55601/00019/09/2021 | W57: 07-SEP-2022 | X57: 181808 | Y57: 10081783 | Z57: NEW | AB57: CULTUS VXL AGS EURO II | AC57: 2021 | AD57: 30-APR-2021 | AE57: 27-SEP-2021 | AF57: 27-Sep-2024 | AG57: OLAMFD300068391 | AH57: 3 | AI57: CTRK | AJ57: DIB0031356 | AK57: 21-SEP-2021 | AM57: 2% | AN57: 0 | AO57: 0
A58: 57 | B58: CLOSED | C58: 9976AD1220590026 | D58: 6AD1 | E58: A | F58: T-PAK | G58: KIA MOTORS SITE | H58: AL-1142049 | I58: 0143869 | J58: 2 | K58: 25.74 | L58: 0143869039 | M58: ZEESHAN JAVED ARAIN | N58: Karachi | O58: 42000-0545296-9 | P58: 0300-8285080 | Q58: 03008285080 | R58: 111222757 | S58: STRUCTURE LAB SERVICE PLOT NO B-83 SECTOR 6-F MEHRAN TOWN KORANGI INDUSTRIAL AREA KARACHI | T58: 1719000 | U58: 2292000 | V58: 63286/00012/09/2022 | W58: 06-SEP-2023 | X58: 074058 | Y58: 710812 | Z58: NEW | AB58: KIA PICANTO 1.0 L A/T | AC58: 2022 | AD58: 28-FEB-2022 | AE58: 21-SEP-2022 | AF58: 21-Sep-2024 | AG58: OLAKHI300084467 | AH58: 2 | AI58: ITECL | AJ58: 8583/09/2022 | AK58: 02-SEP-2022 | AM58: 2% | AN58: 0 | AO58: 0
A59: 58 | B59: CLOSED | C59: 9976AD2211510007 | D59: 6AD2 | E59: A | F59: T-PAK | G59: TOYOTA WALTON MOTORS | H59: 526983 | I59: 0694381 | J59: 1.75 | K59: 26.05 | L59: 0694381001 | M59: MALIK MUHAMMAD ASGHAR AWAN | N59: Sialkot | O59: 34603-3661246-5 | P59: 03235155286 | Q59: 03235155286 | R59: 03235155286 | S59: NEAR ALLIED BANK DALOWALI NEAR ABL BANK SIALKOT | T59: 4823400 | U59: 8039000 | V59: 2021/09/CLFTTCPDP00995 | W59: 06-SEP-2022 | X59: 2TRA871758 | Y59: 0893648 | Z59: NEW | AB59: FORTUNER G 4*2 STD PETROL | AC59: 2021 | AD59: 31-MAY-2021 | AE59: 21-SEP-2021 | AF59: 21-Sep-2024 | AG59: OLASKT300068993 | AH59: 3 | AI59: CTRK | AJ59: DIB0031596 | AK59: 08-SEP-2021 | AM59: 1.75% | AN59: 0 | AO59: 0
A60: 59 | B60: CLOSED | C60: 9976AD1210570039 | D60: 6AD1 | E60: A | F60: T-PAK | G60: TOYOTA WALTON MOTORS | H60: 625642 | I60: 0418319 | J60: 2 | K60: 25.45 | L60: 0418319010 | M60: ANSAR ABBAS | N60: Lahore | O60: 42401-3850533-7 | P60: 03218202012 | Q60: 03218202012 | R60: 37332500 | S60: HNO 117 B 2 JOHAR TOWN NEAR ALLAH HO CHOWK LAHORE PAKISTAN | T60: 2407060 | U60: 3283000 | V60: 55601/00011/09/2021 | W60: 06-SEP-2022 | X60: Q079477 | Y60: 6056939 | Z60: NEW | AB60: COROLLA ALTIS A/T | AC60: 2021 | AD60: 26-FEB-2021 | AE60: 03-OCT-2021 | AF60: 03-Oct-2024 | AG60: OLALHR300066264 | AH60: 3 | AI60: CTRK | AJ60: DIB0031576 | AK60: 08-SEP-2021 | AM60: 2% | AN60: 0 | AO60: 0
A61: 60 | B61: CLOSED | C61: 9976AD2211740019 | D61: 6AD2 | E61: A | F61: T-PAK | G61: TOYOTA SOUTHERN MOTORS | H61: 1091303 | I61: 0644476 | J61: 2 | K61: 23.69 | L61: 0644476002 | M61: SYED MASOOD HUSSAIN | N61: Karachi | O61: 42101-0719485-7 | Q61: 03332112724 | S61: HOUSE NO 505 BLOCK # C AREA NEAR BILAL MASJID NORTH NAZIMABAD KARACHI. | T61: 1942500 | U61: 2775000 | V61: 2021-09-205-V01501DP0002119 | W61: 06-SEP-2022 | X61: 2A34832 | Y61: 7021928 | Z61: NEW | AB61: YARIS ATIV CVT 1.3 | AC61: 2021 | AD61: 23-JUN-2021 | AE61: 11-SEP-2021 | AF61: 11-Sep-2024 | AG61: OLAKHI300069734 | AH61: 3 | AI61: ITMT | AJ61: 5406/09/2021/ITMM | AK61: 02-SEP-2021 | AM61: 2% | AN61: 0 | AO61: 0
A62: 61 | B62: CLOSED | C62: 9976AD1211520089 | D62: 6AD1 | E62: A | F62: T-PAK | G62: PAK SUZUKI MOTOR CO LTD | H62: 1109637 | I62: 0696440 | J62: 2 | K62: 25.56 | L62: 0696440001 | M62: MUHAMMAD WASIF LATIF | N62: Faisalabad | O62: 33100-2839208-7 | P62: 0412573092 | Q62: 03457865070, 03457865070 | R62: 03457865070 | S62: H NO 157-B GULSHAN HAYYAT ABC ROAD FAISALABAD PK | T62: 1631200 | U62: 2039000 | V62: 01-2018-PO-MTR-PCCM-D-001110 | W62: 06-SEP-2022 | X62: 182606 | Y62: 10082608 | Z62: NEW | AB62: CULTUS VXL AGS EURO II | AC62: 2021 | AD62: 01-JUN-2021 | AE62: 03-OCT-2021 | AF62: 03-Oct-2024 | AG62: OLAFSD300069219 | AH62: 3 | AI62: CTRK | AJ62: DIB0031378 | AK62: 07-SEP-2021 | AM62: 2% | AN62: 0 | AO62: 0
A63: 62 | B63: CLOSED | C63: 9976AP1212510007 | D63: 6AP1 | E63: A | F63: T-PAK | G63: FAROOQ MOTORS | H63: 644634 | I63: 0717009 | J63: 2 | K63: 21.86 | L63: 0717009001 | M63: SYED USMAN RIZVI | N63: Lahore | O63: 35202-8641156-3 | P63: 03234818171 | Q63: 03234818171 | R63: 03234818171 | S63: 1ST FLOOR 69-B MAIN BOULEVARD GULBE RG II BEHIND METROPOLITAN BANK LAHORE | T63: 1470000 | U63: 2100000 | V63: 55601/00016/09/2021 | W63: 06-SEP-2022 | X63: 1554801 | Y63: 1302144052 | Z63: NEW | AA63: LEE-18-5590 | AB63: TOYOTA VITZ | AC63: 2015 | AD63: 08-SEP-2021 | AE63: 11-SEP-2021 | AF63: 11-Sep-2026 | AG63: OLULHR300073227 | AH63: 5 | AI63: CTRK | AJ63: DIB0031581 | AK63: 07-SEP-2021 | AM63: 2% | AN63: 0 | AO63: 0
A64: 63 | B64: CLOSED | C64: 9976AP2192550002 | D64: 6AP2 | E64: A | F64: T-PAK | G64: HONDA FORT | H64: 506240 | I64: 0339230 | J64: 2.5 | K64: 27.69 | L64: 0339230004 | M64: ARSALAN ZAHID | N64: Lahore | O64: 35201-6360105-5 | P64: 37176057 | Q64: 03214013931 0322-8444600 | R64: 35760874 | S64: AD WISE SOLUTIONS OFFICE 13/3 E-2 GULBERG III LAHORE | T64: 1157500 | U64: 2315000 | V64: 51132/00016/09/2019 | W64: 05-SEP-2020 | X64: 7534095 | Y64: KR253603 | Z64: NEW | AA64: LE-19A-535 | AB64: CITY I-VTEC M/T | AC64: 2019 | AD64: 12-SEP-2019 | AE64: 11-SEP-2019 | AF64: 11-Sep-2024 | AG64: PODLHR300048951 | AH64: 5 | AI64: CTRK | AJ64: DIB0027825 | AK64: 06-SEP-2019 | AM64: 2.5% | AN64: 0 | AO64: 0
A65: 64 | B65: CLOSED | C65: 9976AP2222510005 | D65: 6AP2 | E65: A | F65: T-PAK | G65: NEW CAR COMPLEX | H65: AL-327148 | I65: 0258608 | J65: 1.75 | K65: 22.87 | L65: 0258608003 | M65: MALIK KHUSHAL KHAN | N65: Karachi | O65: 35201-0506523-7 | Q65: 03323413524 | S65: HOUSE NO 48 A STREET 13 OFF KHAYABAN-E-MUHAFIZ PHASE 6 KARACHI | T65: 1386000 | U65: 1980000 | V65: 63286/00006/09/2022 | W65: 05-SEP-2023 | X65: 199556 | Y65: 10099564 | Z65: USD | AA65: BRH-579 | AB65: SUZUKI WAGNOR VXL AGS | AC65: 2019 | AD65: 08-SEP-2022 | AE65: 11-SEP-2022 | AF65: 11-Sep-2027 | AG65: OLUKHI300089708 | AH65: 5 | AI65: ITFT | AJ65: 8594/09/2022/ITFM | AK65: 06-SEP-2022 | AM65: 1.75% | AN65: 0 | AO65: 0
A66: 65 | B66: CLOSED | C66: 9976AD1211680024 | D66: 6AD1 | E66: A | F66: T-PAK | G66: KIA MOTORS KINGS GATE | H66: 637757 | I66: 0699389 | J66: 1.75 | K66: 25.95 | L66: 0699389001 | M66: MUHAMMAD IMRAN | N66: Faisalabad | O66: 33100-1460395-5 | P66: 03008665101 | Q66: 03008665101, 03008665101 | R66: 03008665101 | S66: H NO P-300-C AYSAHA BLOCK ABDULLAH GARDEN CANAL ROAD FAISALABAD PK | T66: 2964840 | U66: 4782000 | V66: DIB/T/33203/LHR/0821 | W66: 05-SEP-2022 | X66: 512643 | Y66: 306932 | Z66: NEW | AB66: KIA SPORTAGE FWD | AC66: 2021 | AD66: 17-JUN-2021 | AE66: 03-OCT-2021 | AF66: 03-Oct-2024 | AG66: OLAFSD300069516 | AH66: 3 | AM66: 1.75% | AN66: 0 | AO66: 0
A67: 66 | B67: CLOSED | C67: 9976AP2222490002 | D67: 6AP2 | E67: A | F67: T-PAK | G67: CAR DEALS | H67: AL-1204122 | I67: 0508411 | J67: 1.5 | K67: 27.44 | L67: 0508411001 | M67: NASREEN IJAZ | N67: Karachi | O67: 42401-9031847-6 | P67: 03018267285 | Q67: 03018267285 | R67: 32357185 | S67: HOUSE # 118/1 1ST STREET # 21 PHASE # 6 KHAYABN-E-MUHAFIZ DHA NEAR ALI KARACHI PK | T67: 1763300 | U67: 2519000 | V67: 63286/00004/09/2022 | W67: 04-SEP-2023 | X67: 2578374 | Y67: 4205534 | Z67: USD | AB67: TOYOTA COROLLA XLI | AC67: 2020 | AD67: 06-SEP-2022 | AE67: 11-SEP-2022 | AF67: 11-Sep-2024 | AG67: OLUKHI300089705 | AH67: 2 | AI67: ITFM | AJ67: 8588/09/2022/ITFM | AK67: 05-SEP-2022 | AM67: 1.5% | AN67: 0 | AO67: 0
A68: 67 | B68: CLOSED | C68: 997APD2202480004 | D68: APD2 | E68: A | F68: T-PAK | G68: NEW S.S MOTORS | H68: 644076 | I68: 0630454 | J68: 2 | K68: 20.8 | L68: 0630454001 | M68: MUHAMMAD SAJJAD | N68: Faisalabad | O68: 32303-7250203-9 | P68: 03003205176 | Q68: 03003205176, 03003205176 | R68: 0414713501 | S68: CHAK NO 68 R.B MAIN SKP JOHAL STOP BACKSIDE NAIGRA MILL JINNAH ABBADI FAISALABAD PK | T68: 1190000 | U68: 1700000 | V68: 52740/00013/09/2020 | W68: 03-SEP-2021 | X68: 1KR1415387 | Y68: KSP1302091611 | Z68: RCN | AA68: LEA-17-4132 | AB68: TOYOTA VITZ | AC68: 2013 | AD68: 04-SEP-2020 | AE68: 11-SEP-2020 | AF68: 11-Sep-2025 | AG68: POUFSD300057088 | AH68: 5 | AI68: ITFM | AJ68: 2951/08/2020/ITFM | AK68: 04-SEP-2020 | AM68: 2% | AN68: 0 | AO68: 0
A69: 68 | B69: CLOSED | C69: 997AAD1202040019 | D69: AAD1 | E69: A | F69: T-PAK | G69: KIA MOTORS DEFENCE | H69: 600017 | I69: 0083262 | J69: 1.5 | K69: 20.8 | L69: 0083262019 | M69: MUHAMMAD NAVEED WAZIR ALI | N69: Lahore | O69: 35201-0556930-5 | P69: 04235710848 | Q69: 0300-8494801 0300-8441497 | R69: 04236669801 | S69: H NO 130/2 GILLANI STREET NO 1 NADIRABAD CANTT NR WAQAS MARKET LAHORE | T69: 3695250 | U69: 4927000 | V69: COMP/P/52740/09/2020 | W69: 01-SEP-2021 | X69: G4NALH316962 | Y69: NNAQL51AZKP303021 | Z69: NEW | AB69: KIA SPORTAGE FWD | AC69: 2020 | AD69: 22-JUL-2020 | AE69: 11-SEP-2020 | AF69: 11-Sep-2027 | AG69: POALHR300055391 | AH69: 7 | AM69: 1.5% | AN69: 0 | AO69: 0
A70: 69 | B70: CLOSED | C70: 9976AD1211510020 | D70: 6AD1 | E70: A | F70: T-PAK | G70: KIA MOTORS LUCKY ONE | H70: 643350 | I70: 0687056 | J70: 2 | K70: 25.54 | L70: 0687056001 | M70: MUHAMMAD SAAD | N70: Karachi | O70: 42101-2956624-3 | P70: 02134546325 | Q70: 03177117114 | R70: 02134141421 | S70: SHOP # 1 GROUND FLOOR NOBLE HEIGHTS CHANDNI CHOWK KDA SCHEEM # 33 SHOP # 7 OPP ASKARI PARK MAIN UNIVERSTI KARACHI | T70: 2859350 | U70: 4399000 | V70: 55601/00001/09/2021 | W70: 01-SEP-2022 | X70: G4NAMH314527 | Y70: NNAQL51AZLP102121 | Z70: NEW | AB70: KIA SPORTAGE ALPA | AC70: 2021 | AD70: 31-MAY-2021 | AE70: 21-SEP-2021 | AF70: 21-Sep-2024 | AG70: OLAKHI300068980 | AH70: 3 | AM70: 2% | AN70: 0 | AO70: 0
A71: 70 | B71: CLOSED | C71: 9976AP2212460031 | D71: 6AP2 | E71: A | F71: T-PAK | G71: NEW CAR COMPLEX | H71: 1105718 | I71: 0718914 | J71: 2 | K71: 25.6 | L71: 0718914001 | M71: HAMID SAEED | N71: Karachi | O71: 42101-5732830-1 | P71: 03145040473 | Q71: 03145040473 | R71: 0 | S71: HOUSE L- 745 SECTER 5 A- 2 NORTH KH I 4K CHOWRANGI MADIHA STOP KARACHI PK | T71: 2400000 | U71: 4000000 | V71: 55601/00003/09/2021 | W71: 01-SEP-2022 | X71: LEB-5081272 | Y71: RU3-1131206 | Z71: RCN | AB71: HONDA VEZEL HYBRID | AC71: 2016 | AD71: 03-SEP-2021 | AE71: 03-SEP-2021 | AF71: 03-Sep-2024 | AG71: OLUKHI300073082 | AH71: 3 | AI71: CTRK | AJ71: DIB0031541 | AK71: 03-SEP-2021 | AM71: 2% | AN71: 0 | AO71: 0
A72: 71 | B72: NORM | C72: 9976AD1211510031 | D72: 6AD1 | E72: A | F72: T-PAK | G72: PAK SUZUKI MOTOR CO LTD | H72: 649576 | I72: 0695379 | J72: 2 | K72: 25.79 | L72: 0695379001 | M72: MARYAM SIDDIQA | N72: Rahim Yar Khan | O72: 31303-5638787-8 | P72: 03342844446 | Q72: 03342844446 | R72: 03342844446 | S72: HOUSE NO 120-D SCHEME 03 BLOCK Y GU LSHAN IQBAL COLONY RAHIM YAR KHAN PK | T72: 801000 | U72: 1335000 | V72: DIB/T/BT/33330/LHR/0921 | W72: 01-SEP-2022 | X72: 180368 | Y72: 1080364 | Z72: NEW | AB72: ALTO VXR EURO-II | AC72: 2021 | AD72: 31-MAY-2021 | AE72: 03-OCT-2021 | AF72: 03-Oct-2028 | AG72: OLARYK300069033 | AH72: 7 | AI72: FLCN | AJ72: 108568/09/2021 | AK72: 02-SEP-2021 | AM72: 2% | AN72: 1068000 | AO72: 21360
A73: 72 | B73: NORM | C73: 997AAD1202090003 | D73: AAD1 | E73: A | F73: T-PAK | G73: HONDA CHENAB-GREEN VIEW MOTORS | H73: 593276 | I73: 0621607 | J73: 2 | K73: 20.8 | L73: 0621607001 | M73: MUHAMMAD LATIF | N73: SHEIKUPURA | O73: 34103-0458295-1 | P73: 03008893133 | Q73: 03138893133, 03008893133 | R73: 03008893133 | S73: GALI LATIF DOGAR WALI GUJRAWANWALA ROAD MOHALLAH ATA ABAD NEAR SHISH M SHEIKHUPURA PK | T73: 1916000 | U73: 2395000 | V73: DIB/T/BT/28482/LHR/0920 | W73: 01-SEP-2021 | X73: L13Z17540161 | Y73: NFBGM1544LR262747 | Z73: NEW | AB73: CITY IVTEC M/T | AC73: 2020 | AD73: 27-JUL-2020 | AE73: 11-SEP-2020 | AF73: 11-Sep-2025 | AG73: POASHK300055899 | AH73: 5 | AI73: ITFM | AJ73: 09/2020/ITFM | AK73: 02-SEP-2020 | AM73: 2% | AN73: 1796250 | AO73: 35925
A74: 73 | B74: NORM | C74: 9976AD1211680026 | D74: 6AD1 | E74: A | F74: T-PAK | G74: KIA MOTORS TOWNSHIP | H74: 633467 | I74: 0699405 | J74: 2 | K74: 25.79 | L74: 0699405001 | M74: SHAHID IQBAL | N74: Sialkot | O74: 34603-6763335-7 | P74: 03026486200 | Q74: 03026486200 | R74: 03326486200 | S74: NEAR OPPOSITE CHINA HOTEL B-BLOCK C ITY HOUSING SOCIETY SIALKOT | T74: 2880800 | U74: 4432000 | V74: UWT/D/P002/0000000984/0921/109 | W74: 01-SEP-2022 | X74: 312732 | Y74: 101956 | Z74: NEW | AB74: SPORTGE ALPHA | AC74: 2021 | AD74: 17-JUN-2021 | AE74: 27-SEP-2021 | AF74: 27-Sep-2026 | AG74: OLASKT300069462 | AH74: 5 | AM74: 2% | AN74: 3545600 | AO74: 70912
A75: 74 | B75: NORM | C75: 9976AD1211670015 | D75: 6AD1 | E75: A | F75: T-PAK | G75: KIA MOTORS TOWNSHIP | H75: 526980 | I75: 0698981 | J75: 2 | K75: 26.29 | L75: 0698981001 | M75: MUHAMMAD SALEEM | N75: Sialkot | O75: 34603-0385945-5 | P75: 03456861572 | Q75: 03456861572 | R75: 05235422700 | S75: ANJOTAR HUNDAL ROAD NEAR GOVT HIGH SCHOOL SIALKOT | T75: 3102400 | U75: 4432000 | V75: UWT/D/T002/0000001040/0921/109-0 | W75: 01-SEP-2022 | X75: 314208 | Y75: 102175 | Z75: NEW | AB75: KIA SPORTAGE ALPHA | AC75: 2021 | AD75: 16-JUN-2021 | AE75: 21-SEP-2021 | AF75: 21-Sep-2026 | AG75: OLDSKT300069423 | AH75: 5 | AM75: 2% | AN75: 3545600 | AO75: 70912
A76: 75 | B76: NORM | C76: 997AAD1201740007 | D76: AAD1 | E76: A | F76: T-PAK | G76: KIA MOTORS MUREE ROAD | H76: 581825 | I76: 0614893 | J76: 1.5 | K76: 20.8 | L76: 0614893001 | M76: MIAN MUHAMMAD USMAN | N76: Rawalpindi | O76: 37405-9191077-3 | P76: 03325001991 | Q76: 03325001991 | R76: 0518449997 | S76: H # 341 ST # 37 UMER BLOCK BAHRIA T OWN PHASE-8 RAWALPINDI PK | T76: 3995260 | U76: 5399000 | V76: DIB/T/BT/28484/ISB/0920 | W76: 01-SEP-2021 | X76: G4NALH310866 | Y76: NNAQL51AZKP504398 | Z76: NEW | AB76: KIA SPORTAGE AWD | AC76: 2020 | AD76: 22-JUN-2020 | AE76: 11-SEP-2020 | AF76: 11-Sep-2025 | AG76: POARWP300054451 | AH76: 5 | AM76: 1.5% | AN76: 4049250 | AO76: 60738.75
A77: 76 | B77: NORM | C77: 9976AD2210880002 | D77: 6AD2 | E77: A | F77: T-PAK | G77: TOYOTA AIRPORT MOTOR | H77: 599353 | I77: 0059143 | J77: 1.75 | K77: 26.18 | L77: 0059143008 | M77: RAZA ISHAQ BABAR | N77: Lahore | O77: 35201-1236948-3 | Q77: 03217736777 | R77: 37309855 | S77: HOUSE NO 41 FF BLOCK DHA PHASE 04 LAHORE | T77: 4953200 | U77: 7076000 | V77: DIB/T/BT/3327/LHR/0921 | W77: 01-SEP-2022 | X77: 2GD5028612 | Y77: GUN126R-5547602 | Z77: NEW | AB77: TOYOTA HILUX REVO V DC A/T 4X4 | AC77: 2021 | AD77: 29-MAR-2021 | AE77: 21-SEP-2021 | AF77: 21-Sep-2026 | AG77: OLALHR300067061 | AH77: 5 | AI77: CTRK | AJ77: TDIDIB0029595 | AK77: 02-SEP-2021 | AM77: 1.75% | AN77: 5660800 | AO77: 99064
A78: 77 | B78: NORM | C78: 9976AD2211810008 | D78: 6AD2 | E78: A | F78: T-PAK | G78: TOYOTA RAWAL MOTORS | H78: 579222 | I78: 0697627 | J78: 2 | K78: 22.47 | L78: 0697627002 | M78: BIBI SALMA ZAHID NAQVI | N78: Haripur | O78: 13302-5232838-2 | Q78: 03305849914 | S78: W/O ZAHID UL HASSAN ST # 7 H # 13 TIP HOUSING COLONY HRP CITY TEHSIL & DIST. HARIPUR PAKISTAN | T78: 2102250 | U78: 2803000 | V78: UWT/D/T002/0000001039/0921/109-0 | W78: 01-SEP-2022 | X78: 2A34671 | Y78: 150R-7021678 | Z78: NEW | AB78: YARIS ATIV CVT 1.3 | AC78: 2021 | AD78: 30-JUN-2021 | AE78: 11-SEP-2021 | AF78: 11-Sep-2026 | AG78: OLAHRP300070037 | AH78: 5 | AI78: ITECL | AJ78: 5404/09/2021 | AK78: 02-SEP-2021 | AM78: 2% | AN78: 2242400 | AO78: 44848
A79: 78 | B79: NORM | C79: 9976AD1222340001 | D79: 6AD1 | E79: A | F79: T-PAK | G79: KIA MACCA MOTORS | H79: 1204280 | I79: 0388812 | J79: 2 | K79: 26.69 | L79: 0388812006 | M79: FARHAN AHMED | N79: Karachi | O79: 42101-1940633-7 | Q79: 03368518786 | S79: HOUSE NO D49/1 BLOCK 6 F.B.AREA KARACHI NEAR BY RANGERS HEADQUARTERS | T79: 1820000 | U79: 2600000 | V79: 63286/00002/09/2022 | W79: 01-SEP-2023 | X79: 030853 | Y79: 504085 | Z79: NEW | AB79: KIA PICANTO 1.0 L MT | AC79: 2022 | AD79: 22-AUG-2022 | AE79: 21-SEP-2022 | AF79: 21-Sep-2025 | AG79: OLAKHI300089389 | AH79: 3 | AI79: ITFM | AJ79: 8454/08/2022/ITFM | AK79: 26-AUG-2022 | AM79: 2% | AN79: 2210000 | AO79: 44200
A80: 79 | B80: NORM | C80: 997AAD1181710002 | D80: AAD1 | E80: A | F80: T-PAK | G80: HONDA CENTRE | H80: 506645 | I80: 0480153 | J80: 3.1 | K80: 30 | L80: 0480153004 | M80: ANSAR ALI BOTTAR | N80: Islamabad | O80: 34601-0779381-3 | P80: 03215439090 | Q80: 03006157903 | R80: 0519048357 | S80: OVER SEACES PAKISTANIS FOUNDATION BUILDING 3RD FLOOR SHAHRIAH JAHURIAT SECTOR G-5/2 ISLAMABAD | T80: 1462290 | U80: 1851000 | V80: 49817/00004/09/2018 | W80: 02-SEP-2019 | X80: 17518421 | Y80: JR233694 | Z80: NEW | AA80: AKG-090 | AB80: CITY I-VTEC P/T | AC80: 2018 | AD80: 20-JUN-2018 | AE80: 11-SEP-2018 | AF80: 11-Sep-2024 | AG80: POAISD300035162 | AH80: 6 | AI80: CTRK | AJ80: DIB0025711 | AK80: 03-SEP-2018 | AM80: 3.1% | AN80: 0 | AO80: 0
A81: 80 | B81: NORM | C81: 9976AD1211660012 | D81: 6AD1 | E81: A | F81: T-PAK | G81: SUZUKI MINI MOTORS | H81: 1104677 | I81: 0693673 | J81: 2 | K81: 25.79 | L81: 0693673001 | M81: SALMAN AMJAD | N81: Lahore | O81: 35202-4109105-3 | P81: 03333333626 | Q81: 03333333626 | R81: 03333333626 | S81: ISLAMIC HOUSE 99-A TRICON VILLAGE LAHORE | T81: 1146400 | U81: 1433000 | V81: 2524/02640/00010/09/2021 | W81: 02-SEP-2022 | X81: 6R181159 | Y81: NF1AET306H1081166 | Z81: NEW | AB81: SUZUKI ALTO VXR EURO | AC81: 2021 | AD81: 15-JUN-2021 | AE81: 21-SEP-2021 | AF81: 21-Sep-2026 | AG81: OLALHR300069461 | AH81: 5 | AI81: ITECL | AJ81: 5409/09/2021 | AK81: 03-SEP-2021 | AM81: 2% | AN81: 1146400 | AO81: 22928
A82: 81 | B82: NORM | C82: 9976AP2212510006 | D82: 6AP2 | E82: A | F82: T-PAK | G82: MARGALLA MOTORS | H82: 625980 | I82: 0616216 | J82: 2 | K82: 22.02 | L82: 0616216002 | M82: MUHAMMAD HASSAN KHAN | N82: Karachi | O82: 42501-9396639-5 | Q82: 03340295259 | S82: HOUSE # R- 210 CAPITAL SOCIETY SCHEME # 33 NEAR SAFOORA CHOWRANGI KARACHI. | T82: 1408000 | U82: 1760000 | V82: 55601/00004/09/2021 | W82: 02-SEP-2022 | X82: 218938 | Y82: 10118958 | Z82: NEW | AB82: WAGONR VXL AGS | AC82: 2021 | AD82: 08-SEP-2021 | AE82: 11-SEP-2021 | AF82: 11-Sep-2028 | AG82: OLDKHI300073107 | AH82: 7 | AI82: CTRK | AJ82: DIB0031542 | AK82: 08-SEP-2021 | AM82: 2% | AN82: 1408000 | AO82: 28160
A83: 82 | B83: NORM | C83: 997AAD2202120003 | D83: AAD2 | E83: A | F83: T-PAK | G83: HONDA CHENAB-GREEN VIEW MOTORS | H83: 598313 | I83: 0495988 | J83: 2 | K83: 21.05 | L83: 0495988003 | M83: ABDUL REHMAN | N83: Faisalabad | O83: 33100-4936955-5 | P83: 2695119 | Q83: 03028655454, 03028655454 | R83: 03028655454 | S83: 522-A BLOCK GM ABAD FAISALABAD PK | T83: 1921200 | U83: 2401500 | V83: 2524/0211/00003/09/2020 | W83: 02-SEP-2021 | X83: L13Z17540156 | Y83: NFBGM1545LR262742 | Z83: NEW | AA83: ARF-522 | AB83: HONDA CITY IVTEC M/T | AC83: 2020 | AD83: 30-JUL-2020 | AE83: 11-SEP-2020 | AF83: 11-Sep-2025 | AG83: POAFSD300056085 | AH83: 5 | AI83: ITFM | AJ83: 2943/09/2020/ITFM | AK83: 03-SEP-2020 | AM83: 2% | AN83: 1801125 | AO83: 36022.5
A84: 83 | B84: NORM | C84: 9976AD1211510008 | D84: 6AD1 | E84: A | F84: T-PAK | G84: PAK SUZUKI MOTOR CO LTD | H84: 639041 | I84: 0132188 | J84: 2 | K84: 25.79 | L84: 0132188003 | M84: NASIR MEHMOOD | N84: Lahore | O84: 45504-1133892-3 | Q84: 0343-6600006, 0319-3118020 | R84: 051-2096014 | S84: H NO E-66 SHERAZ VILLAS PHASE II GAVALRY GROUND LAHORE | T84: 1704000 | U84: 2130000 | V84: 2021-09-205-V015010PD002106 | W84: 02-SEP-2022 | X84: 183356 | Y84: 10083360 | Z84: NEW | AB84: SUZUKI CULTUS VXL AGS EURO II | AC84: 2021 | AD84: 31-MAY-2021 | AE84: 03-OCT-2021 | AF84: 03-Oct-2026 | AG84: OLALHR300069018 | AH84: 5 | AI84: CTRK | AJ84: DIB0031548 | AK84: 06-SEP-2021 | AM84: 2% | AN84: 1704000 | AO84: 34080
A85: 84 | B85: NORM | C85: 997AAD1202530011 | D85: AAD1 | E85: A | F85: T-PAK | G85: HONDA AVENUE | H85: 635431 | I85: 0630360 | J85: 2 | K85: 27.93 | L85: 0630360001 | M85: SHEIKH AHSAN ANJUM | N85: Islamabad | O85: 37405-2517483-1 | P85: 03218505189 | R85: 0515772064 | S85: H # 184 ST # 11 BLOCK-D MEDIA TOWN ISLAMABAD PK | T85: 2187900 | U85: 2574000 | V85: DIB/T/BT/28487/ISB/0920 | W85: 02-SEP-2021 | X85: 7540202 | Y85: LR262950 | Z85: NEW | AB85: CITY IVTEC P/T | AC85: 2020 | AD85: 09-SEP-2020 | AE85: 21-SEP-2020 | AF85: 21-Sep-2025 | AG85: POAISD300057149 | AH85: 5 | AI85: CTRK | AJ85: TDIDIB0028623 | AK85: 08-SEP-2020 | AM85: 2% | AN85: 1930500 | AO85: 38610
A86: 85 | B86: NORM | C86: 9976AD2211830045 | D86: 6AD2 | E86: A | F86: T-PAK | G86: TOYOTA JINNAH MOTORS | H86: 1094475 | I86: 0705239 | J86: 2 | K86: 26.29 | L86: 0705239001 | M86: ABDUL REHMAN | N86: Lahore | O86: 35202-1658380-7 | P86: 03458461611, 0334-4617900 | Q86: 03458461611, 0334-4617900 | R86: 03458461611 | S86: PLOT NO 380-381 RAVI LANE SUNDAR IN DUSTRIAL ESTATE LAHORE | T86: 2102250 | U86: 2803000 | V86: 2021-09-205-V01501OP0002105 | W86: 02-SEP-2022 | X86: 2A34742 | Y86: NSP150R-7021707 | Z86: NEW | AB86: YARIS ATIV CVT 1.3 | AC86: 2021 | AD86: 02-JUL-2021 | AE86: 21-SEP-2021 | AF86: 21-Sep-2026 | AG86: OLALHR300070327 | AH86: 5 | AI86: ITECL | AJ86: 5410/09/2021 | AK86: 03-SEP-2021 | AM86: 2% | AN86: 2242400 | AO86: 44848
A87: 86 | B87: NORM | C87: 9976AD1210580011 | D87: 6AD1 | E87: A | F87: T-PAK | G87: PRINCE SAJJAD MOTORS | H87: 633662 | I87: 0084680 | J87: 2 | K87: 21.86 | L87: 0084680009 | M87: MUHAMMAD TALHA RASHEED | N87: Rawalpindi | O87: 37405-9507730-3 | P87: 03005214577 | Q87: 03005214577 | R87: 051-5491209 | S87: H # 67-D SECTOR 4-B KHAYABAN E SIRSYED NR D.H.O OFFICE RAWALPINDI | T87: 2956850 | U87: 4549000 | V87: 2021-09-205-V01501DP0002110 | W87: 02-SEP-2022 | X87: 21019969 | Y87: ALR1H1730 | Z87: NEW | AB87: PRINCE GLORY 580 PRO | AC87: 2021 | AD87: 27-FEB-2021 | AE87: 11-SEP-2021 | AF87: 11-Sep-2026 | AG87: OLARWP300066285 | AH87: 5 | AI87: CTRK | AJ87: B0031562 | AK87: 06-SEP-2021 | AM87: 2% | AN87: 3639200 | AO87: 72784
A88: 87 | B88: NORM | C88: 9976AD1211810040 | D88: 6AD1 | E88: A | F88: T-PAK | G88: KIA MACCA MOTORS | H88: 1097834 | I88: 0704828 | J88: 1.75 | K88: 25.95 | L88: 0704828001 | M88: MUDASSER SHAHID | N88: Faisalabad | O88: 33100-0989902-7 | P88: 03217659090 | Q88: 03217659090, 03217659090 | R88: 03217659090 | S88: H NO 61 PARADISE VALLEY SHEIKHUPURA ROAD FAISALABAD PK | T88: 2917020 | U88: 4782000 | V88: DIB/T/33204/LHR/0821 | W88: 02-SEP-2022 | X88: 313847 | Y88: 306935 | Z88: NEW | AB88: SPORTAGE FWD | AC88: 2021 | AD88: 30-JUN-2021 | AE88: 03-OCT-2021 | AF88: 03-Oct-2026 | AG88: OLAFSD300070236 | AH88: 5 | AM88: 1.75% | AN88: 3825600 | AO88: 66948
A89: 88 | B89: NORM | C89: 9976AD2210580011 | D89: 6AD2 | E89: A | F89: T-PAK | G89: MG CENTER | H89: 636858 | I89: 0675736 | J89: 1.75 | K89: 19.87 | L89: 0675736001 | M89: YAHYA MASOOD DAR | N89: Faisalabad | O89: 33100-5686337-3 | P89: 03336533386 | Q89: 03336533386, 03336533386 | R89: 0412500175 | S89: H NO 23-A MADINA TOWN OFFICER COLON Y NO 2 FAISALABAD PK | T89: 3541850 | U89: 5449000 | V89: DIB/T/BT/33214/FSD/0821 | W89: 02-SEP-2022 | X89: 3080081 | Y89: 059722 | Z89: NEW | AB89: MG HS TURBO | AC89: 2021 | AD89: 27-FEB-2021 | AE89: 11-SEP-2021 | AF89: 11-Sep-2026 | AG89: OLAFSD300066229 | AH89: 5 | AI89: CTRK | AJ89: TDIDIB0029566 | AK89: 03-SEP-2021 | AM89: 1.75% | AN89: 4359200 | AO89: 76286
A90: 89 | B90: NORM | C90: 997APD1202680061 | D90: APD1 | E90: A | F90: T-PAK | G90: HONDA EXPRESS PVT LTD | H90: 640552 | I90: 0237825 | J90: 1.5 | K90: 20.3 | L90: 0237825003 | M90: RAANA ZEESHAN | N90: Rawalpindi | O90: 37405-0482476-2 | P90: N/A | Q90: 03455410096 | R90: 4461660 | S90: H # 141 ST # 1 AIRPORT HOUSING SOCIETY SECTOR 1 RAWALPINDI | T90: 2300000 | U90: 2875000 | V90: DIB/T/BT/28251/ISB/0820 | W90: 02-SEP-2021 | X90: 9799259 | Y90: LR262396 | Z90: NEW | AB90: HONDA CITY ASPIRE 1.5 A/T | AC90: 2020 | AD90: 24-SEP-2020 | AE90: 03-SEP-2020 | AF90: 03-Sep-2027 | AG90: PODRWP300056653 | AH90: 7 | AM90: 1.5% | AN90: 2156250 | AO90: 32343.75
A91: 90 | B91: NORM | C91: 9976AD2192100002 | D91: 6AD2 | E91: A | F91: T-PAK | G91: NASEER AUTOS | H91: 578216 | I91: 0547879 | J91: 2.5 | K91: 25.19 | L91: 0547879001 | M91: KIRAN FATIMA | N91: Karachi | O91: 42101-8700799-8 | P91: 03333571867 | Q91: 03333571867, 03333571867 | R91: 03333571867 | S91: FLAT # A-4 AFNAN DUPLEX NEAR KAMRAN CHOWRANGI BLOCK 3-A GULISTAN-E-JOH KARACHI PK | T91: 841750 | U91: 1295000 | V91: 51132/00005/09/2019 | W91: 03-SEP-2020 | X91: 109512 | Y91: 1009498 | Z91: NEW | AA91: BQT-391 | AB91: ALTO VXR AGS EURO-II | AC91: 2019 | AD91: 29-JUL-2019 | AE91: 21-SEP-2019 | AF91: 21-Sep-2026 | AG91: POAKHI300047840 | AH91: 7 | AI91: ITFM | AJ91: 1649/08/2019/ITFM | AK91: 23-SEP-2019 | AM91: 2.5% | AN91: 906500 | AO91: 22662.5
A92: 91 | B92: NORM | C92: 9976AP1232490001 | D92: 6AP1 | E92: A | F92: T-PAK | G92: CITY CARS | H92: 1408905 | I92: 0726894 | J92: 1.5 | K92: 20.87 | L92: 0726894001 | M92: UMAIR ISMAIL | N92: Karachi | O92: 42201-8645528-9 | S92: FLAT NO 370-L BLOCK 3 HAJI LEMO GOTH GULSHAN E IQBAL KARACHI | T92: 3000000 | U92: 6000000 | V92: 74853/00001/09/2023 | W92: 03-SEP-2024 | X92: Q350606 | Y92: R7049790 | Z92: USD | AA92: BUC-943 | AB92: TOYOTA COROLLA ALTIS GRANDE CVT | AC92: 2021 | AD92: 45175 | AE92: 11-SEP-2023 | AF92: 11-Sep-2026 | AG92: OLUKHI300096535 | AH92: 3 | AI92: ITFM | AJ92: 10488/09/2023/ITFM | AK92: 04-SEP-2023 | AM92: 1.5% | AN92: 5400000 | AO92: 81000
A93: 92 | B93: NORM | C93: 9976AD1192120016 | D93: 6AD1 | E93: A | F93: T-PAK | G93: MINI MOTORS | H93: 585736 | I93: 0552977 | J93: 2.5 | K93: 20.87 | L93: 0552977001 | M93: TANZEELA ASHRAF | N93: Lahore | O93: 35202-3282725-8 | P93: 03319315144 | Q93: 03319315144 | R93: 04235441150 | S93: H NO 137 ST NO 8 SECTOR E NISHTAR B LOCK BAHRIA TOWN LAHORE PK | T93: 1036000 | U93: 1295000 | V93: 51132/00013/09/2019 | W93: 04-SEP-2020 | X93: 111794 | Y93: 1011708 | Z93: NEW | AA93: LE-19A-1446 | AB93: ALTO VXL AGS EURO II | AC93: 2019 | AD93: 31-JUL-2019 | AE93: 11-SEP-2019 | AF93: 11-Sep-2026 | AG93: POALHR300048077 | AH93: 7 | AI93: CTRK | AJ93: DIB0027823 | AK93: 06-SEP-2019 | AM93: 2.5% | AN93: 906500 | AO93: 22662.5
A94: 93 | B94: NORM | C94: 9976AD1221400024 | D94: 6AD1 | E94: A | F94: T-PAK | G94: HONDA GATEWAY PVT LTD | H94: 22034621046791 | I94: 0744154 | J94: 1.4 | K94: 18.87 | L94: 0744154004 | M94: MUHAMMAD AWAIS MUNEER | N94: Lahore | O94: 35202-1059168-3 | Q94: 00971522705097 | S94: M 17 MUSAFFAH ABU DHABU 51133 UNITED ARAB EMIRATES | T94: 2377200 | U94: 3396000 | V94: 62089/00082/07/2022 | W94: 04-SEP-2023 | X94: 1012682 | Y94: 022802 | Z94: RDA | AB94: HONDA CIVIC I-VTEC | AC94: 2022 | AD94: 20-MAY-2022 | AE94: 11-SEP-2022 | AF94: 11-Sep-2027 | AG94: OLALHR300087262 | AH94: 5 | AI94: ITFM | AJ94: 8090/07/2022/ITFM | AK94: 20-JUL-2022 | AM94: 1.4% | AN94: 2886600 | AO94: 40412.4
A95: 94 | B95: NORM | C95: 9976AD1220900058 | D95: 6AD1 | E95: A | F95: T-PAK | G95: PAK SUZUKI MOTOR CO LTD | H95: 1149791 | I95: 0521751 | J95: 2 | K95: 22.37 | L95: 0521751003 | M95: KHALID MEHMOOD QURESHI | N95: Rawalpindi | O95: 37405-6717186-9 | P95: 03218502531 | R95: 4446281 | S95: H # B-1334 B-BLOCK SATELLITE TOWN NEAR MASJID UMER RAWALPINDI PK | T95: 1310250 | U95: 1747000 | V95: 62698/00106/08/2022 | W95: 04-SEP-2023 | X95: 247550 | Y95: 1147549 | Z95: NEW | AB95: SUZUKI ALTO VXL AGS EURO II | AC95: 2022 | AD95: 31-MAR-2022 | AE95: 11-SEP-2022 | AF95: 11-Sep-2025 | AG95: OLARWP300086201 | AH95: 3 | AI95: CTRK | AJ95: DIB0034745 | AK95: 05-SEP-2022 | AM95: 2% | AN95: 1484950 | AO95: 29699
A96: 95 | B96: NORM | C96: 9976AD2222360002 | D96: 6AD2 | E96: A | F96: T-PAK | G96: KIA MOTORS MUREE ROAD | H96: AL-1209821 | I96: 0810289 | J96: 2 | K96: 27.44 | L96: 0810289001 | M96: MALIK TAHIR BASHIR | N96: Islamabad | O96: 37405-8477777-9 | P96: 03008501930 | R96: 0514438886 | S96: H # 23 ST # 1 ROSE LANE # 1 NEW LAL AZAR RAWALPINDI PK | T96: 2927400 | U96: 4879000 | V96: 63286/00003/09/2022 | W96: 04-SEP-2023 | X96: 876516 | Y96: 701941 | Z96: NEW | AB96: KIA STONIC EX + | AC96: 2022 | AD96: 24-AUG-2022 | AE96: 21-SEP-2022 | AF96: 21-Sep-2025 | AG96: OLAISD300089502 | AH96: 3 | AI96: ITFT | AJ96: 8601/09/2022/ITFM | AK96: 07-SEP-2022 | AM96: 2% | AN96: 4147150 | AO96: 82943
A97: 96 | B97: NORM | C97: 9976AP2232490002 | D97: 6AP2 | E97: A | F97: T-PAK | G97: AL-QURASH MOTORS | H97: 1441687 | I97: 0901282 | J97: 1.75 | K97: 22.37 | L97: 0901282001 | M97: FAHAD ASHRAF | N97: Lahore | O97: 35201-2118465-7 | P97: 03211486243 | Q97: 03211486243 | R97: 03211486243 | S97: H NO 171-E MOHALLAH BANKER AVENUE C OOPERATIVE HOUSING SOCIETY BEDIAN R LAHORE PK | T97: 2355000 | U97: 7850000 | V97: 74853/00002/09/2023 | W97: 04-SEP-2024 | X97: 180922 | Y97: 206905 | Z97: USD | AA97: AJR-339 | AB97: HYUNDAI TUCSON FWD | AC97: 2022 | AD97: 45175 | AE97: 11-SEP-2023 | AF97: 11-Sep-2025 | AG97: OLULHR300096593 | AH97: 2 | AI97: CTRK | AJ97: DIB0035274 | AK97: 06-SEP-2023 | AM97: 1.75% | AN97: 7065000 | AO97: 123637.5
A98: 97 | B98: NORM | C98: 9976AD2171310003 | D98: 6AD2 | E98: A | F98: T-PAK | G98: PAK SUZUKI MOTOR CO LTD | H98: 333515 | I98: 0405850 | J98: 3.1 | K98: 24.03 | L98: 0405850001 | M98: NASREEN IQBAL NAGANI | N98: Karachi | O98: 42201-8381088-6 | P98: 03463502754 | Q98: 03463502754 | R98: 0 | S98: H NO# 3/A-1 MAKKI SQUARE SHOE MARKET GARDEN EAST KARACHI | T98: 875200 | U98: 1094000 | V98: DIB/T/17528/KHI/0917 | W98: 05-SEP2018 | X98: 139072 | Y98: 10039055 | Z98: NEW | AA98: BKJ-142 | AB98: WAGON R VXL | AC98: 2017 | AD98: 11-MAY-2017 | AE98: 21-SEP-2017 | AF98: 21-Sep-2024 | AG98: POAKHI300021743 | AH98: 7 | AI98: FLCN | AJ98: 13124/09/2017 | AK98: 07-SEP-2017 | AM98: 3.1% | AN98: 0 | AO98: 0
A99: 98 | B99: NORM | C99: 9976AD1211790006 | D99: 6AD1 | E99: A | F99: T-PAK | G99: PAK SUZUKI MOTOR CO LTD | H99: 536205 | I99: 0423485 | J99: 2 | K99: 25.79 | L99: 0423485006 | M99: FARRUKH ABBAS | N99: Lahore | O99: 35202-9924667-9 | P99: 03454181846 | Q99: 03454181846 | R99: 37634642 | S99: H 18 KARIM BAKHSH ROAD NEW SAMANAB AD NEAR BOHAR WALA CHOWK LAHORE PK | T99: 838600 | U99: 1198000 | V99: 2524/02640/00015/09/2021 | W99: 05-SEP-2021 | X99: 6R180191 | Y99: NF1AET306H1080152 | Z99: NEW | AB99: SUZUKI ALTO VX EURO 11 | AC99: 2021 | AD99: 28-JUN-2021 | AE99: 21-SEP-2021 | AF99: 21-Sep-2026 | AG99: OLAHR300069777 | AH99: 5 | AI99: CTRK | AJ99: DIB0031566 | AK99: 06-SEP-2021 | AM99: 2% | AN99: 958400 | AO99: 19168
A100: 99 | B100: NORM | C100: 9976AD1211790007 | D100: 6AD1 | E100: A | F100: T-PAK | G100: PAK SUZUKI MOTOR CO LTD | H100: 536231 | I100: 0423485 | J100: 2 | K100: 25.79 | L100: 0423485004 | M100: FARRUKH ABBAS | N100: Lahore | O100: 35202-9924667-9 | P100: 03454181846 | Q100: 03454181846 | R100: 37634642 | S100: H 18 KARIM BAKHSH ROAD NEW SAMANAB AD NEAR BOHAR WALA CHOWK LAHORE PK | T100: 958400 | U100: 1198000 | V100: 2524/02640/00014/09/2021 | W100: 05-SEP-2022 | X100: 6R180061 | Y100: NF1AET306H1080070 | Z100: NEW | AB100: SUZUKI ALTO VX-11 | AC100: 2021 | AD100: 28-JUN-2021 | AE100: 27-SEP-2021 | AF100: 27-Sep-2026 | AG100: OLAHR300069667 | AH100: 5 | AI100: CTRK | AJ100: DIB0031568 | AK100: 06-SEP-2021 | AM100: 2% | AN100: 958400 | AO100: 19168
...

Sheet Sheet1
AO1: =SUBTOTAL(9,AO3:AO325) -> 14988194
A2: Sr. | B2: Status | C2: Contract No. | D2: Class Code | E2: Contract Status | F2: Insurance Agency | G2: Dealer Name | H2: App ID | I2: CIF # | J2: Insurance Rate | K2: Profit Rate | L2: ISI Account No. | M2: Customer Name | N2: City | O2: CNIC No. | P2: Home Phone# | Q2: Mobile Number | R2: Business Phone# | S2: Mail Address | T2: Finance Amount | U2: Car Price | V2: Ins. Policy | W2: Ins. Expiry Date | X2: Engine No. | Y2: Chassis No. | Z2: Car Category | AA2: Reg. No. | AB2: Car Name | AC2: Model | AD2: Contract Booking Date | AE2: Contract Value Date | AF2: Contract Maturity Date | AG2: Purchase Order No. | AH2: Tenor#2 | AI2: Tracker Company | AJ2: Tracker Reference Number | AK2: Tracker Installation Date | AL2: Contract No.2 | AM2: Rate | AN2: Sum Insured | AO2: Premium | AP2: OLD Contract Ref | AQ2: Remarks-I | AR2: Remarks-II | AS2: Policy # | AT2: End. # | AU2: Tms prem | AV2: Difference | AW2: Tagging | AX2: End. Amount | AY2: End. Difference
A3: 1 | B3: NORM | C3: 9976AD1211510031 | D3: 6AD1 | E3: A | F3: T-PAK | G3: PAK SUZUKI MOTOR CO LTD | H3: 649576 | I3: 0695379 | J3: 2 | K3: 25.79 | L3: 0695379001 | M3: MARYAM SIDDIQA | N3: Rahim Yar Khan | O3: 31303-5638787-8 | P3: 03342844446 | Q3: 03342844446 | R3: 03342844446 | S3: HOUSE NO 120-D SCHEME 03 BLOCK Y GU LSHAN IQBAL COLONY RAHIM YAR KHAN PK | T3: 801000 | U3: 1335000 | V3: DIB/T/BT/33330/LHR/0921 | W3: 01-SEP-2022 | X3: 180368 | Y3: 1080364 | Z3: NEW | AB3: ALTO VXR EURO-II | AC3: 2021 | AD3: 31-MAY-2021 | AE3: 03-OCT-2021 | AF3: 03-Oct-2028 | AG3: OLARYK300069033 | AH3: 7 | AI3: FLCN | AJ3: 108568/09/2021 | AK3: 02-SEP-2021 | AM3: 2% | AN3: 1068000 | AO3: 21360 | AS3: KHI/HO/D/MO/PC COMP/C/97805/1/09/2024 | AU3: 21360 | AV3: 0 | AW3: REN
A4: 2 | B4: NORM | C4: 997AAD1202090003 | D4: AAD1 | E4: A | F4: T-PAK | G4: HONDA CHENAB-GREEN VIEW MOTORS | H4: 593276 | I4: 0621607 | J4: 2 | K4: 20.8 | L4: 0621607001 | M4: MUHAMMAD LATIF | N4: SHEIKUPURA | O4: 34103-0458295-1 | P4: 03008893133 | Q4: 03138893133, 03008893133 | R4: 03008893133 | S4: GALI LATIF DOGAR WALI GUJRAWANWALA ROAD MOHALLAH ATA ABAD NEAR SHISH M SHEIKHUPURA PK | T4: 1916000 | U4: 2395000 | V4: DIB/T/BT/28482/LHR/0920 | W4: 01-SEP-2021 | X4: L13Z17540161 | Y4: NFBGM1544LR262747 | Z4: NEW | AB4: CITY IVTEC M/T | AC4: 2020 | AD4: 27-JUL-2020 | AE4: 11-SEP-2020 | AF4: 11-Sep-2025 | AG4: POASHK300055899 | AH4: 5 | AI4: ITFM | AJ4: 09/2020/ITFM | AK4: 02-SEP-2020 | AM4: 2% | AN4: 1796250 | AO4: 35925 | AS4: KHI/HO/D/MO/PC COMP/C/97805/2/09/2024 | AT4: KHI/HO/D/MO/PC COMP/E/47950/00002/10/2024 | AU4: 40715 | AV4: -4790 | AW4: REN | AX4: -4790 | AY4: 0
A5: 3 | B5: NORM | C5: 9976AD1211680026 | D5: 6AD1 | E5: A | F5: T-PAK | G5: KIA MOTORS TOWNSHIP | H5: 633467 | I5: 0699405 | J5: 2 | K5: 25.79 | L5: 0699405001 | M5: SHAHID IQBAL | N5: Sialkot | O5: 34603-6763335-7 | P5: 03026486200 | Q5: 03026486200 | R5: 03326486200 | S5: NEAR OPPOSITE CHINA HOTEL B-BLOCK C ITY HOUSING SOCIETY SIALKOT | T5: 2880800 | U5: 4432000 | V5: UWT/D/P002/0000000984/0921/109 | W5: 01-SEP-2022 | X5: 312732 | Y5: 101956 | Z5: NEW | AB5: SPORTGE ALPHA | AC5: 2021 | AD5: 17-JUN-2021 | AE5: 27-SEP-2021 | AF5: 27-Sep-2026 | AG5: OLASKT300069462 | AH5: 5 | AM5: 2% | AN5: 3545600 | AO5: 70912 | AS5: KHI/HO/D/MO/PC COMP/C/97805/3/09/2024 | AU5: 70912 | AV5: 0 | AW5: REN
A6: 4 | B6: NORM | C6: 9976AD1211670015 | D6: 6AD1 | E6: A | F6: T-PAK | G6: KIA MOTORS TOWNSHIP | H6: 526980 | I6: 0698981 | J6: 2 | K6: 26.29 | L6: 0698981001 | M6: MUHAMMAD SALEEM | N6: Sialkot | O6: 34603-0385945-5 | P6: 03456861572 | Q6: 03456861572 | R6: 05235422700 | S6: ANJOTAR HUNDAL ROAD NEAR GOVT HIGH SCHOOL SIALKOT | T6: 3102400 | U6: 4432000 | V6: UWT/D/T002/0000001040/0921/109-0 | W6: 01-SEP-2022 | X6: 314208 | Y6: 102175 | Z6: NEW | AB6: KIA SPORTAGE ALPHA | AC6: 2021 | AD6: 16-JUN-2021 | AE6: 21-SEP-2021 | AF6: 21-Sep-2026 | AG6: OLDSKT300069423 | AH6: 5 | AM6: 2% | AN6: 3545600 | AO6: 70912 | AS6: KHI/HO/D/MO/PC COMP/C/97805/4/09/2024 | AU6: 70912 | AV6: 0 | AW6: REN
A7: 5 | B7: NORM | C7: 997AAD1201740007 | D7: AAD1 | E7: A | F7: T-PAK | G7: KIA MOTORS MUREE ROAD | H7: 581825 | I7: 0614893 | J7: 1.5 | K7: 20.8 | L7: 0614893001 | M7: MIAN MUHAMMAD USMAN | N7: Rawalpindi | O7: 37405-9191077-3 | P7: 03325001991 | Q7: 03325001991 | R7: 0518449997 | S7: H # 341 ST # 37 UMER BLOCK BAHRIA T OWN PHASE-8 RAWALPINDI PK | T7: 3995260 | U7: 5399000 | V7: DIB/T/BT/28484/ISB/0920 | W7: 01-SEP-2021 | X7: G4NALH310866 | Y7: NNAQL51AZKP504398 | Z7: NEW | AB7: KIA SPORTAGE AWD | AC7: 2020 | AD7: 22-JUN-2020 | AE7: 11-SEP-2020 | AF7: 11-Sep-2025 | AG7: POARWP300054451 | AH7: 5 | AM7: 1.5% | AN7: 4049250 | AO7: 60738.75 | AS7: KHI/HO/D/MO/PC COMP/C/97805/5/09/2024 | AT7: KHI/HO/D/MO/PC COMP/E/47950/00005/10/2024 | AU7: 68837 | AV7: -8098.25 | AW7: REN | AX7: -8099 | AY7: 0.75
A8: 6 | B8: NORM | C8: 9976AD2210880002 | D8: 6AD2 | E8: A | F8: T-PAK | G8: TOYOTA AIRPORT MOTOR | H8: 599353 | I8: 0059143 | J8: 1.75 | K8: 26.18 | L8: 0059143008 | M8: RAZA ISHAQ BABAR | N8: Lahore | O8: 35201-1236948-3 | Q8: 03217736777 | R8: 37309855 | S8: HOUSE NO 41 FF BLOCK DHA PHASE 04 LAHORE | T8: 4953200 | U8: 7076000 | V8: DIB/T/BT/3327/LHR/0921 | W8: 01-SEP-2022 | X8: 2GD5028612 | Y8: GUN126R-5547602 | Z8: NEW | AB8: TOYOTA HILUX REVO V DC A/T 4X4 | AC8: 2021 | AD8: 29-MAR-2021 | AE8: 21-SEP-2021 | AF8: 21-Sep-2026 | AG8: OLALHR300067061 | AH8: 5 | AI8: CTRK | AJ8: TDIDIB0029595 | AK8: 02-SEP-2021 | AM8: 1.75% | AN8: 5660800 | AO8: 99064 | AS8: KHI/HO/D/MO/PC COMP/C/97805/7/09/2024 | AU8: 99064 | AV8: 0 | AW8: REN
A9: 7 | B9: NORM | C9: 9976AD2211810008 | D9: 6AD2 | E9: A | F9: T-PAK | G9: TOYOTA RAWAL MOTORS | H9: 579222 | I9: 0697627 | J9: 2 | K9: 22.47 | L9: 0697627002 | M9: BIBI SALMA ZAHID NAQVI | N9: Haripur | O9: 13302-5232838-2 | Q9: 03305849914 | S9: W/O ZAHID UL HASSAN ST # 7 H # 13 TIP HOUSING COLONY HRP CITY TEHSIL & DIST. HARIPUR PAKISTAN | T9: 2102250 | U9: 2803000 | V9: UWT/D/T002/0000001039/0921/109-0 | W9: 01-SEP-2022 | X9: 2A34671 | Y9: 150R-7021678 | Z9: NEW | AB9: YARIS ATIV CVT 1.3 | AC9: 2021 | AD9: 30-JUN-2021 | AE9: 11-SEP-2021 | AF9: 11-Sep-2026 | AG9: OLAHRP300070037 | AH9: 5 | AI9: ITECL | AJ9: 5404/09/2021 | AK9: 02-SEP-2021 | AM9: 2% | AN9: 2242400 | AO9: 44848 | AS9: KHI/HO/D/MO/PC COMP/C/97805/8/09/2024 | AU9: 44848 | AV9: 0 | AW9: REN
A10: 8 | B10: NORM | C10: 9976AD1222340001 | D10: 6AD1 | E10: A | F10: T-PAK | G10: KIA MACCA MOTORS | H10: 1204280 | I10: 0388812 | J10: 2 | K10: 26.69 | L10: 0388812006 | M10: FARHAN AHMED | N10: Karachi | O10: 42101-1940633-7 | Q10: 03368518786 | S10: HOUSE NO D49/1 BLOCK 6 F.B.AREA KARACHI NEAR BY RANGERS HEADQUARTERS | T10: 1820000 | U10: 2600000 | V10: 63286/00002/09/2022 | W10: 01-SEP-2023 | X10: 030853 | Y10: 504085 | Z10: NEW | AB10: KIA PICANTO 1.0 L MT | AC10: 2022 | AD10: 22-AUG-2022 | AE10: 21-SEP-2022 | AF10: 21-Sep-2025 | AG10: OLAKHI300089389 | AH10: 3 | AI10: ITFM | AJ10: 8454/08/2022/ITFM | AK10: 26-AUG-2022 | AM10: 2% | AN10: 2210000 | AO10: 44200 | AS10: KHI/HO/D/MO/PC COMP/C/97805/9/09/2024 | AU10: 44200 | AV10: 0 | AW10: REN
A11: 9 | B11: NORM | C11: 9976AD1211660012 | D11: 6AD1 | E11: A | F11: T-PAK | G11: SUZUKI MINI MOTORS | H11: 1104677 | I11: 0693673 | J11: 2 | K11: 25.79 | L11: 0693673001 | M11: SALMAN AMJAD | N11: Lahore | O11: 35202-4109105-3 | P11: 03333333626 | Q11: 03333333626 | R11: 03333333626 | S11: ISLAMIC HOUSE 99-A TRICON VILLAGE LAHORE | T11: 1146400 | U11: 1433000 | V11: 2524/02640/00010/09/2021 | W11: 02-SEP-2022 | X11: 6R181159 | Y11: NF1AET306H1081166 | Z11: NEW | AB11: SUZUKI ALTO VXR EURO | AC11: 2021 | AD11: 15-JUN-2021 | AE11: 21-SEP-2021 | AF11: 21-Sep-2026 | AG11: OLALHR300069461 | AH11: 5 | AI11: ITECL | AJ11: 5409/09/2021 | AK11: 03-SEP-2021 | AM11: 2% | AN11: 1146400 | AO11: 22928 | AS11: KHI/HO/D/MO/PC COMP/C/97805/13/09/2024 | AU11: 22928 | AV11: 0 | AW11: REN
A12: 10 | B12: NORM | C12: 9976AP2212510006 | D12: 6AP2 | E12: A | F12: T-PAK | G12: MARGALLA MOTORS | H12: 625980 | I12: 0616216 | J12: 2 | K12: 22.02 | L12: 0616216002 | M12: MUHAMMAD HASSAN KHAN | N12: Karachi | O12: 42501-9396639-5 | Q12: 03340295259 | S12: HOUSE # R- 210 CAPITAL SOCIETY SCHEME # 33 NEAR SAFOORA CHOWRANGI KARACHI. | T12: 1408000 | U12: 1760000 | V12: 55601/00004/09/2021 | W12: 02-SEP-2022 | X12: 218938 | Y12: 10118958 | Z12: NEW | AB12: WAGONR VXL AGS | AC12: 2021 | AD12: 08-SEP-2021 | AE12: 11-SEP-2021 | AF12: 11-Sep-2028 | AG12: OLDKHI300073107 | AH12: 7 | AI12: CTRK | AJ12: DIB0031542 | AK12: 08-SEP-2021 | AM12: 2% | AN12: 1408000 | AO12: 28160 | AS12: KHI/HO/D/MO/PC COMP/C/97805/14/09/2024 | AU12: 28160 | AV12: 0 | AW12: REN
A13: 11 | B13: NORM | C13: 997AAD2202120003 | D13: AAD2 | E13: A | F13: T-PAK | G13: HONDA CHENAB-GREEN VIEW MOTORS | H13: 598313 | I13: 0495988 | J13: 2 | K13: 21.05 | L13: 0495988003 | M13: ABDUL REHMAN | N13: Faisalabad | O13: 33100-4936955-5 | P13: 2695119 | Q13: 03028655454, 03028655454 | R13: 03028655454 | S13: 522-A BLOCK GM ABAD FAISALABAD PK | T13: 1921200 | U13: 2401500 | V13: 2524/0211/00003/09/2020 | W13: 02-SEP-2021 | X13: L13Z17540156 | Y13: NFBGM1545LR262742 | Z13: NEW | AA13: ARF-522 | AB13: HONDA CITY IVTEC M/T | AC13: 2020 | AD13: 30-JUL-2020 | AE13: 11-SEP-2020 | AF13: 11-Sep-2025 | AG13: POAFSD300056085 | AH13: 5 | AI13: ITFM | AJ13: 2943/09/2020/ITFM | AK13: 03-SEP-2020 | AM13: 2% | AN13: 1801125 | AO13: 36022.5 | AS13: KHI/HO/D/MO/PC COMP/C/97805/15/09/2024 | AT13: KHI/HO/D/MO/PC COMP/E/47950/00015/10/2024 | AU13: 40826 | AV13: -4803.5 | AW13: REN | AX13: -4803 | AY13: -0.5
A14: 12 | B14: NORM | C14: 9976AD1211510008 | D14: 6AD1 | E14: A | F14: T-PAK | G14: PAK SUZUKI MOTOR CO LTD | H14: 639041 | I14: 0132188 | J14: 2 | K14: 25.79 | L14: 0132188003 | M14: NASIR MEHMOOD | N14: Lahore | O14: 45504-1133892-3 | Q14: 0343-6600006, 0319-3118020 | R14: 051-2096014 | S14: H NO E-66 SHERAZ VILLAS PHASE II GAVALRY GROUND LAHORE | T14: 1704000 | U14: 2130000 | V14: 2021-09-205-V015010PD002106 | W14: 02-SEP-2022 | X14: 183356 | Y14: 10083360 | Z14: NEW | AB14: SUZUKI CULTUS VXL AGS EURO II | AC14: 2021 | AD14: 31-MAY-2021 | AE14: 03-OCT-2021 | AF14: 03-Oct-2026 | AG14: OLALHR300069018 | AH14: 5 | AI14: CTRK | AJ14: DIB0031548 | AK14: 06-SEP-2021 | AM14: 2% | AN14: 1704000 | AO14: 34080 | AS14: KHI/HO/D/MO/PC COMP/C/97805/18/09/2024 | AU14: 34080 | AV14: 0 | AW14: REN
A15: 13 | B15: NORM | C15: 997AAD1202530011 | D15: AAD1 | E15: A | F15: T-PAK | G15: HONDA AVENUE | H15: 635431 | I15: 0630360 | J15: 2 | K15: 27.93 | L15: 0630360001 | M15: SHEIKH AHSAN ANJUM | N15: Islamabad | O15: 37405-2517483-1 | P15: 03218505189 | R15: 0515772064 | S15: H # 184 ST # 11 BLOCK-D MEDIA TOWN ISLAMABAD PK | T15: 2187900 | U15: 2574000 | V15: DIB/T/BT/28487/ISB/0920 | W15: 02-SEP-2021 | X15: 7540202 | Y15: LR262950 | Z15: NEW | AB15: CITY IVTEC P/T | AC15: 2020 | AD15: 09-SEP-2020 | AE15: 21-SEP-2020 | AF15: 21-Sep-2025 | AG15: POAISD300057149 | AH15: 5 | AI15: CTRK | AJ15: TDIDIB0028623 | AK15: 08-SEP-2020 | AM15: 2% | AN15: 1930500 | AO15: 38610 | AS15: KHI/HO/D/MO/PC COMP/C/97805/19/09/2024 | AT15: KHI/HO/D/MO/PC COMP/E/47950/00019/10/2024 | AU15: 43758 | AV15: -5148 | AW15: REN | AX15: -5148 | AY15: 0
A16: 14 | B16: NORM | C16: 9976AD2211830045 | D16: 6AD2 | E16: A | F16: T-PAK | G16: TOYOTA JINNAH MOTORS | H16: 1094475 | I16: 0705239 | J16: 2 | K16: 26.29 | L16: 0705239001 | M16: ABDUL REHMAN | N16: Lahore | O16: 35202-1658380-7 | P16: 03458461611, 0334-4617900 | Q16: 03458461611, 0334-4617900 | R16: 03458461611 | S16: PLOT NO 380-381 RAVI LANE SUNDAR IN DUSTRIAL ESTATE LAHORE | T16: 2102250 | U16: 2803000 | V16: 2021-09-205-V01501OP0002105 | W16: 02-SEP-2022 | X16: 2A34742 | Y16: NSP150R-7021707 | Z16: NEW | AB16: YARIS ATIV CVT 1.3 | AC16: 2021 | AD16: 02-JUL-2021 | AE16: 21-SEP-2021 | AF16: 21-Sep-2026 | AG16: OLALHR300070327 | AH16: 5 | AI16: ITECL | AJ16: 5410/09/2021 | AK16: 03-SEP-2021 | AM16: 2% | AN16: 2242400 | AO16: 44848 | AS16: KHI/HO/D/MO/PC COMP/C/97805/21/09/2024 | AU16: 44848 | AV16: 0 | AW16: REN | BA16: 323
A17: 15 | B17: NORM | C17: 9976AD1210580011 | D17: 6AD1 | E17: A | F17: T-PAK | G17: PRINCE SAJJAD MOTORS | H17: 633662 | I17: 0084680 | J17: 2 | K17: 21.86 | L17: 0084680009 | M17: MUHAMMAD TALHA RASHEED | N17: Rawalpindi | O17: 37405-9507730-3 | P17: 03005214577 | Q17: 03005214577 | R17: 051-5491209 | S17: H # 67-D SECTOR 4-B KHAYABAN E SIRSYED NR D.H.O OFFICE RAWALPINDI | T17: 2956850 | U17: 4549000 | V17: 2021-09-205-V01501DP0002110 | W17: 02-SEP-2022 | X17: 21019969 | Y17: ALR1H1730 | Z17: NEW | AB17: PRINCE GLORY 580 PRO | AC17: 2021 | AD17: 27-FEB-2021 | AE17: 11-SEP-2021 | AF17: 11-Sep-2026 | AG17: OLARWP300066285 | AH17: 5 | AI17: CTRK | AJ17: B0031562 | AK17: 06-SEP-2021 | AM17: 2% | AN17: 3639200 | AO17: 72784 | AS17: KHI/HO/D/MO/PC COMP/C/97805/23/09/2024 | AU17: 72784 | AV17: 0 | AW17: REN | BA17: 145
A18: 16 | B18: NORM | C18: 9976AD1211810040 | D18: 6AD1 | E18: A | F18: T-PAK | G18: KIA MACCA MOTORS | H18: 1097834 | I18: 0704828 | J18: 1.75 | K18: 25.95 | L18: 0704828001 | M18: MUDASSER SHAHID | N18: Faisalabad | O18: 33100-0989902-7 | P18: 03217659090 | Q18: 03217659090, 03217659090 | R18: 03217659090 | S18: H NO 61 PARADISE VALLEY SHEIKHUPURA ROAD FAISALABAD PK | T18: 2917020 | U18: 4782000 | V18: DIB/T/33204/LHR/0821 | W18: 02-SEP-2022 | X18: 313847 | Y18: 306935 | Z18: NEW | AB18: SPORTAGE FWD | AC18: 2021 | AD18: 30-JUN-2021 | AE18: 03-OCT-2021 | AF18: 03-Oct-2026 | AG18: OLAFSD300070236 | AH18: 5 | AM18: 1.75% | AN18: 3825600 | AO18: 66948 | AS18: KHI/HO/D/MO/PC COMP/C/97805/24/09/2024 | AU18: 66948 | AV18: 0 | AW18: REN | BA18: =SUM(BA16:BA17) -> 468
A19: 17 | B19: NORM | C19: 9976AD2210580011 | D19: 6AD2 | E19: A | F19: T-PAK | G19: MG CENTER | H19: 636858 | I19: 0675736 | J19: 1.75 | K19: 19.87 | L19: 0675736001 | M19: YAHYA MASOOD DAR | N19: Faisalabad | O19: 33100-5686337-3 | P19: 03336533386 | Q19: 03336533386, 03336533386 | R19: 0412500175 | S19: H NO 23-A MADINA TOWN OFFICER COLON Y NO 2 FAISALABAD PK | T19: 3541850 | U19: 5449000 | V19: DIB/T/BT/33214/FSD/0821 | W19: 02-SEP-2022 | X19: 3080081 | Y19: 059722 | Z19: NEW | AB19: MG HS TURBO | AC19: 2021 | AD19: 27-FEB-2021 | AE19: 11-SEP-2021 | AF19: 11-Sep-2026 | AG19: OLAFSD300066229 | AH19: 5 | AI19: CTRK | AJ19: TDIDIB0029566 | AK19: 03-SEP-2021 | AM19: 1.75% | AN19: 4359200 | AO19: 76286 | AS19: KHI/HO/D/MO/PC COMP/C/97805/25/09/2024 | AU19: 76286 | AV19: 0 | AW19: REN
A20: 18 | B20: NORM | C20: 997APD1202680061 | D20: APD1 | E20: A | F20: T-PAK | G20: HONDA EXPRESS PVT LTD | H20: 640552 | I20: 0237825 | J20: 1.5 | K20: 20.3 | L20: 0237825003 | M20: RAANA ZEESHAN | N20: Rawalpindi | O20: 37405-0482476-2 | P20: N/A | Q20: 03455410096 | R20: 4461660 | S20: H # 141 ST # 1 AIRPORT HOUSING SOCIETY SECTOR 1 RAWALPINDI | T20: 2300000 | U20: 2875000 | V20: DIB/T/BT/28251/ISB/0820 | W20: 02-SEP-2021 | X20: 9799259 | Y20: LR262396 | Z20: NEW | AB20: HONDA CITY ASPIRE 1.5 A/T | AC20: 2020 | AD20: 24-SEP-2020 | AE20: 03-SEP-2020 | AF20: 03-Sep-2027 | AG20: PODRWP300056653 | AH20: 7 | AM20: 1.5% | AN20: 2156250 | AO20: 32343.75 | AS20: KHI/HO/D/MO/PC COMP/C/97805/26/09/2024 | AU20: 32344 | AV20: -0.25 | AW20: REN
A21: 19 | B21: NORM | C21: 9976AD2192100002 | D21: 6AD2 | E21: A | F21: T-PAK | G21: NASEER AUTOS | H21: 578216 | I21: 0547879 | J21: 2.5 | K21: 25.19 | L21: 0547879001 | M21: KIRAN FATIMA | N21: Karachi | O21: 42101-8700799-8 | P21: 03333571867 | Q21: 03333571867, 03333571867 | R21: 03333571867 | S21: FLAT # A-4 AFNAN DUPLEX NEAR KAMRAN CHOWRANGI BLOCK 3-A GULISTAN-E-JOH KARACHI PK | T21: 841750 | U21: 1295000 | V21: 51132/00005/09/2019 | W21: 03-SEP-2020 | X21: 109512 | Y21: 1009498 | Z21: NEW | AA21: BQT-391 | AB21: ALTO VXR AGS EURO-II | AC21: 2019 | AD21: 29-JUL-2019 | AE21: 21-SEP-2019 | AF21: 21-Sep-2026 | AG21: POAKHI300047840 | AH21: 7 | AI21: ITFM | AJ21: 1649/08/2019/ITFM | AK21: 23-SEP-2019 | AM21: 2.5% | AN21: 906500 | AO21: 22662.5 | AS21: KHI/HO/D/MO/PC COMP/C/97805/28/09/2024 | AT21: KHI/HO/D/MO/PC COMP/E/47950/00028/10/2024 | AU21: 25900 | AV21: -3237.5 | AW21: REN | AX21: -3238 | AY21: 0.5
A22: 20 | B22: NORM | C22: 9976AP1232490001 | D22: 6AP1 | E22: A | F22: T-PAK | G22: CITY CARS | H22: 1408905 | I22: 0726894 | J22: 1.5 | K22: 20.87 | L22: 0726894001 | M22: UMAIR ISMAIL | N22: Karachi | O22: 42201-8645528-9 | S22: FLAT NO 370-L BLOCK 3 HAJI LEMO GOTH GULSHAN E IQBAL KARACHI | T22: 3000000 | U22: 6000000 | V22: 74853/00001/09/2023 | W22: 03-SEP-2024 | X22: Q350606 | Y22: R7049790 | Z22: USD | AA22: BUC-943 | AB22: TOYOTA COROLLA ALTIS GRANDE CVT | AC22: 2021 | AD22: 45175 | AE22: 11-SEP-2023 | AF22: 11-Sep-2026 | AG22: OLUKHI300096535 | AH22: 3 | AI22: ITFM | AJ22: 10488/09/2023/ITFM | AK22: 04-SEP-2023 | AM22: 1.5% | AN22: 5400000 | AO22: 81000 | AS22: KHI/HO/D/MO/PC COMP/C/97805/34/09/2024 | AT22: KHI/HO/D/MO/PC COMP/E/47950/00034/10/2024 | AU22: 76500 | AV22: 4500 | AW22: REN | AX22: 4500 | AY22: 0
A23: 21 | B23: NORM | C23: 9976AD1192120016 | D23: 6AD1 | E23: A | F23: T-PAK | G23: MINI MOTORS | H23: 585736 | I23: 0552977 | J23: 2.5 | K23: 20.87 | L23: 0552977001 | M23: TANZEELA ASHRAF | N23: Lahore | O23: 35202-3282725-8 | P23: 03319315144 | Q23: 03319315144 | R23: 04235441150 | S23: H NO 137 ST NO 8 SECTOR E NISHTAR B LOCK BAHRIA TOWN LAHORE PK | T23: 1036000 | U23: 1295000 | V23: 51132/00013/09/2019 | W23: 04-SEP-2020 | X23: 111794 | Y23: 1011708 | Z23: NEW | AA23: LE-19A-1446 | AB23: ALTO VXL AGS EURO II | AC23: 2019 | AD23: 31-JUL-2019 | AE23: 11-SEP-2019 | AF23: 11-Sep-2026 | AG23: POALHR300048077 | AH23: 7 | AI23: CTRK | AJ23: DIB0027823 | AK23: 06-SEP-2019 | AM23: 2.5% | AN23: 906500 | AO23: 22662.5 | AS23: KHI/HO/D/MO/PC COMP/C/97805/37/09/2024 | AT23: KHI/HO/D/MO/PC COMP/E/47950/00037/10/2024 | AU23: 25900 | AV23: -3237.5 | AW23: REN | AX23: -3238 | AY23: 0.5
A24: 22 | B24: NORM | C24: 9976AD1221400024 | D24: 6AD1 | E24: A | F24: T-PAK | G24: HONDA GATEWAY PVT LTD | H24: 22034621046791 | I24: 0744154 | J24: 1.4 | K24: 18.87 | L24: 0744154004 | M24: MUHAMMAD AWAIS MUNEER | N24: Lahore | O24: 35202-1059168-3 | Q24: 00971522705097 | S24: M 17 MUSAFFAH ABU DHABU 51133 UNITED ARAB EMIRATES | T24: 2377200 | U24: 3396000 | V24: 62089/00082/07/2022 | W24: 04-SEP-2023 | X24: 1012682 | Y24: 022802 | Z24: RDA | AB24: HONDA CIVIC I-VTEC | AC24: 2022 | AD24: 20-MAY-2022 | AE24: 11-SEP-2022 | AF24: 11-Sep-2027 | AG24: OLALHR300087262 | AH24: 5 | AI24: ITFM | AJ24: 8090/07/2022/ITFM | AK24: 20-JUL-2022 | AM24: 1.4% | AN24: 2886600 | AO24: 40412.4 | AS24: KHI/HO/D/MO/PC COMP/C/97805/38/09/2024 | AT24: KHI/HO/D/MO/PC COMP/E/47950/00038/10/2024 | AU24: 35658 | AV24: 4754.4 | AW24: REN | AX24: 4754 | AY24: 0.4
A25: 23 | B25: NORM | C25: 9976AD1220900058 | D25: 6AD1 | E25: A | F25: T-PAK | G25: PAK SUZUKI MOTOR CO LTD | H25: 1149791 | I25: 0521751 | J25: 2 | K25: 22.37 | L25: 0521751003 | M25: KHALID MEHMOOD QURESHI | N25: Rawalpindi | O25: 37405-6717186-9 | P25: 03218502531 | R25: 4446281 | S25: H # B-1334 B-BLOCK SATELLITE TOWN NEAR MASJID UMER RAWALPINDI PK | T25: 1310250 | U25: 1747000 | V25: 62698/00106/08/2022 | W25: 04-SEP-2023 | X25: 247550 | Y25: 1147549 | Z25: NEW | AB25: SUZUKI ALTO VXL AGS EURO II | AC25: 2022 | AD25: 31-MAR-2022 | AE25: 11-SEP-2022 | AF25: 11-Sep-2025 | AG25: OLARWP300086201 | AH25: 3 | AI25: CTRK | AJ25: DIB0034745 | AK25: 05-SEP-2022 | AM25: 2% | AN25: 1484950 | AO25: 29699 | AS25: KHI/HO/D/MO/PC COMP/C/97805/40/09/2024 | AU25: 29699 | AV25: 0 | AW25: REN
A26: 24 | B26: NORM | C26: 9976AD2222360002 | D26: 6AD2 | E26: A | F26: T-PAK | G26: KIA MOTORS MUREE ROAD | H26: AL-1209821 | I26: 0810289 | J26: 2 | K26: 27.44 | L26: 0810289001 | M26: MALIK TAHIR BASHIR | N26: Islamabad | O26: 37405-8477777-9 | P26: 03008501930 | R26: 0514438886 | S26: H # 23 ST # 1 ROSE LANE # 1 NEW LAL AZAR RAWALPINDI PK | T26: 2927400 | U26: 4879000 | V26: 63286/00003/09/2022 | W26: 04-SEP-2023 | X26: 876516 | Y26: 701941 | Z26: NEW | AB26: KIA STONIC EX + | AC26: 2022 | AD26: 24-AUG-2022 | AE26: 21-SEP-2022 | AF26: 21-Sep-2025 | AG26: OLAISD300089502 | AH26: 3 | AI26: ITFT | AJ26: 8601/09/2022/ITFM | AK26: 07-SEP-2022 | AM26: 2% | AN26: 4147150 | AO26: 82943 | AS26: KHI/HO/D/MO/PC COMP/C/97805/41/09/2024 | AU26: 82943 | AV26: 0 | AW26: REN
A27: 25 | B27: NORM | C27: 9976AP2232490002 | D27: 6AP2 | E27: A | F27: T-PAK | G27: AL-QURASH MOTORS | H27: 1441687 | I27: 0901282 | J27: 1.75 | K27: 22.37 | L27: 0901282001 | M27: FAHAD ASHRAF | N27: Lahore | O27: 35201-2118465-7 | P27: 03211486243 | Q27: 03211486243 | R27: 03211486243 | S27: H NO 171-E MOHALLAH BANKER AVENUE C OOPERATIVE HOUSING SOCIETY BEDIAN R LAHORE PK | T27: 2355000 | U27: 7850000 | V27: 74853/00002/09/2023 | W27: 04-SEP-2024 | X27: 180922 | Y27: 206905 | Z27: USD | AA27: AJR-339 | AB27: HYUNDAI TUCSON FWD | AC27: 2022 | AD27: 45175 | AE27: 11-SEP-2023 | AF27: 11-Sep-2025 | AG27: OLULHR300096593 | AH27: 2 | AI27: CTRK | AJ27: DIB0035274 | AK27: 06-SEP-2023 | AM27: 1.75% | AN27: 7065000 | AO27: 123637.5 | AS27: KHI/HO/D/MO/PC COMP/C/97805/45/09/2024 | AU27: 123638 | AV27: -0.5 | AW27: REN
A28: 26 | B28: NORM | C28: 9976AD1211790006 | D28: 6AD1 | E28: A | F28: T-PAK | G28: PAK SUZUKI MOTOR CO LTD | H28: 536205 | I28: 0423485 | J28: 2 | K28: 25.79 | L28: 0423485006 | M28: FARRUKH ABBAS | N28: Lahore | O28: 35202-9924667-9 | P28: 03454181846 | Q28: 03454181846 | R28: 37634642 | S28: H 18 KARIM BAKHSH ROAD NEW SAMANAB AD NEAR BOHAR WALA CHOWK LAHORE PK | T28: 838600 | U28: 1198000 | V28: 2524/02640/00015/09/2021 | W28: 05-SEP-2021 | X28: 6R180191 | Y28: NF1AET306H1080152 | Z28: NEW | AB28: SUZUKI ALTO VX EURO 11 | AC28: 2021 | AD28: 28-JUN-2021 | AE28: 21-SEP-2021 | AF28: 21-Sep-2026 | AG28: OLAHR300069777 | AH28: 5 | AI28: CTRK | AJ28: DIB0031566 | AK28: 06-SEP-2021 | AM28: 2% | AN28: 958400 | AO28: 19168 | AS28: KHI/HO/D/MO/PC COMP/C/97805/53/09/2024 | AU28: 19168 | AV28: 0 | AW28: REN
A29: 27 | B29: NORM | C29: 9976AD1211790007 | D29: 6AD1 | E29: A | F29: T-PAK | G29: PAK SUZUKI MOTOR CO LTD | H29: 536231 | I29: 0423485 | J29: 2 | K29: 25.79 | L29: 0423485004 | M29: FARRUKH ABBAS | N29: Lahore | O29: 35202-9924667-9 | P29: 03454181846 | Q29: 03454181846 | R29: 37634642 | S29: H 18 KARIM BAKHSH ROAD NEW SAMANAB AD NEAR BOHAR WALA CHOWK LAHORE PK | T29: 958400 | U29: 1198000 | V29: 2524/02640/00014/09/2021 | W29: 05-SEP-2022 | X29: 6R180061 | Y29: NF1AET306H1080070 | Z29: NEW | AB29: SUZUKI ALTO VX-11 | AC29: 2021 | AD29: 28-JUN-2021 | AE29: 27-SEP-2021 | AF29: 27-Sep-2026 | AG29: OLAHR300069667 | AH29: 5 | AI29: CTRK | AJ29: DIB0031568 | AK29: 06-SEP-2021 | AM29: 2% | AN29: 958400 | AO29: 19168 | AS29: KHI/HO/D/MO/PC COMP/C/97805/54/09/2024 | AU29: 19168 | AV29: 0 | AW29: REN
A30: 28 | B30: NORM | C30: 9976AD1210700022 | D30: 6AD1 | E30: A | F30: T-PAK | G30: CHANGAN ADIL ASHRAF MOTORS | H30: 589731 | I30: 0663901 | J30: 2 | K30: 25.68 | L30: 0663901002 | M30: ABDUL SAMAD | N30: Lahore | O30: 35202-5999191-3 | Q30: 03331439659 | S30: HOUSE NO NILL GULSHAN.E.ISLAM COLONY QAZI PARK SHAHDRA (NEAR FURQAN MODEL SCHOOL) TOWN LAHORE | T30: 1148000 | U30: 1640000 | V30: 55601/00009/09/2021 | W30: 05-SEP-2022 | X30: 504362 | Y30: 1008353 | Z30: NEW | AB30: CHANGAN KARVAAN PLUS | AC30: 2021 | AD30: 11-MAR-2021 | AE30: 21-SEP-2021 | AF30: 21-Sep-2026 | AG30: OLALHR300066548 | AH30: 5 | AI30: CTRK | AJ30: DIB0031574 | AK30: 07-SEP-2021 | AM30: 2% | AN30: 1312000 | AO30: 26240 | AS30: KHI/HO/D/MO/PC COMP/C/97805/55/09/2024 | AU30: 26240 | AV30: 0 | AW30: REN
A31: 29 | B31: NORM | C31: 9976AD1211100017 | D31: 6AD1 | E31: A | F31: T-PAK | G31: SUZUKI MEHRAN MOTORS | H31: 632204 | I31: 0686400 | J31: 2 | K31: 21.96 | L31: 0686400001 | M31: MUHAMMAD ALTAF HUSSAIN | N31: Hyderabad | O31: 41303-2090371-7 | P31: 03332735769 | Q31: 03332735769 | R31: 0720224 | S31: HOUSE # F 1337 SALMAN SOHAG MANZIL KHOKHAR MUHALLAH BEAR BYCO PETROL P HYDERABAD PK | T31: 1379000 | U31: 1970000 | V31: 01-2108-PO-MTR-PCCM-D-001173 | W31: 05-SEP-2022 | X31: 178369 | Y31: 10078364 | Z31: NEW | AB31: SUZUKI CULTUS VXL | AC31: 2021 | AD31: 20-APR-2021 | AE31: 11-SEP-2021 | AF31: 11-Sep-2026 | AG31: OLAHYD300067731 | AH31: 5 | AI31: FLCN | AJ31: 108569/09/2021 | AK31: 02-SEP-2021 | AM31: 2% | AN31: 1576000 | AO31: 31520 | AS31: KHI/HO/D/MO/PC COMP/C/97805/56/09/2024 | AU31: 31520 | AV31: 0 | AW31: REN
A32: 30 | B32: NORM | C32: 9976AD1212450035 | D32: 6AD1 | E32: A | F32: T-PAK | G32: PREMIER SYSTEMS (PVT) LTD | H32: 1107497 | I32: 0157816 | J32: 1.75 | K32: 22.02 | L32: 0157816004 | M32: MUHAMMAD KUMAIL POLANI | N32: Karachi | O32: 42201-5815704-1 | Q32: 03412777777 03332470777 | R32: 32462000 | S32: POLANIS PVT LIMITED 49-53 SINDH MADRESSAH TUL ISLAM HASRAT MOHANI ROAD KARACHI | T32: 10118500 | U32: 14455000 | V32: 2021/09/CLFTTPCDP00986 | W32: 05-SEP-2022 | X32: EAS-138209 | Y32: WAUZZZGE2MB035231 | Z32: NEW | AB32: AUDI E-TRON 50 QUATTRO | AC32: 2021 | AD32: 02-SEP-2021 | AE32: 11-SEP-2021 | AF32: 11-Sep-2026 | AG32: OLAKHI300070315 | AH32: 5 | AM32: 1.75% | AN32: 11564000 | AO32: 202370 | AS32: KHI/HO/D/MO/PC COMP/C/97805/60/09/2024 | AU32: 202370 | AV32: 0 | AW32: REN
A33: 31 | B33: NORM | C33: 9976AD1220260027 | D33: 6AD1 | E33: A | F33: T-PAK | G33: CHANGAN SINDH MOTORS | H33: AL-1092370 | I33: 0753020 | J33: 2 | K33: 22.36 | L33: 0753020001 | M33: RAO MASOOD UR REHMAN | N33: Nawab Shah | O33: 45402-8944172-3 | P33: 03045834464 | Q33: 03045834464 | R33: 03045834464 | S33: HOUSE # IIA 836/154 KAMORA COLONY NAWABSHAH PK | T33: 1269800 | U33: 1814000 | V33: 63286/00008/09/2022 | W33: 05-SEP-2023 | X33: 503846 | Y33: 1016466 | Z33: NEW | AB33: CHANGAN KARVAN PLUS | AC33: 2022 | AD33: 26-JAN-2022 | AE33: 11-SEP-2022 | AF33: 11-Sep-2027 | AG33: OLANWB300083303 | AH33: 5 | AI33: ITECL | AJ33: 8492/08/2022 | AK33: 29-AUG-2022 | AM33: 2% | AN33: 1541900 | AO33: 30838 | AS33: KHI/HO/D/MO/PC COMP/C/97805/62/09/2024 | AT33: KHI/HO/D/MO/PC COMP/E/47950/00062/10/2024 | AU33: 27210 | AV33: 3628 | AW33: REN | AX33: 3628 | AY33: 0
A34: 32 | B34: NORM | C34: 9976AD2220190006 | D34: 6AD2 | E34: A | F34: T-PAK | G34: PAK SUZUKI MOTOR CO LTD | H34: 1141848 | I34: 0716961 | J34: 2 | K34: 22.86 | L34: 0716961004 | M34: BILAL IKRAM | N34: Islamabad | O34: 61101-4385442-7 | Q34: 03335517158 | S34: BLOCK NO.1A, FLAT NO.9-A, ST NO.1, SECTOR I-8/1,ISLAMABAD | T34: 1131000 | U34: 1508000 | V34: 62698/00114/08/2022 | W34: 05-SEP-2023 | X34: 247953 | Y34: 1147941 | Z34: NEW | AB34: SUZUKI ALTO VXR EURO II | AC34: 2022 | AD34: 19-JAN-2022 | AE34: 11-SEP-2022 | AF34: 11-Sep-2029 | AG34: OLAISD300083253 | AH34: 7 | AI34: ITECL | AJ34: 8477/08/2022 | AK34: 06-SEP-2022 | AM34: 2% | AN34: 1281800 | AO34: 25636 | AS34: KHI/HO/D/MO/PC COMP/C/97805/64/09/2024 | AU34: 25636 | AV34: 0 | AW34: REN
A35: 33 | B35: NORM | C35: 9976AP1222510005 | D35: 6AP1 | E35: A | F35: T-PAK | G35: NEW CAR COMPLEX | H35: AL-1147709 | I35: 0801889 | J35: 1.5 | K35: 21.37 | L35: 0801889001 | M35: AMIR KHALID | N35: Karachi | O35: 42201-9594326-7 | P35: 03222130782 | Q35: 03222130782 | R35: 0 | S35: HNO 77/4 STREET 14 KHAYABAN E SEHER PHASE 6 DHA NEAR NIXOR CELLEGE KARACHI PK | T35: 2415000 | U35: 3450000 | V35: 63286/00009/09/2022 | W35: 05-SEP-2023 | X35: Q034703 | Y35: R6012169 | Z35: USD | AA35: BHJ-203 | AB35: TOYOTA COROLLA ALTIS A/T | AC35: 2016 | AD35: 08-SEP-2022 | AE35: 11-SEP-2022 | AF35: 11-Sep-2025 | AG35: OLUKHI300089724 | AH35: 3 | AI35: ITFM | AJ35: 8602/09/2022/ITFM | AK35: 07-SEP-2022 | AM35: 1.5% | AN35: 2932500 | AO35: 43987.5 | AS35: KHI/HO/D/MO/PC COMP/C/97805/65/09/2024 | AU35: 43988 | AV35: -0.5 | AW35: REN
A36: 34 | B36: NORM | C36: 9976AD1221390023 | D36: 6AD1 | E36: A | F36: T-PAK | G36: PAK SUZUKI MOTOR CO LTD | H36: 1209240 | I36: 0786014 | J36: 1.5 | K36: 25.19 | L36: 0786014001 | M36: RABIA AWAN | N36: Lahore | O36: 35202-7590673-0 | Q36: 0346-4687037 / 0333-6812012 | S36: FLAT # 06, 2ND FLOOR JAHANGIR PARK NEW MAZANG LAHORE | T36: 1519100 | U36: 2762000 | V36: 63286/00007/09/2022 | W36: 05-SEP-2023 | X36: 200538 | Y36: 10100532 | Z36: NEW | AB36: SUZUKI CULTUS VXL AGS EURO II | AC36: 2022 | AD36: 19-MAY-2022 | AE36: 21-SEP-2022 | AF36: 21-Sep-2025 | AG36: OLALHR300087344 | AH36: 3 | AI36: ITFM | AJ36: 8598/09/2022/ITFM | AK36: 06-SEP-2022 | AM36: 1.5% | AN36: 2347700 | AO36: 35215.5 | AS36: KHI/HO/D/MO/PC COMP/C/97805/69/09/2024 | AU36: 35216 | AV36: -0.5 | AW36: REN
A37: 35 | B37: NORM | C37: 9976AP2222560002 | D37: 6AP2 | E37: A | F37: T-PAK | G37: NEW CAR COMPLEX | H37: AL-1201870 | I37: 0795572 | J37: 1.5 | K37: 26.19 | L37: 0795572002 | M37: REBAL ISRAIL | N37: Karachi | O37: 42201-4370083-1 | Q37: 03314969006 | S37: HOUSE NO A-1/125 BLOCK 13-A RAILWAY HOUSING SOCIETY GULSHAN-E-IQBAL NEAR STUDENT BIRYANI KARACHI | T37: 1082200 | U37: 1546000 | V37: 63286/00005/09/2022 | W37: 05-SEP-2023 | X37: 6R234553 | Y37: 1134530 | Z37: USD | AA37: BWX-081 | AB37: SUZUKI ALTO VXR EURO II | AC37: 2022 | AD37: 13-SEP-2022 | AE37: 21-SEP-2022 | AF37: 21-Sep-2025 | AG37: OLUKHI300089710 | AH37: 3 | AI37: ITFT | AJ37: 8595/09/2022/ITFM | AK37: 06-SEP-2022 | AM37: 1.5% | AN37: 1314100 | AO37: 19711.5 | AS37: KHI/HO/D/MO/PC COMP/C/97805/70/09/2024 | AU37: 19712 | AV37: -0.5 | AW37: REN
A38: 36 | B38: NORM | C38: 9976AD1222270002 | D38: 6AD1 | E38: A | F38: T-PAK | G38: KIA MOTORS POTOHAR | H38: AL-1191862 | I38: 0807008 | J38: 2 | K38: 26.69 | L38: 0807008001 | M38: ARQAM MUSTAFA | N38: Rawalpindi | O38: 37405-7954606-1 | P38: 03315013061 | R38: 0517066383 | S38: H # 684 ST # 7 SECTOR 1 AIRPORT HOU SING SOCIEITY NEAR CENTRAL PARK RAWALPINDI PK | T38: 1820000 | U38: 2600000 | V38: 62698/00122/08/2022 | W38: 05-SEP-2023 | X38: 047695 | Y38: 504159 | Z38: NEW | AB38: KIA PICANTO 1.0 L M/T | AC38: 2022 | AD38: 15-AUG-2022 | AE38: 21-SEP-2022 | AF38: 21-Sep-2025 | AG38: OLARWP300089282 | AH38: 3 | AI38: ITFM | AJ38: 8485/08/2022/ITFM | AK38: 06-SEP-2022 | AM38: 2% | AN38: 2210000 | AO38: 44200 | AS38: KHI/HO/D/MO/PC COMP/C/97805/72/09/2024 | AU38: 44200 | AV38: 0 | AW38: REN
A39: 37 | B39: NORM | C39: 9976AP1232510004 | D39: 6AP1 | E39: A | F39: T-PAK | G39: KHALID MOTORS | H39: 1441374 | I39: 0804337 | J39: 1.75 | K39: 22.12 | L39: 0804337003 | M39: ALI ARSLAN | N39: Lahore | O39: 35202-0488967-3 | P39: 03217875335 | Q39: 03217875335 | R39: 03217875335 | S39: H NO 250 IRIS BLOCK BAHRIA TOWN LAHORE PK | T39: 1261000 | U39: 1940000 | V39: 74853/0005/09/2023 | W39: 05-SEP-2024 | X39: 1029660 | Y39: 1146173 | Z39: NEW | AB39: SUZUKI BOLAN VX EURO II | AC39: 2023 | AD39: 45177 | AE39: 11-SEP-2023 | AF39: 11-Sep-2028 | AG39: OLDLHR300096603 | AH39: 5 | AI39: CTRK | AJ39: DIB0035279 | AK39: 08-SEP-2023 | AM39: 1.75% | AN39: 1746000 | AO39: 30555 | AS39: KHI/HO/D/MO/PC COMP/C/97805/74/09/2024 | AT39: KHI/HO/D/MO/PC COMP/E/47950/00074/10/2024 | AU39: 27160 | AV39: 3395 | AW39: REN | AX39: 3395 | AY39: 3.6379788e-12
A40: 38 | B40: NORM | C40: 9976AP2232500005 | D40: 6AP2 | E40: A | F40: T-PAK | G40: MOTOR TREND | H40: 1408001 | I40: 0313344 | J40: 1.75 | K40: 22.37 | L40: 0313344004 | M40: SAIF ALI SHOUKAT | N40: Islamabad | O40: 35202-1039697-1 | P40: NA | Q40: 03214007837 | R40: 8355139 | S40: SHOP NO 06, F-7-3 GATE MARKET SHAMSABAD, RAWALPINDI 03214007837 | T40: 1980000 | U40: 3300000 | V40: 74853/00003/09/2023 | W40: 05-SEP-2024 | X40: 503965 | Y40: 1000485 | Z40: USD | AA40: AWH-869 | AB40: CHANGAN ALSVIN COMFORT M/T | AC40: 2021 | AD40: 45176 | AE40: 11-SEP-2023 | AF40: 11-Sep-2026 | AG40: OLUISD300096614 | AH40: 3 | AI40: CTRK | AJ40: DIB0035277 | AK40: 07-SEP-2023 | AM40: 1.75% | AN40: 2970000 | AO40: 51975 | AS40: KHI/HO/D/MO/PC COMP/C/97805/76/09/2024 | AT40: KHI/HO/D/MO/PC COMP/E/47950/00076/10/2024 | AU40: 49088 | AV40: 2887 | AW40: REN | AX40: 2888 | AY40: -1
A41: 39 | B41: NORM | C41: 997AAD1202120017 | D41: AAD1 | E41: A | F41: T-PAK | G41: SUZUKI TAXILA MOTORS | H41: 587002 | I41: 0622012 | J41: 2 | K41: 20.8 | L41: 0622012001 | M41: EHSAN ULLAH | N41: Islamabad | O41: 37405-2319434-1 | P41: 03335371058 | R41: 0 | S41: H # 16 ST # 6-1/B MADINA TOWN ISLAMABAD PK | T41: 879200 | U41: 1099000 | V41: 52740/00020/09/2020 | W41: 06-SEP-2021 | X41: 1005546 | Y41: 1122061 | Z41: NEW | AB41: BOLAN VX EURO II | AC41: 2020 | AD41: 30-JUL-2020 | AE41: 11-SEP-2020 | AF41: 11-Sep-2025 | AG41: POAISD300056124 | AH41: 5 | AI41: CTRK | AJ41: DIB0028680 | AK41: 08-SEP-2020 | AM41: 2% | AN41: 824250 | AO41: 16485 | AS41: KHI/HO/D/MO/PC COMP/C/97805/84/09/2024 | AT41: KHI/HO/D/MO/PC COMP/E/47950/00084/10/2024 | AU41: 18683 | AV41: -2198 | AW41: REN | AX41: -2198 | AY41: 0
A42: 40 | B42: NORM | C42: 9976AD1212090007 | D42: 6AD1 | E42: A | F42: T-PAK | G42: PAK SUZUKI MOTOR CO LTD | H42: 1104645 | I42: 0699870 | J42: 2 | K42: 25.8 | L42: 0699870001 | M42: MUNIR AHMAD | N42: Lahore | O42: 35202-5480542-3 | P42: 03004533851 | Q42: 03004533851 | R42: 04235853909 | S42: SHOP NO 103-15 ABU BAKAR BLOCK RAJA MARKET NEW GARDEN TOWN LAHORE | T42: 946050 | U42: 1113000 | V42: 2524/02640/000018/09/2021 | W42: 06-SEP-2022 | X42: 181472 | Y42: 1081491 | Z42: NEW | AB42: SUZUKI ALTO VX EURO II | AC42: 2021 | AD42: 28-JUL-2021 | AE42: 03-OCT-2021 | AF42: 03-Oct-2026 | AG42: OLALHR300071100 | AH42: 5 | AI42: CTRK | AJ42: DIB0031586 | AK42: 07-SEP-2021 | AM42: 2% | AN42: 890400 | AO42: 17808 | AS42: KHI/HO/D/MO/PC COMP/C/97805/85/09/2024 | AU42: 17808 | AV42: 0 | AW42: REN
A43: 41 | B43: NORM | C43: 9976AD1211510001 | D43: 6AD1 | E43: A | F43: T-PAK | G43: PAK SUZUKI MOTOR CO LTD | H43: 653064 | I43: 0190092 | J43: 2 | K43: 21.97 | L43: 0190092002 | M43: IMRAN ALI | N43: Rawalpindi | O43: 37405-3023879-9 | P43: 0515477911 0515854354 | Q43: 03335393904 | S43: 593 K/2B STREET NO 6 WESTRIDGE ALLABAD RAWALPINDI | T43: 1211000 | U43: 1730000 | V43: 2021/09/CLFTTPCDP00989 | W43: 06-SEP-2022 | X43: 219909 | Y43: 10119925 | Z43: NEW | AB43: SUZUKI WAGONR VXL | AC43: 2021 | AD43: 31-MAY-2021 | AE43: 11-SEP-2021 | AF43: 11-Sep-2028 | AG43: OLARWP300069005 | AH43: 7 | AI43: CTRK | AJ43: DIB0031584 | AK43: 08-SEP-2021 | AM43: 2% | AN43: 1384000 | AO43: 27680 | AS43: KHI/HO/D/MO/PC COMP/C/97805/86/09/2024 | AU43: 27680 | AV43: 0 | AW43: REN
A44: 42 | B44: NORM | C44: 9976AD1211970017 | D44: 6AD1 | E44: A | F44: T-PAK | G44: PAK SUZUKI MOTOR CO LTD | H44: 536229 | I44: 0251278 | J44: 2 | K44: 25.8 | L44: 0251278002 | M44: MUHAMMAD KASHIF NASRULLAH SHEIKH | N44: Lahore | O44: 35202-6201877-5 | Q44: 03227700200 | R44: 37633900 | S44: SHOP NO 209(SB) AMEEN BAZAR AZAM CLOTH MARKET LAHORE | T44: 1281000 | U44: 1830000 | V44: 2021-09-205-V01501OPOOO2128 | W44: 06-SEP-2022 | X44: 184279 | Y44: 10084159 | Z44: NEW | AB44: SUZUKI CULTUS VXL EURO II | AC44: 2021 | AD44: 16-JUL-2021 | AE44: 03-OCT-2021 | AF44: 03-Oct-2026 | AG44: OLALHR300070883 | AH44: 5 | AI44: ITECL | AJ44: 5417/09/2021 | AK44: 07-SEP-2021 | AM44: 2% | AN44: 1464000 | AO44: 29280 | AS44: KHI/HO/D/MO/PC COMP/C/97805/87/09/2024 | AU44: 29280 | AV44: 0 | AW44: REN
A45: 43 | B45: NORM | C45: 9976AP1212520017 | D45: 6AP1 | E45: A | F45: T-PAK | G45: ADIL ZAFAR MOTORS | H45: 1104327 | I45: 0655108 | J45: 2 | K45: 21.86 | L45: 0655108003 | M45: MUHAMMAD ZAHEER AHMAD MUGHAL | N45: Lahore | O45: 35201-6107307-9 | P45: 03214544805 | Q45: 03214544805 | R45: 03214544805 | S45: 212 ALLAMA IQBAL ROAD MUSTAFA ABAD DHARAMPURA LAHORE | T45: 1320000 | U45: 1760000 | V45: 55601/00014/09/2021 | W45: 06-SEP-2022 | X45: PK10B219760 | Y45: A1J310PK10119734 | Z45: NEW | AB45: WAGONR VXL AGS | AC45: 2021 | AD45: 09-SEP-2021 | AE45: 11-SEP-2021 | AF45: 11-Sep-2026 | AG45: OLDLHR300073224 | AH45: 5 | AI45: CTRK | AJ45: DIB0031580 | AK45: 07-SEP-2021 | AM45: 2% | AN45: 1408000 | AO45: 28160 | AS45: KHI/HO/D/MO/PC COMP/C/97805/88/09/2024 | AU45: 28160 | AV45: 0 | AW45: REN
A46: 44 | B46: NORM | C46: 997AAD2202440014 | D46: AAD2 | E46: A | F46: T-PAK | G46: HONDA CHENAB-GREEN VIEW MOTORS | H46: 598377 | I46: 0464175 | J46: 2 | K46: 21.8 | L46: 0464175003 | M46: ADNAN HUSSAIN | N46: Faisalabad | O46: 33100-0600840-3 | P46: 03007618900 | Q46: 03007618900, 03007618900 | R46: 03007618900 | S46: P-278 MAQBOOL ROAD PEOPLES COLONY 0 2 FSD FAISALABAD PK | T46: 1801800 | U46: 2574000 | V46: 2524/02112/00015/09/2020 | W46: 06-SEP-2021 | X46: L13Z17540309 | Y46: NFBGM1642LR262955 | Z46: NEW | AB46: HONDA CITY A/T | AC46: 2020 | AD46: 31-AUG-2020 | AE46: 11-SEP-2020 | AF46: 11-Sep-2025 | AG46: POAFSD300056968 | AH46: 5 | AI46: ITECL | AJ46: 2961/09/2020 | AK46: 07-SEP-2020 | AM46: 2% | AN46: 1930500 | AO46: 38610 | AS46: KHI/HO/D/MO/PC COMP/C/97805/90/09/2024 | AT46: KHI/HO/D/MO/PC COMP/E/47950/00090/10/2024 | AU46: 43758 | AV46: -5148 | AW46: REN | AX46: -5148 | AY46: 0
A47: 45 | B47: NORM | C47: 9976AP1212510008 | D47: 6AP1 | E47: A | F47: T-PAK | G47: TOYOTA GARDEN MOTORS | H47: 1099218 | I47: 0692140 | J47: 2 | K47: 21.86 | L47: 0692140003 | M47: MUHAMMAD SHAHBAZ UL QAMAR | N47: Lahore | O47: 36401-9966175-1 | P47: 03334146747 | Q47: 03334146747 | R47: 03334146747 | S47: 132 BLOCK 2 SECTOR C2 NEAR BUTT CHO WK UTILITY STORE TOWNSHIP LAHORE | T47: 2462250 | U47: 3283000 | V47: 55601/00012/09/2021 | W47: 06-SEP-2022 | X47: Q079693 | Y47: 6057177 | Z47: NEW | AB47: TOYOTA COROLLA ALTIS A/T | AC47: 2021 | AD47: 08-SEP-2021 | AE47: 11-SEP-2021 | AF47: 11-Sep-2028 | AG47: OLDLHR300073229 | AH47: 7 | AI47: CTRK | AJ47: DIB0031577 | AK47: 07-SEP-2021 | AM47: 2% | AN47: 2626400 | AO47: 52528 | AS47: KHI/HO/D/MO/PC COMP/C/97805/94/09/2024 | AU47: 52528 | AV47: 0 | AW47: REN
A48: 46 | B48: NORM | C48: 9976AD2212420001 | D48: 6AD2 | E48: A | F48: T-PAK | G48: HONDA PORT QASIM | H48: 1105820 | I48: 0716259 | J48: 2 | K48: 19.87 | L48: 0716259001 | M48: DANIYAL | N48: Karachi | O48: 42201-2750078-3 | P48: 03453790084 | Q48: 03453790084, 03453790084 | R48: 03453790084 | S48: H # H-545 BLOCK 3 AREA H MALIR NEAR TANGA STAND KARACHI PK | T48: 2615600 | U48: 4024000 | V48: 55601/00015/09/2021 | W48: 06-SEP-2022 | X48: 16925779 | Y48: 078313 | Z48: NEW | AB48: HONDA CIVIC 1.8 ORIEL | AC48: 2021 | AD48: 30-AUG-2021 | AE48: 11-SEP-2021 | AF48: 11-Sep-2026 | AG48: OLAKHI300072711 | AH48: 5 | AI48: CTRK | AJ48: DIB0031573 | AK48: 07-SEP-2021 | AM48: 2% | AN48: 3219200 | AO48: 64384 | AS48: KHI/HO/D/MO/PC COMP/C/97805/95/09/2024 | AU48: 64384 | AV48: 0 | AW48: REN
A49: 47 | B49: NORM | C49: 9976AP1212510005 | D49: 6AP1 | E49: A | F49: T-PAK | G49: HONDA POINT | H49: 1107931 | I49: 0718578 | J49: 2 | K49: 21.86 | L49: 0718578001 | M49: MUHAMMAD ALI | N49: Lahore | O49: 35201-6604907-7 | P49: 03244871700 | Q49: 03244871700 | R49: 03244871700 | S49: GT ROAD SOTAR MILL STOP MANAWAN LAHORE | T49: 2808400 | U49: 4012000 | V49: 55601/00010/09/2021 | W49: 06-SEP-2022 | X49: 6925693 | Y49: MR078230 | Z49: NEW | AB49: HONDA CIVIC VTI ORIEL P/T | AC49: 2021 | AD49: 08-SEP-2021 | AE49: 11-SEP-2021 | AF49: 11-Sep-2026 | AG49: OLDLHR300073203 | AH49: 5 | AI49: CTRK | AJ49: DIB0031575 | AK49: 07-SEP-2021 | AM49: 2% | AN49: 3209600 | AO49: 64192 | AS49: KHI/HO/D/MO/PC COMP/C/97805/96/09/2024 | AU49: 64192 | AV49: 0 | AW49: REN
A50: 48 | B50: NORM | C50: 9976AP1222520007 | D50: 6AP1 | E50: A | F50: T-PAK | G50: AL-QURASH MOTORS | H50: AL-1193213 | I50: 0178425 | J50: 1.75 | K50: 21.62 | L50: 0178425006 | M50: SYED HUSSAIN BARI | N50: Lahore | O50: 35201-7048031-5 | Q50: 03244500500 | R50: 04235172273 | S50: H NO 34 ST NO 53 MOH DARBAR HAZRAT MAIN MEER MUSTAFABAD LAHORE | T50: 1365000 | U50: 2100000 | V50: 63286/00010/09/2022 | W50: 06-SEP-2023 | X50: 6R106685 | Y50: 6H1005693 | Z50: USD | AA50: LEH-19-9716 | AB50: SUZUKI ALTO VXL AGS EURO II | AC50: 2019 | AD50: 09-SEP-2022 | AE50: 11-SEP-2022 | AF50: 11-Sep-2027 | AG50: OLULHR300089736 | AH50: 5 | AI50: ITFM | AJ50: 8604/09/2022/ITFM | AK50: 07-SEP-2022 | AM50: 1.75% | AN50: 1785000 | AO50: 31237.5 | AS50: KHI/HO/D/MO/PC COMP/C/97805/98/09/2024 | AT50: KHI/HO/D/MO/PC COMP/E/47950/00098/10/2024 | AU50: 27563 | AV50: 3674.5 | AW50: REN | AX50: 3675 | AY50: -0.5
A51: 49 | B51: NORM | C51: 9976AD2220570008 | D51: 6AD2 | E51: A | F51: T-PAK | G51: KIA MOTORS KINGS GATE | H51: 1153555 | I51: 0245213 | J51: 2 | K51: 26.44 | L51: 0245213002 | M51: ABDUL HAMEED | N51: Lahore | O51: 61101-9349976-1 | Q51: 03222444112 | R51: 04235840577 | S51: HOUSE NO 160 ALI BLOCK NEW GARDEN TOWN LAHORE | T51: 2330000 | U51: 5825000 | V51: 63286/00011/09/2022 | W51: 06-SEP-2023 | X51: 302394 | Y51: 518034 | Z51: NEW | AB51: KIA SPORTAGE AWD | AC51: 2022 | AD51: 26-FEB-2022 | AE51: 21-SEP-2022 | AF51: 21-Sep-2025 | AG51: OLALHR300084721 | AH51: 3 | AI51: ITECL | AJ51: 8605/09/2022 | AK51: 07-SEP-2022 | AM51: 2% | AN51: 4951250 | AO51: 99025 | AS51: KHI/HO/D/MO/PC COMP/C/97805/100/09/2024 | AU51: 99025 | AV51: 0 | AW51: REN
A52: 50 | B52: NORM | C52: 9976AP2232510004 | D52: 6AP2 | E52: A | F52: T-PAK | G52: ALI JAN MOTORS | H52: 1441973 | I52: 0828514 | J52: 1.75 | K52: 22.37 | L52: 0828514003 | M52: MUHAMMAD ZAIB JAVED | N52: Lahore | O52: 35202-3728510-5 | P52: 03214696451 | Q52: 03214696451 | R52: 03214696451 | S52: HOUSE NO 4 REHMAT ALI ROAD SAMNABAD LAHORE PK | T52: 2654600 | U52: 4084000 | V52: 74853/0008/09/2023 | W52: 06-SEP-2024 | X52: 207203 | Y52: 10107185 | Z52: NEW | AB52: SUZUKI CULTUS VXL EURO II | AC52: 2023 | AD52: 45177 | AE52: 11-SEP-2023 | AF52: 11-Sep-2025 | AG52: OLDLHR300096714 | AH52: 2 | AI52: CTRK | AJ52: DIB0035283 | AK52: 08-SEP-2023 | AM52: 1.75% | AN52: 3675600 | AO52: 64323 | AS52: KHI/HO/D/MO/PC COMP/C/97805/105/09/2024 | AU52: 64323 | AV52: 0 | AW52: REN
A53: 51 | B53: NORM | C53: 9976AP2232510003 | D53: 6AP2 | E53: A | F53: T-PAK | G53: AL-QURASH MOTORS | H53: 1441774 | I53: 0899190 | J53: 1.75 | K53: 22.87 | L53: 0899190002 | M53: MUMTAZ HUSSAIN | N53: Lahore | O53: 33104-4570677-9 | Q53: 03027777211 | S53: HOUSE NO. 308, B-BLOCK, AASHIANA HOUSING SCHEME FEROZPUR ROAD, LAHORE 0302-7777211 | T53: 1300000 | U53: 2000000 | V53: 74853/0009/09/2023 | W53: 06-SEP-2024 | X53: 122878 | Y53: 10023031 | Z53: USD | AA53: MNE-18-403 | AB53: SUZUKI CULTUS VXR EURO II | AC53: 2018 | AD53: 45177 | AE53: 11-SEP-2023 | AF53: 11-Sep-2028 | AG53: OLULHR300096723 | AH53: 5 | AI53: CTRK | AJ53: DIB0035284 | AK53: 08-SEP-2023 | AM53: 1.75% | AN53: 1800000 | AO53: 31500 | AS53: KHI/HO/D/MO/PC COMP/C/97805/106/09/2024 | AT53: KHI/HO/D/MO/PC COMP/E/47950/00106/10/2024 | AU53: 28000 | AV53: 3500 | AW53: REN | AX53: 3500 | AY53: 3.6379788e-12
A54: 52 | B54: NORM | C54: 9976AP1232500005 | D54: 6AP1 | E54: A | F54: T-PAK | G54: TOYOTA WALTON MOTORS | H54: 1414333 | I54: 0691198 | J54: 1.75 | K54: 21.87 | L54: 0691198003 | M54: ALI PERVAIZ | N54: Lahore | O54: 35201-9660821-5 | P54: 03024170003 | Q54: 03024170003 | R54: 03024170003 | S54: 4-CB GIRJA CHOWK ABID MAJEED ROAD C ANTT OPPOSITE PSO PUMP LAHORE | T54: 2965620 | U54: 21183000 | V54: 74853/00006/09/2023 | W54: 06-SEP-2024 | X54: 5418197 | Y54: 1104419 | Z54: NEW | AB54: TOYOTA FORTUNER 188D 4X4 | AC54: 2023 | AD54: 45176 | AE54: 11-SEP-2023 | AF54: 11-Sep-2026 | AG54: OLDLHR300096703 | AH54: 3 | AI54: CTRK | AJ54: DIB0035280 | AK54: 07-SEP-2023 | AM54: 1.75% | AN54: 19064700 | AO54: 333632.25 | AS54: KHI/HO/D/MO/PC COMP/C/97805/107/09/2024 | AT54: KHI/HO/D/MO/PC COMP/E/47950/00107/10/2024 | AU54: 315097 | AV54: 18535.25 | AW54: REN | AX54: 18535 | AY54: 0.25
A55: 53 | B55: NORM | C55: 9976AD1232190003 | D55: 6AD1 | E55: A | F55: T-PAK | G55: PAK SUZUKI MOTOR CO LTD | H55: 1405062 | I55: 0677151 | J55: 2 | K55: 22.37 | L55: 0677151004 | M55: USAMA SABIR | N55: Karachi | O55: 42501-7780268-3 | Q55: 03402235022 | S55: H NO I-64 CANTT BAZAR MALIR CANTT KARACHI 0340-2235022 | T55: 2054500 | U55: 2935000 | V55: 74853/00007/09/2023 | W55: 06-SEP-2024 | X55: 6R281845 | Y55: 1181741 | Z55: NEW | AB55: SUZUKI ALTO VXL AGS EURO II | AC55: 2023 | AD55: 45145 | AE55: 11-SEP-2023 | AF55: 11-Sep-2025 | AG55: OLAKHI300096023 | AH55: 2 | AI55: ITFM | AJ55: 10490/09/2023/ITFM | AK55: 06-SEP-2023 | AM55: 2% | AN55: 2641500 | AO55: 52830 | AS55: KHI/HO/D/MO/PC COMP/C/97805/108/09/2024 | AU55: 52830 | AV55: 0 | AW55: REN
A56: 54 | B56: NORM | C56: 997AAD1202440022 | D56: AAD1 | E56: A | F56: T-PAK | G56: SUZUKI PIONEER TRADERS | H56: 588623 | I56: 0627337 | J56: 2 | K56: 26.93 | L56: 0627337001 | M56: SHAISTA NAZLI | N56: Burewala | O56: 35301-1865335-4 | P56: 03336282110 | Q56: 03336282110 | R56: 03336282110 | S56: H NO 407 ST NO 6 SHAH FAIZ BUREWALA PK | T56: 1118400 | U56: 1398000 | V56: DIB/T/BT/28504/LHR/0920 | W56: 07-SEP-2021 | X56: 135682 | Y56: 1035684 | Z56: NEW | AB56: ALTO VXR | AC56: 2020 | AD56: 31-AUG-2020 | AE56: 27-SEP-2020 | AF56: 27-Sep-2025 | AG56: POABRW300056821 | AH56: 5 | AI56: CTRK | AJ56: DIB0028685 | AK56: 08-SEP-2020 | AM56: 2% | AN56: 1048500 | AO56: 20970 | AS56: KHI/HO/D/MO/PC COMP/C/97805/114/09/2024 | AT56: KHI/HO/D/MO/PC COMP/E/47950/00114/10/2024 | AU56: 23766 | AV56: -2796 | AW56: REN | AX56: -2796 | AY56: 0
A57: 55 | B57: NORM | C57: 997AAD1202410006 | D57: AAD1 | E57: A | F57: T-PAK | G57: HONDA CHENAB-GREEN VIEW MOTORS | H57: 577191 | I57: 0628145 | J57: 2 | K57: 21.8 | L57: 0628145001 | M57: TANVEER AHMAD | N57: Faisalabad | O57: 33100-1885379-7 | P57: 03246823574 | Q57: 03246823574, 03246823574 | R57: 03246823574 | S57: P -109 ST NO 8 MOHALLA KHALID FSD N EAR BISMILLAH GENERAL STORE FAISALABAD PK | T57: 1853280 | U57: 2574000 | V57: 2524/02112/00014/09/2020 | W57: 07-SEP-2021 | X57: L13217540276 | Y57: NFBGM1645LR262917 | Z57: NEW | AB57: CITY IVTEC A/T | AC57: 2020 | AD57: 28-AUG-2020 | AE57: 11-SEP-2020 | AF57: 11-Sep-2025 | AG57: POAFSD300056844 | AH57: 5 | AI57: CTRK | AJ57: DIB0028678 | AK57: 08-SEP-2020 | AM57: 2% | AN57: 1930500 | AO57: 38610 | AS57: KHI/HO/D/MO/PC COMP/C/97805/119/09/2024 | AT57: KHI/HO/D/MO/PC COMP/E/47950/00119/10/2024 | AU57: 43758 | AV57: -5148 | AW57: REN | AX57: -5148 | AY57: 0
A58: 56 | B58: NORM | C58: 9976AP1212530019 | D58: 6AP1 | E58: A | F58: T-PAK | G58: NEW CAR COMPLEX | H58: 1096287 | I58: 0708391 | J58: 2 | K58: 21.78 | L58: 0708391001 | M58: SHEIKH MUHAMMAD TAHIR | N58: Karachi | O58: 42201-2979991-9 | P58: 03228218223 | Q58: 03228218223 | R58: 03228218223 | S58: HOUSE # A-68 KDA OFFICER SOCIETY BE HIND NATIONAL STADIUM BLOCK A GULSH KARACHI PK | T58: 1662500 | U58: 2375000 | V58: 55601/00020/09/2021 | W58: 7-SEP-2022 | X58: Z453966 | Y58: NZE17OR-4083101 | Z58: USD | AA58: BGC-040 | AB58: TOYOTA COROLLA GLI | AC58: 2016 | AD58: 10-SEP-2021 | AE58: 11-SEP-2021 | AF58: 11-Sep-2026 | AG58: OLUKHI300073272 | AH58: 5 | AI58: CTRK | AJ58: DIB0031606 | AK58: 09-SEP-2021 | AM58: 2% | AN58: 1900000 | AO58: 38000 | AS58: KHI/HO/D/MO/PC COMP/C/97805/121/09/2024 | AU58: 38000 | AV58: 0 | AW58: REN
A59: 57 | B59: NORM | C59: 9976AD2212160063 | D59: 6AD2 | E59: A | F59: T-PAK | G59: TOYOTA SOUTHERN MOTORS | H59: 647436 | I59: 0415529 | J59: 2 | K59: 22.47 | L59: 0415529003 | M59: MUHAMMAD ANUS | N59: Karachi | O59: 42101-1473865-7 | P59: 03228268966 | Q59: 03228268966 | R59: 03228268966 | S59: A/44 BLOCK Q NORTH NAZIMABAD 1ST FL OOR BEHIND LAL KOTHI KARACHI PK | T59: 1690500 | U59: 2415000 | V59: 2524/02640/00022/09/2021 | W59: 07-SEP-2022 | X59: 2A35288 | Y59: 7021985 | Z59: NEW | AB59: TOYOTA YARIS GLI MT 1.3 | AC59: 2021 | AD59: 04-AUG-2021 | AE59: 11-SEP-2021 | AF59: 11-Sep-2026 | AG59: OLAKHI300071537 | AH59: 5 | AI59: CTRK | AJ59: DIB0031547 | AK59: 06-SEP-2021 | AM59: 2% | AN59: 1932000 | AO59: 38640 | AS59: KHI/HO/D/MO/PC COMP/C/97805/122/09/2024 | AU59: 38640 | AV59: 0 | AW59: REN
A60: 58 | B60: NORM | C60: 9976AD1212070009 | D60: 6AD1 | E60: A | F60: T-PAK | G60: TOYOTA WALTON MOTORS | H60: 437723 | I60: 0709156 | J60: 1.75 | K60: 25.85 | L60: 0709156001 | M60: RUHMA IHSAN | N60: Lahore | O60: 34101-9773807-2 | P60: 03328183923 | Q60: 03328183923 | R60: 03328183923 | S60: ROOM NO 4 EYE DEPARTMENT DMS OFFICE MAYO HOSPITAL LAHORE | T60: 1678720 | U60: 2623000 | V60: 55601/00018/09/2021 | W60: 07-SEP-2022 | X60: 2A35640 | Y60: 7022136 | Z60: NEW | AB60: YARIS GLI CVT 1.3 | AC60: 2021 | AD60: 26-JUL-2021 | AE60: 03-OCT-2021 | AF60: 03-Oct-2028 | AG60: OLALHR300071120 | AH60: 7 | AI60: CTRK | AJ60: DIB0031601 | AK60: 09-SEP-2021 | AM60: 1.75% | AN60: 2098400 | AO60: 36722 | AS60: KHI/HO/D/MO/PC COMP/C/97805/125/09/2024 | AU60: 36722 | AV60: 0 | AW60: REN
A61: 59 | B61: NORM | C61: 997AAD1201900003 | D61: AAD1 | E61: A | F61: T-PAK | G61: PAK SUZUKI MOTOR CO LTD | H61: 600785 | I61: 0187292 | J61: 1.5 | K61: 20.8 | L61: 0187292005 | M61: ASIF TAYYAB | N61: Faisalabad | O61: 33100-0692389-7 | P61: 0321-9662828 | Q61: 0321-9662828 0321-8222222 | R61: 041-8723239 | S61: H NO P-6 PEOPLES COLONY 1 D-BLOCK PASSPORT ROAD NEAR ALLIED SCHOOL FAISALABAD | T61: 3674250 | U61: 4899000 | V61: DIB/T/28496/LHR/0920 | W61: 07-SEP-2021 | X61: G4NALH317330 | Y61: NNAQL51AZKP302838 | Z61: NEW | AB61: KIA SPORTAGE FWD | AC61: 2020 | AD61: 08-JUL-2020 | AE61: 11-SEP-2020 | AF61: 11-Sep-2025 | AG61: POAFSD300055123 | AH61: 5 | AM61: 1.5% | AN61: 3674250 | AO61: 55113.75 | AS61: KHI/HO/D/MO/PC COMP/C/97805/126/09/2024 | AT61: KHI/HO/D/MO/PC COMP/E/47950/00126/10/2024 | AU61: 62462 | AV61: -7348.25 | AW61: REN | AX61: -7349 | AY61: 0.75
A62: 60 | B62: NORM | C62: 9976AD1211200065 | D62: 6AD1 | E62: A | F62: T-PAK | G62: HONDA SHAHRA-E-FAISAL | H62: 640077 | I62: 0457015 | J62: 2 | K62: 21.96 | L62: 0457015010 | M62: GHULAM QADIR MALIK | N62: Karachi | O62: 42201-2731227-7 | Q62: 03219230285 | S62: HOUSE NO 15 BLOCK 10-A BUKHARI TOWN GULSHAN-E-IQBAL KARACHI | T62: 3311200 | U62: 4139000 | V62: 55601/00021/09/2021 | W62: 07-SEP-2022 | X62: 6925232 | Y62: 077701 | Z62: NEW | AB62: HONDA CIVIC VTI ORIEL | AC62: 2021 | AD62: 30-APR-2021 | AE62: 11-SEP-2021 | AF62: 11-Sep-2026 | AG62: OLAKHI300068499 | AH62: 5 | AI62: ITECL | AJ62: 5411/09/2021 | AK62: 04-SEP-2021 | AM62: 2% | AN62: 3311200 | AO62: 66224 | AS62: KHI/HO/D/MO/PC COMP/C/97805/128/09/2024 | AU62: 66224 | AV62: 0 | AW62: REN
A63: 61 | B63: NORM | C63: 9976AD1211520077 | D63: 6AD1 | E63: A | F63: T-PAK | G63: TOYOTA WESTERN MOTORS | H63: 652301 | I63: 0690536 | J63: 1.75 | K63: 21.97 | L63: 0690536004 | M63: MIAN SYED JAMSHED | N63: Karachi | O63: 42101-1911469-5 | Q63: 03458869674 | S63: KAREEM AL SYEDAN ENTERPRICES OFFICE 1 KPK GENERAL BUS TERMINAL MAIN ABDULLAH COLLEGE ROAD NEAR PAPOSH QABERSTAN NORTH NAZIMABAD | T63: 5794800 | U63: 9658000 | V63: 2021/09/CLFTTPCDP00998 | W63: 07-SEP-2022 | X63: 1GD5024342 | Y63: GUN156R-1095803 | Z63: NEW | AB63: TOYOTA FORTUNER 4X4 SPORTIVO | AC63: 2021 | AD63: 01-JUN-2021 | AE63: 11-SEP-2021 | AF63: 11-Sep-2025 | AG63: OLAKHI300069035 | AH63: 4 | AI63: CTRK | AJ63: DIB0031408 | AK63: 27-AUG-2021 | AM63: 1.75% | AN63: 7726400 | AO63: 135212 | AS63: KHI/HO/D/MO/PC COMP/C/97805/129/09/2024 | AT63: KHI/HO/D/MO/PC COMP/E/47950/00129/10/2024 | AU63: 143663 | AV63: -8451 | AW63: REN | AX63: -8451 | AY63: 0
A64: 62 | B64: NORM | C64: 9976AD2222450001 | D64: 6AD2 | E64: A | F64: T-PAK | G64: KIA MACCA MOTORS | H64: 1208649 | I64: 0802953 | J64: 1.5 | K64: 26.69 | L64: 0802953001 | M64: MALHAR ALI BHUTTO | N64: Karachi | O64: 42201-3402833-9 | P64: 03122351423 | Q64: 03122351423 | R64: 0 | S64: FLAT NO 1006 10TH FLOOR BLOCK A-1 R AFI RESIDENCY UNIVERSITY ROAD NERA KARACHI PK | T64: 2999400 | U64: 4999000 | V64: DIB/T/38290/KHI/0922 | W64: 07-SEP-2023 | X64: 1868506 | Y64: 300130 | Z64: NEW | AB64: PEUGEOT 2008 ACTIVE | AC64: 2022 | AD64: 02-SEP-2022 | AE64: 21-SEP-2022 | AF64: 21-Sep-2025 | AG64: OLAKHI300089675 | AH64: 3 | AI64: ITFT | AJ64: 8584/09/2022/ITFM | AK64: 05-SEP-2022 | AM64: 1.5% | AN64: 4249150 | AO64: 63737.25 | AS64: KHI/HO/D/MO/PC COMP/C/97805/133/09/2024 | AU64: 63737 | AV64: 0.25 | AW64: REN
A65: 63 | B65: NORM | C65: 9976AP1222590003 | D65: 6AP1 | E65: A | F65: T-PAK | G65: DANISH MOTORS | H65: 1196983 | I65: 0245461 | J65: 1.5 | K65: 25.44 | L65: 0245461009 | M65: RAMEEZ SALEEM | N65: Karachi | O65: 42101-4957806-3 | P65: 36947822 | Q65: 03052228383 | S65: H # A-94 CUSTOM PREVATIVE HOUSING SOCITY SCHEM-33 OPP GULSHAN E MAYMAR GATE .# 2 KARACHI | T65: 1435000 | U65: 2050000 | V65: 63286/00015/09/2022 | W65: 07-SEP-2023 | X65: 6R169134 | Y65: 1069127 | Z65: USD | AA65: BTW-163 | AB65: SUZUKI ALTO VXR EURO-II | AC65: 2021 | AD65: 16-SEP-2022 | AE65: 21-SEP-2022 | AF65: 21-Sep-2027 | AG65: OLUKHI300089778 | AH65: 5 | AI65: ITFM | AJ65: 8617/09/2022/ITFM | AK65: 09-SEP-2022 | AM65: 1.5% | AN65: 1742500 | AO65: 26137.5 | AS65: KHI/HO/D/MO/PC COMP/C/97805/135/09/2024 | AT65: KHI/HO/D/MO/PC COMP/E/47950/00135/10/2024 | AU65: 23063 | AV65: 3074.5 | AW65: REN | AX65: 3075 | AY65: -0.5
A66: 64 | B66: NORM | C66: 9976AP2232540007 | D66: 6AP2 | E66: A | F66: T-PAK | G66: SUNRISE AUTOS | H66: 1408193 | I66: 0900263 | J66: 1.75 | K66: 22.87 | L66: 0900263002 | M66: SHAHEEN AKHTER | N66: Rawalpindi | O66: 71502-1462109-0 | Q66: 03365224757 | S66: HOUSE# A-38/1 BLOCK-A, MOHALLAH SATELLITE TOWN RAWALPINDI 0336-5224757 | T66: 877500 | U66: 1350000 | V66: 74853/00010/09/2023 | W66: 07-SEP-2024 | X66: 767014 | Y66: 01305560 | Z66: USD | AA66: AMS-930 | AB66: SUZUKI MEHRAN VXR EURO II | AC66: 2019 | AD66: 45180 | AE66: 11-SEP-2023 | AF66: 11-Sep-2028 | AG66: OLURWP300096783 | AH66: 5 | AI66: CTRK | AJ66: DIB0035285 | AK66: 08-SEP-2023 | AM66: 1.75% | AN66: 1215000 | AO66: 21262.5 | AS66: KHI/HO/D/MO/PC COMP/C/97805/137/09/2024 | AT66: KHI/HO/D/MO/PC COMP/E/47950/00137/10/2024 | AU66: 18900 | AV66: 2362.5 | AW66: REN | AX66: 2363 | AY66: -0.5
A67: 65 | B67: NORM | C67: 9976AP1192750005 | D67: 6AP1 | E67: A | F67: T-PAK | G67: KT MOTORS | H67: 591045 | I67: 0563135 | J67: 2.5 | K67: 27.7 | L67: 0563135001 | M67: MUHAMMAD MANEEF | N67: Faisalabad | O67: 33100-1709915-3 | P67: 03007626747 | Q67: 03007626747, 03007626747 | R67: 041111552741 | S67: H NO 147 ST NO 04 GREEN TOWN MILLAT ROAD FSD FAISALABAD PK | T67: 805000 | U67: 1150000 | V67: 51244/00001/10/2019 | W67: 30-SEP-2020 | X67: B110237 | Y67: PK10010227 | Z67: USD | AA67: UK-234 | AB67: WAGONR VXL | AC67: 2015 | AD67: 02-OCT-2019 | AE67: 03-OCT-2019 | AF67: 03-Oct-2026 | AG67: POUFSD300049602 | AH67: 7 | AI67: CTRK | AJ67: TDIDIB0027323 | AK67: 01-OCT-2019 | AM67: 2.5% | AN67: 805000 | AO67: 20125 | AS67: KHI/HO/D/MO/PC COMP/C/97805/17/09/2024 | AT67: KHI/HO/D/MO/PC COMP/E/47950/00017/10/2024 | AU67: 23000 | AV67: -2875 | AW67: REN | AX67: -2875 | AY67: 0
A68: 66 | B68: NORM | C68: 997APD1202970027 | D68: APD1 | E68: A | F68: T-PAK | G68: SHADOW MOTORS | H68: 626994 | I68: 0638649 | J68: 2 | K68: 25.84 | L68: 0638649001 | M68: MUHAMMAD SAAD AHMED | N68: Karachi | O68: 42101-8174917-7 | P68: 03322400987 | Q68: 03322400987 | R68: 0 | S68: HOUSE # B-211 BLOCK-D NORTH NAZIMAB AD NEAR MASJID E ASHRAF KARACHI PK | T68: 1440000 | U68: 1800000 | V68: 52921/00088/10/2020 | W68: 30-SEP-2021 | X68: R18Z1-3741865 | Y68: NFBFB2669ER115902 | Z68: USD | AA68: BBJ-379 | AB68: CIVIC VTI ORIEL | AC68: 2014 | AD68: 23-OCT-2020 | AE68: 27-OCT-2020 | AF68: 27-Oct-2025 | AG68: POUKHI300058982 | AH68: 5 | AI68: CTRK | AJ68: DIB0028920 | AK68: 22-OCT-2020 | AM68: 2% | AN68: 1350000 | AO68: 27000 | AS68: KHI/HO/D/MO/PC COMP/C/97805/20/09/2024 | AT68: KHI/HO/D/MO/PC COMP/E/47950/00020/10/2024 | AU68: 30600 | AV68: -3600 | AW68: REN | AX68: -3600 | AY68: 0
A69: 67 | B69: NORM | C69: 9976AP1212600049 | D69: 6AP1 | E69: A | F69: T-PAK | G69: MINI MOTORS | H69: 1099087 | I69: 0719594 | J69: 2 | K69: 24.69 | L69: 0719594001 | M69: JAMSHAID HASSAN CHEEMA | N69: Lahore | O69: 34101-2384695-9 | P69: 03338123921 | Q69: 03338123921 | R69: 03338123921 | S69: PAKISTAN RAILWAY PRAIS BURT INSTITU TE ALLAMA IQBAL ROAD LAHORE | T69: 534000 | U69: 1335000 | V69: 55601/00024/09/2021 | W69: 08-SEP-2022 | X69: 182053 | Y69: 1082021 | Z69: NEW | AB69: ALTO VXR EURO-II | AC69: 2021 | AD69: 17-SEP-2021 | AE69: 21-SEP-2021 | AF69: 21-Sep-2026 | AG69: OLDLHR300073302 | AH69: 5 | AI69: CTRK | AJ69: DIB0031624 | AK69: 09-SEP-2021 | AM69: 2% | AN69: 1068000 | AO69: 21360 | AS69: KHI/HO/D/MO/PC COMP/C/97805/142/09/2024 | AU69: 21360 | AV69: 0 | AW69: REN
A70: 68 | B70: NORM | C70: 997APD1202750013 | D70: APD1 | E70: A | F70: T-PAK | G70: MANDVIWALA MOTORS | H70: 579481 | I70: 0638371 | J70: 2 | K70: 26.28 | L70: 0638371001 | M70: MANZOOR ALI UMRANI | N70: Nawab Shah | O70: 45402-0961844-5 | P70: 03163033741 | Q70: 03163033741, 03003231711 | R70: 0 | S70: HOUSE # A-837 STREET # 2 CAMP # 1 G OLIMAR NEAR GHOSIA QABRUSTAN SHAHEE NAWABSHAH PK | T70: 1118400 | U70: 1398000 | V70: 52921/00007/10/2020 | W70: 29-SEP-2021 | X70: 141405 | Y70: 1041404 | Z70: NEW | AB70: SUZUKI ALTO VXR | AC70: 2020 | AD70: 01-OCT-2020 | AE70: 03-OCT-2020 | AF70: 03-Oct-2026 | AG70: PODNWB300058165 | AH70: 6 | AI70: ITMM | AJ70: 3177/09/2020/ITMM | AK70: 30-SEP-2020 | AM70: 2% | AN70: 1048500 | AO70: 20970 | AS70: KHI/HO/D/MO/PC COMP/C/97805/27/09/2024 | AT70: KHI/HO/D/MO/PC COMP/E/47950/00027/10/2024 | AU70: 22368 | AV70: -1398 | AW70: REN | AX70: -1398 | AY70: 0
A71: 69 | B71: NORM | C71: 9976AP1232730030 | D71: 6AP1 | E71: A | F71: T-PAK | G71: MASTER MOTORS | H71: 1412522 | I71: 0304658 | J71: 1.75 | K71: 25.7 | L71: 0304658002 | M71: ASIM MAHBOOB | N71: Lahore | O71: 35202-1176433-7 | P71: 03334321907 | Q71: 03334321907 | S71: LGS 49- CIVIC CENTRE M.A JOHAR TOWN LAHORE | T71: 2054500 | U71: 2935000 | V71: 74853/00035/09/2023 | W71: 29-SEP-2024 | X71: 284535 | Y71: 1184492 | Z71: NEW | AB71: SUZUKI ALTO VXL AGS EURO II | AC71: 2023 | AD71: 45199 | AE71: 03-OCT-2023 | AF71: 03-Oct-2026 | AG71: OLDLHR300097289 | AH71: 3 | AI71: FLCN | AJ71: 109194/09/2023 | AK71: 30-SEP-2023 | AM71: 1.75% | AN71: 2641500 | AO71: 46226.25 | AS71: KHI/HO/D/MO/PC COMP/C/97805/29/09/2024 | AT71: KHI/HO/D/MO/PC COMP/E/47950/00029/10/2024 | AU71: 43658 | AV71: 2568.25 | AW71: REN | AX71: 2568 | AY71: 0.25
A72: 70 | B72: NORM | C72: 9976AP1222730046 | D72: 6AP1 | E72: A | F72: T-PAK | G72: CRESENT CAR COMPANY | H72: 1192507 | I72: 0817811 | J72: 1.75 | K72: 25.2 | L72: 0817811001 | M72: MUHAMMAD IMRAN | N72: Lahore | O72: 35202-0474168-9 | P72: 03008066736 | Q72: 03008066736 | R72: 03008066736 | S72: H NO 423 BLOCK NO 5 SECTOR D-1 MOHA LLAH KEER KALAN TOWNSHIP LAHORE PK | T72: 2176000 | U72: 3200000 | V72: 63286/00094/09/2022 | W72: 29-SEP-2023 | X72: 17533597 | Y72: R252935 | Z72: USD | AA72: LE-20-6663 | AB72: HONDA CITY I-VTEC | AC72: 2019 | AD72: 30-SEP-2022 | AE72: 03-OCT-2022 | AF72: 03-Oct-2025 | AG72: OLULHR300090207 | AH72: 3 | AI72: ITFM | AJ72: 8896/09/2022/ITFM | AK72: 30-SEP-2022 | AM72: 1.75% | AN72: 2720000 | AO72: 47600 | AS72: KHI/HO/D/MO/PC COMP/C/97805/31/09/2024 | AU72: 47600 | AV72: 0 | AW72: REN
A73: 71 | B73: NORM | C73: 9976AD1212070025 | D73: 6AD1 | E73: A | F73: T-PAK | G73: PAK SUZUKI MOTOR CO LTD | H73: 1095953 | I73: 0699801 | J73: 2 | K73: 25.8 | L73: 0699801001 | M73: IRFAN ARSHAD | N73: Lahore | O73: 35200-1571573-7 | P73: 03217171859 | Q73: 03217171859 | R73: 03217171859 | S73: 60 FRUIT MARKET MULTAN CHUNGI WAHDA T ROAD NEAR PANI WALI TANKI LAHORE | T73: 1324000 | U73: 1655000 | V73: 2524/02640/00131/09/2021 | W73: 29-SEP-2021 | X73: 186133 | Y73: 10086135 | Z73: NEW | AB73: CULTUS VXR EURO-II | AC73: 2021 | AD73: 26-JUL-2021 | AE73: 03-OCT-2021 | AF73: 03-Oct-2028 | AG73: OLALHR300071147 | AH73: 7 | AI73: CTRK | AJ73: DIB0031946 | AK73: 30-SEP-2021 | AM73: 2% | AN73: 1324000 | AO73: 26480 | AS73: KHI/HO/D/MO/PC COMP/C/97805/32/09/2024 | AU73: 26480 | AV73: 0 | AW73: REN
A74: 72 | B74: NORM | C74: 997APD2202750013 | D74: APD2 | E74: A | F74: T-PAK | G74: MOTORWAYS PRIVATE LTD | H74: 579711 | I74: 0638223 | J74: 2 | K74: 27.28 | L74: 0638223001 | M74: AFTAB SHEIKH | N74: Karachi | O74: 42201-0475686-3 | P74: 03168605174 | Q74: 03168605174 | R74: 02199072031 | S74: HOUSE # L-5 SHEET # 16 JAFAR BAGH M ODEL COLONY NEAR BURHAN MASJID KARACHI PK | T74: 907200 | U74: 1134000 | V74: 52921/00004/10/2020 | W74: 29-SEP-2021 | X74: 1006236 | Y74: 1122742 | Z74: NEW | AB74: BOLAN VX EURO II | AC74: 2020 | AD74: 01-OCT-2020 | AE74: 03-OCT-2020 | AF74: 03-Oct-2025 | AG74: PODKHI300058141 | AH74: 5 | AI74: ITECL | AJ74: 3169/09/2020 | AK74: 30-SEP-2020 | AM74: 2% | AN74: 850500 | AO74: 17010 | AS74: KHI/HO/D/MO/PC COMP/C/97805/33/09/2024 | AT74: KHI/HO/D/MO/PC COMP/E/47950/00033/10/2024 | AU74: 19278 | AV74: -2268 | AW74: REN | AX74: -2268 | AY74: 0
A75: 73 | B75: NORM | C75: 9976AP1212570017 | D75: 6AP1 | E75: A | F75: T-PAK | G75: AL-QURASH MOTORS | H75: 1104364 | I75: 0720331 | J75: 2 | K75: 25.68 | L75: 0720331001 | M75: SAEED ANWAR | N75: Lahore | O75: 35202-4316138-5 | P75: 03227970580 | Q75: 03227970580 | R75: 03227970580 | S75: 9 RASOOL PARK MAIN SHAMA ROAD NEAR KASHMIR BAKERY LAHORE | T75: 1560000 | U75: 2400000 | V75: 55601/00025/09/2021 | W75: 08-SEP-2022 | X75: L13Z17504131 | Y75: NFBGM1546HR215372 | Z75: USD | AA75: LEA-18-9318 | AB75: HONDA CITY I-VTEC | AC75: 2018 | AD75: 14-SEP-2021 | AE75: 21-SEP-2021 | AF75: 21-Sep-2026 | AG75: OLULHR300073308 | AH75: 5 | AI75: CTRK | AJ75: DIB0031626 | AK75: 09-SEP-2021 | AM75: 2% | AN75: 1920000 | AO75: 38400 | AS75: KHI/HO/D/MO/PC COMP/C/97805/148/09/2024 | AU75: 38400 | AV75: 0 | AW75: REN
A76: 74 | B76: NORM | C76: 9976AP2222760040 | D76: 6AP2 | E76: A | F76: T-PAK | G76: NEW CAR COMPLEX | H76: AL-643207 | I76: 0801152 | J76: 1.5 | K76: 26.2 | L76: 0801152007 | M76: QAZI AMJAD ABID ABBASI | N76: Karachi | O76: 42301-1470554-5 | Q76: 03008244440 | S76: FLAT # SF-1 , SEA VIEW APPT, BEACH AVENUE PHASE 5 EXT DHA KARACHI 0300-8244440 | T76: 2970000 | U76: 4950000 | V76: 63286/00092/09/2022 | W76: 29-SEP-2023 | X76: 12955514 | Y76: LR059219 | Z76: USD | AA76: BRJ-212 | AB76: HONDA CIVIC 1.8L ORIEL | AC76: 2020 | AD76: 03-OCT-2022 | AE76: 03-OCT-2022 | AF76: 03-Oct-2025 | AG76: OLUKHI300090169 | AH76: 3 | AI76: ITFM | AJ76: 8883/09/2022/ITFM | AK76: 30-SEP-2022 | AM76: 1.5% | AN76: 4207500 | AO76: 63112.5 | AS76: KHI/HO/D/MO/PC COMP/C/97805/35/09/2024 | AU76: 63113 | AV76: -0.5 | AW76: REN
A77: 75 | B77: NORM | C77: 9976AD1211690033 | D77: 6AD1 | E77: A | F77: T-PAK | G77: PAK SUZUKI MOTOR CO LTD | H77: 638302 | I77: 0699928 | J77: 2 | K77: 25.79 | L77: 0699928001 | M77: BILAL SIKANDER | N77: Lahore | O77: 38401-7412616-9 | P77: 03434712494 | Q77: 03434712494 | R77: 04235880062 | S77: HOUSE NO 1189 STREET NO 11 NEAR SAN A CLINIC NISHAT COLONY LAHORE PK | T77: 1810500 | U77: 2130000 | V77: 2021-09-205-V01501OP0002138 | W77: 08-SEP-2021 | X77: 182585 | Y77: 10082597 | Z77: NEW | AB77: SUZUKI CULTUX VXL AGS EURO 11 | AC77: 2021 | AD77: 18-JUN-2021 | AE77: 03-OCT-2021 | AF77: 03-Oct-2028 | AG77: OLALHR300069566 | AH77: 7 | AI77: CTRK | AJ77: DIB0031619 | AK77: 09-SEP-2021 | AM77: 2% | AN77: 1704000 | AO77: 34080 | AS77: KHI/HO/D/MO/PC COMP/C/97805/150/09/2024 | AU77: 34080 | AV77: 0 | AW77: REN
A78: 76 | B78: NORM | C78: 9976AD1211960008 | D78: 6AD1 | E78: A | F78: T-PAK | G78: TOYOTA JINNAH MOTORS | H78: 1100085 | I78: 0488309 | J78: 2 | K78: 25.8 | L78: 0488309003 | M78: MUHAMMAD USMAN ZIA | N78: Lahore | O78: 35202-4574823-1 | P78: 03004444999 | Q78: 0, 03004444999 | R78: 03004444999 | S78: HAJI SARDAR MACHLI SHAHTAJ CENTER W ALTON ROAD LAHORE | T78: 2199750 | U78: 2933000 | V78: 2021-09-205-V01501OP0002134 | W78: 08-SEP-2022 | X78: 2A35534 | Y78: NSP151R-9513374 | Z78: NEW | AB78: YARIS ATIV X CVT 1.5 | AC78: 2021 | AD78: 15-JUL-2021 | AE78: 03-OCT-2021 | AF78: 03-Oct-2025 | AG78: OLALHR300070687 | AH78: 4 | AI78: CTRK | AJ78: DIB0031599 | AK78: 08-SEP-2021 | AM78: 2% | AN78: 2346400 | AO78: 46928 | AS78: KHI/HO/D/MO/PC COMP/C/97805/151/09/2024 | AT78: KHI/HO/D/MO/PC COMP/E/47950/00151/10/2024 | AU78: 49861 | AV78: -2933 | AW78: REN | AX78: -2933 | AY78: 0
A79: 77 | B79: NORM | C79: 9976AD1212000008 | D79: 6AD1 | E79: A | F79: T-PAK | G79: TOYOTA GARDEN MOTORS | H79: 1093657 | I79: 0601368 | J79: 2 | K79: 25.84 | L79: 0601368003 | M79: SHEZA MOEEN | N79: Lahore | O79: 35201-1181687-0 | P79: 03334288435 | Q79: 111448800, 03334288435 | R79: 111448800 | S79: HOUSE NO 691 STREET NO 14 BLOCK-C A SKARI 10 CANTT LAHORE PK | T79: 2042400 | U79: 2553000 | V79: 2524/02640/00031/09/2021 | W79: 08-SEP-2022 | X79: 2A35401 | Y79: 7022012 | Z79: NEW | AB79: TOYOTA YARIS ATI V M T 1.3 | AC79: 2021 | AD79: 19-JUL-2021 | AE79: 21-SEP-2021 | AF79: 21-Sep-2028 | AG79: OLALHR300070957 | AH79: 7 | AI79: CTRK | AJ79: DIB0031622 | AK79: 09-SEP-2021 | AM79: 2% | AN79: 2042400 | AO79: 40848 | AS79: KHI/HO/D/MO/PC COMP/C/97805/152/09/2024 | AU79: 40848 | AV79: 0 | AW79: REN
A80: 78 | B80: NORM | C80: 9976AD1222720004 | D80: 6AD1 | E80: A | F80: T-PAK | G80: KIA MACCA MOTORS | H80: AL-1200614 | I80: 0189347 | J80: 2 | K80: 26.7 | L80: 0189347012 | M80: DANISH ATIQ | N80: Karachi | O80: 42201-4457023-5 | P80: 02134583364 | Q80: 03316043931 | R80: 34536207 | S80: H NO-27 DOHS 2 MALIR CANTT 1ST FLOOR STREET-1 NEAR-CHECK POST-1 KARACHI | T80: 2925000 | U80: 5850000 | V80: DIB/T/38673/KHI/0922 | W80: 29-SEP-2023 | X80: 1869437 | Y80: 500578 | Z80: NEW | AB80: PEUGEOT 2008 ALLURE | AC80: 2022 | AD80: 29-SEP-2022 | AE80: 03-OCT-2022 | AF80: 03-Oct-2025 | AG80: OLAKHI300090143 | AH80: 3 | AI80: ITFM | AJ80: 8863/09/2022/ITFM | AK80: 30-SEP-2022 | AM80: 2% | AN80: 4972500 | AO80: 99450 | AS80: KHI/HO/D/MO/PC COMP/C/97805/36/09/2024 | AU80: 99450 | AV80: 0 | AW80: REN
A81: 79 | B81: NORM | C81: 9976AP1222730062 | D81: 6AP1 | E81: A | F81: T-PAK | G81: AL JANAT MOTORS | H81: AL-1096997 | I81: 0340701 | J81: 1.75 | K81: 25.2 | L81: 0340701002 | M81: MUHAMMAD WASEEM | N81: Lahore | O81: 35201-9340992-1 | Q81: 03239999119 | S81: AZEEM MARBLE AND GRANITE SHARIF PARK OPP ATTOCK PETROL PUMP CENTRAL PARK 31-KM FEROZEPUR ROAD LAHORE | T81: 2052000 | U81: 3600000 | V81: 63286/00095/09/2022 | W81: 29-SEP-2023 | X81: 12933100 | Y81: R036532 | Z81: USD | AA81: LEE-18-6664 | AB81: HONDA CIVIC VTI ORIEL P/T | AC81: 2018 | AD81: 30-SEP-2022 | AE81: 03-OCT-2022 | AF81: 03-Oct-2025 | AG81: OLULHR300090205 | AH81: 3 | AI81: ITFM | AJ81: 30-SEP-2022 | AK81: 29-SEP-2023 | AM81: 1.75% | AN81: 3060000 | AO81: 53550 | AS81: KHI/HO/D/MO/PC COMP/C/97805/39/09/2024 | AU81: 53550 | AV81: 0 | AW81: REN
A82: 80 | B82: NORM | C82: 9976AD1210830011 | D82: 6AD1 | E82: A | F82: T-PAK | G82: TOYOTA SOUTHERN MOTORS | H82: 591955 | I82: 0682525 | J82: 2 | K82: 25.68 | L82: 0682525001 | M82: ASFAND MARI | N82: Karachi | O82: 41306-8663031-5 | P82: 03342139606 | Q82: 03342139606 | R82: 0 | S82: FLAT NO 1 1ST FLOOR PLOT 60/C STREE T 25 TH TOUHEED COMMERCIOL MOVIN PI KARACHI PK | T82: 2700000 | U82: 3375000 | V82: 2524/02640/00028/09/2021 | W82: 08-SEP-2022 | X82: Q079832 | Y82: 6057325 | Z82: NEW | AB82: TOYOTA COROLLA ALTIS A/T | AC82: 2021 | AD82: 24-MAR-2021 | AE82: 21-SEP-2021 | AF82: 21-Sep-2026 | AG82: OLAKHI300066991 | AH82: 5 | AI82: CTRK | AJ82: DIB0031529 | AK82: 06-SEP-2021 | AM82: 2% | AN82: 2700000 | AO82: 54000 | AS82: KHI/HO/D/MO/PC COMP/C/97805/154/09/2024 | AU82: 54000 | AV82: 0 | AW82: REN
A83: 81 | B83: NORM | C83: 9976AP2222730031 | D83: 6AP2 | E83: A | F83: T-PAK | G83: CRESENT CAR COMPANY | H83: 1192559 | I83: 0267823 | J83: 1.75 | K83: 26.7 | L83: 0267823003 | M83: UMAR IQBAL | N83: Lahore | O83: 35202-8270908-7 | P83: N/A | Q83: 03006237894 | R83: 0300-6237894 | S83: H# 01 ST# 01 BARKAT TOWN FAISAL PARK SHAHDRA LAHORE | T83: 1382500 | U83: 1975000 | V83: 63286/00096/09/2022 | W83: 29-SEP-2023 | X83: 151141 | Y83: 10051105 | Z83: USD | AA83: LEA-18-6529 | AB83: SUZUKI WAGONR VXL | AC83: 2018 | AD83: 30-SEP-2022 | AE83: 03-OCT-2022 | AF83: 03-Oct-2027 | AG83: OLULHR30090211 | AH83: 5 | AI83: ITFM | AJ83: 899/09/2022/ITFM | AK83: 30-SEP-2022 | AM83: 1.75% | AN83: 1678750 | AO83: 29378.125 | AS83: KHI/HO/D/MO/PC COMP/C/97805/42/09/2024 | AT83: KHI/HO/D/MO/PC COMP/E/47950/00042/10/2024 | AU83: 25922 | AV83: 3456.125 | AW83: REN | AX83: 3456 | AY83: 0.125
A84: 82 | B84: NORM | C84: 9976AD1210890017 | D84: 6AD1 | E84: A | F84: T-PAK | G84: SUBHAN MOTORS | H84: 626175 | I84: 0682586 | J84: 2 | K84: 25.78 | L84: 0682586001 | M84: MALIK ALI RIZWAN | N84: Sialkot | O84: 34603-2299631-9 | P84: 03018617660 | Q84: 03018617660 | R84: 03018617660 | S84: MALIK STREET NEW MIANA PURA RORAS R OAD NEAR OPPOSITE SIKANDAR CORP. SIALKOT | T84: 2956850 | U84: 4549000 | V84: 2021-09-205-V01501OP0002133 | W84: 08-SEP-2022 | X84: SFG15T-21019961 | Y84: PDF508PALR21H1716 | Z84: NEW | AB84: PRINCE GLORY 580 PRO | AC84: 2021 | AD84: 30-MAR-2021 | AE84: 21-SEP-2021 | AF84: 21-Sep-2026 | AG84: OLASKT300067124 | AH84: 5 | AI84: FLCN | AJ84: 10857/09/2021 | AK84: 08-SEP-2021 | AM84: 2% | AN84: 3639200 | AO84: 72784 | AS84: KHI/HO/D/MO/PC COMP/C/97805/156/09/2024 | AU84: 72784 | AV84: 0 | AW84: REN
A85: 83 | B85: NORM | C85: 9976AP1222730056 | D85: 6AP1 | E85: A | F85: T-PAK | G85: CAR CAPITAL | H85: 1198521 | I85: 0822469 | J85: 1.75 | K85: 25.2 | L85: 0822469001 | M85: SHEHZAD ALI KHAN | N85: Karachi | O85: 42201-4740858-1 | P85: 03232022596 | Q85: 03232022596, 03232022596 | R85: 0 | S85: H. NO. D-444 SEC 33/A KORANGI # 2 1 /2 NEAR OPP CHINIGOT HOSPITAL KARACHI PK | T85: 1798000 | U85: 2900000 | V85: 63286/00089/09/2022 | W85: 29-SEP-2023 | X85: 13050601 | Y85: 10050539 | Z85: USD | AA85: BTY-908 | AB85: SUZUKI SWIFT A/T NAVIGATION | AC85: 2021 | AD85: 30-SEP-2022 | AE85: 03-OCT-2022 | AF85: 03-Oct-2025 | AG85: OLUKHI300090184 | AH85: 3 | AI85: ITFM | AJ85: 8880/09/2022/ITFM | AK85: 30-SEP-2022 | AM85: 1.75% | AN85: 2465000 | AO85: 43137.5 | AS85: KHI/HO/D/MO/PC COMP/C/97805/43/09/2024 | AU85: 43138 | AV85: -0.5 | AW85: REN
A86: 84 | B86: NORM | C86: 997AAD1202120027 | D86: AAD1 | E86: A | F86: T-PAK | G86: TOYOTA AIRPORT MOTOR | H86: 577415 | I86: 0618908 | J86: 1.5 | K86: 26.93 | L86: 0618908003 | M86: ALI AKBAR | N86: Lahore | O86: 35201-1555277-1 | Q86: 03008478505 | S86: HOUSE NO. 241, STREET NO. 04, PHASE 04, DHA LAHORE CANTT 0300-8478505 | T86: 7347200 | U86: 9184000 | V86: COMP/P/52740/09/2020 | W86: 08-SEP-2021 | X86: 1GD0838553 | Y86: GUN156R-1093706 | Z86: NEW | AB86: FORTUNER DIESEL 4X4 | AC86: 2020 | AD86: 30-JUL-2020 | AE86: 21-SEP-2020 | AF86: 21-Sep-2027 | AG86: POALHR300056083 | AH86: 7 | AI86: ITFM | AJ86: 2982/09/2020/ITFM | AK86: 10-SEP-2020 | AM86: 1.5% | AN86: 6888000 | AO86: 103320 | AS86: KHI/HO/D/MO/PC COMP/C/97805/158/09/2024 | AU86: 103320 | AV86: 0 | AW86: REN
A87: 85 | B87: NORM | C87: 9976AP1222730050 | D87: 6AP1 | E87: A | F87: T-PAK | G87: NEW CAR COMPLEX | H87: 1200679 | I87: 0390197 | J87: 1.75 | K87: 25.45 | L87: 0390197006 | M87: SYED MEHDI HASAN RIZVI | N87: Karachi | O87: 42101-4771450-9 | P87: 03219254631 | Q87: 03219254631 | R87: 35221133 | S87: L-753 SECTOR # 5-D SURJANI TOWN KARACHI PK | T87: 1655500 | U87: 2365000 | V87: 63286/00091/09/2022 | W87: 29-SEP-2023 | X87: R177188 | Y87: 1077179 | Z87: USD | AA87: BUZ-721 | AB87: SUZUKI ALTO VXL AGS EURO-II | AC87: 2021 | AD87: 30-SEP-2022 | AE87: 03-OCT-2022 | AF87: 03-Oct-2027 | AG87: OLUKHI300090195 | AH87: 5 | AI87: ITFM | AJ87: 8882/09/2022/ITFM | AK87: 30-SEP-2022 | AM87: 1.75% | AN87: 2010250 | AO87: 35179.375 | AS87: KHI/HO/D/MO/PC COMP/C/97805/44/09/2024 | AT87: KHI/HO/D/MO/PC COMP/E/47950/00044/10/2024 | AU87: 31041 | AV87: 4138.375 | AW87: REN | AX87: 4139 | AY87: -0.625
A88: 86 | B88: NORM | C88: 9976AP2222560001 | D88: 6AP2 | E88: A | F88: T-PAK | G88: CAR CAPITAL | H88: AL-1150012 | I88: 0803645 | J88: 1.75 | K88: 26.19 | L88: 0803645002 | M88: MUHAMMAD ALI | N88: Karachi | O88: 42301-6811072-7 | Q88: 03312233199 | S88: FLAT NO 207, AZHAN GARDEN JAMSHAID QUARTER KARACHI 0331-2233199 | T88: 1026000 | U88: 1900000 | V88: 63286/00017/09/2022 | W88: 08-SEP-2023 | X88: 13036457 | Y88: 10036448 | Z88: USD | AA88: BJR-391 | AB88: SUZUKI SWIFT DLX ABS WITH EBD A/T | AC88: 2017 | AD88: 13-SEP-2022 | AE88: 21-SEP-2022 | AF88: 21-Sep-2025 | AG88: OLUKHI300089782 | AH88: 3 | AI88: ITFM | AJ88: 8638/09/2022/ITFM | AK88: 12-SEP-2022 | AM88: 1.75% | AN88: 1615000 | AO88: 28262.5 | AS88: KHI/HO/D/MO/PC COMP/C/97805/159/09/2024 | AU88: 28263 | AV88: -0.5 | AW88: REN
A89: 87 | B89: NORM | C89: 9976AP1222560002 | D89: 6AP1 | E89: A | F89: T-PAK | G89: CITY CARS | H89: AL-598769 | I89: 0327054 | J89: 1.75 | K89: 25.44 | L89: 0327054002 | M89: ISMAIL KHAN | N89: Karachi | O89: 42501-1003173-7 | Q89: 03132590938 | S89: SHOP NO 6-7,GROUND FLOOR,BLOCK-2 SURYA RESIDENCY,SURVEY SHEET P.E.C.H.S, KARACHI | T89: 1652000 | U89: 2360000 | V89: 63286/00019/09/2022 | W89: 08-SEP-2023 | X89: 6R221057 | Y89: 1120741 | Z89: USD | AA89: BWF-485 | AB89: SUZUKI ALTO VXL AGS EURO II | AC89: 2022 | AD89: 13-SEP-2022 | AE89: 21-SEP-2022 | AF89: 21-Sep-2027 | AG89: OLUKHI300089775 | AH89: 5 | AI89: ITFM | AJ89: 8630/09/2022 | AK89: 10-SEP-2022 | AM89: 1.75% | AN89: 2006000 | AO89: 35105 | AS89: KHI/HO/D/MO/PC COMP/C/97805/160/09/2024 | AT89: KHI/HO/D/MO/PC COMP/E/47950/00160/10/2024 | AU89: 30975 | AV89: 4130 | AW89: REN | AX89: 4130 | AY89: 0
A90: 88 | B90: NORM | C90: 9976AP2222730020 | D90: 6AP2 | E90: A | F90: T-PAK | G90: MASTER MOTORS | H90: 1414298 | I90: 0822857 | J90: 1.75 | K90: 26.7 | L90: 0822857002 | M90: AMIR IQBAL | N90: Lahore | O90: 33302-4984722-3 | P90: 03364552806 | Q90: 03364552806 | R90: 03364552806 | S90: H NO 91 BLOCK C NEW OFFICERS COLONY SADAR CANTT LAHORE PK | T90: 1282000 | U90: 2564000 | V90: 63286/00093/09/2022 | W90: 29-SEP-2023 | X90: 240565 | Y90: 10140576 | Z90: NEW | AB90: SUZUKI WAGONR VXL | AC90: 2022 | AD90: 30-SEP-2022 | AE90: 03-OCT-2022 | AF90: 03-Oct-2027 | AG90: OLDLHR300090202 | AH90: 5 | AI90: ITFM | AJ90: 8890/09/2022/ITFM | AK90: 30-SEP-2022 | AM90: 1.75% | AN90: 2179400 | AO90: 38139.5 | AS90: KHI/HO/D/MO/PC COMP/C/97805/46/09/2024 | AT90: KHI/HO/D/MO/PC COMP/E/47950/00046/10/2024 | AU90: 33653 | AV90: 4486.5 | AW90: REN | AX90: 4487 | AY90: -0.5
A91: 89 | B91: NORM | C91: 9976AP1222730041 | D91: 6AP1 | E91: A | F91: T-PAK | G91: ALI JAN MOTORS | H91: 1192548 | I91: 0822259 | J91: 1.75 | K91: 25.7 | L91: 0822259001 | M91: ABDULLAH BUTT | N91: Lahore | O91: 35202-5363329-9 | P91: 03047643095 | Q91: 03047643095 | R91: 03047643095 | S91: H NO 116-B SHAH JAMAL COLONY LAHORE PK | T91: 2394000 | U91: 3420000 | V91: 63286/00088/09/2022 | W91: 29-SEP-2023 | X91: 1007593 | Y91: 107591 | Z91: NEW | AB91: SUZUKI SWIFT GL CVT | AC91: 2022 | AD91: 30-SEP-2022 | AE91: 03-OCT-2022 | AF91: 03-Oct-2025 | AG91: OLDLHR300090171 | AH91: 3 | AI91: ITFM | AJ91: 8871/09/2022/ITFM | AK91: 30-SEP-2022 | AM91: 1.75% | AN91: 2907000 | AO91: 50872.5 | AS91: KHI/HO/D/MO/PC COMP/C/97805/47/09/2024 | AU91: 50873 | AV91: -0.5 | AW91: REN
A92: 90 | B92: NORM | C92: 9976AP1222730040 | D92: 6AP1 | E92: A | F92: T-PAK | G92: AL JANAT MOTORS | H92: 1414287 | I92: 0820222 | J92: 1.75 | K92: 25.45 | L92: 0820222001 | M92: MUHAMMAD AFZAL | N92: Lahore | O92: 33104-7125847-5 | P92: 03227948137 | Q92: 03227948137 | R92: 04237723656 | S92: HOUSE NO 568 BLOCK B STREET NO 14 A SKARI 10 LAHORE PK | T92: 1618500 | U92: 2490000 | V92: 63286/00090/09/2022 | W92: 29-SEP-2023 | X92: 140264 | Y92: 10039977 | Z92: USD | AA92: LEE-19-132 | AB92: SUZUKI CULTUS VXL AGS EURO-II | AC92: 2019 | AD92: 30-SEP-2022 | AE92: 03-OCT-2022 | AF92: 03-Oct-2027 | AG92: OLULHR300090177 | AH92: 5 | AI92: ITFM | AJ92: 8878/09/2022/ITFM | AK92: 30-SEP-2022 | AM92: 1.75% | AN92: 2116500 | AO92: 37038.75 | AS92: KHI/HO/D/MO/PC COMP/C/97805/48/09/2024 | AT92: KHI/HO/D/MO/PC COMP/E/47950/00048/10/2024 | AU92: 32681 | AV92: 4357.75 | AW92: REN | AX92: 4358 | AY92: -0.25
A93: 91 | B93: NORM | C93: 9976AP1222730031 | D93: 6AP1 | E93: A | F93: T-PAK | G93: MINI MOTORS | H93: 1103803 | I93: 0822635 | J93: 1.75 | K93: 25.7 | L93: 0822635001 | M93: MALIK DILAWAR HUSSAIN | N93: Lahore | O93: 35202-6793460-5 | P93: 03214789562 | Q93: 03214789562 | S93: H NO 69 ST NO 3 SAEED PARK SHAHDARA NEAR CHAIR MARKET LAHORE | T93: 717920 | U93: 2564000 | V93: 63286/00087/09/2022 | W93: 29-SEP-2023 | X93: 240648 | Y93: 10140650 | Z93: NEW | AB93: SUZUKI WAGONR VXL | AC93: 2022 | AD93: 30-SEP-2022 | AE93: 03-OCT-2022 | AF93: 03-Oct-2025 | AG93: OLDLHR300090173 | AH93: 3 | AI93: ITFM | AJ93: 8869/09/2022/ITFM | AK93: 30-SEP-2022 | AM93: 1.75% | AN93: 2179400 | AO93: 38139.5 | AS93: KHI/HO/D/MO/PC COMP/C/97805/49/09/2024 | AU93: 38140 | AV93: -0.5 | AW93: REN
A94: 92 | B94: NORM | C94: 9976AP1222730030 | D94: 6AP1 | E94: A | F94: T-PAK | G94: CRESENT CAR COMPANY | H94: 1192544 | I94: 0821131 | J94: 1.75 | K94: 25.45 | L94: 0821131001 | M94: SHEIKH SHOAIB AHMAD | N94: Lahore | O94: 35202-6570294-9 | P94: 03222696969 | Q94: 03222696969 | R94: 03222696969 | S94: H NO 59-B KACHA FEROZPUR ROAD NEAR SUZUKI KHALID MOTORS LAHORE PK | T94: 1216000 | U94: 1900000 | V94: 63286/00086/09/2022 | W94: 29-SEP-2023 | X94: 119556 | Y94: 10019543 | Z94: USD | AA94: LEE-18-4720 | AB94: SUZUKI CULTUS VXR EURO-II | AC94: 2018 | AD94: 30-SEP-2022 | AE94: 03-OCT-2022 | AF94: 03-Oct-2027 | AG94: OLULHR300090164 | AH94: 5 | AI94: ITFT | AJ94: 8860/09/2022/ITFM | AK94: 30-SEP-2022 | AM94: 1.75% | AN94: 1615000 | AO94: 28262.5 | AS94: KHI/HO/D/MO/PC COMP/C/97805/50/09/2024 | AT94: KHI/HO/D/MO/PC COMP/E/47950/00050/10/2024 | AU94: 24938 | AV94: 3324.5 | AW94: REN | AX94: 3325 | AY94: -0.5
A95: 93 | B95: NORM | C95: 9976AD1210910115 | D95: 6AD1 | E95: A | F95: T-PAK | G95: HYUNDAI CENTRAL MOTORS | H95: 526243 | I95: 0684427 | J95: 2 | K95: 25.79 | L95: 0684427001 | M95: ASAD EJAZ | N95: Lahore | O95: 35202-2970709-5 | P95: 03009404061 | Q95: 03009404061 | R95: 03009404061 | S95: SHOP NO 14,15 GROUND FLOOR SULTANA ARCADE KAREEM BLOCK MARKET ALLAMA I QBAL TOWN LAHORE | T95: 3314350 | U95: 5099000 | V95: 2524/02640/00134/09/2021 | W95: 29-SEP-2021 | X95: G4NAMU087667 | Y95: PMHJ2813MMN203476 | Z95: NEW | AB95: TUCSON FWD | AC95: 2021 | AD95: 01-APR-2021 | AE95: 03-OCT-2021 | AF95: 03-Oct-2026 | AG95: OLALHR300067529 | AH95: 5 | AI95: CTRK | AJ95: DIB0031950 | AK95: 30-SEP-2021 | AM95: 2% | AN95: 4079200 | AO95: 81584 | AS95: KHI/HO/D/MO/PC COMP/C/97805/51/09/2024 | AU95: 81584 | AV95: 0 | AW95: REN
A96: 94 | B96: NORM | C96: 9976AD1211510064 | D96: 6AD1 | E96: A | F96: T-PAK | G96: PAK SUZUKI MOTOR CO LTD | H96: 1094035 | I96: 0140598 | J96: 2 | K96: 25.8 | L96: 0140598004 | M96: ALI HAMMAD RAZA | N96: Multan | O96: 36302-4233549-5 | Q96: 03146153385 | R96: 0614541092 | S96: SWIFT POWER PAY SERVICES, 108-C, TUGLUQ ROAD, CHUNGI NO.7, AL HASSAN MANZIL, MULTAN. | T96: 1064700 | U96: 1521000 | V96: 55601/00027/09/2021 | W96: 09-SEP-2022 | X96: 6R177394 | Y96: NF1AET306H1077381 | Z96: NEW | AB96: ALTO VXL AGS EURO II | AC96: 2021 | AD96: 31-MAY-2021 | AE96: 03-OCT-2021 | AF96: 03-Oct-2026 | AG96: OLAMUX300069168 | AH96: 5 | AI96: FLCN | AJ96: 1058574/09/2021 | AK96: 10-SEP-2021 | AM96: 2% | AN96: 1216800 | AO96: 24336 | AS96: KHI/HO/D/MO/PC COMP/C/97805/168/09/2024 | AT96: 0 | AU96: 24336 | AV96: 0 | AW96: REN
A97: 95 | B97: NORM | C97: 9976AD2210880004 | D97: 6AD2 | E97: A | F97: T-PAK | G97: CHANGAN ADIL ASHRAF MOTORS | H97: 648651 | I97: 0679219 | J97: 2 | K97: 26.18 | L97: 0679219001 | M97: AFZAL ISHAQ MIRZA | N97: Sialkot | O97: 34603-0506725-5 | P97: 03096140446 | Q97: 03096140446 | R97: 03096140446 | S97: NEAR NATIONAL POSHISH DEFENCE ROAD SIALKOT | T97: 1148000 | U97: 1640000 | V97: 2021/09/CLFTTPCDP01008 | W97: 09-SEP-2022 | X97: 466Q9M69U504981 | Y97: NKMAAB3D1M1008755 | Z97: NEW | AB97: KARVAAN PLUS | AC97: 2021 | AD97: 29-MAR-2021 | AE97: 27-SEP-2021 | AF97: 27-Sep-2026 | AG97: OLASKT300066954 | AH97: 5 | AI97: FLCN | AJ97: 108575/09/2021 | AK97: 10-SEP-2021 | AM97: 2% | AN97: 1312000 | AO97: 26240 | AS97: KHI/HO/D/MO/PC COMP/C/97805/169/09/2024 | AU97: 26240 | AV97: 0 | AW97: REN
A98: 96 | B98: NORM | C98: 997APD1202750004 | D98: APD1 | E98: A | F98: T-PAK | G98: KIA MOTORS FEROZEPUR | H98: 633039 | I98: 0475555 | J98: 1.5 | K98: 26.78 | L98: 0475555003 | M98: GHULAM SHABBIR SHAHEEN | N98: Lahore | O98: 37203-1485511-1 | P98: 03219463428 | Q98: 03219463428 | R98: 36362870 | S98: SHOP# 4 GROUND FLOOTR EMPIRE CENTRE 1 MAIN ABBOT ROAD NEAR NATIONAL HO TEL LAHORE | T98: 4072500 | U98: 5430000 | V98: 52740/00102/09/2020 | W98: 29-SEP-2021 | X98: H323747 | Y98: KP505067 | Z98: NEW | AB98: KIA SPORTAGE AWD | AC98: 2020 | AD98: 01-OCT-2020 | AE98: 03-OCT-2020 | AF98: 03-Oct-2025 | AG98: PODLHR300058092 | AH98: 5 | AM98: 1.5% | AN98: 4072500 | AO98: 61087.5 | AS98: KHI/HO/D/MO/PC COMP/C/97805/52/09/2024 | AT98: KHI/HO/D/MO/PC COMP/E/47950/00052/10/2024 | AU98: 69233 | AV98: -8145.5 | AW98: REN | AX98: -8145 | AY98: -0.5
A99: 97 | B99: NORM | C99: 997AAD1201820042 | D99: AAD1 | E99: A | F99: T-PAK | G99: KIA SAMA MOTORS | H99: 588102 | I99: 0035542 | J99: 1.5 | K99: 26.78 | L99: 0035542003 | M99: NADEEM HUSSAIN | N99: Lahore | O99: 35202-2356167-3 | P99: 042-7241449 | Q99: 03224493518 | R99: 042-8557041 | S99: H NO 13/1NAND STR-47 CHUBARGI SHAM NAGAR NEAR ILAHI CLINIC Lahore | T99: 3961710 | U99: 5427000 | V99: 52921/00017/10/2020 | W99: 29-SEP-2021 | X99: G4NALH323163 | Y99: NNAQL51AZKP505281 | Z99: NEW | AB99: KIS SPORTAGE AWD | AC99: 2020 | AD99: 30-JUN-2020 | AE99: 11-OCT-2020 | AF99: 11-Oct-2025 | AG99: POALHR300054911 | AH99: 5 | AM99: 1.5% | AN99: 4070250 | AO99: 61053.75 | AS99: KHI/HO/D/MO/PC COMP/C/97805/59/09/2024 | AT99: KHI/HO/D/MO/PC COMP/E/47950/00059/10/2024 | AU99: 69194 | AV99: -8140.25 | AW99: REN | AX99: -8141 | AY99: 0.75
A100: 98 | B100: NORM | C100: 9976AD2212120027 | D100: 6AD2 | E100: A | F100: T-PAK | G100: FEDERAL MOTORS | H100: 646420 | I100: 0711440 | J100: 2 | K100: 26.34 | L100: 0711440001 | M100: SANIA KHALID | N100: Islamabad | O100: 61101-3969863-0 | P100: 03450539140 | R100: 0 | S100: H # 391 ST # 75 E-11/3 NEAR CITY SC HOOL E-11/3 ISLAMABAD PK | T100: 1281000 | U100: 1830000 | V100: 01-2109-PO-MTR-PCCM-D-001996 | W100: 09-SEP-2022 | X100: 184394 | Y100: 10084378 | Z100: NEW | AB100: SUZUKI CULTUS VXL EURO II | AC100: 2021 | AD100: 31-JUL-2021 | AE100: 27-SEP-2021 | AF100: 27-Sep-2026 | AG100: OLAISD300071543 | AH100: 5 | AI100: ITECL | AJ100: 5425/09/2021 | AK100: 10-SEP-2021 | AM100: 2% | AN100: 1464000 | AO100: 29280 | AS100: KHI/HO/D/MO/PC COMP/C/97805/172/09/2024 | AU100: 29280 | AV100: 0 | AW100: REN
...

Sheet working
A1: POLICY NO. | B1: Assorted_code | D1: Premium | E1: 29Oct240041
A2: KHI/HO/D/MO/PC COMP/C/97805/1/09/2024 | B2: =VLOOKUP(A2,policy!B:C,2,0) -> 070000165775 | C2: 21360 | D2: =ROUND(C2,0) -> 21360 | E2: 29Oct240041 | F2: ="insert into ins_premium_det (premium_rcv_code,assorted_code, rec_amount,premium_rcv_detail_code,remaining_amt, payrec, mode_code,coinsurance_code,class_cd,it_remarks) values" -> insert into ins_premium_det (premium_rcv_code,assorted_code, rec_amount,premium_rcv_detail_code,remaining_amt, payrec, mode_code,coinsurance_code,class_cd,it_remarks) values | G2: ="('"&E2&"','"&B2&"','"&D2&"',(select max(to_number(i.premium_rcv_detail_code))+1 from ins_premium_det i),'"&D2&"','"&D2&"','02', '11000003','00','Request by Mr. Saqib Saleem 30-Oct-2024');" -> ('29Oct240041','070000165775','21360',(select max(to_number(i.premium_rcv_detail_code))+1 from ins_premium_det i),'21360','21360','02', '11000003','00','Request by Mr. Saqib Saleem 30-Oct-2024'); | H2: =F2&G2 -> insert into ins_premium_det (premium_rcv_code,assorted_code, rec_amount,premium_rcv_detail_code,remaining_amt, payrec, mode_code,coinsurance_code,class_cd,it_remarks) values('29Oct240041','070000165775','21360',(select max(to_number(i.premium_rcv_detail_code))+1 from ins_premium_det i),'21360','21360','02', '11000003','00','Request by Mr. Saqib Saleem 30-Oct-2024');
A3: KHI/HO/D/MO/PC COMP/C/97805/2/09/2024 | B3: =VLOOKUP(A3,policy!B:C,2,0) -> 070000165777 | C3: 40715 | D3: =ROUND(C3,0) -> 40715 | E3: 29Oct240041 | F3: ="insert into ins_premium_det (premium_rcv_code,assorted_code, rec_amount,premium_rcv_detail_code,remaining_amt, payrec, mode_code,coinsurance_code,class_cd,it_remarks) values" -> insert into ins_premium_det (premium_rcv_code,assorted_code, rec_amount,premium_rcv_detail_code,remaining_amt, payrec, mode_code,coinsurance_code,class_cd,it_remarks) values | G3: ="('"&E3&"','"&B3&"','"&D3&"',(select max(to_number(i.premium_rcv_detail_code))+1 from ins_premium_det i),'"&D3&"','"&D3&"','02', '11000003','00','Request by Mr. Saqib Saleem 30-Oct-2024');" -> ('29Oct240041','070000165777','40715',(select max(to_number(i.premium_rcv_detail_code))+1 from ins_premium_det i),'40715','40715','02', '11000003','00','Request by Mr. Saqib Saleem 30-Oct-2024'); | H3: =F3&G3 -> insert into ins_premium_det (premium_rcv_code,assorted_code, rec_amount,premium_rcv_detail_code,remaining_amt, payrec, mode_code,coinsurance_code,class_cd,it_remarks) values('29Oct240041','070000165777','40715',(select max(to_number(i.premium_rcv_detail_code))+1 from ins_premium_det i),'40715','40715','02', '11000003','00','Request by Mr. Saqib Saleem 30-Oct-2024');
A4: KHI/HO/D/MO/PC COMP/C/97805/3/09/2024 | B4: =VLOOKUP(A4,policy!B:C,2,0) -> 070000165778 | C4: 70912 | D4: =ROUND(C4,0) -> 70912 | E4: 29Oct240041 | F4: ="insert into ins_premium_det (premium_rcv_code,assorted_code, rec_amount,premium_rcv_detail_code,remaining_amt, payrec, mode_code,coinsurance_code,class_cd,it_remarks) values" -> insert into ins_premium_det (premium_rcv_code,assorted_code, rec_amount,premium_rcv_detail_code,remaining_amt, payrec, mode_code,coinsurance_code,class_cd,it_remarks) values | G4: ="('"&E4&"','"&B4&"','"&D4&"',(select max(to_number(i.premium_rcv_detail_code))+1 from ins_premium_det i),'"&D4&"','"&D4&"','02', '11000003','00','Request by Mr. Saqib Saleem 30-Oct-2024');" -> ('29Oct240041','070000165778','70912',(select max(to_number(i.premium_rcv_detail_code))+1 from ins_premium_det i),'70912','70912','02', '11000003','00','Request by Mr. Saqib Saleem 30-Oct-2024'); | H4: =F4&G4 -> insert into ins_premium_det (premium_rcv_code,assorted_code, rec_amount,premium_rcv_detail_code,remaining_amt, payrec, mode_code,coinsurance_code,class_cd,it_remarks) values('29Oct240041','070000165778','70912',(select max(to_number(i.premium_rcv_detail_code))+1 from ins_premium_det i),'70912','70912','02', '11000003','00','Request by Mr. Saqib Saleem 30-Oct-2024');
A5: KHI/HO/D/MO/PC COMP/C/97805/4/09/2024 | B5: =VLOOKUP(A5,policy!B:C,2,0) -> 070000165779 | C5: 70912 | D5: =ROUND(C5,0) -> 70912 | E5: 29Oct240041 | F5: ="insert into ins_premium_det (premium_rcv_code,assorted_code, rec_amount,premium_rcv_detail_code,remaining_amt, payrec, mode_code,coinsurance_code,class_cd,it_remarks) values" -> insert into ins_premium_det (premium_rcv_code,assorted_code, rec_amount,premium_rcv_detail_code,remaining_amt, payrec, mode_code,coinsurance_code,class_cd,it_remarks) values | G5: ="('"&E5&"','"&B5&"','"&D5&"',(select max(to_number(i.premium_rcv_detail_code))+1 from ins_premium_det i),'"&D5&"','"&D5&"','02', '11000003','00','Request by Mr. Saqib Saleem 30-Oct-2024');" -> ('29Oct240041','070000165779','70912',(select max(to_number(i.premium_rcv_detail_code))+1 from ins_premium_det i),'70912','70912','02', '11000003','00','Request by Mr. Saqib Saleem 30-Oct-2024'); | H5: =F5&G5 -> insert into ins_premium_det (premium_rcv_code,assorted_code, rec_amount,premium_rcv_detail_code,remaining_amt, payrec, mode_code,coinsurance_code,class_cd,it_remarks) values('29Oct240041','070000165779','70912',(select max(to_number(i.premium_rcv_detail_code))+1 from ins_premium_det i),'70912','70912','02', '11000003','00','Request by Mr. Saqib Saleem 30-Oct-2024');
A6: KHI/HO/D/MO/PC COMP/C/97805/5/09/2024 | B6: =VLOOKUP(A6,policy!B:C,2,0) -> 070000165780 | C6: 68837 | D6: =ROUND(C6,0) -> 68837 | E6: 29Oct240041 | F6: ="insert into ins_premium_det (premium_rcv_code,assorted_code, rec_amount,premium_rcv_detail_code,remaining_amt, payrec, mode_code,coinsurance_code,class_cd,it_remarks) values" -> insert into ins_premium_det (premium_rcv_code,assorted_code, rec_amount,premium_rcv_detail_code,remaining_amt, payrec, mode_code,coinsurance_code,class_cd,it_remarks) values | G6: ="('"&E6&"','"&B6&"','"&D6&"',(select max(to_number(i.premium_rcv_detail_code))+1 from ins_premium_det i),'"&D6&"','"&D6&"','02', '11000003','00','Request by Mr. Saqib Saleem 30-Oct-2024');" -> ('29Oct240041','070000165780','68837',(select max(to_number(i.premium_rcv_detail_code))+1 from ins_premium_det i),'68837','68837','02', '11000003','00','Request by Mr. Saqib Saleem 30-Oct-2024'); | H6: =F6&G6 -> insert into ins_premium_det (premium_rcv_code,assorted_code, rec_amount,premium_rcv_detail_code,remaining_amt, payrec, mode_code,coinsurance_code,class_cd,it_remarks) values('29Oct240041','070000165780','68837',(select max(to_number(i.premium_rcv_detail_code))+1 from ins_premium_det i),'68837','68837','02', '11000003','00','Request by Mr. Saqib Saleem 30-Oct-2024');
A7: KHI/HO/D/MO/PC COMP/C/97805/7/09/2024 | B7: =VLOOKUP(A7,policy!B:C,2,0) -> 070000165782 | C7: 99064 | D7: =ROUND(C7,0) -> 99064 | E7: 29Oct240041 | F7: ="insert into ins_premium_det (premium_rcv_code,assorted_code, rec_amount,premium_rcv_detail_code,remaining_amt, payrec, mode_code,coinsurance_code,class_cd,it_remarks) values" -> insert into ins_premium_det (premium_rcv_code,assorted_code, rec_amount,premium_rcv_detail_code,remaining_amt, payrec, mode_code,coinsurance_code,class_cd,it_remarks) values | G7: ="('"&E7&"','"&B7&"','"&D7&"',(select max(to_number(i.premium_rcv_detail_code))+1 from ins_premium_det i),'"&D7&"','"&D7&"','02', '11000003','00','Request by Mr. Saqib Saleem 30-Oct-2024');" -> ('29Oct240041','070000165782','99064',(select max(to_number(i.premium_rcv_detail_code))+1 from ins_premium_det i),'99064','99064','02', '11000003','00','Request by Mr. Saqib Saleem 30-Oct-2024'); | H7: =F7&G7 -> insert into ins_premium_det (premium_rcv_code,assorted_code, rec_amount,premium_rcv_detail_code,remaining_amt, payrec, mode_code,coinsurance_code,class_cd,it_remarks) values('29Oct240041','070000165782','99064',(select max(to_number(i.premium_rcv_detail_code))+1 from ins_premium_det i),'99064','99064','02', '11000003','00','Request by Mr. Saqib Saleem 30-Oct-2024');
A8: KHI/HO/D/MO/PC COMP/C/97805/8/09/2024 | B8: =VLOOKUP(A8,policy!B:C,2,0) -> 070000165783 | C8: 44848 | D8: =ROUND(C8,0) -> 44848 | E8: 29Oct240041 | F8: ="insert into ins_premium_det (premium_rcv_code,assorted_code, rec_amount,premium_rcv_detail_code,remaining_amt, payrec, mode_code,coinsurance_code,class_cd,it_remarks) values" -> insert into ins_premium_det (premium_rcv_code,assorted_code, rec_amount,premium_rcv_detail_code,remaining_amt, payrec, mode_code,coinsurance_code,class_cd,it_remarks) values | G8: ="('"&E8&"','"&B8&"','"&D8&"',(select max(to_number(i.premium_rcv_detail_code))+1 from ins_premium_det i),'"&D8&"','"&D8&"','02', '11000003','00','Request by Mr. Saqib Saleem 30-Oct-2024');" -> ('29Oct240041','070000165783','44848',(select max(to_number(i.premium_rcv_detail_code))+1 from ins_premium_det i),'44848','44848','02', '11000003','00','Request by Mr. Saqib Saleem 30-Oct-2024'); | H8: =F8&G8 -> insert into ins_premium_det (premium_rcv_code,assorted_code, rec_amount,premium_rcv_detail_code,remaining_amt, payrec, mode_code,coinsurance_code,class_cd,it_remarks) values('29Oct240041','070000165783','44848',(select max(to_number(i.premium_rcv_detail_code))+1 from ins_premium_det i),'44848','44848','02', '11000003','00','Request by Mr. Saqib Saleem 30-Oct-2024');
A9: KHI/HO/D/MO/PC COMP/C/97805/9/09/2024 | B9: =VLOOKUP(A9,policy!B:C,2,0) -> 070000165784 | C9: 44200 | D9: =ROUND(C9,0) -> 44200 | E9: 29Oct240041 | F9: ="insert into ins_premium_det (premium_rcv_code,assorted_code, rec_amount,premium_rcv_detail_code,remaining_amt, payrec, mode_code,coinsurance_code,class_cd,it_remarks) values" -> insert into ins_premium_det (premium_rcv_code,assorted_code, rec_amount,premium_rcv_detail_code,remaining_amt, payrec, mode_code,coinsurance_code,class_cd,it_remarks) values | G9: ="('"&E9&"','"&B9&"','"&D9&"',(select max(to_number(i.premium_rcv_detail_code))+1 from ins_premium_det i),'"&D9&"','"&D9&"','02', '11000003','00','Request by Mr. Saqib Saleem 30-Oct-2024');" -> ('29Oct240041','070000165784','44200',(select max(to_number(i.premium_rcv_detail_code))+1 from ins_premium_det i),'44200','44200','02', '11000003','00','Request by Mr. Saqib Saleem 30-Oct-2024'); | H9: =F9&G9 -> insert into ins_premium_det (premium_rcv_code,assorted_code, rec_amount,premium_rcv_detail_code,remaining_amt, payrec, mode_code,coinsurance_code,class_cd,it_remarks) values('29Oct240041','070000165784','44200',(select max(to_number(i.premium_rcv_detail_code))+1 from ins_premium_det i),'44200','44200','02', '11000003','00','Request by Mr. Saqib Saleem 30-Oct-2024');
A10: KHI/HO/D/MO/PC COMP/C/97805/13/09/2024 | B10: =VLOOKUP(A10,policy!B:C,2,0) -> 070000165788 | C10: 22928 | D10: =ROUND(C10,0) -> 22928 | E10: 29Oct240041 | F10: ="insert into ins_premium_det (premium_rcv_code,assorted_code, rec_amount,premium_rcv_detail_code,remaining_amt, payrec, mode_code,coinsurance_code,class_cd,it_remarks) values" -> insert into ins_premium_det (premium_rcv_code,assorted_code, rec_amount,premium_rcv_detail_code,remaining_amt, payrec, mode_code,coinsurance_code,class_cd,it_remarks) values | G10: ="('"&E10&"','"&B10&"','"&D10&"',(select max(to_number(i.premium_rcv_detail_code))+1 from ins_premium_det i),'"&D10&"','"&D10&"','02', '11000003','00','Request by Mr. Saqib Saleem 30-Oct-2024');" -> ('29Oct240041','070000165788','22928',(select max(to_number(i.premium_rcv_detail_code))+1 from ins_premium_det i),'22928','22928','02', '11000003','00','Request by Mr. Saqib Saleem 30-Oct-2024'); | H10: =F10&G10 -> insert into ins_premium_det (premium_rcv_code,assorted_code, rec_amount,premium_rcv_detail_code,remaining_amt, payrec, mode_code,coinsurance_code,class_cd,it_remarks) values('29Oct240041','070000165788','22928',(select max(to_number(i.premium_rcv_detail_code))+1 from ins_premium_det i),'22928','22928','02', '11000003','00','Request by Mr. Saqib Saleem 30-Oct-2024');
A11: KHI/HO/D/MO/PC COMP/C/97805/14/09/2024 | B11: =VLOOKUP(A11,policy!B:C,2,0) -> 070000165789 | C11: 28160 | D11: =ROUND(C11,0) -> 28160 | E11: 29Oct240041 | F11: ="insert into ins_premium_det (premium_rcv_code,assorted_code, rec_amount,premium_rcv_detail_code,remaining_amt, payrec, mode_code,coinsurance_code,class_cd,it_remarks) values" -> insert into ins_premium_det (premium_rcv_code,assorted_code, rec_amount,premium_rcv_detail_code,remaining_amt, payrec, mode_code,coinsurance_code,class_cd,it_remarks) values | G11: ="('"&E11&"','"&B11&"','"&D11&"',(select max(to_number(i.premium_rcv_detail_code))+1 from ins_premium_det i),'"&D11&"','"&D11&"','02', '11000003','00','Request by Mr. Saqib Saleem 30-Oct-2024');" -> ('29Oct240041','070000165789','28160',(select max(to_number(i.premium_rcv_detail_code))+1 from ins_premium_det i),'28160','28160','02', '11000003','00','Request by Mr. Saqib Saleem 30-Oct-2024'); | H11: =F11&G11 -> insert into ins_premium_det (premium_rcv_code,assorted_code, rec_amount,premium_rcv_detail_code,remaining_amt, payrec, mode_code,coinsurance_code,class_cd,it_remarks) values('29Oct240041','070000165789','28160',(select max(to_number(i.premium_rcv_detail_code))+1 from ins_premium_det i),'28160','28160','02', '11000003','00','Request by Mr. Saqib Saleem 30-Oct-2024');
A12: KHI/HO/D/MO/PC COMP/C/97805/15/09/2024 | B12: =VLOOKUP(A12,policy!B:C,2,0) -> 070000165790 | C12: 40826 | D12: =ROUND(C12,0) -> 40826 | E12: 29Oct240041 | F12: ="insert into ins_premium_det (premium_rcv_code,assorted_code, rec_amount,premium_rcv_detail_code,remaining_amt, payrec, mode_code,coinsurance_code,class_cd,it_remarks) values" -> insert into ins_premium_det (premium_rcv_code,assorted_code, rec_amount,premium_rcv_detail_code,remaining_amt, payrec, mode_code,coinsurance_code,class_cd,it_remarks) values | G12: ="('"&E12&"','"&B12&"','"&D12&"',(select max(to_number(i.premium_rcv_detail_code))+1 from ins_premium_det i),'"&D12&"','"&D12&"','02', '11000003','00','Request by Mr. Saqib Saleem 30-Oct-2024');" -> ('29Oct240041','070000165790','40826',(select max(to_number(i.premium_rcv_detail_code))+1 from ins_premium_det i),'40826','40826','02', '11000003','00','Request by Mr. Saqib Saleem 30-Oct-2024'); | H12: =F12&G12 -> insert into ins_premium_det (premium_rcv_code,assorted_code, rec_amount,premium_rcv_detail_code,remaining_amt, payrec, mode_code,coinsurance_code,class_cd,it_remarks) values('29Oct240041','070000165790','40826',(select max(to_number(i.premium_rcv_detail_code))+1 from ins_premium_det i),'40826','40826','02', '11000003','00','Request by Mr. Saqib Saleem 30-Oct-2024');
A13: KHI/HO/D/MO/PC COMP/C/97805/18/09/2024 | B13: =VLOOKUP(A13,policy!B:C,2,0) -> 070000165793 | C13: 34080 | D13: =ROUND(C13,0) -> 34080 | E13: 29Oct240041 | F13: ="insert into ins_premium_det (premium_rcv_code,assorted_code, rec_amount,premium_rcv_detail_code,remaining_amt, payrec, mode_code,coinsurance_code,class_cd,it_remarks) values" -> insert into ins_premium_det (premium_rcv_code,assorted_code, rec_amount,premium_rcv_detail_code,remaining_amt, payrec, mode_code,coinsurance_code,class_cd,it_remarks) values | G13: ="('"&E13&"','"&B13&"','"&D13&"',(select max(to_number(i.premium_rcv_detail_code))+1 from ins_premium_det i),'"&D13&"','"&D13&"','02', '11000003','00','Request by Mr. Saqib Saleem 30-Oct-2024');" -> ('29Oct240041','070000165793','34080',(select max(to_number(i.premium_rcv_detail_code))+1 from ins_premium_det i),'34080','34080','02', '11000003','00','Request by Mr. Saqib Saleem 30-Oct-2024'); | H13: =F13&G13 -> insert into ins_premium_det (premium_rcv_code,assorted_code, rec_amount,premium_rcv_detail_code,remaining_amt, payrec, mode_code,coinsurance_code,class_cd,it_remarks) values('29Oct240041','070000165793','34080',(select max(to_number(i.premium_rcv_detail_code))+1 from ins_premium_det i),'34080','34080','02', '11000003','00','Request by Mr. Saqib Saleem 30-Oct-2024');
... A233: KHI/HO/D/MO/PC COMP/C/97805/320/09/2024 | B233: =VLOOKUP(A233,policy!B:C,2,0) -> 070000166095 | C233: 35789 | D233: =ROUND(C233,0) -> 35789 | E233: 29Oct240041 | F233: ="insert into ins_premium_det (premium_rcv_code,assorted_code, rec_amount,premium_rcv_detail_code,remaining_amt, payrec, mode_code,coinsurance_code,class_cd,it_remarks) values" -> insert into ins_premium_det (premium_rcv_code,assorted_code, rec_amount,premium_rcv_detail_code,remaining_amt, payrec, mode_code,coinsurance_code,class_cd,it_remarks) values | G233: ="('"&E233&"','"&B233&"','"&D233&"',(select max(to_number(i.premium_rcv_detail_code))+1 from ins_premium_det i),'"&D233&"','"&D233&"','02', '11000003','00','Request by Mr. Saqib Saleem 30-Oct-2024');" -> ('29Oct240041','070000166095','35789',(select max(to_number(i.premium_rcv_detail_code))+1 from ins_premium_det i),'35789','35789','02', '11000003','00','Request by Mr. Saqib Saleem 30-Oct-2024'); | H233: =F233&G233 -> insert into ins_premium_det (premium_rcv_code,assorted_code, rec_amount,premium_rcv_detail_code,remaining_amt, payrec, mode_code,coinsurance_code,class_cd,it_remarks) values('29Oct240041','070000166095','35789',(select max(to_number(i.premium_rcv_detail_code))+1 from ins_premium_det i),'35789','35789','02', '11000003','00','Request by Mr. Saqib Saleem 30-Oct-2024');
A234: KHI/HO/D/MO/PC COMP/P/99821/000366/10/2024 | B234: =VLOOKUP(A234,policy!B:C,2,0) -> #N/A | C234: 19560 | D234: =ROUND(C234,0) -> 19560 | E234: 29Oct240041 | F234: ="insert into ins_premium_det (premium_rcv_code,assorted_code, rec_amount,premium_rcv_detail_code,remaining_amt, payrec, mode_code,coinsurance_code,class_cd,it_remarks) values" -> insert into ins_premium_det (premium_rcv_code,assorted_code, rec_amount,premium_rcv_detail_code,remaining_amt, payrec, mode_code,coinsurance_code,class_cd,it_remarks) values | G234: ="('"&E234&"','"&B234&"','"&D234&"',(select max(to_number(i.premium_rcv_detail_code))+1 from ins_premium_det i),'"&D234&"','"&D234&"','02', '11000003','00','Request by Mr. Saqib Saleem 30-Oct-2024');" -> #N/A
A235: KHI/HO/D/MO/PC COMP/C/97805/321/09/2024 | B235: =VLOOKUP(A235,policy!B:C,2,0) -> 070000166096 | C235: 61600 | D235: =ROUND(C235,0) -> 61600 | E235: 29Oct240041 | F235: ="insert into ins_premium_det (premium_rcv_code,assorted_code, rec_amount,premium_rcv_detail_code,remaining_amt, payrec, mode_code,coinsurance_code,class_cd,it_remarks) values" -> insert into ins_premium_det (premium_rcv_code,assorted_code, rec_amount,premium_rcv_detail_code,remaining_amt, payrec, mode_code,coinsurance_code,class_cd,it_remarks) values | G235: ="('"&E235&"','"&B235&"','"&D235&"',(select max(to_number(i.premium_rcv_detail_code))+1 from ins_premium_det i),'"&D235&"','"&D235&"','02', '11000003','00','Request by Mr. Saqib Saleem 30-Oct-2024');" -> ('29Oct240041','070000166096','61600',(select max(to_number(i.premium_rcv_detail_code))+1 from ins_premium_det i),'61600','61600','02', '11000003','00','Request by Mr. Saqib Saleem 30-Oct-2024'); | H235: =F235&G235 -> insert into ins_premium_det (premium_rcv_code,assorted_code, rec_amount,premium_rcv_detail_code,remaining_amt, payrec, mode_code,coinsurance_code,class_cd,it_remarks) values('29Oct240041','070000166096','61600',(select max(to_number(i.premium_rcv_detail_code))+1 from ins_premium_det i),'61600','61600','02', '11000003','00','Request by Mr. Saqib Saleem 30-Oct-2024');
A236: KHI/HO/D/MO/PC COMP/C/97805/322/09/2024 | B236: =VLOOKUP(A236,policy!B:C,2,0) -> 070000166097 | C236: 62858 | D236: =ROUND(C236,0) -> 62858 | E236: 29Oct240041 | F236: ="insert into ins_premium_det (premium_rcv_code,assorted_code, rec_amount,premium_rcv_detail_code,remaining_amt, payrec, mode_code,coinsurance_code,class_cd,it_remarks) values" -> insert into ins_premium_det (premium_rcv_code,assorted_code, rec_amount,premium_rcv_detail_code,remaining_amt, payrec, mode_code,coinsurance_code,class_cd,it_remarks) values | G236: ="('"&E236&"','"&B236&"','"&D236&"',(select max(to_number(i.premium_rcv_detail_code))+1 from ins_premium_det i),'"&D236&"','"&D236&"','02', '11000003','00','Request by Mr. Saqib Saleem 30-Oct-2024');" -> ('29Oct240041','070000166097','62858',(select max(to_number(i.premium_rcv_detail_code))+1 from ins_premium_det i),'62858','62858','02', '11000003','00','Request by Mr. Saqib Saleem 30-Oct-2024'); | H236: =F236&G236 -> insert into ins_premium_det (premium_rcv_code,assorted_code, rec_amount,premium_rcv_detail_code,remaining_amt, payrec, mode_code,coinsurance_code,class_cd,it_remarks) values('29Oct240041','070000166097','62858',(select max(to_number(i.premium_rcv_detail_code))+1 from ins_premium_det i),'62858','62858','02', '11000003','00','Request by Mr. Saqib Saleem 30-Oct-2024');
A237: KHI/HO/D/MO/PC COMP/C/97805/214/09/2024 | B237: =VLOOKUP(A237,policy!B:C,2,0) -> 070000165989 | C237: 20400 | D237: =ROUND(C237,0) -> 20400 | E237: 29Oct240041 | F237: ="insert into ins_premium_det (premium_rcv_code,assorted_code, rec_amount,premium_rcv_detail_code,remaining_amt, payrec, mode_code,coinsurance_code,class_cd,it_remarks) values" -> insert into ins_premium_det (premium_rcv_code,assorted_code, rec_amount,premium_rcv_detail_code,remaining_amt, payrec, mode_code,coinsurance_code,class_cd,it_remarks) values | G237: ="('"&E237&"','"&B237&"','"&D237&"',(select max(to_number(i.premium_rcv_detail_code))+1 from ins_premium_det i),'"&D237&"','"&D237&"','02', '11000003','00','Request by Mr. Saqib Saleem 30-Oct-2024');" -> ('29Oct240041','070000165989','20400',(select max(to_number(i.premium_rcv_detail_code))+1 from ins_premium_det i),'20400','20400','02', '11000003','00','Request by Mr. Saqib Saleem 30-Oct-2024'); | H237: =F237&G237 -> insert into ins_premium_det (premium_rcv_code,assorted_code, rec_amount,premium_rcv_detail_code,remaining_amt, payrec, mode_code,coinsurance_code,class_cd,it_remarks) values('29Oct240041','070000165989','20400',(select max(to_number(i.premium_rcv_detail_code))+1 from ins_premium_det i),'20400','20400','02', '11000003','00','Request by Mr. Saqib Saleem 30-Oct-2024');
A238: KHI/HO/D/MO/PC COMP/C/97805/323/09/2024 | B238: =VLOOKUP(A238,policy!B:C,2,0) -> 070000166098 | C238: 75586 | D238: =ROUND(C238,0) -> 75586 | E238: 29Oct240041 | F238: ="insert into ins_premium_det (premium_rcv_code,assorted_code, rec_amount,premium_rcv_detail_code,remaining_amt, payrec, mode_code,coinsurance_code,class_cd,it_remarks) values" -> insert into ins_premium_det (premium_rcv_code,assorted_code, rec_amount,premium_rcv_detail_code,remaining_amt, payrec, mode_code,coinsurance_code,class_cd,it_remarks) values | G238: ="('"&E238&"','"&B238&"','"&D238&"',(select max(to_number(i.premium_rcv_detail_code))+1 from ins_premium_det i),'"&D238&"','"&D238&"','02', '11000003','00','Request by Mr. Saqib Saleem 30-Oct-2024');" -> ('29Oct240041','070000166098','75586',(select max(to_number(i.premium_rcv_detail_code))+1 from ins_premium_det i),'75586','75586','02', '11000003','00','Request by Mr. Saqib Saleem 30-Oct-2024'); | H238: =F238&G238 -> insert into ins_premium_det (premium_rcv_code,assorted_code, rec_amount,premium_rcv_detail_code,remaining_amt, payrec, mode_code,coinsurance_code,class_cd,it_remarks) values('29Oct240041','070000166098','75586',(select max(to_number(i.premium_rcv_detail_code))+1 from ins_premium_det i),'75586','75586','02', '11000003','00','Request by Mr. Saqib Saleem 30-Oct-2024');
A239: KHI/HO/D/MO/PC COMP/C/97805/215/09/2024 | B239: =VLOOKUP(A239,policy!B:C,2,0) -> 070000165990 | C239: 38140 | D239: =ROUND(C239,0) -> 38140 | E239: 29Oct240041 | F239: ="insert into ins_premium_det (premium_rcv_code,assorted_code, rec_amount,premium_rcv_detail_code,remaining_amt, payrec, mode_code,coinsurance_code,class_cd,it_remarks) values" -> insert into ins_premium_det (premium_rcv_code,assorted_code, rec_amount,premium_rcv_detail_code,remaining_amt, payrec, mode_code,coinsurance_code,class_cd,it_remarks) values | G239: ="('"&E239&"','"&B239&"','"&D239&"',(select max(to_number(i.premium_rcv_detail_code))+1 from ins_premium_det i),'"&D239&"','"&D239&"','02', '11000003','00','Request by Mr. Saqib Saleem 30-Oct-2024');" -> ('29Oct240041','070000165990','38140',(select max(to_number(i.premium_rcv_detail_code))+1 from ins_premium_det i),'38140','38140','02', '11000003','00','Request by Mr. Saqib Saleem 30-Oct-2024'); | H239: =F239&G239 -> insert into ins_premium_det (premium_rcv_code,assorted_code, rec_amount,premium_rcv_detail_code,remaining_amt, payrec, mode_code,coinsurance_code,class_cd,it_remarks) values('29Oct240041','070000165990','38140',(select max(to_number(i.premium_rcv_detail_code))+1 from ins_premium_det i),'38140','38140','02', '11000003','00','Request by Mr. Saqib Saleem 30-Oct-2024');
A240: KHI/HO/D/MO/PC COMP/C/97805/217/09/2024 | B240: =VLOOKUP(A240,policy!B:C,2,0) -> 070000165992 | C240: 37931 | D240: =ROUND(C240,0) -> 37931 | E240: 29Oct240041 | F240: ="insert into ins_premium_det (premium_rcv_code,assorted_code, rec_amount,premium_rcv_detail_code,remaining_amt, payrec, mode_code,coinsurance_code,class_cd,it_remarks) values" -> insert into ins_premium_det (premium_rcv_code,assorted_code, rec_amount,premium_rcv_detail_code,remaining_amt, payrec, mode_code,coinsurance_code,class_cd,it_remarks) values | G240: ="('"&E240&"','"&B240&"','"&D240&"',(select max(to_number(i.premium_rcv_detail_code))+1 from ins_premium_det i),'"&D240&"','"&D240&"','02', '11000003','00','Request by Mr. Saqib Saleem 30-Oct-2024');" -> ('29Oct240041','070000165992','37931',(select max(to_number(i.premium_rcv_detail_code))+1 from ins_premium_det i),'37931','37931','02', '11000003','00','Request by Mr. Saqib Saleem 30-Oct-2024'); | H240: =F240&G240 -> insert into ins_premium_det (premium_rcv_code,assorted_code, rec_amount,premium_rcv_detail_code,remaining_amt, payrec, mode_code,coinsurance_code,class_cd,it_remarks) values('29Oct240041','070000165992','37931',(select max(to_number(i.premium_rcv_detail_code))+1 from ins_premium_det i),'37931','37931','02', '11000003','00','Request by Mr. Saqib Saleem 30-Oct-2024');
A241: KHI/HO/D/MO/PC COMP/C/97805/218/09/2024 | B241: =VLOOKUP(A241,policy!B:C,2,0) -> 070000165993 | C241: 44625 | D241: =ROUND(C241,0) -> 44625 | E241: 29Oct240041 | F241: ="insert into ins_premium_det (premium_rcv_code,assorted_code, rec_amount,premium_rcv_detail_code,remaining_amt, payrec, mode_code,coinsurance_code,class_cd,it_remarks) values" -> insert into ins_premium_det (premium_rcv_code,assorted_code, rec_amount,premium_rcv_detail_code,remaining_amt, payrec, mode_code,coinsurance_code,class_cd,it_remarks) values | G241: ="('"&E241&"','"&B241&"','"&D241&"',(select max(to_number(i.premium_rcv_detail_code))+1 from ins_premium_det i),'"&D241&"','"&D241&"','02', '11000003','00','Request by Mr. Saqib Saleem 30-Oct-2024');" -> ('29Oct240041','070000165993','44625',(select max(to_number(i.premium_rcv_detail_code))+1 from ins_premium_det i),'44625','44625','02', '11000003','00','Request by Mr. Saqib Saleem 30-Oct-2024'); | H241: =F241&G241 -> insert into ins_premium_det (premium_rcv_code,assorted_code, rec_amount,premium_rcv_detail_code,remaining_amt, payrec, mode_code,coinsurance_code,class_cd,it_remarks) values('29Oct240041','070000165993','44625',(select max(to_number(i.premium_rcv_detail_code))+1 from ins_premium_det i),'44625','44625','02', '11000003','00','Request by Mr. Saqib Saleem 30-Oct-2024');
A242: KHI/HO/D/MO/PC COMP/C/97805/219/09/2024 | B242: =VLOOKUP(A242,policy!B:C,2,0) -> 070000165994 | C242: 36281 | D242: =ROUND(C242,0) -> 36281 | E242: 29Oct240041 | F242: ="insert into ins_premium_det (premium_rcv_code,assorted_code, rec_amount,premium_rcv_detail_code,remaining_amt, payrec, mode_code,coinsurance_code,class_cd,it_remarks) values" -> insert into ins_premium_det (premium_rcv_code,assorted_code, rec_amount,premium_rcv_detail_code,remaining_amt, payrec, mode_code,coinsurance_code,class_cd,it_remarks) values | G242: ="('"&E242&"','"&B242&"','"&D242&"',(select max(to_number(i.premium_rcv_detail_code))+1 from ins_premium_det i),'"&D242&"','"&D242&"','02', '11000003','00','Request by Mr. Saqib Saleem 30-Oct-2024');" -> ('29Oct240041','070000165994','36281',(select max(to_number(i.premium_rcv_detail_code))+1 from ins_premium_det i),'36281','36281','02', '11000003','00','Request by Mr. Saqib Saleem 30-Oct-2024'); | H242: =F242&G242 -> insert into ins_premium_det (premium_rcv_code,assorted_code, rec_amount,premium_rcv_detail_code,remaining_amt, payrec, mode_code,coinsurance_code,class_cd,it_remarks) values('29Oct240041','070000165994','36281',(select max(to_number(i.premium_rcv_detail_code))+1 from ins_premium_det i),'36281','36281','02', '11000003','00','Request by Mr. Saqib Saleem 30-Oct-2024');
A243: KHI/HO/D/MO/PC COMP/C/97805/221/09/2024 | B243: =VLOOKUP(A243,policy!B:C,2,0) -> 070000165996 | C243: 43485 | D243: =ROUND(C243,0) -> 43485 | E243: 29Oct240041 | F243: ="insert into ins_premium_det (premium_rcv_code,assorted_code, rec_amount,premium_rcv_detail_code,remaining_amt, payrec, mode_code,coinsurance_code,class_cd,it_remarks) values" -> insert into ins_premium_det (premium_rcv_code,assorted_code, rec_amount,premium_rcv_detail_code,remaining_amt, payrec, mode_code,coinsurance_code,class_cd,it_remarks) values | G243: ="('"&E243&"','"&B243&"','"&D243&"',(select max(to_number(i.premium_rcv_detail_code))+1 from ins_premium_det i),'"&D243&"','"&D243&"','02', '11000003','00','Request by Mr. Saqib Saleem 30-Oct-2024');" -> ('29Oct240041','070000165996','43485',(select max(to_number(i.premium_rcv_detail_code))+1 from ins_premium_det i),'43485','43485','02', '11000003','00','Request by Mr. Saqib Saleem 30-Oct-2024'); | H243: =F243&G243 -> insert into ins_premium_det (premium_rcv_code,assorted_code, rec_amount,premium_rcv_detail_code,remaining_amt, payrec, mode_code,coinsurance_code,class_cd,it_remarks) values('29Oct240041','070000165996','43485',(select max(to_number(i.premium_rcv_detail_code))+1 from ins_premium_det i),'43485','43485','02', '11000003','00','Request by Mr. Saqib Saleem 30-Oct-2024');
A244: KHI/HO/D/MO/PC COMP/C/97805/222/09/2024 | B244: =VLOOKUP(A244,policy!B:C,2,0) -> 070000165997 | C244: 26205 | D244: =ROUND(C244,0) -> 26205 | E244: 29Oct240041 | F244: ="insert into ins_premium_det (premium_rcv_code,assorted_code, rec_amount,premium_rcv_detail_code,remaining_amt, payrec, mode_code,coinsurance_code,class_cd,it_remarks) values" -> insert into ins_premium_det (premium_rcv_code,assorted_code, rec_amount,premium_rcv_detail_code,remaining_amt, payrec, mode_code,coinsurance_code,class_cd,it_remarks) values | G244: ="('"&E244&"','"&B244&"','"&D244&"',(select max(to_number(i.premium_rcv_detail_code))+1 from ins_premium_det i),'"&D244&"','"&D244&"','02', '11000003','00','Request by Mr. Saqib Saleem 30-Oct-2024');" -> ('29Oct240041','070000165997','26205',(select max(to_number(i.premium_rcv_detail_code))+1 from ins_premium_det i),'26205','26205','02', '11000003','00','Request by Mr. Saqib Saleem 30-Oct-2024'); | H244: =F244&G244 -> insert into ins_premium_det (premium_rcv_code,assorted_code, rec_amount,premium_rcv_detail_code,remaining_amt, payrec, mode_code,coinsurance_code,class_cd,it_remarks) values('29Oct240041','070000165997','26205',(select max(to_number(i.premium_rcv_detail_code))+1 from ins_premium_det i),'26205','26205','02', '11000003','00','Request by Mr. Saqib Saleem 30-Oct-2024');
A245: KHI/HO/D/MO/PC COMP/C/97805/223/09/2024 | B245: =VLOOKUP(A245,policy!B:C,2,0) -> 070000165998 | C245: 22444 | D245: =ROUND(C245,0) -> 22444 | E245: 29Oct240041 | F245: ="insert into ins_premium_det (premium_rcv_code,assorted_code, rec_amount,premium_rcv_detail_code,remaining_amt, payrec, mode_code,coinsurance_code,class_cd,it_remarks) values" -> insert into ins_premium_det (premium_rcv_code,assorted_code, rec_amount,premium_rcv_detail_code,remaining_amt, payrec, mode_code,coinsurance_code,class_cd,it_remarks) values | G245: ="('"&E245&"','"&B245&"','"&D245&"',(select max(to_number(i.premium_rcv_detail_code))+1 from ins_premium_det i),'"&D245&"','"&D245&"','02', '11000003','00','Request by Mr. Saqib Saleem 30-Oct-2024');" -> ('29Oct240041','070000165998','22444',(select max(to_number(i.premium_rcv_detail_code))+1 from ins_premium_det i),'22444','22444','02', '11000003','00','Request by Mr. Saqib Saleem 30-Oct-2024'); | H245: =F245&G245 -> insert into ins_premium_det (premium_rcv_code,assorted_code, rec_amount,premium_rcv_detail_code,remaining_amt, payrec, mode_code,coinsurance_code,class_cd,it_remarks) values('29Oct240041','070000165998','22444',(select max(to_number(i.premium_rcv_detail_code))+1 from ins_premium_det i),'22444','22444','02', '11000003','00','Request by Mr. Saqib Saleem 30-Oct-2024');
A246: KHI/HO/D/MO/PC COMP/C/97805/331/09/2024 | B246: =VLOOKUP(A246,policy!B:C,2,0) -> 070000166106 | C246: 66032 | D246: =ROUND(C246,0) -> 66032 | E246: 29Oct240041 | F246: ="insert into ins_premium_det (premium_rcv_code,assorted_code, rec_amount,premium_rcv_detail_code,remaining_amt, payrec, mode_code,coinsurance_code,class_cd,it_remarks) values" -> insert into ins_premium_det (premium_rcv_code,assorted_code, rec_amount,premium_rcv_detail_code,remaining_amt, payrec, mode_code,coinsurance_code,class_cd,it_remarks) values | G246: ="('"&E246&"','"&B246&"','"&D246&"',(select max(to_number(i.premium_rcv_detail_code))+1 from ins_premium_det i),'"&D246&"','"&D246&"','02', '11000003','00','Request by Mr. Saqib Saleem 30-Oct-2024');" -> ('29Oct240041','070000166106','66032',(select max(to_number(i.premium_rcv_detail_code))+1 from ins_premium_det i),'66032','66032','02', '11000003','00','Request by Mr. Saqib Saleem 30-Oct-2024'); | H246: =F246&G246 -> insert into ins_premium_det (premium_rcv_code,assorted_code, rec_amount,premium_rcv_detail_code,remaining_amt, payrec, mode_code,coinsurance_code,class_cd,it_remarks) values('29Oct240041','070000166106','66032',(select max(to_number(i.premium_rcv_detail_code))+1 from ins_premium_det i),'66032','66032','02', '11000003','00','Request by Mr. Saqib Saleem 30-Oct-2024');
... A324: KHI/HO/D/MO/PC COMP/C/97805/324/09/2024 | B324: =VLOOKUP(A324,policy!B:C,2,0) -> 070000166099 | C324: 51200 | D324: =ROUND(C324,0) -> 51200 | E324: 29Oct240041 | F324: ="insert into ins_premium_det (premium_rcv_code,assorted_code, rec_amount,premium_rcv_detail_code,remaining_amt, payrec, mode_code,coinsurance_code,class_cd,it_remarks) values" -> insert into ins_premium_det (premium_rcv_code,assorted_code, rec_amount,premium_rcv_detail_code,remaining_amt, payrec, mode_code,coinsurance_code,class_cd,it_remarks) values | G324: ="('"&E324&"','"&B324&"','"&D324&"',(select max(to_number(i.premium_rcv_detail_code))+1 from ins_premium_det i),'"&D324&"','"&D324&"','02', '11000003','00','Request by Mr. Saqib Saleem 30-Oct-2024');" -> ('29Oct240041','070000166099','51200',(select max(to_number(i.premium_rcv_detail_code))+1 from ins_premium_det i),'51200','51200','02', '11000003','00','Request by Mr. Saqib Saleem 30-Oct-2024'); | H324: =F324&G324 -> insert into ins_premium_det (premium_rcv_code,assorted_code, rec_amount,premium_rcv_detail_code,remaining_amt, payrec, mode_code,coinsurance_code,class_cd,it_remarks) values('29Oct240041','070000166099','51200',(select max(to_number(i.premium_rcv_detail_code))+1 from ins_premium_det i),'51200','51200','02', '11000003','00','Request by Mr. Saqib Saleem 30-Oct-2024');
A325: KHI/HO/D/MO/PC COMP/E/47950/00002/10/2024 | B325: =VLOOKUP(A325,Sheet5!B:C,2,0) -> 050000812208 | C325: -4790 | D325: =ROUND(C325,0) -> -4790 | E325: 29Oct240041 | F325: ="insert into ins_premium_det (premium_rcv_code,assorted_code, rec_amount,premium_rcv_detail_code,remaining_amt, payrec, mode_code,coinsurance_code,class_cd,it_remarks) values" -> insert into ins_premium_det (premium_rcv_code,assorted_code, rec_amount,premium_rcv_detail_code,remaining_amt, payrec, mode_code,coinsurance_code,class_cd,it_remarks) values | G325: ="('"&E325&"','"&B325&"','"&D325&"',(select max(to_number(i.premium_rcv_detail_code))+1 from ins_premium_det i),'"&D325&"','"&D325&"','02', '11000003','00','Request by Mr. Saqib Saleem 30-Oct-2024');" -> ('29Oct240041','050000812208','-4790',(select max(to_number(i.premium_rcv_detail_code))+1 from ins_premium_det i),'-4790','-4790','02', '11000003','00','Request by Mr. Saqib Saleem 30-Oct-2024'); | H325: =F325&G325 -> insert into ins_premium_det (premium_rcv_code,assorted_code, rec_amount,premium_rcv_detail_code,remaining_amt, payrec, mode_code,coinsurance_code,class_cd,it_remarks) values('29Oct240041','050000812208','-4790',(select max(to_number(i.premium_rcv_detail_code))+1 from ins_premium_det i),'-4790','-4790','02', '11000003','00','Request by Mr. Saqib Saleem 30-Oct-2024');
A326: KHI/HO/D/MO/PC COMP/E/47950/00005/10/2024 | B326: =VLOOKUP(A326,Sheet5!B:C,2,0) -> 050000812211 | C326: -8098.25 | D326: =ROUND(C326,0) -> -8098 | E326: 29Oct240041 | F326: ="insert into ins_premium_det (premium_rcv_code,assorted_code, rec_amount,premium_rcv_detail_code,remaining_amt, payrec, mode_code,coinsurance_code,class_cd,it_remarks) values" -> insert into ins_premium_det (premium_rcv_code,assorted_code, rec_amount,premium_rcv_detail_code,remaining_amt, payrec, mode_code,coinsurance_code,class_cd,it_remarks) values | G326: ="('"&E326&"','"&B326&"','"&D326&"',(select max(to_number(i.premium_rcv_detail_code))+1 from ins_premium_det i),'"&D326&"','"&D326&"','02', '11000003','00','Request by Mr. Saqib Saleem 30-Oct-2024');" -> ('29Oct240041','050000812211','-8098',(select max(to_number(i.premium_rcv_detail_code))+1 from ins_premium_det i),'-8098','-8098','02', '11000003','00','Request by Mr. Saqib Saleem 30-Oct-2024'); | H326: =F326&G326 -> insert into ins_premium_det (premium_rcv_code,assorted_code, rec_amount,premium_rcv_detail_code,remaining_amt, payrec, mode_code,coinsurance_code,class_cd,it_remarks) values('29Oct240041','050000812211','-8098',(select max(to_number(i.premium_rcv_detail_code))+1 from ins_premium_det i),'-8098','-8098','02', '11000003','00','Request by Mr. Saqib Saleem 30-Oct-2024');
A327: KHI/HO/D/MO/PC COMP/E/47950/00015/10/2024 | B327: =VLOOKUP(A327,Sheet5!B:C,2,0) -> 050000812221 | C327: -4803.5 | D327: =ROUND(C327,0) -> -4804 | E327: 29Oct240041 | F327: ="insert into ins_premium_det (premium_rcv_code,assorted_code, rec_amount,premium_rcv_detail_code,remaining_amt, payrec, mode_code,coinsurance_code,class_cd,it_remarks) values" -> insert into ins_premium_det (premium_rcv_code,assorted_code, rec_amount,premium_rcv_detail_code,remaining_amt, payrec, mode_code,coinsurance_code,class_cd,it_remarks) values | G327: ="('"&E327&"','"&B327&"','"&D327&"',(select max(to_number(i.premium_rcv_detail_code))+1 from ins_premium_det i),'"&D327&"','"&D327&"','02', '11000003','00','Request by Mr. Saqib Saleem 30-Oct-2024');" -> ('29Oct240041','050000812221','-4804',(select max(to_number(i.premium_rcv_detail_code))+1 from ins_premium_det i),'-4804','-4804','02', '11000003','00','Request by Mr. Saqib Saleem 30-Oct-2024'); | H327: =F327&G327 -> insert into ins_premium_det (premium_rcv_code,assorted_code, rec_amount,premium_rcv_detail_code,remaining_amt, payrec, mode_code,coinsurance_code,class_cd,it_remarks) values('29Oct240041','050000812221','-4804',(select max(to_number(i.premium_rcv_detail_code))+1 from ins_premium_det i),'-4804','-4804','02', '11000003','00','Request by Mr. Saqib Saleem 30-Oct-2024');
A328: KHI/HO/D/MO/PC COMP/E/47950/00019/10/2024 | B328: =VLOOKUP(A328,Sheet5!B:C,2,0) -> 050000812225 | C328: -5148 | D328: =ROUND(C328,0) -> -5148 | E328: 29Oct240041 | F328: ="insert into ins_premium_det (premium_rcv_code,assorted_code, rec_amount,premium_rcv_detail_code,remaining_amt, payrec, mode_code,coinsurance_code,class_cd,it_remarks) values" -> insert into ins_premium_det (premium_rcv_code,assorted_code, rec_amount,premium_rcv_detail_code,remaining_amt, payrec, mode_code,coinsurance_code,class_cd,it_remarks) values | G328: ="('"&E328&"','"&B328&"','"&D328&"',(select max(to_number(i.premium_rcv_detail_code))+1 from ins_premium_det i),'"&D328&"','"&D328&"','02', '11000003','00','Request by Mr. Saqib Saleem 30-Oct-2024');" -> ('29Oct240041','050000812225','-5148',(select max(to_number(i.premium_rcv_detail_code))+1 from ins_premium_det i),'-5148','-5148','02', '11000003','00','Request by Mr. Saqib Saleem 30-Oct-2024'); | H328: =F328&G328 -> insert into ins_premium_det (premium_rcv_code,assorted_code, rec_amount,premium_rcv_detail_code,remaining_amt, payrec, mode_code,coinsurance_code,class_cd,it_remarks) values('29Oct240041','050000812225','-5148',(select max(to_number(i.premium_rcv_detail_code))+1 from ins_premium_det i),'-5148','-5148','02', '11000003','00','Request by Mr. Saqib Saleem 30-Oct-2024');
A329: KHI/HO/D/MO/PC COMP/E/47950/00028/10/2024 | B329: =VLOOKUP(A329,Sheet5!B:C,2,0) -> 050000812234 | C329: -3237.5 | D329: =ROUND(C329,0) -> -3238 | E329: 29Oct240041 | F329: ="insert into ins_premium_det (premium_rcv_code,assorted_code, rec_amount,premium_rcv_detail_code,remaining_amt, payrec, mode_code,coinsurance_code,class_cd,it_remarks) values" -> insert into ins_premium_det (premium_rcv_code,assorted_code, rec_amount,premium_rcv_detail_code,remaining_amt, payrec, mode_code,coinsurance_code,class_cd,it_remarks) values | G329: ="('"&E329&"','"&B329&"','"&D329&"',(select max(to_number(i.premium_rcv_detail_code))+1 from ins_premium_det i),'"&D329&"','"&D329&"','02', '11000003','00','Request by Mr. Saqib Saleem 30-Oct-2024');" -> ('29Oct240041','050000812234','-3238',(select max(to_number(i.premium_rcv_detail_code))+1 from ins_premium_det i),'-3238','-3238','02', '11000003','00','Request by Mr. Saqib Saleem 30-Oct-2024'); | H329: =F329&G329 -> insert into ins_premium_det (premium_rcv_code,assorted_code, rec_amount,premium_rcv_detail_code,remaining_amt, payrec, mode_code,coinsurance_code,class_cd,it_remarks) values('29Oct240041','050000812234','-3238',(select max(to_number(i.premium_rcv_detail_code))+1 from ins_premium_det i),'-3238','-3238','02', '11000003','00','Request by Mr. Saqib Saleem 30-Oct-2024');
A330: KHI/HO/D/MO/PC COMP/E/47950/00034/10/2024 | B330: =VLOOKUP(A330,Sheet5!B:C,2,0) -> 050000812240 | C330: 4500 | D330: =ROUND(C330,0) -> 4500 | E330: 29Oct240041 | F330: ="insert into ins_premium_det (premium_rcv_code,assorted_code, rec_amount,premium_rcv_detail_code,remaining_amt, payrec, mode_code,coinsurance_code,class_cd,it_remarks) values" -> insert into ins_premium_det (premium_rcv_code,assorted_code, rec_amount,premium_rcv_detail_code,remaining_amt, payrec, mode_code,coinsurance_code,class_cd,it_remarks) values | G330: ="('"&E330&"','"&B330&"','"&D330&"',(select max(to_number(i.premium_rcv_detail_code))+1 from ins_premium_det i),'"&D330&"','"&D330&"','02', '11000003','00','Request by Mr. Saqib Saleem 30-Oct-2024');" -> ('29Oct240041','050000812240','4500',(select max(to_number(i.premium_rcv_detail_code))+1 from ins_premium_det i),'4500','4500','02', '11000003','00','Request by Mr. Saqib Saleem 30-Oct-2024'); | H330: =F330&G330 -> insert into ins_premium_det (premium_rcv_code,assorted_code, rec_amount,premium_rcv_detail_code,remaining_amt, payrec, mode_code,coinsurance_code,class_cd,it_remarks) values('29Oct240041','050000812240','4500',(select max(to_number(i.premium_rcv_detail_code))+1 from ins_premium_det i),'4500','4500','02', '11000003','00','Request by Mr. Saqib Saleem 30-Oct-2024');
A331: KHI/HO/D/MO/PC COMP/E/47950/00037/10/2024 | B331: =VLOOKUP(A331,Sheet5!B:C,2,0) -> 050000812243 | C331: -3237.5 | D331: =ROUND(C331,0) -> -3238 | E331: 29Oct240041 | F331: ="insert into ins_premium_det (premium_rcv_code,assorted_code, rec_amount,premium_rcv_detail_code,remaining_amt, payrec, mode_code,coinsurance_code,class_cd,it_remarks) values" -> insert into ins_premium_det (premium_rcv_code,assorted_code, rec_amount,premium_rcv_detail_code,remaining_amt, payrec, mode_code,coinsurance_code,class_cd,it_remarks) values | G331: ="('"&E331&"','"&B331&"','"&D331&"',(select max(to_number(i.premium_rcv_detail_code))+1 from ins_premium_det i),'"&D331&"','"&D331&"','02', '11000003','00','Request by Mr. Saqib Saleem 30-Oct-2024');" -> ('29Oct240041','050000812243','-3238',(select max(to_number(i.premium_rcv_detail_code))+1 from ins_premium_det i),'-3238','-3238','02', '11000003','00','Request by Mr. Saqib Saleem 30-Oct-2024'); | H331: =F331&G331 -> insert into ins_premium_det (premium_rcv_code,assorted_code, rec_amount,premium_rcv_detail_code,remaining_amt, payrec, mode_code,coinsurance_code,class_cd,it_remarks) values('29Oct240041','050000812243','-3238',(select max(to_number(i.premium_rcv_detail_code))+1 from ins_premium_det i),'-3238','-3238','02', '11000003','00','Request by Mr. Saqib Saleem 30-Oct-2024');
A332: KHI/HO/D/MO/PC COMP/E/47950/00038/10/2024 | B332: =VLOOKUP(A332,Sheet5!B:C,2,0) -> 050000812244 | C332: 4754.4 | D332: =ROUND(C332,0) -> 4754 | E332: 29Oct240041 | F332: ="insert into ins_premium_det (premium_rcv_code,assorted_code, rec_amount,premium_rcv_detail_code,remaining_amt, payrec, mode_code,coinsurance_code,class_cd,it_remarks) values" -> insert into ins_premium_det (premium_rcv_code,assorted_code, rec_amount,premium_rcv_detail_code,remaining_amt, payrec, mode_code,coinsurance_code,class_cd,it_remarks) values | G332: ="('"&E332&"','"&B332&"','"&D332&"',(select max(to_number(i.premium_rcv_detail_code))+1 from ins_premium_det i),'"&D332&"','"&D332&"','02', '11000003','00','Request by Mr. Saqib Saleem 30-Oct-2024');" -> ('29Oct240041','050000812244','4754',(select max(to_number(i.premium_rcv_detail_code))+1 from ins_premium_det i),'4754','4754','02', '11000003','00','Request by Mr. Saqib Saleem 30-Oct-2024'); | H332: =F332&G332 -> insert into ins_premium_det (premium_rcv_code,assorted_code, rec_amount,premium_rcv_detail_code,remaining_amt, payrec, mode_code,coinsurance_code,class_cd,it_remarks) values('29Oct240041','050000812244','4754',(select max(to_number(i.premium_rcv_detail_code))+1 from ins_premium_det i),'4754','4754','02', '11000003','00','Request by Mr. Saqib Saleem 30-Oct-2024');
A333: KHI/HO/D/MO/PC COMP/E/47950/00062/10/2024 | B333: =VLOOKUP(A333,Sheet5!B:C,2,0) -> 050000812268 | C333: 3628 | D333: =ROUND(C333,0) -> 3628 | E333: 29Oct240041 | F333: ="insert into ins_premium_det (premium_rcv_code,assorted_code, rec_amount,premium_rcv_detail_code,remaining_amt, payrec, mode_code,coinsurance_code,class_cd,it_remarks) values" -> insert into ins_premium_det (premium_rcv_code,assorted_code, rec_amount,premium_rcv_detail_code,remaining_amt, payrec, mode_code,coinsurance_code,class_cd,it_remarks) values | G333: ="('"&E333&"','"&B333&"','"&D333&"',(select max(to_number(i.premium_rcv_detail_code))+1 from ins_premium_det i),'"&D333&"','"&D333&"','02', '11000003','00','Request by Mr. Saqib Saleem 30-Oct-2024');" -> ('29Oct240041','050000812268','3628',(select max(to_number(i.premium_rcv_detail_code))+1 from ins_premium_det i),'3628','3628','02', '11000003','00','Request by Mr. Saqib Saleem 30-Oct-2024'); | H333: =F333&G333 -> insert into ins_premium_det (premium_rcv_code,assorted_code, rec_amount,premium_rcv_detail_code,remaining_amt, payrec, mode_code,coinsurance_code,class_cd,it_remarks) values('29Oct240041','050000812268','3628',(select max(to_number(i.premium_rcv_detail_code))+1 from ins_premium_det i),'3628','3628','02', '11000003','00','Request by Mr. Saqib Saleem 30-Oct-2024');
