Workbook

Sheet Payment
A1: Sr. | B1: Status | C1: Contract No. | D1: Status2 | E1: Insurance Agency | F1: Dealer Name | G1: Customer Name | H1: City | I1: CNIC No. | J1: Home Phone# | K1: Mobile Number | L1: Business Phone# | M1: Mail Address | N1: Finance Amount | O1: Car Price | P1: Ins. Policy | Q1: Ins. Expiry Date | R1: Engine No. | S1: Chassis No. | T1: Car Category | U1: Reg. No. | V1: Car Name | W1: Model | X1: Contract Booking Date | Y1: Contract Value Date | Z1: Contract Maturity Date | AA1: Purchase Order No. | AB1: Tenor#2 | AC1: Tracker Company | AD1: Tracker Reference Number | AE1: Tracker Installation Date | AF1: Rate | AG1: Sum Insured | AH1: Premium | AI1: OLD Contract Ref | AJ1: Remarks-I | AK1: Remarks-II | AL1: Policy # 2024 | AM1: Tms prem | AN1: Difference
A2: 1 | B2: NORM | C2: 9976AD1211950014 | D2: Active | E2: T-PAK | F2: TOYOTA FAISALABAD | G2: MUHAMMAD ASIF | H2: Faisalabad | I2: 33100-5411156-3 | J2: 03217606970 | K2: 03217606970, 03217606970 | L2: 03217606970 | M2: H NO P-162 MAIN CHOWK ALI HOUSING C OLONY JHANG ROAD FAISALABAD PK | N2: 1156991 | O2: 2933000 | Q2: 45566 | R2: 2A34500 | S2: 9512872 | T2: NEW | V2: TOYOTA YARIS ATIV X CVT 1.5 | W2: 2021 | X2: 14-JUL-2021 | Y2: 03-SEP-2021 | Z2: 03-Sep-2026 | AA2: OLAFSD0300070634 | AB2: 5 | AC2: ITECL | AD2: 5370/08/2021 | AE2: 25-AUG-2021 | AF2: 2% | AG2: 2346400 | AH2: 46928 | AL2: KHI/HO/D/MO/PC COMP/C/99821/2/10/2024 | AM2: 46928 | AN2: =Table9[[#This Row],[Premium]]-Table9[[#This Row],[Tms prem]] -> 0
A3: 2 | B3: NORM | C3: 9976AD1232710002 | D3: Active | E3: T-PAK | F3: PAK SUZUKI MOTOR CO LTD | G3: MISBAH BATOOL | H3: Rawalpindi | I3: 37201-9259868-6 | K3: 03327555233 | M3: PLAZA # 10 ORCHARD RD, SECTOR-A,COMMERICAL DHA-2 ISLAMABAD 03327555233 | N3: 1874609 | O3: 2935000 | P3: 76078/000021/10/2023 | Q3: 02-OCT-2024 | R3: 284024 | S3: 1184046 | T3: NEW | V3: SUZUKI ALTO VXL AGS EURO II | W3: 2023 | X3: 45197 | Y3: 11-OCT-2023 | Z3: 11-Oct-2028 | AA3: OLARWP300097295 | AB3: 5 | AC3: CTRK | AD3: DIB0035359 | AE3: 04-OCT-2023 | AF3: 2% | AG3: 2641500 | AH3: 52830 | AL3: KHI/HO/D/MO/PC COMP/C/99821/5/10/2024 | AM3: 52830 | AN3: =Table9[[#This Row],[Premium]]-Table9[[#This Row],[Tms prem]] -> 0
A4: 3 | B4: NORM | C4: 9976AD1212070016 | D4: Active | E4: T-PAK | F4: PAK SUZUKI MOTOR CO LTD | G4: SAFIA BASHIR | H4: Lahore | I4: 35404-1497221-2 | J4: 03017982777 | K4: 03017982777 | L4: 04236680434 | M4: LAHORE GARRISON ACADEMY FOR BOYS TU FAIL ROAD CAMPUS LAHORE | N4: 374556 | O4: 1521000 | P4: 2524/02692/00002/10/2021 | Q4: 45568 | R4: 187796 | S4: 1085753 | T4: NEW | V4: SUZUKI ALTO VXL AGS EURO II | W4: 2021 | X4: 26-JUL-2021 | Y4: 27-OCT-2021 | Z4: 27-Oct-2026 | AA4: OLALHR300071150 | AB4: 5 | AC4: CTRK | AD4: DIB0032003 | AE4: 04-OCT-2021 | AF4: 2% | AG4: 1216800 | AH4: 24336 | AL4: KHI/HO/D/MO/PC COMP/C/99821/6/10/2024 | AM4: 24336 | AN4: =Table9[[#This Row],[Premium]]-Table9[[#This Row],[Tms prem]] -> 0
A5: 4 | B5: NORM | C5: 9976AD1211950016 | D5: Active | E5: T-PAK | F5: PAK SUZUKI MOTOR CO LTD | G5: FAISAL AHMAD | H5: Faisalabad | I5: 33100-0218679-7 | J5: 03006635147 | K5: 03006635147, 03006635147 | L5: 03006635147 | M5: P-12 ST 1 SHADMAN COLONY NEAR CITY MEGA MART FAISALABAD PK | N5: 273496 | O5: 1521000 | P5: 2021/09/CLFTTPCDP01047 | Q5: 45568 | R5: 6R185734 | S5: NF1AET306H1085750 | T5: NEW | V5: SUZUKI ALTO VXL AGS EURO-II | W5: 2021 | X5: 14-JUL-2021 | Y5: 11-OCT-2021 | Z5: 11-Oct-2025 | AA5: OLAFSD300070632 | AB5: 4 | AC5: ITECL | AD5: 5473/09/2021 | AE5: 04-OCT-2021 | AF5: 2% | AG5: 1216800 | AH5: 24336 | AL5: KHI/HO/D/MO/PC COMP/C/99821/7/10/2024 | AM5: 24336 | AN5: =Table9[[#This Row],[Premium]]-Table9[[#This Row],[Tms prem]] -> 0
A6: 5 | B6: NORM | C6: 9976AD2211180001 | D6: Active | E6: T-PAK | F6: CHANGAN JHELUM MOTORS | G6: ABAIDA LATIF | H6: Rawalpindi | I6: 35404-1723467-2 | K6: 03007969570 | M6: SHOP NO 07 GROUND FLOOR SADAT ARCADE WALLAYAT COMPLEX BAHRIA TOWN PH 7 RAWLAPINDI | N6: 590378 | O6: 1490000 | P6: DIB/T/BT/33754/ISB/1021 | Q6: 45568 | R6: M69U505255 | S6: M1009190 | T6: NEW | V6: CHANGAN KARVAAN | W6: 2021 | X6: 28-APR-2021 | Y6: 27-OCT-2021 | Z6: 27-Oct-2026 | AA6: OLARWP300068075 | AB6: 5 | AC6: FLCN | AD6: 108582/10/2021 | AE6: 01-OCT-2021 | AF6: 2% | AG6: 1192000 | AH6: 23840 | AL6: KHI/HO/D/MO/PC COMP/C/99821/8/10/2024 | AM6: 23840 | AN6: =Table9[[#This Row],[Premium]]-Table9[[#This Row],[Tms prem]] -> 0
A7: 6 | B7: NORM | C7: 9976AD1210890010 | D7: Active | E7: T-PAK | F7: CHANGAN JHELUM MOTORS | G7: MUHAMMAD NAWAZ | H7: Islamabad | I7: 61101-7100750-7 | K7: 03005750960 | M7: SHOP 9-B ROSE ARCADE G-11 MARKAZ ISLAMABAD | N7: 691695 | O7: 1640000 | P7: DIB/T/BT/33756/ISB/1021 | Q7: 45568 | R7: U504960 | S7: 1008837 | T7: NEW | V7: CHANGAN KARVAAN PLUS | W7: 2021 | X7: 30-MAR-2021 | Y7: 21-OCT-2021 | Z7: 21-Oct-2026 | AA7: OLAISD300067083 | AB7: 5 | AC7: CTRK | AD7: TDIDIB0029635 | AE7: 06-OCT-2021 | AF7: 2% | AG7: 1312000 | AH7: 26240 | AL7: KHI/HO/D/MO/PC COMP/C/99821/9/10/2024 | AM7: 26240 | AN7: =Table9[[#This Row],[Premium]]-Table9[[#This Row],[Tms prem]] -> 0
A8: 7 | B8: NORM | C8: 9976AD1211510006 | D8: Active | E8: T-PAK | F8: KIA MOTORS KINGS GATE | G8: ZUBAID UL HASSAN | H8: Lahore | I8: 35301-1959371-7 | M8: PUNJAB EDUCATION FOUNDATION 52 -L GULBERG III LAHORE | N8: 2024250 | O8: 4815000 | P8: DIB/T/33758/LHR/1021 | Q8: 45568 | R8: G4NAMH318860 | S8: NNAQL51AZKP307432 | T8: NEW | V8: SPORTAGE FWD | W8: 2021 | X8: 31-MAY-2021 | Y8: 03-NOV-2021 | Z8: 03-Nov-2026 | AA8: OLALHR300069013 | AB8: 5 | AF8: 1.75% | AG8: 3852000 | AH8: 67410 | AL8: KHI/HO/D/MO/PC COMP/C/99821/10/10/2024 | AM8: 67410 | AN8: =Table9[[#This Row],[Premium]]-Table9[[#This Row],[Tms prem]] -> 0
A9: 8 | B9: NORM | C9: 9976AD1211800009 | D9: Active | E9: T-PAK | F9: KIA MOTORS KINGS GATE | G9: EHSAN ULLAH KHAN | H9: Lahore | I9: 42301-1181720-5 | K9: 03248444007 | M9: H.NO 8 GULBERG II LAHORE 0324-8444007 LAHORE | N9: 2080252 | O9: 5303000 | P9: 56038/00008/10/2021 | Q9: 45568 | R9: 312329 | S9: 513332 | T9: NEW | V9: SPORTAGE AWD | W9: 2021 | X9: 29-JUN-2021 | Y9: 03-NOV-2021 | Z9: 03-Nov-2026 | AA9: OLALHR300070015 | AB9: 5 | AC9: ITECL | AD9: 5487/10/2021 | AE9: 05-OCT-2021 | AF9: 1.75% | AG9: 4242400 | AH9: 74242 | AL9: KHI/HO/D/MO/PC COMP/C/99821/11/10/2024 | AM9: 74242 | AN9: =Table9[[#This Row],[Premium]]-Table9[[#This Row],[Tms prem]] -> 0
A10: 10 | B10: WACH | C10: 9976AP1212810009 | D10: Active | E10: T-PAK | F10: SHADOW MOTORS | G10: SYED ALI JAFFER NAQVI | H10: Karachi | I10: 42101-9473365-1 | J10: 03121014890 | K10: 03121014890 | L10: 02138771111 | M10: DOW UNIVERSITY HOSPITAL GROUND OJHA CAMP OFFICE SAFOORA GOTH KARACHI | N10: 567765 | O10: 1400000 | P10: 56038/00071/10/2021 | Q10: 45568 | R10: 690501437 | S10: 1L100173D | T10: USD | U10: CY-9101 | V10: CHANGAN KARVAAN PLUS | W10: 2020 | X10: 08-OCT-2021 | Y10: 11-OCT-2021 | Z10: 11-Oct-2026 | AA10: OLUKHI300074602 | AB10: 5 | AC10: CTRK | AD10: DIB0032006 | AE10: 05-OCT-2021 | AF10: 2% | AG10: 1120000 | AH10: 22400 | AL10: KHI/HO/D/MO/PC COMP/C/99821/12/10/2024 | AM10: 22400 | AN10: =Table9[[#This Row],[Premium]]-Table9[[#This Row],[Tms prem]] -> 0
A11: 11 | B11: NORM | C11: 9976AD2211980007 | D11: Active | E11: T-PAK | F11: SUZUKI SUMMIT MOTORS PVT LTD. | G11: WASEEM HAIDER | H11: Lahore | I11: 35201-3439490-1 | J11: 03004252278 | K11: 03004252278 | L11: 04235921742 | M11: 109/F MAIN BOULEVARD STATE LIFE SOC IETY LAHORE | N11: 546851 | O11: 1610000 | P11: 2524/02692/0005/10/2021 | Q11: 45569 | R11: 221437 | S11: 10121456 | T11: NEW | V11: SUZUKI WA GONR VXL | W11: 2021 | X11: 17-JUL-2021 | Y11: 27-OCT-2021 | Z11: 27-Oct-2026 | AA11: OLALHR300070905 | AB11: 5 | AC11: CTRK | AD11: DIB0032013 | AE11: 05-OCT-2021 | AF11: 2% | AG11: 1288000 | AH11: 25760 | AL11: KHI/HO/D/MO/PC COMP/C/99821/13/10/2024 | AM11: 25760 | AN11: =Table9[[#This Row],[Premium]]-Table9[[#This Row],[Tms prem]] -> 0
A12: 12 | B12: NORM | C12: 9976AD2211960006 | D12: Active | E12: T-PAK | F12: PAK SUZUKI MOTOR CO LTD | G12: HAMZA JAVAID | H12: Lahore | I12: 35202-0424391-9 | J12: 03214251488 | K12: 03214251488 | L12: 04232174604 | M12: 136-MB 4TH FLOOR J BLOCK DHA PHASE 6 LAHORE | N12: 585536 | O12: 1521000 | P12: 2524/02692/00041/10/2021 | Q12: 45569 | R12: 6R183797 | S12: 1084378 | T12: NEW | V12: ALTO VXL EURO II | W12: 2021 | X12: 15-JUL-2021 | Y12: 27-OCT-2021 | Z12: 27-Oct-2026 | AA12: OLALHR300070758 | AB12: 5 | AC12: ITECL | AD12: 5485/10/2021 | AE12: 05-OCT-2021 | AF12: 2% | AG12: 1216800 | AH12: 24336 | AL12: KHI/HO/D/MO/PC COMP/C/99821/14/10/2024 | AM12: 24336 | AN12: =Table9[[#This Row],[Premium]]-Table9[[#This Row],[Tms prem]] -> 0
A13: 14 | B13: NORM | C13: 9976AD1211830096 | D13: Active | E13: T-PAK | F13: PAK SUZUKI MOTOR CO LTD | G13: IMRAN ALI | H13: Lahore | I13: 35201-9659682-3 | J13: 03214570085 | K13: 03214570085 | L13: 03214570085 | M13: SHOP NO 1 MADINA MARKET DAKKHANA BA TAPUR JALLO MORE NEAR KHALID ABID M EDICAL STORE LAHORE | N13: 663971 | O13: 1610000 | P13: 2021-10-205-V01501OP0002387 | Q13: 45569 | R13: PK10B220862 | S13: 10120866 | T13: NEW | V13: SUZUKI WAGON R VXL | W13: 2021 | X13: 02-JUL-2021 | Y13: 03-NOV-2021 | Z13: 03-Nov-2026 | AA13: OLALHR300070342 | AB13: 5 | AC13: ITECL | AD13: 5488/10/2021 | AE13: 05-OCT-2021 | AF13: 2% | AG13: 1288000 | AH13: 25760 | AL13: KHI/HO/D/MO/PC COMP/C/99821/15/10/2024 | AM13: 25760 | AN13: =Table9[[#This Row],[Premium]]-Table9[[#This Row],[Tms prem]] -> 0
A14: 15 | B14: NORM | C14: 9976AD1212250009 | D14: Active | E14: T-PAK | F14: TOYOTA LAYALPUR MOTOR | G14: KHURAM ASLAM | H14: Faisalabad | I14: 33100-5280143-7 | K14: 03137228656 | M14: HOUSE NO.121, STREET NO.04, RAZA ABAD BAZAT 03, FASISALABAD CELL NO:0313-7228656 | N14: 1035681 | O14: 2703000 | P14: DIB/T/BT/33717/LHR/0921 | Q14: 45569 | R14: 2A37296 | S14: 7023330 | T14: NEW | V14: TOYATA YARIS AITV CVT 1.3 | W14: 2021 | X14: 13-AUG-2021 | Y14: 11-OCT-2021 | Z14: 11-Oct-2026 | AA14: OLAFSD300071796 | AB14: 5 | AC14: CTRK | AD14: DIB0031912 | AE14: 05-OCT-2021 | AF14: 2% | AG14: 2162400 | AH14: 43248 | AL14: KHI/HO/D/MO/PC COMP/C/99821/17/10/2024 | AM14: 43248 | AN14: =Table9[[#This Row],[Premium]]-Table9[[#This Row],[Tms prem]] -> 0
A15: 17 | B15: NORM | C15: 9976AD1212420005 | D15: Active | E15: T-PAK | F15: TOYOTA CENTRAL MOTORS | G15: RIAZ AHMED | H15: Karachi | I15: 42301-3237044-9 | K15: 00966544056631 | M15: BUILDING NO.284 HAI ALWAZARAT KSA RIYADH HAI ALWAZARAT 11564 SAUDIA ARABIA | N15: 1432879 | O15: 3875000 | P15: PL-1021-1101010102-V14-D-00464 | Q15: 45569 | R15: A352653 | S15: ZE172R-7051829 | T15: RDA | V15: COROLLA ALTIS GRANDE CVT | W15: 2021 | X15: 30-AUG-2021 | Y15: 11-OCT-2021 | Z15: 11-Oct-2026 | AA15: OLAKHI300072688 | AB15: 5 | AC15: CTRK | AD15: DIB0031910 | AE15: 29-SEP-2021 | AF15: 1.4% | AG15: 3100000 | AH15: 43400 | AL15: KHI/HO/D/MO/PC COMP/C/99821/18/10/2024 | AM15: 43400 | AN15: =Table9[[#This Row],[Premium]]-Table9[[#This Row],[Tms prem]] -> 0
A16: 18 | B16: NORM | C16: 9976AD1212120088 | D16: Active | E16: T-PAK | F16: CHANGAN YAZDANI MOTORS | G16: LIAQUAT ALI | H16: Karachi | I16: 42201-0256366-7 | J16: 03222042469 | K16: 03222042469 | L16: 02135064445 | M16: PLOT # 27 SEC 23 KORANGI INDUSTRIAL ARERA NEAR SUKI SOUTH KARACHI | N16: 283181 | O16: 1399000 | P16: 2524/02692/00009/10/2021 | Q16: 45570 | R16: JL466Q9M69U505280 | S16: NKMAAB3D1M1009187 | T16: NEW | V16: CHANGAN KARVAN PLUS | W16: 2021 | X16: 31-JUL-2021 | Y16: 11-OCT-2021 | Z16: 11-Oct-2026 | AA16: OLAKHI300071194 | AB16: 5 | AC16: ITECL | AD16: 5477/09/2021 | AE16: 30-SEP-2021 | AF16: 2% | AG16: 1119200 | AH16: 22384 | AL16: KHI/HO/D/MO/PC COMP/C/99821/32/10/2024 | AM16: 22384 | AN16: =Table9[[#This Row],[Premium]]-Table9[[#This Row],[Tms prem]] -> 0
A17: 19 | B17: NORM | C17: 9976AD2212120023 | D17: Active | E17: T-PAK | F17: SUZUKI RACECOURSE MOTORS | G17: MURAD ALI | H17: Islamabad | I17: 37405-6776422-1 | J17: 03215052143 | L17: 0512326121 | M17: UNION CONSAL ROAD OPP NEW ISLAMIC M OHIUD DEEN UNIVERSITY NEAR MAIN SIH ISLAMABAD PK | N17: 386828 | O17: 1335000 | P17: 01-2110-PO-MTR-PCCM-D-001362 | Q17: 45570 | R17: 186805 | S17: 1086812 | T17: NEW | V17: SUZUKI ALTO VXR EURO II | W17: 2021 | X17: 31-JUL-2021 | Y17: 21-OCT-2021 | Z17: 21-Oct-2027 | AA17: OLAISD300071378 | AB17: 6 | AC17: ITECL | AD17: 5494/10/2021 | AE17: 06-OCT-2021 | AF17: 2% | AG17: 1068000 | AH17: 21360 | AL17: KHI/HO/D/MO/PC COMP/C/99821/33/10/2024 | AM17: 21360 | AN17: =Table9[[#This Row],[Premium]]-Table9[[#This Row],[Tms prem]] -> 0
A18: 20 | B18: NORM | C18: 9976AD2211510034 | D18: Active | E18: T-PAK | F18: PAK SUZUKI MOTOR CO LTD | G18: ABDUL AHAD | H18: Karachi | I18: 42201-7837972-7 | J18: 03340313754 | K18: 03340313754, 03122017660 | L18: 02134507660 | M18: ABU ZAID TRAVEL and TOURS PVT LTD SHO P # 9 POPULAR PLAZA OPP DISTRICT and SESSION COURT MALIR MAIN NATIONAL H KARACHI | N18: 569103 | O18: 1335000 | P18: 2524/06292/00007/10/2021 | Q18: 45570 | R18: 6R185075 | S18: NF1AET306H1085049 | T18: NEW | V18: SUZUKI ALTO VXL AGS EURO II | W18: 2021 | X18: 31-MAY-2021 | Y18: 03-NOV-2021 | Z18: 03-Nov-2026 | AA18: OLAKHI300069137 | AB18: 5 | AC18: CTRK | AD18: DIB0032002 | AE18: 05-OCT-2021 | AF18: 2% | AG18: 1068000 | AH18: 21360 | AL18: KHI/HO/D/MO/PC COMP/C/99821/1/10/2024 | AM18: 21360 | AN18: =Table9[[#This Row],[Premium]]-Table9[[#This Row],[Tms prem]] -> 0
A19: 21 | B19: NORM | C19: 9976AD2211800006 | D19: Active | E19: T-PAK | F19: PAK SUZUKI MOTOR CO LTD | G19: MUHAMMAD SHAHZEB KHAN | H19: Karachi | I19: 42201-6028139-1 | J19: 0213453442 | K19: 03333114064 | L19: 0213453442 | M19: S 1 J BLOCK 2 PECHS NOORANI KABAB KARACHI | N19: 566861 | O19: 1655000 | P19: 2524/02692/00006/10/2021 | Q19: 45570 | R19: 186714 | S19: 10086714 | T19: NEW | V19: SUZUKI CULTUS VXR | W19: 2021 | X19: 29-JUN-2021 | Y19: 21-OCT-2021 | Z19: 21-Oct-2026 | AA19: OLAKHI300070136 | AB19: 5 | AC19: ITECL | AD19: 5495/10/2021 | AE19: 06-OCT-2021 | AF19: 2% | AG19: 1324000 | AH19: 26480 | AL19: KHI/HO/D/MO/PC COMP/C/99821/34/10/2024 | AM19: 26480 | AN19: =Table9[[#This Row],[Premium]]-Table9[[#This Row],[Tms prem]] -> 0
A20: 22 | B20: NORM | C20: 9976AP1212810007 | D20: Active | E20: T-PAK | F20: SAEED AUTOS | G20: BASIT QAYYUM | H20: Faisalabad | I20: 33100-2045155-1 | J20: 03216612621 | K20: 03216612621, 03216612621 | L20: 03216612621 | M20: P-142 SAMUNDRI ROAD SEGHAL CITY FAISALABAD PK | N20: 590122 | O20: 1350000 | P20: 56038/00013/10/2021 | Q20: 45570 | R20: PK10B115726 | S20: A1L310PK10015730 | T20: USD | U20: LEE-16-3731 | V20: SUZUKI WAGONR VXL | W20: 2016 | X20: 08-OCT-2021 | Y20: 11-OCT-2021 | Z20: 11-Oct-2026 | AA20: OLUFSD300074693 | AB20: 5 | AC20: CTRK | AD20: DIB0032024 | AE20: 06-OCT-2021 | AF20: 2% | AG20: 1080000 | AH20: 21600 | AL20: KHI/HO/D/MO/PC COMP/C/99821/35/10/2024 | AM20: 21600 | AN20: =Table9[[#This Row],[Premium]]-Table9[[#This Row],[Tms prem]] -> 0
A21: 23 | B21: NORM | C21: 9976AD1212120081 | D21: Active | E21: T-PAK | F21: SUZUKI RACECOURSE MOTORS | G21: FAISAL AKHTAR | H21: Islamabad | I21: 37405-0555458-1 | J21: 0515708627 | K21: 03215558255 | L21: 0512251891-93 | M21: H NO. 1024 A, ST 01, BLOCK C, NATIONAL POLICE FOUNDATION, ISLAMABAD. | N21: 849587 | O21: 1335000 | P21: 01-2110-PO-MTR-PCCM-D-001361 | Q21: 45570 | R21: 186804 | S21: 1086805 | T21: NEW | V21: SUZUKI ALTO VXR EURO II | W21: 2021 | X21: 31-JUL-2021 | Y21: 21-OCT-2021 | Z21: 21-Oct-2028 | AA21: OLAISD300071344 | AB21: 7 | AC21: ITECL | AD21: 5493/10/2021 | AE21: 06-OCT-2021 | AF21: 2% | AG21: 1068000 | AH21: 21360 | AL21: KHI/HO/D/MO/PC COMP/C/99821/37/10/2024 | AM21: 21360 | AN21: =Table9[[#This Row],[Premium]]-Table9[[#This Row],[Tms prem]] -> 0
A22: 24 | B22: NORM | C22: 9976AD1212000019 | D22: Active | E22: T-PAK | F22: PAK SUZUKI MOTOR CO LTD | G22: NASIR ALI | H22: Lahore | I22: 35201-4822544-9 | J22: 03094460040 | K22: 03094460040 | L22: 03094460040 | M22: STREET NO 1 MANAWAN STOP NEAR LASAN I PHARMA LAHORE PK | N22: 685181 | O22: 1521000 | P22: 2021-10-205-V01501OP0002394 | Q22: 45570 | R22: 185038 | S22: 1085041 | T22: NEW | V22: ALTO VXL AGS EURO-II | W22: 2021 | X22: 19-JUL-2021 | Y22: 27-OCT-2021 | Z22: 27-Oct-2026 | AA22: OLALHR300070954 | AB22: 5 | AC22: CTRK | AD22: DIB0032022 | AE22: 06-OCT-2021 | AF22: 2% | AG22: 1216800 | AH22: 24336 | AL22: KHI/HO/D/MO/PC COMP/C/99821/39/10/2024 | AM22: 24336 | AN22: =Table9[[#This Row],[Premium]]-Table9[[#This Row],[Tms prem]] -> 0
A23: 25 | B23: NORM | C23: 9976AP1212950001 | D23: Active | E23: T-PAK | F23: KHALID MOTORS | G23: MUBASHIR ALI | H23: Lahore | I23: 35202-5513748-1 | J23: 03247842306 | K23: 03247842306 | L23: 03247842306 | M23: OFFICE NO 3 JOHAR VIEW G-BLOCK JOHA R TOWN LAHORE | N23: 769146 | O23: 1760000 | P23: 2524/02692/00019/10/2021 | Q23: 45570 | R23: 221199 | S23: 10121213 | T23: NEW | V23: SUZUKI WAGON R VXL AGS | W23: 2021 | X23: 22-OCT-2021 | Y23: 27-OCT-2021 | Z23: 27-Oct-2026 | AA23: OLDLHR300074655 | AB23: 5 | AC23: CTRK | AD23: DIB0032034 | AE23: 12-OCT-2021 | AF23: 2% | AG23: 1408000 | AH23: 28160 | AL23: KHI/HO/D/MO/PC COMP/C/99821/41/10/2024 | AM23: 28160 | AN23: =Table9[[#This Row],[Premium]]-Table9[[#This Row],[Tms prem]] -> 0
A24: 27 | B24: NORM | C24: 9976AD1211400016 | D24: Active | E24: T-PAK | F24: CHANGAN YAZDANI MOTORS | G24: NIRMALA | H24: Hyderabad | I24: 44101-0154353-4 | K24: 03332841080 | M24: FLAT NO 43 4TH FLOOR CHANDNI SHOPPING CENTRE SADDAR CANTT HYDERABAD | N24: 1013218 | O24: 2650000 | P24: PL-1021-1101010102-V14-D-00466 | Q24: 45570 | R24: JL473QFM3CAD517773 | S24: NKMA2ASE5M1003376 | T24: NEW | V24: CHANGAN ALSVIN 1.5L LUMIERE | W24: 2021 | X24: 20-MAY-2021 | Y24: 21-OCT-2021 | Z24: 21-Oct-2026 | AA24: OLAHYD300068773 | AB24: 5 | AC24: ITECL | AD24: 5483/10/2021 | AE24: 04-OCT-2021 | AF24: 2% | AG24: 2120000 | AH24: 42400 | AL24: KHI/HO/D/MO/PC COMP/C/99821/42/10/2024 | AM24: 42400 | AN24: =Table9[[#This Row],[Premium]]-Table9[[#This Row],[Tms prem]] -> 0
A25: 28 | B25: NORM | C25: 9976AD1212250015 | D25: Active | E25: T-PAK | F25: TOYOTA ISLAMABAD MOTORS | G25: HASAN MEHMOOD BUTT | H25: Islamabad | I25: 61101-8755355-9 | J25: 03212036843 | L25: 0 | M25: H # 13-C ST # 9 SECTOR F-11/1 ISLAMABAD PK | N25: 1156549 | O25: 2933000 | P25: DIB/T/BT/33764/ISB/1021 | Q25: 45570 | R25: 2A37485 | S25: NSP151R-9514082 | T25: NEW | V25: TOYOTA YARIS ATIV X CVT 1.5 | W25: 2021 | X25: 13-AUG-2021 | Y25: 21-OCT-2021 | Z25: 21-Oct-2026 | AA25: OLAISD300071917 | AB25: 5 | AC25: CTRK | AD25: TDIDIB0029677 | AE25: 06-OCT-2021 | AF25: 2% | AG25: 2346400 | AH25: 46928 | AL25: KHI/HO/D/MO/PC COMP/C/99821/43/10/2024 | AM25: 46928 | AN25: =Table9[[#This Row],[Premium]]-Table9[[#This Row],[Tms prem]] -> 0
A26: 29 | B26: NORM | C26: 9976AD1212250010 | D26: Active | E26: T-PAK | F26: TOYOTA SOUTHERN MOTORS | G26: HARIS AHMED | H26: Karachi | I26: 42000-6970640-3 | J26: 03053000454 | L26: 02135374194 | M26: B8 KHY-ERUM BLOCK-13B GULSHAN E IQB AL KARACHI PK | N26: 1134684 | O26: 2595000 | P26: 56038/00011/10/2021 | Q26: 45570 | R26: 2A37336 | S26: 7023452 | T26: NEW | V26: TOYOTA YARIS GLI CVT 1.3 | W26: 2021 | X26: 13-AUG-2021 | Y26: 21-OCT-2021 | Z26: 21-Oct-2026 | AA26: OLAKHI300071817 | AB26: 5 | AC26: ITECL | AD26: 5475/09/2021 | AE26: 29-SEP-2021 | AF26: 2% | AG26: 2076000 | AH26: 41520 | AL26: KHI/HO/D/MO/PC COMP/C/99821/44/10/2024 | AM26: 41520 | AN26: =Table9[[#This Row],[Premium]]-Table9[[#This Row],[Tms prem]] -> 0
A27: 30 | B27: NORM | C27: 9976AD1212160152 | D27: Active | E27: T-PAK | F27: TOYOTA FAISALABAD | G27: TAHIR HUSSAIN | H27: Faisalabad | I27: 33100-2644226-1 | K27: 03208653379 | M27: 343-B EDEN GARDEN FSD | N27: 1533867 | O27: 2703000 | P27: 2021/10/CLFTTPCDP01114 | Q27: 45570 | R27: 2A37985 | S27: 7023828 | T27: NEW | V27: TOYOTA YARIS ATIV CVT 1.3 | W27: 2021 | X27: 04-AUG-2021 | Y27: 21-OCT-2021 | Z27: 21-Oct-2028 | AA27: OLASFSD300071601 | AB27: 7 | AC27: ITECL | AD27: 5492/10/2021 | AE27: 06-OCT-2021 | AF27: 2% | AG27: 2162400 | AH27: 43248 | AL27: KHI/HO/D/MO/PC COMP/C/99821/45/10/2024 | AM27: 43248 | AN27: =Table9[[#This Row],[Premium]]-Table9[[#This Row],[Tms prem]] -> 0
A28: 31 | B28: NORM | C28: 9976AD1211180015 | D28: Active | E28: T-PAK | F28: HONDA GATEWAY PVT LTD | G28: ASIF ALI | H28: Lahore | I28: 35201-1378953-7 | J28: 03004337415 | K28: 03004337415 | L28: 03004337415 | M28: MAIN CANAL ROAD NEAR LAL PUL MUGHAL PURA LAHORE | N28: 1292266 | O28: 2865000 | P28: 252403898/10/2021 | Q28: 45570 | R28: 1000984 | S28: 003623 | T28: NEW | V28: HONDA CITY ASPIRE | W28: 2021 | X28: 28-APR-2021 | Y28: 03-NOV-2021 | Z28: 03-Nov-2026 | AA28: OLALHR300068212 | AB28: 5 | AC28: CTRK | AD28: DIB0032031 | AE28: 07-OCT-2021 | AF28: 2% | AG28: 2292000 | AH28: 45840 | AL28: KHI/HO/D/MO/PC COMP/C/99821/46/10/2024 | AM28: 45840 | AN28: =Table9[[#This Row],[Premium]]-Table9[[#This Row],[Tms prem]] -> 0
A29: 32 | B29: NORM | C29: 9976AP1212880037 | D29: Active | E29: T-PAK | F29: TOYOTA AIRPORT MOTOR | G29: ANSAR ALI | H29: Lahore | I29: 35201-0874888-1 | J29: 03213943808 | K29: 03213943808 | L29: 03213943808 | M29: PL 51 SIDDIQ TRADE CENTER GULBERG I I LAHORE | N29: 1425134 | O29: 3903000 | P29: 2524/02692/00012/10/2021 | Q29: 45570 | R29: Q352901 | S29: 7052057 | T29: NEW | V29: TOYOTA COROLLA ALTIS GRANDE | W29: 2021 | X29: 15-OCT-2021 | Y29: 21-OCT-2021 | Z29: 21-Oct-2026 | AA29: OLDLHR300074666 | AB29: 5 | AC29: CTRK | AD29: DIB0032023 | AE29: 06-OCT-2021 | AF29: 2% | AG29: 3122400 | AH29: 62448 | AL29: KHI/HO/D/MO/PC COMP/C/99821/47/10/2024 | AM29: 62448 | AN29: =Table9[[#This Row],[Premium]]-Table9[[#This Row],[Tms prem]] -> 0
A30: 33 | B30: NORM | C30: 9976AD1211830098 | D30: Active | E30: T-PAK | F30: MG CENTER | G30: MUHAMMAD AHSAN | H30: Faisalabad | I30: 33100-0579077-5 | J30: 0418523339 | K30: 03218661622 | L30: 0412696716 | M30: HOUSE NO 41 AHMAD STREET MOHALLAH KHAYIBAN COLONY NO 1 NEAR PRIME CARE HOSPITAL FAISALABAD. | N30: 1371960 | O30: 5449000 | P30: DIB/T/BT/33708/FSD/0921 | Q30: 45570 | R30: 5MGM6180193 | S30: MN110733 | T30: NEW | V30: MG MOTORS MG HS TURBO | W30: 2021 | X30: 02-JUL-2021 | Y30: 21-OCT-2021 | Z30: 21-Oct-2025 | AA30: OLAFSD300070368 | AB30: 4 | AC30: CTRK | AD30: TDIDIB0029645 | AE30: 06-OCT-2021 | AF30: 1.75% | AG30: 4359200 | AH30: 76286 | AL30: KHI/HO/D/MO/PC COMP/C/99821/48/10/2024 | AM30: 76286 | AN30: =Table9[[#This Row],[Premium]]-Table9[[#This Row],[Tms prem]] -> 0
A31: 34 | B31: NORM | C31: 9976AD1212100029 | D31: Active | E31: T-PAK | F31: KIA MACCA MOTORS | G31: MUHAMMAD RAFIQ | H31: Karachi | I31: 42201-0733928-5 | J31: N/A | K31: 0300-8229541 | L31: 34944352 | M31: FLAT# D-2 JAN KABIR REDENCY PLOT# 160/0 BLOCK-3 PECHS NEAR PECHS GOVT BOYS COLLEGE KARACHI | N31: 2021485 | O31: 5270000 | P31: 56038/00010/10/2021 | Q31: 45570 | R31: G4NAMH3105350 | S31: NNAQL51AZKP512857 | T31: NEW | V31: KIA SPORTAGE AWD | W31: 2021 | X31: 29-JUL-2021 | Y31: 11-OCT-2021 | Z31: 11-Oct-2026 | AA31: OLAKHI300071316 | AB31: 5 | AF31: 2% | AG31: 4216000 | AH31: 84320 | AL31: KHI/HO/D/MO/PC COMP/C/99821/49/10/2024 | AM31: 84320 | AN31: =Table9[[#This Row],[Premium]]-Table9[[#This Row],[Tms prem]] -> 0
A32: 35 | B32: NORM | C32: 9976AP2222800007 | D32: Active | E32: T-PAK | F32: AL-QURASH MOTORS | G32: NASIR KHAN | H32: Lahore | I32: 21201-4848113-5 | J32: N/A | K32: 03218265003 0308-5999985 | L32: 32734422 | M32: FLAT# 103 BLOCK-B IST FLOOR NAZ PLAZA M A JINNAH ROAD NEAR NISHAT CINEMA KARACHI | N32: 629716 | O32: 2000000 | P32: 64081/000006/10/2022 | Q32: 45570 | R32: 6R123909 | S32: 1023608 | T32: USD | U32: AAW-884 | V32: SUZUKI ALTO VXR AGS EURO II | W32: 2019 | X32: 07-OCT-2022 | Y32: 11-OCT-2022 | Z32: 11-Oct-2025 | AA32: OLULHR300090255 | AB32: 3 | AC32: ITFT | AD32: 8955/10/2022/ITFM | AE32: 06-OCT-2022 | AF32: 1.75% | AG32: 1700000 | AH32: 29750 | AL32: KHI/HO/D/MO/PC COMP/C/99821/52/10/2024 | AM32: 29750 | AN32: =Table9[[#This Row],[Premium]]-Table9[[#This Row],[Tms prem]] -> 0
A33: 36 | B33: NORM | C33: 9976AD1213620030 | D33: Active | E33: T-PAK | F33: TOYOTA ISLAMABAD MOTORS | G33: SHAHZARA ABID | H33: Islamabad | I33: 61101-6668987-8 | J33: 03215099485 | L33: 03215099485 | M33: H # 480 ST # 67 SECTOR I-8/3 ISLAMABAD PK | N33: 1840431 | O33: 3490000 | P33: 64081/00005/10/2022 | Q33: 45570 | R33: 100624 | S33: 6077924 | T33: NEW | V33: TOYOTA COROLLA ALTIS A/T | W33: 2022 | X33: 28-DEC-2021 | Y33: 11-OCT-2022 | Z33: 11-Oct-2027 | AA33: OLAISD300082495 | AB33: 5 | AC33: ITFM | AD33: 8941/10/2022/ITFM | AE33: 06-OCT-2022 | AF33: 2% | AG33: 2966500 | AH33: 59330 | AL33: KHI/HO/D/MO/PC COMP/C/99821/54/10/2024 | AM33: 59330 | AN33: =Table9[[#This Row],[Premium]]-Table9[[#This Row],[Tms prem]] -> 0
A34: 37 | B34: NORM | C34: 9976AD1212090003 | D34: Active | E34: T-PAK | F34: PAK SUZUKI MOTOR CO LTD | G34: SALAMAT LATIF | H34: Faisalabad | I34: 33102-8605139-7 | J34: 0418753867 | K34: 03007913402, 03007913402 | L34: 03007913402 | M34: H NO P-05 ST NO 03 GHAZI ABAD NO 01 MILLAT ROAD FAISALABAD PK | N34: 328717 | O34: 1830000 | P34: DIB/T/BT/33759/LHR/1021 | Q34: 45571 | R34: 186632 | S34: 10086600 | T34: NEW | V34: CULTUS VXL | W34: 2021 | X34: 28-JUL-2021 | Y34: 21-OCT-2021 | Z34: 21-Oct-2025 | AA34: OLAFSD300071183 | AB34: 4 | AC34: CTRK | AD34: DIB0032012 | AE34: 07-OCT-2021 | AF34: 2% | AG34: 1464000 | AH34: 29280 | AL34: KHI/HO/D/MO/PC COMP/C/99821/59/10/2024 | AM34: 29280 | AN34: =Table9[[#This Row],[Premium]]-Table9[[#This Row],[Tms prem]] -> 0
A35: 38 | B35: NORM | C35: 9976AD1212120109 | D35: Active | E35: T-PAK | F35: PAK SUZUKI MOTOR CO LTD | G35: FATIMA SYED | H35: Rawalpindi | I35: 37406-6812273-4 | J35: 03325621994 | L35: 0518441376 | M35: H # 27 (FIRST FLOOR ) ST # 5 SECTOR # D DHA 1 NEAR DHA AVENUE MALL RAWALPINDI PK | N35: 887205 | O35: 1975000 | P35: 01-2110-PO-MTR-PCCM-D-001368 | Q35: 45571 | R35: 183915 | S35: 10083928 | T35: NEW | V35: SUZUKI CULTUS VXL AGS EURO II | W35: 2021 | X35: 31-JUL-2021 | Y35: 21-OCT-2021 | Z35: 21-Oct-2028 | AA35: OLARWP300071536 | AB35: 7 | AC35: ITECL | AD35: 5506/10/2021 | AE35: 07-OCT-2021 | AF35: 2% | AG35: 1580000 | AH35: 31600 | AL35: KHI/HO/D/MO/PC COMP/C/99821/62/10/2024 | AM35: 31600 | AN35: =Table9[[#This Row],[Premium]]-Table9[[#This Row],[Tms prem]] -> 0
A36: 39 | B36: NORM | C36: 9976AD1212110035 | D36: Active | E36: T-PAK | F36: SUZUKI GUJRANWALA MOTOR | G36: MUHAMMAD ZAKIR MAHMOOD-ASAAN ACCOUN | H36: Gujranwala | I36: 34101-2511164-5 | K36: 0300300884 03009646209 | L36: 554215233 | M36: CIRCULAR ROAD LOHA BAZAR KHALID MAHMOOD IRON MERCHANT GRW 03000300884/03009646209 | N36: 771918 | O36: 1830000 | P36: 56038/00016/10/2021 | Q36: 45571 | R36: PK10K186803 | S36: NF1AVK31H10086799 | T36: NEW | V36: CULTUS VXL EURO-II | W36: 2021 | X36: 30-JUL-2021 | Y36: 21-OCT-2021 | Z36: 21-Oct-2026 | AA36: OLAGWL300071242 | AB36: 5 | AC36: ITECL | AD36: 5502/10/2021 | AE36: 07-OCT-2021 | AF36: 2% | AG36: 1464000 | AH36: 29280 | AL36: KHI/HO/D/MO/PC COMP/C/99821/63/10/2024 | AM36: 29280 | AN36: =Table9[[#This Row],[Premium]]-Table9[[#This Row],[Tms prem]] -> 0
A37: 41 | B37: NORM | C37: 9976AD1212090006 | D37: Active | E37: T-PAK | F37: KIA CLIFTON | G37: ZAMAN ZED | H37: Hyderabad | I37: 41303-2362189-9 | K37: 03163029266,03313567600 | M37: M/S RAHAT PETROLIUM SERVICE NEAR NEW INDUS BRIDGE BY PASS HYDERABAD | N37: 1424967 | O37: 5270000 | P37: DIB/T/BT/33774/HYD/1021 | Q37: 45571 | R37: 306026 | S37: 513039 | T37: NEW | V37: KIA SPORTGE AWD | W37: 2021 | X37: 28-JUL-2021 | Y37: 21-OCT-2021 | Z37: 21-Oct-2026 | AA37: OLAHYD300070985 | AB37: 5 | AF37: 1.75% | AG37: 4216000 | AH37: 73780 | AL37: KHI/HO/D/MO/PC COMP/C/99821/65/10/2024 | AM37: 73780 | AN37: =Table9[[#This Row],[Premium]]-Table9[[#This Row],[Tms prem]] -> 0
A38: 42 | B38: NORM | C38: 9976AP1212930013 | D38: Active | E38: T-PAK | F38: H.N. MOTORS | G38: MANZOOR SHAHEEN RUPAL | H38: Lahore | I38: 35201-1513681-3 | K38: 03000773331 | M38: 278 R DHA PHASE 2 LAHORE 03000773331 | N38: 1608642 | O38: 5303000 | P38: 56038/00018/10/2021 | Q38: 45571 | R38: 318184 | S38: 513534 | T38: NEW | V38: KIA SPORTAGE AWD | W38: 2021 | X38: 20-OCT-2021 | Y38: 21-OCT-2021 | Z38: 21-Oct-2026 | AA38: OLDLHR300074733 | AB38: 5 | AC38: ITECL | AD38: 5501/10/2021 | AE38: 07-OCT-2021 | AF38: 2% | AG38: 4242400 | AH38: 84848 | AL38: KHI/HO/D/MO/PC COMP/C/99821/66/10/2024 | AM38: 84848 | AN38: =Table9[[#This Row],[Premium]]-Table9[[#This Row],[Tms prem]] -> 0
A39: 43 | B39: NORM | C39: 9976AD1212430085 | D39: Active | E39: T-PAK | F39: KIA MACCA MOTORS | G39: FAZAL ULLAH NOONARI | H39: Hyderabad | I39: 41306-0439472-3 | J39: 03008371215 | K39: 03008371215 | L39: 0223411264 | M39: B.NO RHS MAIN AUTO BHAN ROAD LATIFA BAD # 3 NEAR TANDORI GRILL HYD HYDERABAD | N39: 2226509 | O39: 5270000 | P39: 2021/10/CLFTTPCDP01118 | Q39: 45571 | R39: G4NAMH312305 | S39: NNAQL51AZKP513369 | T39: NEW | V39: KIA SPORTGE AWD | W39: 2021 | X39: 31-AUG-2021 | Y39: 21-OCT-2021 | Z39: 21-Oct-2026 | AA39: OLAHYD300072861 | AB39: 5 | AC39: CTRK | AF39: 1.75% | AG39: 4216000 | AH39: 73780 | AL39: KHI/HO/D/MO/PC COMP/C/99821/67/10/2024 | AM39: 73780 | AN39: =Table9[[#This Row],[Premium]]-Table9[[#This Row],[Tms prem]] -> 0
A40: 44 | B40: NORM | C40: 9976AP1222840011 | D40: Active | E40: T-PAK | F40: CRESENT CAR COMPANY | G40: MUHAMMAD AHMAD KHAN | H40: Lahore | I40: 42501-1030528-9 | J40: 03344317595 | K40: 03214305069, 03344317595 | L40: 03344317595 | M40: H NO 751 ST NO 46 OVERSEAS-B BLOCK BAHRIA TOWN LAHORE PK | N40: 634615 | O40: 1150000 | P40: 64081/00007/10/2022 | Q40: 45571 | R40: 726340 | S40: 01264862 | T40: USD | U40: LEH-19-3401 | V40: SUZUKI MEHRAN VX-EURO II | W40: 2019 | X40: 11-OCT-2022 | Y40: 11-OCT-2022 | Z40: 11-Oct-2027 | AA40: OLULHR300090256 | AB40: 5 | AC40: ITFT | AD40: 8983/10/2022/ITFM | AE40: 10-OCT-2022 | AF40: 1.75% | AG40: 977500 | AH40: 17106 | AL40: KHI/HO/D/MO/PC COMP/C/99821/72/10/2024 | AM40: 17106 | AN40: =Table9[[#This Row],[Premium]]-Table9[[#This Row],[Tms prem]] -> 0
A41: 46 | B41: NORM | C41: 9976AD2211940005 | D41: Active | E41: T-PAK | F41: PAK SUZUKI MOTOR CO LTD | G41: MUHAMMAD IRFAN | H41: Faisalabad | I41: 33104-8750479-9 | J41: 03006602180 | K41: 03006602180, 03006602180 | L41: 0412640799 | M41: HOUSE NO P-01 CHAK NO 194 RB ST 04 MAIN BAZAR KHURRIANWALA ROAD LATIAN FAISALABAD PK | N41: 513303 | O41: 1335000 | P41: 2021/10/CLFTTPCDP01110 | Q41: 45572 | R41: 186485 | S41: 1086491 | T41: NEW | V41: SUZUKI ALTO VXE EURO II | W41: 2021 | X41: 13-JUL-2021 | Y41: 21-OCT-2021 | Z41: 21-Oct-2026 | AA41: OLAFSD300070633 | AB41: 5 | AC41: ITECL | AD41: 5498/10/2021 | AE41: 08-OCT-2021 | AF41: 2% | AG41: 1068000 | AH41: 21360 | AL41: KHI/HO/D/MO/PC COMP/C/99821/80/10/2024 | AM41: 21360 | AN41: =Table9[[#This Row],[Premium]]-Table9[[#This Row],[Tms prem]] -> 0
A42: 47 | B42: NORM | C42: 9976AD1212070007 | D42: Active | E42: T-PAK | F42: PAK SUZUKI MOTOR CO LTD | G42: SYED ZULFIQAR ALI NAQVI | H42: Faisalabad | I42: 33100-2522268-7 | J42: 03007649820 | K42: 03007649820 | L42: 0418797972 | M42: P-372 STREET NO 8 FAREED CHOWK SIDDIQUE AKBAR TOWN FAISALABAD | N42: 681058 | O42: 1335000 | P42: 2021/10/CLFTTPCDP01206 | Q42: 45572 | R42: 190187 | S42: 1090159 | T42: NEW | V42: SUZUKI ALTO VXR | W42: 2021 | X42: 26-JUL-2021 | Y42: 11-NOV-2021 | Z42: 11-Nov-2027 | AA42: OLASFSD300070662 | AB42: 6 | AC42: CTRK | AD42: DIB0032362 | AE42: 08-NOV-2021 | AF42: 2% | AG42: 1068000 | AH42: 21360 | AL42: KHI/HO/D/MO/PC COMP/C/99821/82/10/2024 | AM42: 21360 | AN42: =Table9[[#This Row],[Premium]]-Table9[[#This Row],[Tms prem]] -> 0
A43: 48 | B43: NORM | C43: 9976AD2211800004 | D43: Active | E43: T-PAK | F43: SUZUKI MEHRAN MOTORS | G43: AZRA PERVEEN | H43: Nawab Shah | I43: 45402-0889568-6 | J43: 03337888993 | K43: 03337888993 | L43: 03337888993 | M43: HOUSE # 05 BLOCK 10 POLICE LINE NAW AB SHAH POLICE HEAD QUARTER NEAR PO NAWABSHAH PK | N43: 700556 | O43: 1830000 | P43: DIB/T/BT/33776/HYD/1021 | Q43: 45572 | R43: 186025 | S43: 10086003 | T43: NEW | V43: CULTUS VXL | W43: 2021 | X43: 29-JUN-2021 | Y43: 21-OCT-2021 | Z43: 21-Oct-2026 | AA43: OLANWB300069850 | AB43: 5 | AC43: CTRK | AD43: DIB0032014 | AE43: 07-OCT-2021 | AF43: 2% | AG43: 1464000 | AH43: 29280 | AL43: KHI/HO/D/MO/PC COMP/C/99821/83/10/2024 | AM43: 29280 | AN43: =Table9[[#This Row],[Premium]]-Table9[[#This Row],[Tms prem]] -> 0
A44: 49 | B44: NORM | C44: 9976AD1212110040 | D44: Active | E44: T-PAK | F44: TOYOTA WALTON MOTORS | G44: MUHAMMAD AKRAM | H44: Lahore | I44: 35201-9667854-3 | J44: 03218400571 | K44: 03218400571 | L44: 04235292905 | M44: PLOT NO 1 SAMSANI ROAD NEAR SUPARCO HANJARWAL LAHORE | N44: 1218290 | O44: 2703000 | P44: 2524/02692/00031/10/2021 | Q44: 45572 | R44: 2A37466 | S44: 7023746 | T44: NEW | V44: TOYOTA YARIS ATIV CVT 1.3 | W44: 2021 | X44: 30-JUL-2021 | Y44: 27-OCT-2021 | Z44: 27-Oct-2026 | AA44: OLALHR300071282 | AB44: 5 | AC44: CTRK | AD44: DIB0032067 | AE44: 09-OCT-2021 | AF44: 2% | AG44: 2162400 | AH44: 43248 | AL44: KHI/HO/D/MO/PC COMP/C/99821/86/10/2024 | AM44: 43248 | AN44: =Table9[[#This Row],[Premium]]-Table9[[#This Row],[Tms prem]] -> 0
A45: 50 | B45: NORM | C45: 9976AP2222850010 | D45: Active | E45: T-PAK | F45: KIA MOTORS FESTIVAL CITY | G45: ARSHIA SHUJAAT | H45: Lahore | I45: 35202-2412910-6 | J45: 03024545012 | K45: 03024545012 | L45: 03024545012 | M45: H NO 192-M BLOCK SABZAZAR MULTAN RO AD NEAR MAKKAH CHOWK NEAR NEW KASHM LAHORE PK | N45: 1186052 | O45: 4891000 | P45: 64081/00009/10/2022 | Q45: 45574 | R45: 879013 | S45: 701994 | T45: NEW | V45: KIA STONIC EX+ | W45: 2022 | X45: 12-OCT-2022 | Y45: 21-OCT-2022 | Z45: 21-Oct-2025 | AA45: OLDLHR300090252 | AB45: 3 | AC45: ITFM | AD45: 8969/10/2022/ITFM | AE45: 10-OCT-2022 | AF45: 1.75% | AG45: 4157350 | AH45: 72754 | AL45: KHI/HO/D/MO/PC COMP/C/99821/94/10/2024 | AM45: 72754 | AN45: =Table9[[#This Row],[Premium]]-Table9[[#This Row],[Tms prem]] -> 0
A46: 51 | B46: NORM | C46: 9976AD1221130013 | D46: Active | E46: T-PAK | F46: PAK SUZUKI MOTOR CO LTD | G46: ALEEM MERAJ | H46: Faisalabad | I46: 33102-8497767-1 | J46: 03008820112 | K46: 03008820112, 03008820112 | L46: 03008820112 | M46: P-411 A BLOCK SUMANDRI ROAD SEHGAL CITY FAISALABAD FAISALABAD PK | N46: 635211 | O46: 1886000 | P46: 64081/00014/10/2022 | Q46: 45574 | R46: 6R250106 | S46: 1150131 | T46: NEW | V46: SUZUKI ALTO VXL AGS EURO II | W46: 2022 | X46: 23-APR-2022 | Y46: 21-OCT-2022 | Z46: 21-Oct-2025 | AA46: OLAFSD300086807 | AB46: 3 | AC46: ITFM | AD46: 8977/10/2022/ITFM | AE46: 10-OCT-2022 | AF46: 2% | AG46: 1603100 | AH46: 32062 | AL46: KHI/HO/D/MO/PC COMP/C/99821/96/10/2024 | AM46: 32062 | AN46: =Table9[[#This Row],[Premium]]-Table9[[#This Row],[Tms prem]] -> 0
A47: 52 | B47: NORM | C47: 9976AD2222730003 | D47: Active | E47: T-PAK | F47: CHANGAN BILAL AUTOMOBILES | G47: HAFIZ MUHAMMAD ADEEL-ASAAN ACCOUNT | H47: Lahore | I47: 35202-5634147-1 | K47: 03234859490 | M47: 8-C HAIDER PARK SHAD BAGH LAHORE | N47: 1220249 | O47: 3844000 | P47: 64081/00010/10/2022 | Q47: 45574 | R47: 509198 | S47: 1009958 | T47: NEW | V47: CHANGAN ALSVIN 1.5L LUMIERE | W47: 2022 | X47: 30-SEP-2022 | Y47: 21-OCT-2022 | Z47: 21-Oct-2025 | AA47: OLALHR300090203 | AB47: 3 | AC47: ITFT | AD47: 8984/10/2022/ITFM | AE47: 10-OCT-2022 | AF47: 2% | AG47: 3267400 | AH47: 65348 | AL47: KHI/HO/D/MO/PC COMP/C/99821/97/10/2024 | AM47: 65348 | AN47: =Table9[[#This Row],[Premium]]-Table9[[#This Row],[Tms prem]] -> 0
A48: 53 | B48: NORM | C48: 9976AD1221600001 | D48: Active | E48: T-PAK | F48: CHANGAN ADIL ASHRAF MOTORS | G48: MALIK MUHAMMAD IMRAN | H48: Lahore | I48: 35201-1701117-9 | J48: 03004442933 | K48: 03004442933 | L48: 03004442933 | M48: OLYMPIC TOWN ST NO 1 MIAN AMEER UD DIN PARK HARBANSPURA LAHORE PK | N48: 697539 | O48: 2219000 | P48: 64082/00015/10/2022 | Q48: 45574 | R48: 503746 | S48: 1016716 | T48: NEW | V48: CHANGAN KARVAAN PLUS | W48: 2022 | X48: 09-JUN-2022 | Y48: 21-OCT-2022 | Z48: 21-Oct-2025 | AA48: OLALHR300087953 | AB48: 3 | AC48: ITECL | AD48: 9013/10/2022 | AE48: 10-OCT-2022 | AF48: 2% | AG48: 1886150 | AH48: 37723 | AL48: KHI/HO/D/MO/PC COMP/C/99821/98/10/2024 | AM48: 37723 | AN48: =Table9[[#This Row],[Premium]]-Table9[[#This Row],[Tms prem]] -> 0
A49: 54 | B49: NORM | C49: 9976AD1221100033 | D49: Active | E49: T-PAK | F49: PAK SUZUKI MOTOR CO LTD | G49: SOHAIB AHMAD | H49: Faisalabad | I49: 33100-7852626-5 | J49: 03005706076 | K49: 03005706076, 03005706076 | L49: 0414713501 | M49: HOUSE # 18 STREET # 01 PREMIER COLO NY NAZIMABAD FAISALABAD PK | N49: 697591 | O49: 1675000 | P49: 64081/00013/10/2022 | Q49: 45574 | R49: 6R250574 | S49: 1150579 | T49: NEW | V49: SUZUKI ALTO VXR EURO-II | W49: 2022 | X49: 20-APR-2022 | Y49: 21-OCT-2022 | Z49: 21-Oct-2027 | AA49: OLAFSD300086635 | AB49: 5 | AC49: ITFM | AD49: 8978/10/2022/ITFM | AE49: 10-OCT-2022 | AF49: 2% | AG49: 1423750 | AH49: 28475 | AL49: KHI/HO/D/MO/PC COMP/C/99821/99/10/2024 | AM49: 28475 | AN49: =Table9[[#This Row],[Premium]]-Table9[[#This Row],[Tms prem]] -> 0
A50: 55 | B50: NORM | C50: 9976AP2222900004 | D50: Active | E50: T-PAK | F50: FAROOQ MOTORS | G50: SHABEER AHMED | H50: Lahore | I50: 35301-7377030-5 | K50: 03084557218 | M50: HOUSE NO 39 40 BLOCK A GEO PARK GREEN TOWN BAGRIAN LAHORE | N50: 1030344 | O50: 2100000 | P50: 64081/00011/10/2022 | Q50: 45574 | R50: 6R158628 | S50: 1058599 | T50: USD | U50: AHC-242 | V50: SUZUKI ALTO VXR EURO-II | W50: 2021 | X50: 17-OCT-2022 | Y50: 21-OCT-2022 | Z50: 21-Oct-2027 | AA50: OLULHR300090271 | AB50: 5 | AC50: ITFM | AD50: 8980/10/2022/ITFM | AE50: 10-OCT-2022 | AF50: 1.75% | AG50: 1785000 | AH50: 31238 | AL50: KHI/HO/D/MO/PC COMP/C/99821/103/10/2024 | AM50: 31238 | AN50: =Table9[[#This Row],[Premium]]-Table9[[#This Row],[Tms prem]] -> 0
A51: 56 | B51: NORM | C51: 9976AD1211960003 | D51: Active | E51: T-PAK | F51: PAK SUZUKI MOTOR CO LTD | G51: MUHAMMAD MOAZZAM | H51: Lahore | I51: 33100-8719701-3 | J51: 03336622338 | K51: 03336622338 | L51: 04235717090 | M51: 17-B AZIZ AVENUE UNIT NO 3 CANAL BA NK ROAD GULBERG V LAHORE | N51: 650068 | O51: 1335000 | P51: 2021-10-205-V01501OP0002413 | Q51: 45575 | R51: 186483 | S51: 1086250 | T51: NEW | V51: ALTO VXR EURO-II | W51: 2021 | X51: 15-JUL-2021 | Y51: 27-OCT-2021 | Z51: 27-Oct-2028 | AA51: OLALHR300070674 | AB51: 7 | AC51: ITECL | AD51: 5509/10/2021 | AE51: 09-OCT-2021 | AF51: 2% | AG51: 1068000 | AH51: 21360 | AL51: KHI/HO/D/MO/PC COMP/C/99821/108/10/2024 | AM51: 21360 | AN51: =Table9[[#This Row],[Premium]]-Table9[[#This Row],[Tms prem]] -> 0
A52: 57 | B52: NORM | C52: 9976AD1212080029 | D52: Active | E52: T-PAK | F52: PAK SUZUKI MOTOR CO LTD | G52: IKRAM HUSSAIN | H52: Lahore | I52: 35202-6342864-7 | J52: 03004456627 | K52: 03004456627 | L52: 04235118808 | M52: PLOT NO 1 BLOCK 11-B1 AL MADINA and K ASHMIR ROAD TOWNSHIP LAHORE | N52: 723469 | O52: 1521000 | P52: 2021-10-205-V01501OP0002419 | Q52: 45575 | R52: 185481 | S52: 1085473 | T52: NEW | V52: SUZUKI ALTO VXL AGS EURO II | W52: 2021 | X52: 27-JUL-2021 | Y52: 03-NOV-2021 | Z52: 03-Nov-2027 | AA52: OLALHR300071163 | AB52: 6 | AC52: CTRK | AD52: DIB0032076 | AE52: 12-OCT-2021 | AF52: 2% | AG52: 1216800 | AH52: 24336 | AL52: KHI/HO/D/MO/PC COMP/C/99821/109/10/2024 | AM52: 24336 | AN52: =Table9[[#This Row],[Premium]]-Table9[[#This Row],[Tms prem]] -> 0
A53: 58 | B53: NORM | C53: 9976AP1212880034 | D53: Active | E53: T-PAK | F53: SUBHAN MOTORS | G53: OSAMA ANWAR RAZA | H53: Gujranwala | I53: 34101-1325863-3 | J53: 03000410440 | K53: 03000410440 | L53: 03000410440 | M53: MAIN NEEAI CHOWK NEAR FRAZ CLINIC GUJRANWALA | N53: 842632 | O53: 3000000 | P53: PL-1021-1101010102-V14-D-00472 | Q53: 45575 | R53: Z557156 | S53: R4182893 | T53: USD | U53: LED-19-8930 | V53: TOYOTA COROLLA GLI | W53: 2019 | X53: 15-OCT-2021 | Y53: 21-OCT-2021 | Z53: 21-Oct-2026 | AA53: OLUGWL300074852 | AB53: 5 | AC53: CTRK | AD53: DIB0032078 | AE53: 11-OCT-2021 | AF53: 2% | AG53: 2400000 | AH53: 48000 | AL53: KHI/HO/D/MO/PC COMP/C/99821/110/10/2024 | AM53: 48000 | AN53: =Table9[[#This Row],[Premium]]-Table9[[#This Row],[Tms prem]] -> 0
A54: 59 | B54: NORM | C54: 9976AD2211720002 | D54: Active | E54: T-PAK | F54: HONDA KHAIR | G54: FAHMEEDA MUSTAFA | H54: Hyderabad | I54: 41306-0350417-0 | K54: 03003509074 | M54: HOUSE NO B-12 MUHALLAH NASEEM NAGAR PHASE 1 QASIMABAD HYDERABAD. | N54: 948523 | O54: 2467000 | P54: PL-1021-1101010102-V14-D-00473 | Q54: 45575 | R54: 51002696 | S54: 003711 | T54: NEW | V54: HONDA CITY I-VTEC M/T | W54: 2021 | X54: 21-JUN-2021 | Y54: 21-OCT-2021 | Z54: 21-Oct-2026 | AA54: OLAHYD300069447 | AB54: 5 | AC54: CTRK | AD54: DIB0032070 | AE54: 11-OCT-2021 | AF54: 2% | AG54: 1973600 | AH54: 39472 | AL54: KHI/HO/D/MO/PC COMP/C/99821/111/10/2024 | AM54: 39472 | AN54: =Table9[[#This Row],[Premium]]-Table9[[#This Row],[Tms prem]] -> 0
A55: 60 | B55: NORM | C55: 9976AP1212860021 | D55: Active | E55: T-PAK | F55: NEW S.S MOTORS | G55: ABDUL SATTAR | H55: Faisalabad | I55: 33100-8134929-7 | J55: 03007966233 | K55: 03007966233, 03007966233 | L55: 03007966233 | M55: P-66-D D BLOCK TECH TOWN SATYANA RO AD NEAR ALLIED BANK FAISALABAD PK | N55: 943743 | O55: 2100000 | P55: 56038/00023/10/2021 | Q55: 45575 | R55: PK10K167170 | S55: 10067142 | T55: USD | U55: ACK-933 | V55: SUZUKI CULTUS VXL EURO II | W55: 2021 | X55: 13-OCT-2021 | Y55: 21-OCT-2021 | Z55: 21-Oct-2026 | AA55: OLUFSD300074858 | AB55: 5 | AC55: CTRK | AD55: DIB0032075 | AE55: 12-OCT-2021 | AF55: 2% | AG55: 1680000 | AH55: 33600 | AL55: KHI/HO/D/MO/PC COMP/C/99821/112/10/2024 | AM55: 33600 | AN55: =Table9[[#This Row],[Premium]]-Table9[[#This Row],[Tms prem]] -> 0
A56: 62 | B56: NORM | C56: 9976AD2212120033 | D56: Active | E56: T-PAK | F56: TOYOTA CREEK MOTORS PVT LTD | G56: WAJAHAT NADEEM-ASAAN ACCOUNT | H56: Karachi | I56: 42101-4429760-5 | M56: FLAT # L-24 AREA AL-AZAM SQUARE LIAQUATABAD KARACHI | N56: 1134977 | O56: 2675000 | P56: 56038/00025/10/2021 | Q56: 45575 | R56: 2A38033 | S56: 7023889 | T56: NEW | V56: TOYOTA YARIS ATIV CVT 1.3 | W56: 2021 | X56: 31-JUL-2021 | Y56: 21-OCT-2021 | Z56: 21-Oct-2026 | AA56: OLAKHI300071525 | AB56: 5 | AC56: ITECL | AD56: 5496/10/2021 | AE56: 06-OCT-2021 | AF56: 2% | AG56: 2140000 | AH56: 42800 | AL56: KHI/HO/D/MO/PC COMP/C/99821/113/10/2024 | AM56: 42800 | AN56: =Table9[[#This Row],[Premium]]-Table9[[#This Row],[Tms prem]] -> 0
A57: 63 | B57: NORM | C57: 9976AD1211510027 | D57: Active | E57: T-PAK | F57: KIA MOTORS CITY OF SAINTS | G57: FARRUKH KARIM HASHMI (G) | H57: Bahawalpur | I57: 31202-0269096-5 | K57: 03226159359 | M57: H NO 135 B MODEL TOWN B PO MODEL TOWN B BAHAWAL PUR | N57: 1218534 | O57: 4322000 | P57: 56038/00024/10/2021 | Q57: 45575 | R57: G4NAMH312809 | S57: NNAQL51AZLP101971 | T57: NEW | V57: SPORTAGE ALPHA | W57: 2021 | X57: 31-MAY-2021 | Y57: 03-NOV-2021 | Z57: 03-Nov-2026 | AA57: OLABHP300068934 | AB57: 5 | AF57: 2% | AG57: 3457600 | AH57: 69152 | AL57: KHI/HO/D/MO/PC COMP/C/99821/114/10/2024 | AM57: 69152 | AN57: =Table9[[#This Row],[Premium]]-Table9[[#This Row],[Tms prem]] -> 0
A58: 64 | B58: NORM | C58: 9976AP2222790005 | D58: Active | E58: T-PAK | F58: MINI MOTORS | G58: MUHAMMAD SOHAIL AMJAD | H58: Lahore | I58: 35202-2308361-9 | J58: N/A | K58: 0300-8472409 | L58: 111-111-660 | M58: H NO-104 BLOCK AZAM GARDEN MULTAN ROAD LAHORE | N58: 492258 | O58: 3420000 | P58: 64081/00004/10/2022 | Q58: 45575 | R58: 1007710 | S58: 107724 | T58: NEW | V58: SUZUKI SWIFT GL CVT | W58: 2022 | X58: 06-OCT-2022 | Y58: 11-OCT-2022 | Z58: 11-Oct-2025 | AA58: OLDLHR300090247 | AB58: 3 | AC58: ITFM | AD58: 8942/10/2022/ITFM | AE58: 05-OCT-2022 | AF58: 1.75% | AG58: 2907000 | AH58: 50873 | AL58: KHI/HO/D/MO/PC COMP/C/99821/117/10/2024 | AM58: 50873 | AN58: =Table9[[#This Row],[Premium]]-Table9[[#This Row],[Tms prem]] -> 0
A59: 65 | B59: NORM | C59: 9976AP1222850014 | D59: Active | E59: T-PAK | F59: FAROOQ MOTORS | G59: SUFYAN JAMIL | H59: Lahore | I59: 34503-0345109-5 | K59: 03216959568 | M59: E 724/7 B MAIN STREET MEHRABAD ALI PARK BEDIAN ROAD LAHORE | N59: 828369 | O59: 3560000 | P59: 64081/00015/10/2022 | Q59: 45575 | R59: 2A41619 | S59: 7026128 | T59: USD | U59: AGP-169 | V59: TOYOTA YARIS ATIV CVT 1.3 | W59: 2021 | X59: 12-OCT-2022 | Y59: 21-OCT-2022 | Z59: 21-Oct-2025 | AA59: OLULHR300090285 | AB59: 3 | AC59: ITFM | AD59: 8992/10/2022/ITFM | AE59: 11-OCT-2022 | AF59: 1.75% | AG59: 3026000 | AH59: 52955 | AL59: KHI/HO/D/MO/PC COMP/C/99821/120/10/2024 | AM59: 52955 | AN59: =Table9[[#This Row],[Premium]]-Table9[[#This Row],[Tms prem]] -> 0
A60: 66 | B60: NORM | C60: 9976AP1222850016 | D60: Active | E60: T-PAK | F60: AL-QURASH MOTORS | G60: OMER SAJJAD | H60: Lahore | I60: 35202-4460398-1 | J60: 03214188220 | K60: 03214188220 | L60: 04237652192 | M60: H NO 316-A SHADMAN 1 LAHORE PK | N60: 1205966 | O60: 2700000 | P60: 64081/00016/10/2022 | Q60: 45575 | R60: 82861 | S60: 704960 | T60: USD | U60: ACD-342 | V60: KIA PICANTO 1.0 L A/T | W60: 2021 | X60: 12-OCT-2022 | Y60: 21-OCT-2022 | Z60: 21-Oct-2026 | AA60: OLULHR300090284 | AB60: 4 | AC60: ITFT | AD60: 8997/10/2022/ITFM | AE60: 11-OCT-2022 | AF60: 1.75% | AG60: 2295000 | AH60: 40163 | AL60: KHI/HO/D/MO/PC COMP/C/99821/122/10/2024 | AM60: 40163 | AN60: =Table9[[#This Row],[Premium]]-Table9[[#This Row],[Tms prem]] -> 0
A61: 67 | B61: NORM | C61: 9976AP2222860011 | D61: Active | E61: T-PAK | F61: MOTOR TREND | G61: MUHAMMAD AKHTAR | H61: Lahore | I61: 35201-2982306-7 | K61: 03269888818 | M61: AHATA NO.222 ST NO.12 MOHALLAH QAZI SADDAR BAZAR LAHORE CANTT | N61: 1310383 | O61: 2480000 | P61: 64081/00017/10/2022 | Q61: 45575 | R61: 501098 | S61: 1014137 | T61: USD | V61: CHANGAN KARVAAN PLUS | W61: 2022 | X61: 13-OCT-2022 | Y61: 21-OCT-2022 | Z61: 21-Oct-2027 | AA61: OLULHR300090297 | AB61: 5 | AC61: ITFM | AD61: 9000/10/2022/ITFM | AE61: 11-OCT-2022 | AF61: 1.75% | AG61: 2108000 | AH61: 36890 | AL61: KHI/HO/D/MO/PC COMP/C/99821/124/10/2024 | AM61: 36890 | AN61: =Table9[[#This Row],[Premium]]-Table9[[#This Row],[Tms prem]] -> 0
A62: 68 | B62: NORM | C62: 9976AD1211510054 | D62: Active | E62: T-PAK | F62: PAK SUZUKI MOTOR CO LTD | G62: NASREEN GULL | H62: Lahore | I62: 36402-5529606-4 | J62: 03314455579 | K62: 03314455579 | L62: 3111223377 | M62: OFFICE 152 BLOCK G-1 CANAL BANK JOH AR TOWN LAHORE | N62: 979000 | O62: 1780000 | P62: 2524/02640/00121/09/2021 | Q62: 27-SEP-2022 | R62: 182963 | S62: 10082946 | T62: NEW | V62: CULTUS VXR EURO-II | W62: 2021 | X62: 31-MAY-2021 | Y62: 03-OCT-2021 | Z62: 03-Oct-2026 | AA62: OLDLHR300069141 | AB62: 5 | AC62: CTRK | AD62: DIB0031906 | AE62: 28-SEP-2021 | AF62: 2% | AG62: 1424000 | AH62: 28480 | AL62: KHI/HO/D/MO/PC COMP/C/97805/155/09/2024 | AM62: 28480 | AN62: =Table9[[#This Row],[Premium]]-Table9[[#This Row],[Tms prem]] -> 0
A63: 69 | B63: NORM | C63: 9976AD1210500017 | D63: Active | E63: T-PAK | F63: JW SEZ (PVT) LTD | G63: FARHANA JAMIL | H63: Karachi | I63: 42201-9569904-8 | J63: 03218232717 | K63: 03218232717 | L63: 34534580 | M63: HOUSE # 30/2 21 STREET KHAYABAN E T ANZEEM DHA PH-05NEAR ZAMZAMA PARK KARACHI PK | N63: 4086750 | O63: 5449000 | P63: DIB/T/BT/33705/FSD/0921 | Q63: 22-SEP-2022 | R63: 6160137 | S63: MN107674 | T63: NEW | V63: MG HS TURBO | W63: 2021 | X63: 19-FEB-2021 | Y63: 11-NOV-2021 | Z63: 11-Nov-2026 | AA63: OLAKHI300066012 | AB63: 5 | AC63: CTRK | AD63: TDIDIB00029642 | AE63: 27-SEP-2021 | AF63: 1.75% | AG63: 4359200 | AH63: 76286 | AL63: KHI/HO/D/MO/PC COMP/C/97805/226/09/2024 | AM63: 76286 | AN63: =Table9[[#This Row],[Premium]]-Table9[[#This Row],[Tms prem]] -> 0
A64: 70 | B64: NORM | C64: 9976AD1211030014 | D64: Active | E64: T-PAK | F64: CITY SALES PVT LTD | G64: MUHAMMAD SOHAIL SARWAR | H64: Lahore | I64: 35201-6566129-3 | J64: 03218806418 | K64: 03218806418 | L64: 04235691715 | M64: F-34 1ST FLOOR , PHASE 1 DHA NEAR M ASJID CHOWK LAHORE | N64: 1590000 | O64: 2650000 | P64: 2524/02640/00077/09/2021 | Q64: 20-SEP-2022 | R64: 51588 | S64: 1003041 | T64: NEW | V64: CHANGAN ALSVIN 1.5L | W64: 2021 | X64: 13-APR-2021 | Y64: 03-OCT-2021 | Z64: 03-Oct-2026 | AA64: OLALHR300067669 | AB64: 5 | AC64: CTRK | AD64: DIB0031771 | AE64: 21-SEP-2021 | AF64: 2% | AG64: 2120000 | AH64: 42400 | AL64: KHI/HO/D/MO/PC COMP/C/97805/292/09/2024 | AM64: 42400 | AN64: =Table9[[#This Row],[Premium]]-Table9[[#This Row],[Tms prem]] -> 0
A65: 71 | B65: NORM | C65: 9976AD2211740016 | D65: Active | E65: T-PAK | F65: PAK SUZUKI MOTOR CO LTD | G65: NOOR UL MUSTAFA | H65: Lahore | I65: 35201-9192235-1 | J65: 03214505671 | K65: 03214505671 | L65: 04235123451 | M65: SECTOR C-1 BLOCK 2 TOWNSHIP LAHORE | N65: 886500 | O65: 1970000 | P65: 2021-09-205-V01501OP0002164 | Q65: 15-SEP-2022 | R65: PK10K184714 | S65: NF1AVK31H10084723 | T65: NEW | V65: SUZUKI CULTUS VXL AGS EURO II | W65: 2021 | X65: 23-JUN-2021 | Y65: 03-OCT-2021 | Z65: 03-Oct-2026 | AA65: OLALHR300069783 | AB65: 5 | AC65: CTRK | AD65: DIB0031704 | AE65: 22-SEP-2021 | AF65: 2% | AG65: 1576000 | AH65: 31520 | AL65: KHI/HO/D/MO/PC COMP/C/97805/314/09/2024 | AM65: 31520 | AN65: =Table9[[#This Row],[Premium]]-Table9[[#This Row],[Tms prem]] -> 0
A66: 72 | B66: NORM | C66: 9976AD1212230028 | D66: Active | E66: T-PAK | F66: TOYOTA PORT QASIM MOTORS | G66: SADAF AZHAR | H66: Karachi | I66: 42301-8382631-4 | J66: 03452317764 | K66: 03452317764 | L66: 03452317764 | M66: HOUSE NO. 11, 35TH STREET, PHASE VI , D.H.A KHAY-E-MUHAFIZ KARACHI PK | N66: 2469250 | O66: 2905000 | P66: 55601/00007/09/2021 | Q66: 05-SEP-2022 | R66: 2A35039 | S66: NSP151R-9513144 | T66: NEW | V66: TOYOTA YARIS ATIV X CVT 1.5 | W66: 2021 | X66: 11-AUG-2021 | Y66: 11-SEP-2021 | Z66: 11-Sep-2026 | AA66: OLAKHI300071764 | AB66: 5 | AC66: CTRK | AD66: DIB0031450 | AE66: 03-SEP-2021 | AF66: 2% | AG66: 2324000 | AH66: 46480 | AL66: KHI/HO/D/MO/PC COMP/C/97805/58/09/2024 | AM66: 46480 | AN66: =Table9[[#This Row],[Premium]]-Table9[[#This Row],[Tms prem]] -> 0
A67: 73 | B67: NORM | C67: 9976AD2211660006 | D67: Active | E67: T-PAK | F67: PAK SUZUKI MOTOR CO LTD | G67: MUHAMMAD ISMAIL | H67: Karachi | I67: 38302-1183588-1 | K67: 03007064166 | M67: PAKLINE TRANSPORT CO PLOT NO. A-459 GATE 03 QUAID E AZAM TRUCK STAND HAWKS BAY ROAD KARACHIPAKISTAN | N67: 1379000 | O67: 1970000 | P67: 2021-09-205-V01501DP0002114 | Q67: 05-SEP-2022 | R67: 180448 | S67: 10080446 | T67: NEW | V67: SUZUKI CULTUS VXL | W67: 2021 | X67: 15-JUN-2021 | Y67: 11-SEP-2021 | Z67: 11-Sep-2026 | AA67: OLAKHI300069422 | AB67: 5 | AC67: ITECL | AD67: 5393/08/20021 | AE67: 31-AUG-2021 | AF67: 2% | AG67: 1576000 | AH67: 31520 | AL67: KHI/HO/D/MO/PC COMP/C/97805/57/09/2024 | AM67: 31520 | AN67: =Table9[[#This Row],[Premium]]-Table9[[#This Row],[Tms prem]] -> 0
A68: 75 | B68: NORM | C68: 9976AP2201750002 | D68: Active | E68: T-PAK | F68: MOTOR TREND | G68: SAAD HANIF AWAN | H68: Rawalpindi | I68: 37405-9265252-3 | J68: 03225090377 | L68: 0518315100 | M68: H # 174/D-2 AFSHAN COLONY KASHMIR M ARKET RAWALPINDI PK | N68: 1127826 | O68: 2331000 | P68: 51244/00020/10/2019 | Q68: 45573 | R68: Z547520 | S68: 4173264 | U68: APT-288 | V68: TOYOTA COROLLA GLI M/T | W68: 2018 | X68: 11-OCT-2019 | Y68: 11-OCT-2019 | Z68: 11-Oct-2026 | AA68: POURWP300049691 | AB68: 7 | AC68: CTRK | AD68: DIB0027893 | AE68: 09-OCT-2019 | AF68: 2.5% | AG68: 1748250 | AH68: 43706 | AI68: 9976AP2192840002 | AJ68: CO19 Relief Principal Deferment Cases | AL68: KHI/HO/D/MO/PC COMP/C/99821/4/10/2024 | AM68: 43706 | AN68: =Table9[[#This Row],[Premium]]-Table9[[#This Row],[Tms prem]] -> 0
A69: 79 | B69: NORM | C69: 9976AP1212870028 | D69: Active | E69: T-PAK | F69: NEW S.S MOTORS | G69: MOHAMMAD SALEH SALEEM | H69: Faisalabad | I69: 33100-1333917-3 | J69: 03216638275 | K69: 03216638275, 03216638275 | L69: 03216638275 | M69: P-207ST NO 01 JHANG ROAD SAIF ABAD FAISALABAD PK | N69: 337048 | O69: 800000 | P69: 56038/00031/10/2021 | Q69: 45576 | R69: PKB722518 | S69: 01621038 | T69: USD | U69: AJK-901 | V69: SUZUKI MEHRAN VX EURO II | W69: 2018 | X69: 14-OCT-2021 | Y69: 21-OCT-2021 | Z69: 21-Oct-2026 | AA69: OLUFSD300074966 | AB69: 5 | AC69: CTRK | AD69: DIB0032092 | AE69: 13-OCT-2021 | AF69: 2% | AG69: 640000 | AH69: 12800 | AL69: KHI/HO/D/MO/PC COMP/C/99821/137/10/2024 | AM69: 12800 | AN69: =Table9[[#This Row],[Premium]]-Table9[[#This Row],[Tms prem]] -> 0
A70: 80 | B70: NORM | C70: 9976AD1211670014 | D70: Active | E70: T-PAK | F70: PAK SUZUKI MOTOR CO LTD | G70: SYED ALI JAWAD BUKHARI | H70: Lahore | I70: 61101-1962418-9 | J70: 03335168050 | K70: 03335168050 | L70: 03335168050 | M70: AL FATAH WARE HOUSE NEAR ATARI SARO BA FEROZPUR ROAD LAHORE | N70: 445127 | O70: 1655000 | P70: 2021-10-205-V01501OP0002425 | Q70: 45576 | R70: 185548 | S70: 10085561 | T70: NEW | V70: CULTUS XVR EURO-II | W70: 2021 | X70: 16-JUN-2021 | Y70: 03-NOV-2021 | Z70: 03-Nov-2028 | AA70: OLALHR300069488 | AB70: 7 | AC70: ITECL | AD70: 5517/10/2021 | AE70: 12-OCT-2021 | AF70: 2% | AG70: 1324000 | AH70: 26480 | AL70: KHI/HO/D/MO/PC COMP/C/99821/138/10/2024 | AM70: 26480 | AN70: =Table9[[#This Row],[Premium]]-Table9[[#This Row],[Tms prem]] -> 0
A71: 81 | B71: NORM | C71: 9976AD2212360016 | D71: Active | E71: T-PAK | F71: PAK SUZUKI MOTOR CO LTD | G71: SADAF IQBAL | H71: Faisalabad | I71: 33102-7329393-4 | J71: 03015229271 | K71: 03015229271, 03015229271 | L71: 03015229271 | M71: H NO P-55 BLOCK B RAHIM GARDENS ST NO 23 MAIN NAWABANWALA ROAD FAISALABAD PK | N71: 550270 | O71: 1335000 | P71: DIB/T/BT/33769/LHR/1021 | Q71: 45576 | R71: 185279 | S71: 1085231 | T71: NEW | V71: SUZUKI ALTO VXR EURO II | W71: 2021 | X71: 24-AUG-2021 | Y71: 21-OCT-2021 | Z71: 21-Oct-2026 | AA71: OLAFSD300072255 | AB71: 5 | AC71: CTRK | AD71: DIB0032035 | AE71: 12-OCT-2021 | AF71: 2% | AG71: 1068000 | AH71: 21360 | AL71: KHI/HO/D/MO/PC COMP/C/99821/139/10/2024 | AM71: 21360 | AN71: =Table9[[#This Row],[Premium]]-Table9[[#This Row],[Tms prem]] -> 0
A72: 83 | B72: NORM | C72: 9976AD1212700048 | D72: Active | E72: T-PAK | F72: SUZUKI GUJRANWALA MOTOR | G72: WAQAS IDRESS | H72: Gujranwala | I72: 35202-6801459-1 | J72: 03034633723 | K72: 03034633723 | L72: 03034633723 | M72: NEAR ZEBI MASJID KANGNI WALA MOH GR EEN TOWN GUJRANWALA PK | N72: 602993 | O72: 1335000 | P72: PL-1021-1101010102-V14-D-00475 | Q72: 45576 | R72: 187471 | S72: 1087473 | T72: NEW | V72: SUZUKI ALTO VXR EURO II | W72: 2021 | X72: 27-SEP-2021 | Y72: 27-OCT-2021 | Z72: 27-Oct-2026 | AA72: OLAGWL300074112 | AB72: 5 | AC72: CTRK | AD72: DIB0032090 | AE72: 13-OCT-2021 | AF72: 2% | AG72: 1068000 | AH72: 21360 | AL72: KHI/HO/D/MO/PC COMP/C/99821/141/10/2024 | AM72: 21360 | AN72: =Table9[[#This Row],[Premium]]-Table9[[#This Row],[Tms prem]] -> 0
A73: 84 | B73: NORM | C73: 9976AD1211800001 | D73: Active | E73: T-PAK | F73: SUZUKI SUMMIT MOTORS PVT LTD. | G73: AFTAB-ASAAN ACCOUNT | H73: Gujrat | I73: 34201-5446992-9 | K73: 03024247274 | M73: NEAR ISLAMIA SCHOOL ,OH ALI MASJID GUJRAT 0302-4247274 | N73: 632438 | O73: 1730000 | P73: 56038/00028/10/2021 | Q73: 45576 | R73: PK10B221583 | S73: PK10121719 | T73: NEW | V73: WAGONR VXL | W73: 2021 | X73: 29-JUN-2021 | Y73: 21-OCT-2021 | Z73: 21-Oct-2026 | AA73: OLAGJR300069842 | AB73: 5 | AC73: CTRK | AD73: DIB0032026 | AE73: 06-OCT-2021 | AF73: 2% | AG73: 1384000 | AH73: 27680 | AL73: KHI/HO/D/MO/PC COMP/C/99821/142/10/2024 | AM73: 27680 | AN73: =Table9[[#This Row],[Premium]]-Table9[[#This Row],[Tms prem]] -> 0
A74: 85 | B74: NORM | C74: 9976AP2212880011 | D74: Active | E74: T-PAK | F74: SIDDIQUI MOTORS | G74: ABDUL MAJID | H74: Karachi | I74: 41306-7775557-3 | J74: 03335833329 | K74: 03335833329 | L74: 02132803061 | M74: CLOUD VENTURE (PVT) LTD ROYAL CYBER SUIT NO CEASAR TOWER SHAHR E FAISA L 11TH FLOORASHA SCHOOL KARACHI | N74: 425826 | O74: 1912906 | P74: PL-1021-1101010102-V14-D-00474 | Q74: 45576 | R74: 177540 | S74: 10077561 | T74: USD | V74: SUZUKI CULTUS VXL | W74: 2021 | X74: 15-OCT-2021 | Y74: 21-OCT-2021 | Z74: 21-Oct-2025 | AA74: OLUKHI300074982 | AB74: 4 | AC74: ITECL | AD74: 5521/10/2021 | AE74: 13-OCT-2021 | AF74: 2% | AG74: 1530324.8 | AH74: 30606 | AL74: KHI/HO/D/MO/PC COMP/C/99821/143/10/2024 | AM74: 30606 | AN74: =Table9[[#This Row],[Premium]]-Table9[[#This Row],[Tms prem]] -> 0
A75: 86 | B75: NORM | C75: 9976AD1211670016 | D75: Active | E75: T-PAK | F75: SUZUKI SUMMIT MOTORS PVT LTD. | G75: NUHAMMAD NADEEM | H75: Gujranwala | I75: 34101-7885693-1 | J75: 03216408824 | K75: 03216408824 | L75: 03216408824 | M75: X BLOCK HOUSE NO 14 STREET NO 3 PRO PLES COLONY GUJRANWALA PK | N75: 950025 | O75: 1780000 | P75: TOO2/0000001084/1021/109/-0 | Q75: 45576 | R75: 185465 | S75: 10085473 | T75: NEW | V75: SUZUKI CULTUS VXR EURO II | W75: 2021 | X75: 16-JUN-2021 | Y75: 27-OCT-2021 | Z75: 27-Oct-2027 | AA75: OLAGWL300069471 | AB75: 6 | AC75: CTRK | AD75: DIB0032077 | AE75: 11-OCT-2021 | AF75: 2% | AG75: 1424000 | AH75: 28480 | AL75: KHI/HO/D/MO/PC COMP/C/99821/144/10/2024 | AM75: 28480 | AN75: =Table9[[#This Row],[Premium]]-Table9[[#This Row],[Tms prem]] -> 0
A76: 87 | B76: NORM | C76: 9976AP1212870025 | D76: Active | E76: T-PAK | F76: AL-QURASH MOTORS | G76: HAFIZ MUHAMMAD USAMA | H76: Gujranwala | I76: 34101-8608060-5 | J76: 03006323651 | K76: 03006323651 | L76: 03006323651 | M76: H NO R 3 ST NO A-1 MOH QASIM TOWN G REEN STREET RATTA ROAD GUJRANWALA PK | N76: 831393 | O76: 1850000 | P76: 01-2110-PO-MTR-PCCM-D-001391 | Q76: 45576 | R76: PK10K143032 | S76: NF1AVK31H10043014 | T76: USD | U76: ANA-383 | V76: CULTUS VXL EURO-II | W76: 2019 | X76: 14-OCT-2021 | Y76: 21-OCT-2021 | Z76: 21-Oct-2026 | AA76: OLUGWL300075012 | AB76: 5 | AC76: CTRK | AD76: DIB0032093 | AE76: 13-OCT-2021 | AF76: 2% | AG76: 1480000 | AH76: 29600 | AL76: KHI/HO/D/MO/PC COMP/C/99821/145/10/2024 | AM76: 29600 | AN76: =Table9[[#This Row],[Premium]]-Table9[[#This Row],[Tms prem]] -> 0
A77: 89 | B77: NORM | C77: 9976AD1211970015 | D77: Active | E77: T-PAK | F77: SNA MOTORS | G77: RANA ARIF IRSHAD | H77: Karachi | I77: 42501-8963872-9 | K77: 00971547075049 | M77: ROYAL CATERING CAMP NEAR AL MADINA MARKET GHAYATHI ROAD RUWAIS 73085 ABU DHABI UNITED ARAB EMIRATES | N77: 1143486 | O77: 1830000 | P77: 2524/02721/00001/10/2021 | Q77: 45576 | R77: 186887 | S77: 10086873 | T77: RDA | V77: CULTUS VXL AGS EURO-II | W77: 2021 | X77: 16-JUL-2021 | Y77: 21-OCT-2021 | Z77: 21-Oct-2028 | AA77: OLAKHI300070793 | AB77: 7 | AC77: CTRK | AD77: DIB0032038 | AE77: 11-OCT-2021 | AF77: 1.4% | AG77: 1464000 | AH77: 20496 | AL77: KHI/HO/D/MO/PC COMP/C/99821/148/10/2024 | AM77: 20496 | AN77: =Table9[[#This Row],[Premium]]-Table9[[#This Row],[Tms prem]] -> 0
A78: 90 | B78: NORM | C78: 9976AD2212570006 | D78: Active | E78: T-PAK | F78: CHANGAN YAZDANI MOTORS | G78: JAZIB ALI | H78: Karachi | I78: 42101-3349091-7 | J78: 03152038127 | K78: 03152038127, 03122608533 | L78: 02135822401 | M78: HORIZON TOWER GROUND FLOOR BLOCK-3 CLIFTON NEAR B.B.Q TONIGHT KARACHI KARACHI | N78: 1026339 | O78: 2589000 | P78: 2524/02692/00034/10/2021 | Q78: 45576 | R78: 517847 | S78: 1003396 | T78: NEW | V78: CHANGAN ALSVIN 1.5L LUMIERE | W78: 2021 | X78: 14-SEP-2021 | Y78: 21-OCT-2021 | Z78: 21-Oct-2026 | AA78: OLAKHI300073519 | AB78: 5 | AC78: CTRK | AD78: DIB0032050 | AE78: 08-OCT-2021 | AF78: 2% | AG78: 2071200 | AH78: 41424 | AL78: KHI/HO/D/MO/PC COMP/C/99821/149/10/2024 | AM78: 41424 | AN78: =Table9[[#This Row],[Premium]]-Table9[[#This Row],[Tms prem]] -> 0
A79: 91 | B79: NORM | C79: 9976AD1211650006 | D79: Active | E79: T-PAK | F79: HONDA CLASSIC | G79: DANIYAL JUNAID KHAN | H79: Islamabad | I79: 61101-8793709-7 | J79: 03018541148 | L79: 05159054643 | M79: H # 221 ST # 13 NPF SECTOR E-11/4 ISLAMABAD PK | N79: 1113706 | O79: 4077500 | P79: 56038/00029/10/2021 | Q79: 45576 | R79: 16926833 | S79: 079410 | T79: NEW | V79: CIVIC VTI ORIEL P/T | W79: 2021 | X79: 14-JUN-2021 | Y79: 21-OCT-2021 | Z79: 21-Oct-2026 | AA79: OLAISD300069503 | AB79: 5 | AC79: CTRK | AD79: DIB0032088 | AE79: 12-OCT-2021 | AF79: 1.75% | AG79: 3262000 | AH79: 57085 | AL79: KHI/HO/D/MO/PC COMP/C/99821/150/10/2024 | AM79: 57085 | AN79: =Table9[[#This Row],[Premium]]-Table9[[#This Row],[Tms prem]] -> 0
A80: 92 | B80: NORM | C80: 9976AD2212120034 | D80: Active | E80: T-PAK | F80: TOYOTA AIRPORT MOTOR | G80: ZEESHAN ALI KHAN | H80: Lahore | I80: 42201-0667472-5 | J80: NA | K80: 03028478927 | L80: 36297609 | M80: H NO 188 ST NO 28, BLOCK-Z, PHASE 3 DHA LAHORE | N80: 1544886 | O80: 2703000 | P80: 2524/02692/00037/10/2021 | Q80: 45576 | R80: 2A37984 | S80: NSP150R-7023895 | T80: NEW | V80: TOYOTA YARIS ATIV | W80: 2021 | X80: 31-JUL-2021 | Y80: 03-NOV-2021 | Z80: 03-Nov-2028 | AA80: OLALHR300071498 | AB80: 7 | AC80: ITECL | AD80: 5520/10/2021 | AE80: 12-OCT-2021 | AF80: 2% | AG80: 2162400 | AH80: 43248 | AL80: KHI/HO/D/MO/PC COMP/C/99821/151/10/2024 | AM80: 43248 | AN80: =Table9[[#This Row],[Premium]]-Table9[[#This Row],[Tms prem]] -> 0
A81: 95 | B81: NORM | C81: 9976AD2210300015 | D81: Active | E81: T-PAK | F81: AL-HAJ AUTOMOTIVE PVT LTD | G81: ASIF RAZA RIZVI | H81: Karachi | I81: 42201-0820461-1 | J81: N/A | K81: 0333-3556660 | L81: N/A | M81: KHOKHRA PAR MALIR HOUSE F-1 8-1 NEAR SHELL PETROL PUMP KARACHI | N81: 1917036 | O81: 5390000 | P81: DIB/T/BT/33830/KHI/1021 | Q81: 45576 | R81: 3UA3101408 | S81: 028145 | T81: NEW | V81: PROTON X70 PREMIUM 2WD | W81: 2021 | X81: 30-JAN-2021 | Y81: 21-OCT-2021 | Z81: 21-Oct-2026 | AA81: OLAKHI300065582 | AB81: 5 | AC81: ITECL | AD81: 5514/10/2021 | AE81: 12-OCT-2021 | AF81: 1.75% | AG81: 4312000 | AH81: 75460 | AL81: KHI/HO/D/MO/PC COMP/C/99821/153/10/2024 | AM81: 75460 | AN81: =Table9[[#This Row],[Premium]]-Table9[[#This Row],[Tms prem]] -> 0
A82: 96 | B82: NORM | C82: 9976AP1201770031 | D82: Active | E82: T-PAK | F82: KT MOTORS | G82: HURAIN JAVAID | H82: Faisalabad | I82: 38403-3380375-6 | J82: 03336504092 | K82: 03336504092, 03336504092 | L82: 0418735540 | M82: H NO P-14 ST NO 7 ARFAN SATYAN ROAD FSD FAISALABAD PK | N82: 176992 | O82: 680000 | P82: DIB/T/BT/23026/LHR/1018 | Q82: 45583 | R82: PKB659492 | S82: SB308PK01198001 | T82: USD | U82: LEB-18A-1691 | V82: SUZUKI MEHRAN VXR | W82: 2016 | X82: 22-OCT-2018 | Y82: 27-OCT-2018 | Z82: 27-Oct-2025 | AA82: POUFSD300039404 | AB82: 7 | AC82: CTRK | AD82: DIB0026071 | AE82: 22-OCT-2018 | AF82: 3.1% | AG82: 442000 | AH82: 13702 | AI82: 9976AP1182950002 | AJ82: CO19 Relief Principal Deferment Cases | AL82: KHI/HO/D/MO/PC COMP/C/99821/16/10/2024 | AM82: 13702 | AN82: =Table9[[#This Row],[Premium]]-Table9[[#This Row],[Tms prem]] -> 0
A83: 97 | B83: NORM | C83: 9976AP1201670040 | D83: Active | E83: T-PAK | F83: SNA MOTORS | G83: HASAN MAQBOOL SIDDIQUI | H83: Karachi | I83: 42000-5843792-3 | J83: 03333423478 | K83: 03333423478 | L83: 0 | M83: C- 24 KAUSER TOWN MALIR AL KHIDMAT HOSPITAL KHI KARACHI PK | N83: 193255 | O83: 840000 | P83: PL-0918-1101010102-V14-D-00658 | Q83: 45566 | R83: 745178 | S83: 1283701 | T83: NEW | U83: BNM-946 | V83: MEHRAN XVR EURO-II | W83: 2018 | X83: 18-SEP-2018 | Y83: 21-SEP-2018 | Z83: 21-Sep-2025 | AA83: PODKHI300038145 | AB83: 7 | AC83: CTRK | AD83: DIB0025799 | AE83: 18-SEP-2018 | AF83: 3.1% | AG83: 504000 | AH83: 15624 | AI83: 9976AP1182610003 | AJ83: CO19 Relief Principal Deferment Cases | AL83: KHI/HO/D/MO/PC COMP/C/99821/19/10/2024 | AM83: 15624 | AN83: =Table9[[#This Row],[Premium]]-Table9[[#This Row],[Tms prem]] -> 0
A84: 101 | B84: NORM | C84: 9976AD1212120101 | D84: Active | E84: T-PAK | F84: PAK SUZUKI MOTOR CO LTD | G84: MUHAMMAD USMAN ANWAR | H84: Faisalabad | I84: 33102-9190027-7 | J84: 03219999915 | K84: 03219999915, 03219999915 | L84: 0412615083 | M84: H NO P-5-B BLOCK B MOHALLA SHEIKH C OLONY JHANG ROAD FAISALABAD PK | N84: 350572 | O84: 1335000 | P84: DIB/T/BT/33932/LHR/1021 | Q84: 45584 | R84: 6R187761 | S84: 1087775 | T84: NEW | V84: SUZUKI ALTO VXR EURO II | W84: 2021 | X84: 31-JUL-2021 | Y84: 27-OCT-2021 | Z84: 27-Oct-2025 | AA84: OLAFSD300071420 | AB84: 4 | AC84: CTRK | AD84: TDIDIB0029720 | AE84: 20-OCT-2021 | AF84: 2% | AG84: 1068000 | AH84: 21360 | AL84: KHI/HO/D/MO/PC COMP/C/99821/22/10/2024 | AM84: 21360 | AN84: =Table9[[#This Row],[Premium]]-Table9[[#This Row],[Tms prem]] -> 0
A85: 102 | B85: NORM | C85: 9976AD1212100024 | D85: Active | E85: T-PAK | F85: PAK SUZUKI MOTOR CO LTD | G85: AMIR UN NISA BIBI | H85: Islamabad | I85: 61101-5011695-6 | J85: 03315440684 | L85: 0 | M85: H # 853 ST # 23 AREA I-14/1 NEAR NO ON POLICE STATION ISLAMABAD PK | N85: 687236 | O85: 1521000 | P85: 01-2110-PO-MTR-PCCM-D-001415 | Q85: 45582 | R85: 187864 | S85: 1087878 | T85: NEW | V85: SUZUKI ALTO VXL AGS EUROO II | W85: 2021 | X85: 29-JUL-2021 | Y85: 03-NOV-2021 | Z85: 03-Nov-2026 | AA85: OLAISD300071285 | AB85: 5 | AC85: ITECL | AD85: 5532/10/2021 | AE85: 18-OCT-2021 | AF85: 2% | AG85: 1216800 | AH85: 24336 | AL85: KHI/HO/D/MO/PC COMP/C/99821/23/10/2024 | AM85: 24336 | AN85: =Table9[[#This Row],[Premium]]-Table9[[#This Row],[Tms prem]] -> 0
A86: 103 | B86: NORM | C86: 9976AD1210580088 | D86: Active | E86: T-PAK | F86: AL-HAJ AUTOMOTIVE PVT LTD | G86: SALMAN REHMAN | H86: Lahore | I86: 35202-9367102-3 | J86: 03224983119 | K86: 03224983119 | L86: 37664388 | M86: 35 RAZA ELECTRIC MARKET BRANDRETH R OAD LAHORE | N86: 1328788 | O86: 5390000 | P86: DIB/T/BT/33836/LHR/1021 | Q86: 45576 | R86: 3101337 | S86: RMG028136 | T86: NEW | V86: PROTON X70 PREMIUM 2WD | W86: 2021 | X86: 27-FEB-2021 | Y86: 27-OCT-2021 | Z86: 27-Oct-2026 | AA86: OLALHR300066257 | AB86: 5 | AC86: ITFT | AD86: 5518/10/2021/ITFM | AE86: 12-OCT-2021 | AF86: 1.75% | AG86: 4312000 | AH86: 75460 | AL86: KHI/HO/D/MO/PC COMP/C/99821/24/10/2024 | AM86: 75460 | AN86: =Table9[[#This Row],[Premium]]-Table9[[#This Row],[Tms prem]] -> 0
A87: 104 | B87: NORM | C87: 9976AD1211970013 | D87: Active | E87: T-PAK | F87: TOYOTA RAWAL MOTORS | G87: AJAZ MIR | H87: Rawalpindi | I87: 82203-5557069-1 | K87: 00971543836661 | M87: MOVELLAH SHARJAH BUILDING NO 1543 FLAT NO 203 SHARJAH UNITED ARAB EMIRATES | N87: 1119834 | O87: 3033000 | P87: 56038/00005/10/2021 | Q87: 45566 | R87: 2A37151 | S87: R-9513819 | T87: RDA | V87: YARIS ATIV X 1.5 A/T | W87: 2021 | X87: 16-JUL-2021 | Y87: 03-OCT-2021 | Z87: 03-Oct-2026 | AA87: OLARWP300070809 | AB87: 5 | AC87: CTRK | AD87: DIB0031995 | AE87: 04-OCT-2021 | AF87: 1.4% | AG87: 2426400 | AH87: 33970 | AL87: KHI/HO/D/MO/PC COMP/C/99821/25/10/2024 | AM87: 33970 | AN87: =Table9[[#This Row],[Premium]]-Table9[[#This Row],[Tms prem]] -> 0
A88: 105 | B88: NORM | C88: 9976AD1222090002 | D88: Active | E88: T-PAK | F88: FAW APOLLO MOTORS | G88: MOHAMMED MAROOF | H88: Karachi | I88: 42301-9184914-1 | J88: 03335274274 | K88: 03335274274 | L88: 0 | M88: 136/2 STREET NO 31 KHAYABAN-E- MUHA FIZ DHA PHASE 6 NEAR CHOTA BUKHARI KARACHI PK | N88: 1419285 | O88: 6311400 | P88: 64081/00021/10/2022 | Q88: 45576 | R88: 3109867 | S88: 000511 | T88: NEW | V88: PROTON X701 PREMIUM 2WD | W88: 2022 | X88: 28-JUL-2022 | Y88: 27-OCT-2022 | Z88: 27-Oct-2025 | AA88: OLAKHI300089024 | AB88: 3 | AC88: ITFM | AD88: 8989/10/2022/ITFM | AE88: 11-OCT-2022 | AF88: 2% | AG88: 5364690 | AH88: 107294 | AL88: KHI/HO/D/MO/PC COMP/C/99821/161/10/2024 | AM88: 107294 | AN88: =Table9[[#This Row],[Premium]]-Table9[[#This Row],[Tms prem]] -> 0
A89: 107 | B89: NORM | C89: 997APD2203050096 | D89: Active | E89: T-PAK | F89: MIDWAY MOTORS | G89: MUHAMMAD SALMAN KHAN | H89: Karachi | I89: 42101-5899174-3 | J89: 03332231983 | K89: 03332231983 | L89: 0 | M89: HOUSE # F-3 BLOCK-F NORTH NAZIMABAD NEAR ZIAUDDIN HOSPITAL KARACHI PK | N89: 817794 | O89: 4300000 | P89: 52921/00149/10/2020 | Q89: 45595 | R89: 8279324 | S89: NKE165-7155598 | T89: RCN | V89: COROLLA AXIO | W89: 2017 | X89: 31-OCT-2020 | Y89: 03-NOV-2020 | Z89: 03-Nov-2025 | AA89: POUKHI300059871 | AB89: 5 | AC89: CTRK | AD89: DIB0028984 | AE89: 31-OCT-2020 | AF89: 2% | AG89: 3225000 | AH89: 64500 | AL89: KHI/HO/D/MO/PC COMP/C/99821/27/10/2024 | AM89: 64500 | AN89: =Table9[[#This Row],[Premium]]-Table9[[#This Row],[Tms prem]] -> 0
A90: 108 | B90: NORM | C90: 9976AD1210490005 | D90: Active | E90: T-PAK | F90: CHANGAN ADIL ASHRAF MOTORS | G90: BILAL ARIF | H90: Lahore | I90: 35202-5449282-3 | J90: 03215228417 | K90: 03215228417 | L90: 04237658417 | M90: KICK SHOES SULTAN CENTER MOTI BAZAR LAHORE | N90: 413402 | O90: 1554000 | P90: 56036/00033/10/2021 | Q90: 45577 | R90: 505912 | S90: 1009656 | T90: NEW | V90: CHANGAN KARVAAN N PLUS | W90: 2021 | X90: 18-FEB-2021 | Y90: 03-NOV-2021 | Z90: 03-Nov-2026 | AA90: OLALHR300065940 | AB90: 5 | AC90: CTRK | AD90: DIB0032111 | AE90: 14-OCT-2021 | AF90: 2% | AG90: 1243200 | AH90: 24864 | AL90: KHI/HO/D/MO/PC COMP/C/99821/162/10/2024 | AM90: 24864 | AN90: =Table9[[#This Row],[Premium]]-Table9[[#This Row],[Tms prem]] -> 0
A91: 109 | B91: NORM | C91: 997APD2203050095 | D91: Active | E91: T-PAK | F91: SUBHAN MOTORS | G91: HAFIZ ALI SALEEM | H91: Gujranwala | I91: 34101-9535622-1 | J91: 03456254666 | K91: 03456254666 | L91: 03456254666 | M91: SIALKOT ROAD SARFRAZ TOWN BUTTRANWA LI GUJRANWALA | N91: 643455 | O91: 2900000 | P91: 01-2010-PO-MTR-PCCM-D-001963 | Q91: 45595 | R91: 13506930 | S91: R006941 | T91: NEW | U91: AHH-961 | V91: HONDA BRV IVTEC | W91: 2018 | X91: 31-OCT-2020 | Y91: 03-NOV-2020 | Z91: 03-Nov-2025 | AA91: PODGWL300059888 | AB91: 5 | AC91: ITFM | AD91: 3421/10/2020/ITFM | AE91: 31-OCT-2020 | AF91: 2% | AG91: 2175000 | AH91: 43500 | AL91: KHI/HO/D/MO/PC COMP/C/99821/28/10/2024 | AM91: 43500 | AN91: =Table9[[#This Row],[Premium]]-Table9[[#This Row],[Tms prem]] -> 0
A92: 110 | B92: NORM | C92: 9976AD2211810022 | D92: Active | E92: T-PAK | F92: PAK SUZUKI MOTOR CO LTD | G92: NAEEM QADIR | H92: Faisalabad | I92: 33100-0770584-1 | J92: 03237001165 | K92: 03237001165, 03237001165 | L92: 03237001165 | M92: H NO 41 NAI ABADI 248 RB SAMUNDRI R OAD NEAR DALOWAL CAMP STOP BISMILLA FAISALABAD PK | N92: 609825 | O92: 1655000 | P92: 2021/10/CLFTTPCDP01043 | Q92: 45577 | R92: 185825 | S92: 10086039 | T92: NEW | V92: CULTUS VXR EURO II | W92: 2021 | X92: 30-JUN-2021 | Y92: 03-NOV-2021 | Z92: 03-Nov-2026 | AA92: OLAFSD300070193 | AB92: 5 | AC92: CTRK | AD92: DIB0031884 | AE92: 13-OCT-2021 | AF92: 2% | AG92: 1324000 | AH92: 26480 | AL92: KHI/HO/D/MO/PC COMP/C/99821/164/10/2024 | AM92: 26480 | AN92: =Table9[[#This Row],[Premium]]-Table9[[#This Row],[Tms prem]] -> 0
A93: 111 | B93: NORM | C93: 9976AD2211540055 | D93: Active | E93: T-PAK | F93: CHANGAN GUL MOTORS | G93: ABDUL RAZZAQ | H93: Karachi | I93: 42501-9335631-9 | J93: 03062535902 | K93: 03062535902 | L93: 34830869 | M93: HOUSE # E-122 MOHALLA GULFISHAN SOC IETY MALIR HALT NEAR JAMA MASJID GH KARACHI PK | N93: 646838 | O93: 1554000 | P93: 2021-10-205-V01501DP0002429 | Q93: 45577 | R93: JL466Q9M69U505663 | S93: NKMAAB3D1M1009754 | T93: NEW | V93: CHANGAN KRAVAAN PLUS | W93: 2021 | X93: 03-JUN-2021 | Y93: 21-OCT-2021 | Z93: 21-Oct-2026 | AA93: OLAKHI300069283 | AB93: 5 | AC93: CTRK | AD93: DIB0032082 | AE93: 12-OCT-2021 | AF93: 2% | AG93: 1243200 | AH93: 24864 | AL93: KHI/HO/D/MO/PC COMP/C/99821/165/10/2024 | AM93: 24864 | AN93: =Table9[[#This Row],[Premium]]-Table9[[#This Row],[Tms prem]] -> 0
A94: 112 | B94: NORM | C94: 997APD1203050101 | D94: Active | E94: T-PAK | F94: AL-QURASH MOTORS | G94: FATIMA IDREES | H94: Lahore | I94: 35201-4004648-8 | J94: 03334812152 | K94: 03334812152 | L94: 03334812152 | M94: MAIN OFFICE COMPLEX BLOCK A DHA PHA SE VI LAHORE | N94: 920711 | O94: 2200000 | P94: 52921/00150/10/2020 | Q94: 45595 | R94: 1KR-1799687 | S94: KSP130-2201255 | T94: RCN | V94: VITZ | W94: 2017 | X94: 31-OCT-2020 | Y94: 03-NOV-2020 | Z94: 03-Nov-2027 | AA94: POULHR300059721 | AB94: 7 | AC94: ITFM | AD94: 3431/10/2020/ITFM | AE94: 31-OCT-2020 | AF94: 2% | AG94: 1650000 | AH94: 33000 | AL94: KHI/HO/D/MO/PC COMP/C/99821/29/10/2024 | AM94: 33000 | AN94: =Table9[[#This Row],[Premium]]-Table9[[#This Row],[Tms prem]] -> 0
A95: 113 | B95: NORM | C95: 997APD1203050152 | D95: Active | E95: T-PAK | F95: MINI MOTORS | G95: NAVEED SHAHZAD | H95: Lahore | I95: 35202-2985358-3 | J95: 03334597198 | K95: 03334597198 | L95: 03334597198 | M95: HOUSE NO 12 STREET NO 6-B NEW ABADI LAJPAT ROAD SHAHDARA LAHORE PK | N95: 435198 | O95: 1730000 | P95: 52921/00155/10/2020 | Q95: 45595 | R95: 207102 | S95: 10107102 | T95: NEW | V95: WAGON R VXL | W95: 2020 | X95: 31-OCT-2020 | Y95: 03-NOV-2020 | Z95: 03-Nov-2025 | AA95: PODLHR300059947 | AB95: 5 | AC95: ITFM | AD95: 3456/10/2020/ITFM | AE95: 31-OCT-2020 | AF95: 2% | AG95: 1297500 | AH95: 25950 | AL95: KHI/HO/D/MO/PC COMP/C/99821/30/10/2024 | AM95: 25950 | AN95: =Table9[[#This Row],[Premium]]-Table9[[#This Row],[Tms prem]] -> 0
A96: 114 | B96: NORM | C96: 997APD2203050092 | D96: Active | E96: T-PAK | F96: AL-QURASH MOTORS | G96: SOBIA JAWAD | H96: Sialkot | I96: 34603-2107042-4 | J96: 03216132767 | K96: 03216132767 | L96: 03216132767 | M96: SAID PUR ROAD THE CITY SCHOOL SIALKOT | N96: 432675 | O96: 1950000 | P96: 2020/10/CLFTTPCDP00678 | Q96: 45595 | R96: 1KR1486050 | S96: KSP1302118788 | T96: RCN | U96: LEB-18-3314 | V96: VITZ | W96: 2014 | X96: 31-OCT-2020 | Y96: 03-NOV-2020 | Z96: 03-Nov-2025 | AA96: POUSKT300059889 | AB96: 5 | AC96: ITFM | AD96: 3439/10/2020/ITFM | AE96: 31-OCT-2020 | AF96: 2% | AG96: 1462500 | AH96: 29250 | AL96: KHI/HO/D/MO/PC COMP/C/99821/36/10/2024 | AM96: 29250 | AN96: =Table9[[#This Row],[Premium]]-Table9[[#This Row],[Tms prem]] -> 0
A97: 115 | B97: NORM | C97: 997APD2203050087 | D97: Active | E97: T-PAK | F97: SUZUKI RACECOURSE MOTORS | G97: MONA LIZA | H97: Rawalpindi | I97: 54400-6008594-4 | J97: 03314659988 | L97: 0518312156 | M97: UNIVERSAL GIRLS HOSTEL, 14/13 PARK AVENUE PESHAWAR | N97: 687434 | O97: 1605000 | P97: 2524/02150/00166/10/2020 | Q97: 45595 | R97: 206148 | S97: 10106128 | T97: NEW | V97: WAGON R VXR | W97: 2020 | X97: 31-OCT-2020 | Y97: 03-NOV-2020 | Z97: 03-Nov-2027 | AA97: PODRWP300059907 | AB97: 7 | AC97: ITFM | AD97: 3437/10/2020/ITFM | AE97: 31-OCT-2020 | AF97: 2% | AG97: 1203750 | AH97: 24075 | AL97: KHI/HO/D/MO/PC COMP/C/99821/38/10/2024 | AM97: 24075 | AN97: =Table9[[#This Row],[Premium]]-Table9[[#This Row],[Tms prem]] -> 0
A98: 116 | B98: NORM | C98: 9976AP1222870002 | D98: Active | E98: T-PAK | F98: CAR DEALS | G98: HAMMAD KHALID | H98: Karachi | I98: 42101-8642987-9 | J98: 03332085028 | K98: 03332085028 | L98: 0 | M98: L- 497 1ST FLOOR SEC 5-C /2 NORTH K HI ROSE APPARTMENT KARACHI PK | N98: 881781 | O98: 1600000 | P98: 64081/00025/10/2022 | Q98: 45577 | R98: 3602856W | S98: 02520 | T98: USD | U98: BUJ-102 | V98: PRINCE PEARL | W98: 2021 | X98: 14-OCT-2022 | Y98: 21-OCT-2022 | Z98: 21-Oct-2027 | AA98: OLUKHI300090324 | AB98: 5 | AC98: ITFT | AD98: 9019/10/2022/ITFM | AE98: 13-OCT-2022 | AF98: 1.75% | AG98: 1360000 | AH98: 23800 | AL98: KHI/HO/D/MO/PC COMP/C/99821/169/10/2024 | AM98: 23800 | AN98: =Table9[[#This Row],[Premium]]-Table9[[#This Row],[Tms prem]] -> 0
A99: 117 | B99: NORM | C99: 9976AP1222870004 | D99: Active | E99: T-PAK | F99: FAROOQ MOTORS | G99: SALMAN MUNIR | H99: Lahore | I99: 35202-3145992-9 | J99: 03086563617 | K99: 03086563617 | L99: 03086563617 | M99: H NO 106-A WEST WOOD COLONY RAIWIND ROAD LAHORE PK | N99: 1119725 | O99: 2100000 | P99: 64081/00024/10/2022 | Q99: 45577 | R99: 6R218730 | S99: 1118695 | T99: USD | U99: ALS-688 | V99: SUZUKI ALTO VXR EURO-II | W99: 2022 | X99: 14-OCT-2022 | Y99: 21-OCT-2022 | Z99: 21-Oct-2027 | AA99: OLULHR300090332 | AB99: 5 | AC99: ITFT | AD99: 9023/10/2022/ITFM | AE99: 14-OCT-2022 | AF99: 1.75% | AG99: 1785000 | AH99: 31238 | AL99: KHI/HO/D/MO/PC COMP/C/99821/170/10/2024 | AM99: 31238 | AN99: =Table9[[#This Row],[Premium]]-Table9[[#This Row],[Tms prem]] -> 0
A100: 118 | B100: NORM | C100: 997APD1183040029 | D100: Active | E100: T-PAK | F100: HONDA DRIVE IN | G100: SALMAN BARI | H100: Karachi | I100: 42201-8067627-5 | J100: 34984547 | K100: 03222244408, 03222244408 | L100: 03222244408 | M100: MAYMAR PLAZA L-4/lll BLOCK-1 2ND FL OOR MUHALLA GULSHAN-E-IQBAL NEAR IQ KARACHI PK | N100: 380459 | O100: 1883000 | P100: 49889/00149/10/2018 | Q100: 45595 | R100: 7519825 | S100: 235430 | T100: NEW | U100: BNV-654 | V100: HONDA CITY IVTEC | W100: 2018 | X100: 31-OCT-2018 | Y100: 03-NOV-2018 | Z100: 03-Nov-2025 | AA100: PODKHI300039654 | AB100: 7 | AC100: FSPT | AD100: 16734/10/2018/SPD | AE100: 31-OCT-2018 | AF100: 3.1% | AG100: 1223950 | AH100: 37942 | AL100: KHI/HO/D/MO/PC COMP/C/99821/40/10/2024 | AM100: 37942 | AN100: =Table9[[#This Row],[Premium]]-Table9[[#This Row],[Tms prem]] -> 0
...

Sheet working
A1: POLICY NO. | B1: Assorted_code | D1: Premium | E1: 29Nov240034
A2: KHI/HO/D/MO/PC COMP/C/99821/2/10/2024 | B2: =VLOOKUP(A2,policy!B:C,2,0) -> 070000167978 | C2: 46928 | D2: =ROUND(C2,0) -> 46928 | E2: 29Nov240034 | F2: ="insert into ins_premium_det (premium_rcv_code,assorted_code, rec_amount,premium_rcv_detail_code,remaining_amt, payrec, mode_code,coinsurance_code,class_cd,it_remarks) values" -> insert into ins_premium_det (premium_rcv_code,assorted_code, rec_amount,premium_rcv_detail_code,remaining_amt, payrec, mode_code,coinsurance_code,class_cd,it_remarks) values | G2: ="('"&E2&"','"&B2&"','"&D2&"',(select max(to_number(i.premium_rcv_detail_code))+1 from ins_premium_det i),'"&D2&"','"&D2&"','02', '11000003','00','Request by Mr. Reheel Malik 02-Dec-2024');" -> ('29Nov240034','070000167978','46928',(select max(to_number(i.premium_rcv_detail_code))+1 from ins_premium_det i),'46928','46928','02', '11000003','00','Request by Mr. Reheel Malik 02-Dec-2024'); | H2: =F2&G2 -> insert into ins_premium_det (premium_rcv_code,assorted_code, rec_amount,premium_rcv_detail_code,remaining_amt, payrec, mode_code,coinsurance_code,class_cd,it_remarks) values('29Nov240034','070000167978','46928',(select max(to_number(i.premium_rcv_detail_code))+1 from ins_premium_det i),'46928','46928','02', '11000003','00','Request by Mr. Reheel Malik 02-Dec-2024');
A3: KHI/HO/D/MO/PC COMP/C/99821/5/10/2024 | B3: =VLOOKUP(A3,policy!B:C,2,0) -> 070000167981 | C3: 52830 | D3: =ROUND(C3,0) -> 52830 | E3: 29Nov240034 | F3: ="insert into ins_premium_det (premium_rcv_code,assorted_code, rec_amount,premium_rcv_detail_code,remaining_amt, payrec, mode_code,coinsurance_code,class_cd,it_remarks) values" -> insert into ins_premium_det (premium_rcv_code,assorted_code, rec_amount,premium_rcv_detail_code,remaining_amt, payrec, mode_code,coinsurance_code,class_cd,it_remarks) values | G3: ="('"&E3&"','"&B3&"','"&D3&"',(select max(to_number(i.premium_rcv_detail_code))+1 from ins_premium_det i),'"&D3&"','"&D3&"','02', '11000003','00','Request by Mr. Reheel Malik 02-Dec-2024');" -> ('29Nov240034','070000167981','52830',(select max(to_number(i.premium_rcv_detail_code))+1 from ins_premium_det i),'52830','52830','02', '11000003','00','Request by Mr. Reheel Malik 02-Dec-2024'); | H3: =F3&G3 -> insert into ins_premium_det (premium_rcv_code,assorted_code, rec_amount,premium_rcv_detail_code,remaining_amt, payrec, mode_code,coinsurance_code,class_cd,it_remarks) values('29Nov240034','070000167981','52830',(select max(to_number(i.premium_rcv_detail_code))+1 from ins_premium_det i),'52830','52830','02', '11000003','00','Request by Mr. Reheel Malik 02-Dec-2024');
A4: KHI/HO/D/MO/PC COMP/C/99821/6/10/2024 | B4: =VLOOKUP(A4,policy!B:C,2,0) -> 070000167982 | C4: 24336 | D4: =ROUND(C4,0) -> 24336 | E4: 29Nov240034 | F4: ="insert into ins_premium_det (premium_rcv_code,assorted_code, rec_amount,premium_rcv_detail_code,remaining_amt, payrec, mode_code,coinsurance_code,class_cd,it_remarks) values" -> insert into ins_premium_det (premium_rcv_code,assorted_code, rec_amount,premium_rcv_detail_code,remaining_amt, payrec, mode_code,coinsurance_code,class_cd,it_remarks) values | G4: ="('"&E4&"','"&B4&"','"&D4&"',(select max(to_number(i.premium_rcv_detail_code))+1 from ins_premium_det i),'"&D4&"','"&D4&"','02', '11000003','00','Request by Mr. Reheel Malik 02-Dec-2024');" -> ('29Nov240034','070000167982','24336',(select max(to_number(i.premium_rcv_detail_code))+1 from ins_premium_det i),'24336','24336','02', '11000003','00','Request by Mr. Reheel Malik 02-Dec-2024'); | H4: =F4&G4 -> insert into ins_premium_det (premium_rcv_code,assorted_code, rec_amount,premium_rcv_detail_code,remaining_amt, payrec, mode_code,coinsurance_code,class_cd,it_remarks) values('29Nov240034','070000167982','24336',(select max(to_number(i.premium_rcv_detail_code))+1 from ins_premium_det i),'24336','24336','02', '11000003','00','Request by Mr. Reheel Malik 02-Dec-2024');
A5: KHI/HO/D/MO/PC COMP/C/99821/7/10/2024 | B5: =VLOOKUP(A5,policy!B:C,2,0) -> 070000167983 | C5: 24336 | D5: =ROUND(C5,0) -> 24336 | E5: 29Nov240034 | F5: ="insert into ins_premium_det (premium_rcv_code,assorted_code, rec_amount,premium_rcv_detail_code,remaining_amt, payrec, mode_code,coinsurance_code,class_cd,it_remarks) values" -> insert into ins_premium_det (premium_rcv_code,assorted_code, rec_amount,premium_rcv_detail_code,remaining_amt, payrec, mode_code,coinsurance_code,class_cd,it_remarks) values | G5: ="('"&E5&"','"&B5&"','"&D5&"',(select max(to_number(i.premium_rcv_detail_code))+1 from ins_premium_det i),'"&D5&"','"&D5&"','02', '11000003','00','Request by Mr. Reheel Malik 02-Dec-2024');" -> ('29Nov240034','070000167983','24336',(select max(to_number(i.premium_rcv_detail_code))+1 from ins_premium_det i),'24336','24336','02', '11000003','00','Request by Mr. Reheel Malik 02-Dec-2024'); | H5: =F5&G5 -> insert into ins_premium_det (premium_rcv_code,assorted_code, rec_amount,premium_rcv_detail_code,remaining_amt, payrec, mode_code,coinsurance_code,class_cd,it_remarks) values('29Nov240034','070000167983','24336',(select max(to_number(i.premium_rcv_detail_code))+1 from ins_premium_det i),'24336','24336','02', '11000003','00','Request by Mr. Reheel Malik 02-Dec-2024');
A6: KHI/HO/D/MO/PC COMP/C/99821/8/10/2024 | B6: =VLOOKUP(A6,policy!B:C,2,0) -> 070000167984 | C6: 23840 | D6: =ROUND(C6,0) -> 23840 | E6: 29Nov240034 | F6: ="insert into ins_premium_det (premium_rcv_code,assorted_code, rec_amount,premium_rcv_detail_code,remaining_amt, payrec, mode_code,coinsurance_code,class_cd,it_remarks) values" -> insert into ins_premium_det (premium_rcv_code,assorted_code, rec_amount,premium_rcv_detail_code,remaining_amt, payrec, mode_code,coinsurance_code,class_cd,it_remarks) values | G6: ="('"&E6&"','"&B6&"','"&D6&"',(select max(to_number(i.premium_rcv_detail_code))+1 from ins_premium_det i),'"&D6&"','"&D6&"','02', '11000003','00','Request by Mr. Reheel Malik 02-Dec-2024');" -> ('29Nov240034','070000167984','23840',(select max(to_number(i.premium_rcv_detail_code))+1 from ins_premium_det i),'23840','23840','02', '11000003','00','Request by Mr. Reheel Malik 02-Dec-2024'); | H6: =F6&G6 -> insert into ins_premium_det (premium_rcv_code,assorted_code, rec_amount,premium_rcv_detail_code,remaining_amt, payrec, mode_code,coinsurance_code,class_cd,it_remarks) values('29Nov240034','070000167984','23840',(select max(to_number(i.premium_rcv_detail_code))+1 from ins_premium_det i),'23840','23840','02', '11000003','00','Request by Mr. Reheel Malik 02-Dec-2024');
A7: KHI/HO/D/MO/PC COMP/C/99821/9/10/2024 | B7: =VLOOKUP(A7,policy!B:C,2,0) -> 070000167985 | C7: 26240 | D7: =ROUND(C7,0) -> 26240 | E7: 29Nov240034 | F7: ="insert into ins_premium_det (premium_rcv_code,assorted_code, rec_amount,premium_rcv_detail_code,remaining_amt, payrec, mode_code,coinsurance_code,class_cd,it_remarks) values" -> insert into ins_premium_det (premium_rcv_code,assorted_code, rec_amount,premium_rcv_detail_code,remaining_amt, payrec, mode_code,coinsurance_code,class_cd,it_remarks) values | G7: ="('"&E7&"','"&B7&"','"&D7&"',(select max(to_number(i.premium_rcv_detail_code))+1 from ins_premium_det i),'"&D7&"','"&D7&"','02', '11000003','00','Request by Mr. Reheel Malik 02-Dec-2024');" -> ('29Nov240034','070000167985','26240',(select max(to_number(i.premium_rcv_detail_code))+1 from ins_premium_det i),'26240','26240','02', '11000003','00','Request by Mr. Reheel Malik 02-Dec-2024'); | H7: =F7&G7 -> insert into ins_premium_det (premium_rcv_code,assorted_code, rec_amount,premium_rcv_detail_code,remaining_amt, payrec, mode_code,coinsurance_code,class_cd,it_remarks) values('29Nov240034','070000167985','26240',(select max(to_number(i.premium_rcv_detail_code))+1 from ins_premium_det i),'26240','26240','02', '11000003','00','Request by Mr. Reheel Malik 02-Dec-2024');
A8: KHI/HO/D/MO/PC COMP/C/99821/10/10/2024 | B8: =VLOOKUP(A8,policy!B:C,2,0) -> 070000167986 | C8: 67410 | D8: =ROUND(C8,0) -> 67410 | E8: 29Nov240034 | F8: ="insert into ins_premium_det (premium_rcv_code,assorted_code, rec_amount,premium_rcv_detail_code,remaining_amt, payrec, mode_code,coinsurance_code,class_cd,it_remarks) values" -> insert into ins_premium_det (premium_rcv_code,assorted_code, rec_amount,premium_rcv_detail_code,remaining_amt, payrec, mode_code,coinsurance_code,class_cd,it_remarks) values | G8: ="('"&E8&"','"&B8&"','"&D8&"',(select max(to_number(i.premium_rcv_detail_code))+1 from ins_premium_det i),'"&D8&"','"&D8&"','02', '11000003','00','Request by Mr. Reheel Malik 02-Dec-2024');" -> ('29Nov240034','070000167986','67410',(select max(to_number(i.premium_rcv_detail_code))+1 from ins_premium_det i),'67410','67410','02', '11000003','00','Request by Mr. Reheel Malik 02-Dec-2024'); | H8: =F8&G8 -> insert into ins_premium_det (premium_rcv_code,assorted_code, rec_amount,premium_rcv_detail_code,remaining_amt, payrec, mode_code,coinsurance_code,class_cd,it_remarks) values('29Nov240034','070000167986','67410',(select max(to_number(i.premium_rcv_detail_code))+1 from ins_premium_det i),'67410','67410','02', '11000003','00','Request by Mr. Reheel Malik 02-Dec-2024');
A9: KHI/HO/D/MO/PC COMP/C/99821/11/10/2024 | B9: =VLOOKUP(A9,policy!B:C,2,0) -> 070000167987 | C9: 74242 | D9: =ROUND(C9,0) -> 74242 | E9: 29Nov240034 | F9: ="insert into ins_premium_det (premium_rcv_code,assorted_code, rec_amount,premium_rcv_detail_code,remaining_amt, payrec, mode_code,coinsurance_code,class_cd,it_remarks) values" -> insert into ins_premium_det (premium_rcv_code,assorted_code, rec_amount,premium_rcv_detail_code,remaining_amt, payrec, mode_code,coinsurance_code,class_cd,it_remarks) values | G9: ="('"&E9&"','"&B9&"','"&D9&"',(select max(to_number(i.premium_rcv_detail_code))+1 from ins_premium_det i),'"&D9&"','"&D9&"','02', '11000003','00','Request by Mr. Reheel Malik 02-Dec-2024');" -> ('29Nov240034','070000167987','74242',(select max(to_number(i.premium_rcv_detail_code))+1 from ins_premium_det i),'74242','74242','02', '11000003','00','Request by Mr. Reheel Malik 02-Dec-2024'); | H9: =F9&G9 -> insert into ins_premium_det (premium_rcv_code,assorted_code, rec_amount,premium_rcv_detail_code,remaining_amt, payrec, mode_code,coinsurance_code,class_cd,it_remarks) values('29Nov240034','070000167987','74242',(select max(to_number(i.premium_rcv_detail_code))+1 from ins_premium_det i),'74242','74242','02', '11000003','00','Request by Mr. Reheel Malik 02-Dec-2024');
A10: KHI/HO/D/MO/PC COMP/C/99821/12/10/2024 | B10: =VLOOKUP(A10,policy!B:C,2,0) -> 070000167988 | C10: 22400 | D10: =ROUND(C10,0) -> 22400 | E10: 29Nov240034 | F10: ="insert into ins_premium_det (premium_rcv_code,assorted_code, rec_amount,premium_rcv_detail_code,remaining_amt, payrec, mode_code,coinsurance_code,class_cd,it_remarks) values" -> insert into ins_premium_det (premium_rcv_code,assorted_code, rec_amount,premium_rcv_detail_code,remaining_amt, payrec, mode_code,coinsurance_code,class_cd,it_remarks) values | G10: ="('"&E10&"','"&B10&"','"&D10&"',(select max(to_number(i.premium_rcv_detail_code))+1 from ins_premium_det i),'"&D10&"','"&D10&"','02', '11000003','00','Request by Mr. Reheel Malik 02-Dec-2024');" -> ('29Nov240034','070000167988','22400',(select max(to_number(i.premium_rcv_detail_code))+1 from ins_premium_det i),'22400','22400','02', '11000003','00','Request by Mr. Reheel Malik 02-Dec-2024'); | H10: =F10&G10 -> insert into ins_premium_det (premium_rcv_code,assorted_code, rec_amount,premium_rcv_detail_code,remaining_amt, payrec, mode_code,coinsurance_code,class_cd,it_remarks) values('29Nov240034','070000167988','22400',(select max(to_number(i.premium_rcv_detail_code))+1 from ins_premium_det i),'22400','22400','02', '11000003','00','Request by Mr. Reheel Malik 02-Dec-2024');
A11: KHI/HO/D/MO/PC COMP/C/99821/13/10/2024 | B11: =VLOOKUP(A11,policy!B:C,2,0) -> 070000167989 | C11: 25760 | D11: =ROUND(C11,0) -> 25760 | E11: 29Nov240034 | F11: ="insert into ins_premium_det (premium_rcv_code,assorted_code, rec_amount,premium_rcv_detail_code,remaining_amt, payrec, mode_code,coinsurance_code,class_cd,it_remarks) values" -> insert into ins_premium_det (premium_rcv_code,assorted_code, rec_amount,premium_rcv_detail_code,remaining_amt, payrec, mode_code,coinsurance_code,class_cd,it_remarks) values | G11: ="('"&E11&"','"&B11&"','"&D11&"',(select max(to_number(i.premium_rcv_detail_code))+1 from ins_premium_det i),'"&D11&"','"&D11&"','02', '11000003','00','Request by Mr. Reheel Malik 02-Dec-2024');" -> ('29Nov240034','070000167989','25760',(select max(to_number(i.premium_rcv_detail_code))+1 from ins_premium_det i),'25760','25760','02', '11000003','00','Request by Mr. Reheel Malik 02-Dec-2024'); | H11: =F11&G11 -> insert into ins_premium_det (premium_rcv_code,assorted_code, rec_amount,premium_rcv_detail_code,remaining_amt, payrec, mode_code,coinsurance_code,class_cd,it_remarks) values('29Nov240034','070000167989','25760',(select max(to_number(i.premium_rcv_detail_code))+1 from ins_premium_det i),'25760','25760','02', '11000003','00','Request by Mr. Reheel Malik 02-Dec-2024');
A12: KHI/HO/D/MO/PC COMP/C/99821/14/10/2024 | B12: =VLOOKUP(A12,policy!B:C,2,0) -> 070000167990 | C12: 24336 | D12: =ROUND(C12,0) -> 24336 | E12: 29Nov240034 | F12: ="insert into ins_premium_det (premium_rcv_code,assorted_code, rec_amount,premium_rcv_detail_code,remaining_amt, payrec, mode_code,coinsurance_code,class_cd,it_remarks) values" -> insert into ins_premium_det (premium_rcv_code,assorted_code, rec_amount,premium_rcv_detail_code,remaining_amt, payrec, mode_code,coinsurance_code,class_cd,it_remarks) values | G12: ="('"&E12&"','"&B12&"','"&D12&"',(select max(to_number(i.premium_rcv_detail_code))+1 from ins_premium_det i),'"&D12&"','"&D12&"','02', '11000003','00','Request by Mr. Reheel Malik 02-Dec-2024');" -> ('29Nov240034','070000167990','24336',(select max(to_number(i.premium_rcv_detail_code))+1 from ins_premium_det i),'24336','24336','02', '11000003','00','Request by Mr. Reheel Malik 02-Dec-2024'); | H12: =F12&G12 -> insert into ins_premium_det (premium_rcv_code,assorted_code, rec_amount,premium_rcv_detail_code,remaining_amt, payrec, mode_code,coinsurance_code,class_cd,it_remarks) values('29Nov240034','070000167990','24336',(select max(to_number(i.premium_rcv_detail_code))+1 from ins_premium_det i),'24336','24336','02', '11000003','00','Request by Mr. Reheel Malik 02-Dec-2024');
A13: KHI/HO/D/MO/PC COMP/C/99821/15/10/2024 | B13: =VLOOKUP(A13,policy!B:C,2,0) -> 070000167991 | C13: 25760 | D13: =ROUND(C13,0) -> 25760 | E13: 29Nov240034 | F13: ="insert into ins_premium_det (premium_rcv_code,assorted_code, rec_amount,premium_rcv_detail_code,remaining_amt, payrec, mode_code,coinsurance_code,class_cd,it_remarks) values" -> insert into ins_premium_det (premium_rcv_code,assorted_code, rec_amount,premium_rcv_detail_code,remaining_amt, payrec, mode_code,coinsurance_code,class_cd,it_remarks) values | G13: ="('"&E13&"','"&B13&"','"&D13&"',(select max(to_number(i.premium_rcv_detail_code))+1 from ins_premium_det i),'"&D13&"','"&D13&"','02', '11000003','00','Request by Mr. Reheel Malik 02-Dec-2024');" -> ('29Nov240034','070000167991','25760',(select max(to_number(i.premium_rcv_detail_code))+1 from ins_premium_det i),'25760','25760','02', '11000003','00','Request by Mr. Reheel Malik 02-Dec-2024'); | H13: =F13&G13 -> insert into ins_premium_det (premium_rcv_code,assorted_code, rec_amount,premium_rcv_detail_code,remaining_amt, payrec, mode_code,coinsurance_code,class_cd,it_remarks) values('29Nov240034','070000167991','25760',(select max(to_number(i.premium_rcv_detail_code))+1 from ins_premium_det i),'25760','25760','02', '11000003','00','Request by Mr. Reheel Malik 02-Dec-2024');
... A335: KHI/HO/D/MO/PC COMP/C/99821/327/10/2024 | B335: =VLOOKUP(A335,policy!B:C,2,0) -> 070000168303 | C335: 21360 | D335: =ROUND(C335,0) -> 21360 | E335: 29Nov240034 | F335: ="insert into ins_premium_det (premium_rcv_code,assorted_code, rec_amount,premium_rcv_detail_code,remaining_amt, payrec, mode_code,coinsurance_code,class_cd,it_remarks) values" -> insert into ins_premium_det (premium_rcv_code,assorted_code, rec_amount,premium_rcv_detail_code,remaining_amt, payrec, mode_code,coinsurance_code,class_cd,it_remarks) values | G335: ="('"&E335&"','"&B335&"','"&D335&"',(select max(to_number(i.premium_rcv_detail_code))+1 from ins_premium_det i),'"&D335&"','"&D335&"','02', '11000003','00','Request by Mr. Reheel Malik 02-Dec-2024');" -> ('29Nov240034','070000168303','21360',(select max(to_number(i.premium_rcv_detail_code))+1 from ins_premium_det i),'21360','21360','02', '11000003','00','Request by Mr. Reheel Malik 02-Dec-2024'); | H335: =F335&G335 -> insert into ins_premium_det (premium_rcv_code,assorted_code, rec_amount,premium_rcv_detail_code,remaining_amt, payrec, mode_code,coinsurance_code,class_cd,it_remarks) values('29Nov240034','070000168303','21360',(select max(to_number(i.premium_rcv_detail_code))+1 from ins_premium_det i),'21360','21360','02', '11000003','00','Request by Mr. Reheel Malik 02-Dec-2024');
C336: =SUM(C2:C335) -> 13701580 | D336: =SUM(D2:D335) -> 13701580

Sheet Sheet2
A2: KHI/HO/D/MO/PC COMP/C/99821/2/10/2024 | B2: -10-2024 | H2: 99821 | I2: 00002 | J2: ="ia.assorted_string like '%"&H2&"-"&I2&B2&"%' or" -> ia.assorted_string like '%99821-00002-10-2024%' or
A3: KHI/HO/D/MO/PC COMP/C/99821/5/10/2024 | B3: -10-2024 | H3: 99821 | I3: 00005 | J3: ="ia.assorted_string like '%"&H3&"-"&I3&B3&"%' or" -> ia.assorted_string like '%99821-00005-10-2024%' or
A4: KHI/HO/D/MO/PC COMP/C/99821/6/10/2024 | B4: -10-2024 | H4: 99821 | I4: 00006 | J4: ="ia.assorted_string like '%"&H4&"-"&I4&B4&"%' or" -> ia.assorted_string like '%99821-00006-10-2024%' or
A5: KHI/HO/D/MO/PC COMP/C/99821/7/10/2024 | B5: -10-2024 | H5: 99821 | I5: 00007 | J5: ="ia.assorted_string like '%"&H5&"-"&I5&B5&"%' or" -> ia.assorted_string like '%99821-00007-10-2024%' or
A6: KHI/HO/D/MO/PC COMP/C/99821/8/10/2024 | B6: -10-2024 | H6: 99821 | I6: 00008 | J6: ="ia.assorted_string like '%"&H6&"-"&I6&B6&"%' or" -> ia.assorted_string like '%99821-00008-10-2024%' or
A7: KHI/HO/D/MO/PC COMP/C/99821/9/10/2024 | B7: -10-2024 | H7: 99821 | I7: 00009 | J7: ="ia.assorted_string like '%"&H7&"-"&I7&B7&"%' or" -> ia.assorted_string like '%99821-00009-10-2024%' or
A8: KHI/HO/D/MO/PC COMP/C/99821/10/10/2024 | B8: -10-2024 | H8: 99821 | I8: 00010 | J8: ="ia.assorted_string like '%"&H8&"-"&I8&B8&"%' or" -> ia.assorted_string like '%99821-00010-10-2024%' or
A9: KHI/HO/D/MO/PC COMP/C/99821/11/10/2024 | B9: -10-2024 | H9: 99821 | I9: 00011 | J9: ="ia.assorted_string like '%"&H9&"-"&I9&B9&"%' or" -> ia.assorted_string like '%99821-00011-10-2024%' or
A10: KHI/HO/D/MO/PC COMP/C/99821/12/10/2024 | B10: -10-2024 | H10: 99821 | I10: 00012 | J10: ="ia.assorted_string like '%"&H10&"-"&I10&B10&"%' or" -> ia.assorted_string like '%99821-00012-10-2024%' or
A11: KHI/HO/D/MO/PC COMP/C/99821/13/10/2024 | B11: -10-2024 | H11: 99821 | I11: 00013 | J11: ="ia.assorted_string like '%"&H11&"-"&I11&B11&"%' or" -> ia.assorted_string like '%99821-00013-10-2024%' or
A12: KHI/HO/D/MO/PC COMP/C/99821/14/10/2024 | B12: -10-2024 | H12: 99821 | I12: 00014 | J12: ="ia.assorted_string like '%"&H12&"-"&I12&B12&"%' or" -> ia.assorted_string like '%99821-00014-10-2024%' or
A13: KHI/HO/D/MO/PC COMP/C/99821/15/10/2024 | B13: -10-2024 | H13: 99821 | I13: 00015 | J13: ="ia.assorted_string like '%"&H13&"-"&I13&B13&"%' or" -> ia.assorted_string like '%99821-00015-10-2024%' or
... A335: KHI/HO/D/MO/PC COMP/C/99821/327/10/2024 | B335: -10-2024 | H335: 99821 | I335: 00327 | J335: ="ia.assorted_string like '%"&H335&"-"&I335&B335&"%' or" -> ia.assorted_string like '%99821-00327-10-2024%' or

Sheet policy
B1: FUNC_ASSORTED_STRING(IA.ASSORTED_CODE) | C1: ASSORTED_CODE
A2: 1 | B2: KHI/HO/D/MO/PC COMP/C/99821/297/10/2024 | C2: 070000168273
A3: 2 | B3: KHI/HO/D/MO/PC COMP/C/99821/301/10/2024 | C3: 070000168277
A4: 3 | B4: KHI/HO/D/MO/PC COMP/C/99821/305/10/2024 | C4: 070000168281
A5: 4 | B5: KHI/HO/D/MO/PC COMP/C/99821/308/10/2024 | C5: 070000168284
A6: 5 | B6: KHI/HO/D/MO/PC COMP/C/99821/331/10/2024 | C6: 070000168307
A7: 6 | B7: KHI/HO/D/MO/PC COMP/C/99821/64/10/2024 | C7: 070000168040
A8: 7 | B8: KHI/HO/D/MO/PC COMP/C/99821/67/10/2024 | C8: 070000168043
A9: 8 | B9: KHI/HO/D/MO/PC COMP/C/99821/138/10/2024 | C9: 070000168114
A10: 9 | B10: KHI/HO/D/MO/PC COMP/C/99821/172/10/2024 | C10: 070000168148
A11: 10 | B11: KHI/HO/D/MO/PC COMP/C/99821/365/10/2024 | C11: 070000168341
A12: 11 | B12: KHI/HO/D/MO/PC COMP/C/99821/122/10/2024 | C12: 070000168098
A13: 12 | B13: KHI/HO/D/MO/PC COMP/C/99821/123/10/2024 | C13: 070000168099
... A335: 334 | B335: KHI/HO/D/MO/PC COMP/C/99821/235/10/2024 | C335: 070000168211

Sheet Cancelaltion cases
A1: Sr. | B1: Status | C1: Contract No. | D1: Status2 | E1: Insurance Agency | F1: Dealer Name | G1: Customer Name | H1: City | I1: CNIC No. | J1: Home Phone# | K1: Mobile Number | L1: Business Phone# | M1: Mail Address | N1: Finance Amount | O1: Car Price | P1: Ins. Policy | Q1: Ins. Expiry Date | R1: Engine No. | S1: Chassis No. | T1: Car Category | U1: Reg. No. | V1: Car Name | W1: Model | X1: Contract Booking Date | Y1: Contract Value Date | Z1: Contract Maturity Date | AA1: Purchase Order No. | AB1: Tenor#2 | AC1: Tracker Company | AD1: Tracker Reference Number | AE1: Tracker Installation Date | AF1: Rate | AG1: Sum Insured | AH1: Premium | AI1: OLD Contract Ref | AJ1: Remarks-I | AK1: Remarks-II | AL1: Policy # 2024 | AM1: Match
A2: 379 | B2: NORM | C2: 997APD2203020054 | D2: Closed | E2: T-PAK | F2: MIDWAY MOTORS | G2: SHERAZ AHMED | H2: Karachi | I2: 42000-5003107-5 | K2: 0345-8309626 | M2: FLAT#A-35 2ND FLOOR EVACUE SOCIETY GULSHAN E IQBAL BLOCK A-10 RASHID MINHAS ROAD KARACHI | N2: 64263 | O2: 1500000 | P2: 52921/00122/10/2020 | Q2: 45592 | R2: 9302212 | S2: 401691 | T2: RCN | U2: CY-5356 | V2: NISSAN CLIPPER | W2: 2014 | X2: 28-OCT-2020 | Y2: 27-OCT-2020 | Z2: 27-Oct-2024 | AA2: POUKHI300059221 | AB2: 4 | AC2: CTRK | AD2: DIB0028958 | AE2: 28-OCT-2020 | AF2: 2% | AG2: 1200000 | AH2: 0 | AL2: #N/A | AM2: 0
A3: 380 | B3: NORM | C3: 997APD2202960016 | D3: Closed | E3: T-PAK | F3: FAROOQ MOTORS | G3: JAWWAD AHMAD | H3: Lahore | I3: 35202-2471233-9 | J3: 03008436394 | K3: 03008436394 | L3: 35987000 | M3: 61 C MAIN BOULEVARD GULBERG III LAHORE | N3: 118814 | O3: 2600000 | P3: 52921/00092/10/2020 | Q3: 45586 | R3: Q033457 | S3: ZRE171R-6010925 | T3: USD | U3: LE-16-A-5534 | V3: COROLLA ALTIS A/T | W3: 2016 | X3: 22-OCT-2020 | Y3: 27-OCT-2020 | Z3: 27-Oct-2024 | AA3: POULHR300059022 | AB3: 4 | AC3: ITFM | AD3: 3351/10/2020/ITFM | AE3: 22-OCT-2020 | AF3: 2% | AG3: 2080000 | AH3: 0 | AL3: #N/A | AM3: 0
A4: 381 | B4: NORM | C4: 9976AD1221650011 | D4: Closed | E4: T-PAK | F4: PAK SUZUKI MOTOR CO LTD | G4: RASHID MASOOD | H4: Karachi | I4: 42401-0115108-3 | J4: 32890039 | K4: 03332279932, 03083772828 | L4: 03332279932 | M4: H # 7 SECTOR 4-A SAEEDABAD NEAR FAROOQ-E-AZAM MASJID NEAR BONITA BEAUTI PARLOR KARACHI PAKISTAN | N4: 173330 | O4: 2399000 | P4: 64081/00062/10/2022 | Q4: 45591 | R4: 242115 | S4: 10142115 | T4: NEW | V4: SUZUKI WAGNOR VXL AGS | W4: 2022 | X4: 14-JUN-2022 | Y4: 27-NOV-2022 | Z4: 27-Nov-2024 | AA4: OLAKHI300088028 | AB4: 2 | AC4: ITFM | AD4: 9163/10/2022/ITFM | AE4: 26-OCT-2022 | AF4: 2% | AG4: 1919200 | AH4: 0 | AL4: #N/A | AM4: 0
A5: 382 | B5: NORM | C5: 9976AD1211230086 | D5: Closed | E5: T-PAK | F5: TOYOTA WALTON MOTORS | G5: RANA RIZWAN AHMAD | H5: Lahore | I5: 35201-5124611-3 | J5: 03226941025 | K5: 03226941025 | L5: 04237663204 | M5: SHOP NO 07-A MADINA MARKET SHAH ALA M MARKET LAHORE | N5: 296269 | O5: 7414000 | P5: 2021/10/CLFTTPCDP01150 | Q5: 45589 | R5: 1GS5063015 | S5: 8723 | T5: NEW | V5: HLIUX REVO V DC A/T 4X4 | W5: 2021 | X5: 03-MAY-2021 | Y5: 03-NOV-2021 | Z5: 03-Nov-2024 | AA5: OLALHR300068645 | AB5: 3 | AC5: CTRK | AD5: DIB0032243 | AE5: 25-OCT-2021 | AF5: 1.75% | AG5: 5931200 | AH5: 0 | AL5: #N/A | AM5: 0
A6: 383 | B6: NORM | C6: 997APD1182600002 | D6: Closed | E6: T-PAK | F6: ALI JAN MOTORS | G6: AZEEM AMJAD | H6: Gujranwala | I6: 34101-7096736-5 | J6: 03074441107 | K6: 03074441107 | L6: 030744411107 | M6: ST# 10 MOH NATIONAL TOWN SIALKOT RO AD MUGHAL CHOWK GUJRANWALA PK | N6: 653650 | O6: 769000 | P6: 2018/09/CLFTTPCDP01654 | Q6: 09-SEP-2019 | R6: 743765 | S6: 1282892 | T6: NEW | U6: LEB-18A-8775 | V6: MEHRAN VX EURO-II | W6: 2018 | X6: 17-SEP-2018 | Y6: 21-SEP-2018 | Z6: 21-Sep-2025 | AA6: POAGWL300037973 | AB6: 7 | AC6: CTRK | AD6: DIB0025772 | AE6: 14-SEP-2018 | AF6: 3.1% | AG6: 499850 | AH6: 0 | AL6: KHI/HO/D/MO/PC COMP/C/97805/167/09/2024 | AM6: 15495
A7: 384 | B7: NORM | C7: 997APD1203050129 | D7: Closed | E7: T-PAK | F7: ALI JAN MOTORS | G7: ZAHID MEHMOOD | H7: Gujranwala | I7: 34101-1899214-7 | J7: 03008615820 | K7: 03008615820 | L7: 03008615820 | M7: GALA ASLAM NIMKO WALA MAIN ROAD NEW ABADI NOWSHEHRA GUJRANWALA | N7: 487068 | O7: 1730000 | P7: 01-2010-PO-MTR-PCCM-D-001965 | Q7: 45595 | R7: 207790 | S7: 10107788 | T7: NEW | V7: WAGON R VXL | W7: 2020 | X7: 31-OCT-2020 | Y7: 03-NOV-2020 | Z7: 03-Nov-2025 | AA7: PODGWL300059797 | AB7: 5 | AC7: ITFM | AD7: 3424/10/2020/ITFM | AE7: 31-OCT-2020 | AF7: 2% | AG7: 1297500 | AH7: 0 | AL7: KHI/HO/D/MO/PC COMP/C/99821/26/10/2024 | AM7: 25950
A8: 385 | B8: NORM | C8: 997AAD1202120036 | D8: Closed | E8: T-PAK | F8: KIA MOTORS TOWNSHIP | G8: ANJUM PERVAIZ | H8: Lahore | I8: 34603-2339147-3 | J8: 03217446366 | K8: 03217446366 | L8: 03217446366 | M8: OFF NO 301-3RD FLOOR THE ENTERPRISE BUILDING MULTAN ROAD LAHORE | N8: 173147 | O8: 5430000 | P8: 52921/00131/10/2020 | Q8: 45593 | R8: G4NALH326945 | S8: NNAQL51AZKP506071 | T8: NEW | V8: SPORATGE AWD | W8: 2020 | X8: 30-JUL-2020 | Y8: 03-NOV-2020 | Z8: 03-Nov-2024 | AA8: POALHR300056177 | AB8: 4 | AF8: 1.5% | AG8: 4344000 | AH8: 0 | AL8: #N/A | AM8: 0
A9: 386 | B9: NORM | C9: 997APD1203010050 | D9: Closed | E9: T-PAK | F9: FAROOQ MOTORS | G9: ABDUL WAJID KHILJI | H9: Lahore | I9: 35202-2338858-1 | J9: 03099113711 | K9: 03099113711 | L9: 03099113711 | M9: 39 ITIFAQ PAINT MANSOORA MULTAN ROA D LAHORE | N9: 36518 | O9: 1700000 | P9: 52921/00108/10/2020 | Q9: 45588 | R9: 1KR1503445 | S9: KGC300197325 | T9: RCN | U9: LE-17A-9574 | V9: TOYOTA PASSO | W9: 2014 | X9: 27-OCT-2020 | Y9: 27-OCT-2020 | Z9: 27-Oct-2024 | AA9: POULHR300059096 | AB9: 4 | AC9: CTRK | AD9: DIB0028939 | AE9: 26-OCT-2020 | AF9: 2% | AG9: 1360000 | AH9: 0 | AL9: #N/A | AM9: 0
A10: 387 | B10: NORM | C10: 997AAD1202530013 | D10: Closed | E10: T-PAK | F10: KIA SAMA MOTORS | G10: MUHAMMAD HAMEED | H10: Lahore | I10: 35202-2526081-3 | J10: 35187750 | K10: 03219478056 | L10: 37632400 37632500 | M10: HOUSE NO 167-D-1 NESPAK HOUSING SOCIETY COLLEGE ROAD LAHORE | N10: 1161433 | O10: 4930000 | P10: 52921/00095/10/2020 | Q10: 45586 | R10: G4NALH326560 | S10: NNAQL51AZKP303669 | T10: NEW | V10: SPORTAGE FWD | W10: 2020 | X10: 09-SEP-2020 | Y10: 27-OCT-2020 | Z10: 27-Oct-2025 | AA10: POALHR300057163 | AB10: 5 | AF10: 1.5% | AG10: 3697500 | AH10: 0 | AL10: KHI/HO/D/MO/PC COMP/C/99821/119/10/2024 | AM10: 55462.5
A11: 388 | B11: NORM | C11: 997AAD1202090001 | D11: Closed | E11: T-PAK | F11: TOYOTA FAISALABAD | G11: FARAH SOHAIL | H11: OKARA | I11: 35302-9084187-6 | J11: 0442511713 | K11: 03216957713 | M11: HOUSE NO B II 4S 52 STREET NO 4 MOHALLAH C BLOCK OKARA | N11: 111358 | O11: 3928000 | P11: DIB/T/BT/29050/LHR/1020 | Q11: 45585 | R11: Q345470 | S11: 7044638 | T11: NEW | V11: TOYOTA COROLLA ALTIS GRANDE CVT | W11: 2020 | X11: 27-JUL-2020 | Y11: 03-NOV-2020 | Z11: 03-Nov-2024 | AA11: POAOKR300055801 | AB11: 4 | AC11: ITFM | AD11: 3347/10/2020/ITFM | AE11: 22-OCT-2020 | AF11: 2% | AG11: 3142400 | AH11: 0 | AL11: #N/A | AM11: 0
A12: 389 | B12: NORM | C12: 997APD2202950008 | D12: Closed | E12: T-PAK | F12: CHANGAN GUL MOTORS | G12: MUHAMMAD SAJJAD | H12: Karachi | I12: 42401-1994186-7 | J12: 03132675799 | K12: 03132675799 | L12: 02135121220 | M12: PLOT # 5/2 SEC 15 KORANGI INDUSTRIA L AREA KARACHI | N12: 26956 | O12: 1555000 | P12: 52921/00074/10/2020 | Q12: 45584 | R12: U500860 | S12: L1002697 | T12: NEW | V12: KARAVAAN PLUS | W12: 2020 | X12: 21-OCT-2020 | Y12: 21-OCT-2020 | Z12: 21-Oct-2024 | AA12: PODKHI300058782 | AB12: 4 | AC12: ITFM | AD12: 3305/10/2020/ITFM | AE12: 16-OCT-2020 | AF12: 2% | AG12: 1244000 | AH12: 0 | AL12: #N/A | AM12: 0
A13: 390 | B13: NORM | C13: 997APD1202940001 | D13: Closed | E13: T-PAK | F13: SIDDIQUI MOTORS | G13: MUHAMMAD ASHRAF | H13: Hyderabad | I13: 44101-7685210-5 | J13: 03023263208 | K13: 03023263208, 03322693563 | L13: 0222789229 | M13: HOUSE # 44/2 ABDULLAH HAVEN NASEEM NAGAR QASIMABAD NEAR ABDULLAH SPORT HYDERABAD PK | N13: 108314 | O13: 2550000 | P13: 01-2010-PO-MTR-PCCM-D-001912 | Q13: 45580 | R13: Z504038 | S13: 4130481 | T13: USD | U13: BMV-934 | V13: TOYOTA COROLLA GLI | W13: 2017 | X13: 20-OCT-2020 | Y13: 21-OCT-2020 | Z13: 21-Oct-2024 | AA13: POUHYD300058601 | AB13: 4 | AC13: ITMM | AD13: 3304/10/2020/ITMM | AE13: 16-OCT-2020 | AF13: 2% | AG13: 2040000 | AH13: 0 | AL13: #N/A | AM13: 0
A14: 391 | B14: NORM | C14: 997AAD2202040004 | D14: Closed | E14: T-PAK | F14: TOYOTA CENTRAL MOTORS | G14: ZAMEER SIDDIQUE QURESHI | H14: Karachi | I14: 42301-6462847-9 | K14: 03008221646 | M14: 3RD FLOOR,E-23 2ND COMM.LANE ZAMZAMA,PHASE,V DHA KARACHI | N14: 297187 | O14: 7048500 | P14: DIB/T/BT/28942/KHI/1020 | Q14: 45578 | R14: 1GD0840309 | S14: GUN126R-5541061 | T14: NEW | V14: TOYOTA HILUX REVO DC A/T 4X4 | W14: 2020 | X14: 22-JUL-2020 | Y14: 03-NOV-2020 | Z14: 03-Nov-2024 | AA14: POAKHI300055421 | AB14: 4 | AC14: CTRK | AD14: TDIDIB0028679 | AE14: 13-OCT-2020 | AF14: 1.5% | AG14: 5638800 | AH14: 0 | AL14: #N/A | AM14: 0
A15: 392 | B15: NORM | C15: 997AAD2202750005 | D15: Closed | E15: T-PAK | F15: HONDA PORT QASIM | G15: SYED MUHAMMAD ALI | H15: Karachi | I15: 42000-1239224-7 | K15: 03332304595 | M15: 82-M BLOCK-2 P.E.C.H.S KARACHI | N15: 575062 | O15: 2574000 | P15: 52921/00047/10/2020 | Q15: 45576 | R15: 17540881 | S15: 263835 | T15: NEW | V15: HONDA CITY IVTEC | W15: 2020 | X15: 01-OCT-2020 | Y15: 21-OCT-2020 | Z15: 21-Oct-2025 | AA15: POAKHI300058151 | AB15: 5 | AC15: ITECL | AD15: 3233/10/2020 | AE15: 09-OCT-2020 | AF15: 2% | AG15: 1930500 | AH15: 0 | AL15: KHI/HO/D/MO/PC COMP/C/99821/185/10/2024 | AM15: 38610
A16: 393 | B16: NORM | C16: 997AAD1202690017 | D16: Closed | E16: T-PAK | F16: HONDA TOWNSHIP (PVT) LTD | G16: SHAHLA SAMREEN | H16: Lahore | I16: 36103-7152065-4 | K16: 0303-4440772 | L16: 042-35880156 | M16: HOUSE NO. 285 BLOCK F REHMANPURA, LINK WAHDAT ROAD LAHORE | N16: 548010 | O16: 2645000 | P16: DIB/T/BT/28933/LHR/1020 | Q16: 45573 | R16: 17541114 | S16: LR264043 | T16: NEW | V16: CITY IVTEC P/T | W16: 2020 | X16: 25-SEP-2020 | Y16: 21-OCT-2020 | Z16: 21-Oct-2025 | AA16: POALHR300057622 | AB16: 5 | AC16: CTRK | AD16: TDIDIB0028674 | AE16: 10-OCT-2020 | AF16: 2% | AG16: 1983750 | AH16: 0 | AL16: KHI/HO/D/MO/PC COMP/C/99821/197/10/2024 | AM16: 39675
A17: 394 | B17: NORM | C17: 997AAD2202250001 | D17: Closed | E17: T-PAK | F17: SUZUKI CANAL MOTORS | G17: MUHAMMAD ASIF | H17: Faisalabad | I17: 33100-6406686-3 | J17: 0300-6696873 | K17: 0300-6696873 0300-0999213 | L17: 0300-6696873 | M17: ASIF KHALIS ATA CHAKI MADINA TOWN Y BLOCK 104 ROAD MUHALLAH BISHAN SINGH WALA ABBAS CHOWK FAISALABAD | N17: 59768 | O17: 1745000 | P17: 2524/02150/00012/10/2020 | Q17: 45571 | R17: PK10K162708 | S17: NF1AVK31H10062737 | T17: NEW | V17: CULTUS VXR EURO-II | W17: 2020 | X17: 12-AUG-2020 | Y17: 11-OCT-2020 | Z17: 11-Oct-2024 | AA17: POAFSD300056477 | AB17: 4 | AC17: CTRK | AD17: DIB0028850 | AE17: 07-OCT-2020 | AF17: 2% | AG17: 1396000 | AH17: 0 | AL17: #N/A | AM17: 0
A18: 395 | B18: NORM | C18: 997AAD1202100010 | D18: Closed | E18: T-PAK | F18: KIA SAMA MOTORS | G18: MUHAMMAD KHALID MASOOD | H18: Bahawalpur | I18: 33201-0977628-1 | J18: 03218591759 | K18: 03218591759 | L18: 03218591759 | M18: NRSP COLONY PO KHAS CHAK NO 10 BC B AHAWALPUR BAHAWALPUR PK | N18: 91953 | O18: 5399000 | P18: DIB/T/28898/LHR/1020 | Q18: 45569 | R18: F4NALH323524 | S18: NNAQL51A2KP505323 | T18: NEW | V18: SPORTAGE AWD | W18: 2020 | X18: 28-JUL-2020 | Y18: 21-OCT-2020 | Z18: 21-Oct-2024 | AA18: POABHP300055863 | AB18: 4 | AF18: 1.5% | AG18: 4319200 | AH18: 0 | AL18: #N/A | AM18: 0
A19: 396 | B19: NORM | C19: 997AAD1202730029 | D19: Closed | E19: T-PAK | F19: HYUNDAI SOUTH | G19: SYED AHMED ALI | H19: Karachi | I19: 42101-5818216-5 | J19: 03212424266 | K19: 03212424266 | L19: 32582448 | M19: FLAT 805 FRERE TOWN QTRS BLOCK 2-3 CLIFTON CANT STATION KARACHI PK | N19: 188475 | O19: 5485000 | P19: 2524/02692/00043/10/2021 | Q19: 45577 | R19: G4NAMU088028 | S19: PMHJ2813SMN202615 | T19: NEW | V19: HYUNDAI TUCSON | W19: 2020 | X19: 29-SEP-2020 | Y19: 03-NOV-2021 | Z19: 03-Nov-2024 | AA19: POAKHI300057210 | AB19: 3 | AC19: CTRK | AD19: DIB0032089 | AE19: 13-OCT-2021 | AF19: 2% | AG19: 4388000 | AH19: 0 | AL19: #N/A | AM19: 0
A20: 397 | B20: NORM | C20: 9976AD1212630009 | D20: Closed | E20: T-PAK | F20: HYUNDAI D GROUND MOTORS | G20: MUHAMMAD AFZAL | H20: Faisalabad | I20: 33100-4795485-3 | J20: 03008625851 | K20: 03008625851, 03008625851 | L20: 03008625851 | M20: P-321/25 MIAN STEET NEW KHALIDABAD BABAR FLOOR MILLS FAISALABAD | N20: 143734 | O20: 3903000 | P20: 2021-10-205-V01501OP0002443 | Q20: 45584 | R20: 842402 | S20: 301805 | T20: NEW | V20: HYUNDAI ELANTRA | W20: 2021 | X20: 20-SEP-2021 | Y20: 27-OCT-2021 | Z20: 27-Oct-2024 | AA20: OLAFSD300073720 | AB20: 3 | AC20: CTRK | AD20: DIB0032132 | AE20: 20-OCT-2021 | AF20: 2% | AG20: 3122400 | AH20: 0 | AL20: #N/A | AM20: 0
A21: 398 | B21: NORM | C21: 9976AP2193040023 | D21: Closed | E21: T-PAK | F21: HONDA TOWNSHIP (PVT) LTD | G21: AHMED NOMAN ANWER | H21: Lahore | I21: 35202-2464107-9 | K21: 03218409606 | M21: H NO 555 BLOCK 3 SECTOR C -1 NEAR AL-NOOR STORE TOWNSHIP LAHORE | N21: 84277 | O21: 2315000 | P21: DIB/T/BT/25832/LHR/1019 | Q21: 45595 | R21: 17535906 | S21: KR256636 | T21: NEW | U21: LE-20-3925 | V21: HONDA CITY M/T | W21: 2019 | X21: 31-OCT-2019 | Y21: 03-NOV-2019 | Z21: 03-Nov-2024 | AA21: PODLHR300050375 | AB21: 5 | AC21: CTRK | AD21: TDIDIB0027380 | AE21: 31-OCT-2019 | AF21: 2.5% | AG21: 1852000 | AH21: 0 | AL21: #N/A | AM21: 0
A22: 399 | B22: NORM | C22: 9976AP2193040026 | D22: Closed | E22: T-PAK | F22: SUZUKI BURJ MOTORS | G22: MUHAMMAD USMAN | H22: Faisalabad | I22: 33100-7370107-7 | J22: 03216033567 | K22: 03216033567, 03216033567 | L22: 0412437544 | M22: P-135 NAZIMABAD CITY COLONY REHMANI A ROAD FSD FAISALABAD PK | N22: 65494 | O22: 1855000 | P22: 51244/00092/10/2019 | Q22: 45595 | R22: 150882 | S22: 10050849 | T22: NEW | U22: APU-176 | V22: CULTUS VXL EURO II | W22: 2019 | X22: 31-OCT-2019 | Y22: 03-NOV-2019 | Z22: 03-Nov-2024 | AA22: PODFSD300050487 | AB22: 5 | AC22: FLCN | AD22: 17143/10/2019 | AE22: 31-OCT-2019 | AF22: 2.5% | AG22: 1484000 | AH22: 0 | AL22: #N/A | AM22: 0
A23: 400 | B23: NORM | C23: 9976AP2193040034 | D23: Closed | E23: T-PAK | F23: MARGALLA MOTORS | G23: AVINASH | H23: Karachi | I23: 45101-3653631-5 | K23: 03333777877 | L23: 02135384765 | M23: FLAT NO B-39, PEARL HEAVEN APPARTMENT, CLIFTON, BLOCK 5, KARACHI. | N23: 59995 | O23: 1518000 | Q23: 45595 | R23: 119940 | S23: 1020112 | T23: NEW | U23: BRC-383 | V23: ALTO VXL AGS EURO II | W23: 2019 | X23: 31-OCT-2019 | Y23: 03-NOV-2019 | Z23: 03-Nov-2024 | AA23: PODKHI300050490 | AB23: 5 | AC23: CTRK | AD23: DIB0027957 | AE23: 31-OCT-2019 | AF23: 2.5% | AG23: 1214400 | AH23: 0 | AL23: #N/A | AM23: 0
A24: 401 | B24: NORM | C24: 9976AP2173040032 | D24: Closed | E24: T-PAK | F24: HYUNDAI SAJJAD MOTORS | G24: WASEEM AKRAM | H24: Lahore | I24: 35104-0340990-1 | J24: 03214117860 | K24: 03214117860 | L24: 03214117860 | M24: 138 RAVI BLOCK ALLAMA IQBAL TOWN LAHORE PK | N24: 48323 | O24: 1094000 | P24: DIB/T/18499/LHR/1017 | Q24: 45595 | R24: 142124 | S24: 10042265 | T24: NEW | U24: LEC-17A-138 | V24: SUZUKI WAGONR VXL | W24: 2017 | X24: 31-OCT-2017 | Y24: 03-NOV-2017 | Z24: 03-Nov-2024 | AA24: PODLHR300026948 | AB24: 7 | AC24: FLCN | AD24: 13678/10/2017 | AE24: 31-OCT-2017 | AF24: 3.2% | AG24: 875200 | AH24: 0 | AL24: #N/A | AM24: 0
A25: 402 | B25: NORM | C25: 9976AD2171510009 | D25: Closed | E25: T-PAK | F25: TOYOTA CENTRAL MOTORS | G25: MUHAMMAD IQBAL | H25: Karachi | I25: 41304-9655841-9 | K25: 03013534766 03313518433 | M25: HOUSE NO 11-C BLOCK C UNIT NO-6 NEAR AISHA MASJID LATIFABAD HYDERABAD | N25: 53949 | O25: 1864000 | P25: DIB/T/18475/KHI/1017 | Q25: 45594 | R25: Z505497 | S25: NZE170R-4131233 | T25: NEW | U25: BKU-053 | V25: COROLLA GLI | W25: 2017 | X25: 31-MAY-2017 | Y25: 03-NOV-2017 | Z25: 03-Nov-2024 | AA25: POAKHI300022505 | AB25: 7 | AC25: CTRK | AD25: TDIDIB0021123 | AE25: 11-OCT-2017 | AF25: 2% | AG25: 1491200 | AH25: 0 | AL25: #N/A | AM25: 0
A26: 403 | B26: NORM | C26: 9976AD2171090001 | D26: Closed | E26: T-PAK | F26: PAK SUZUKI MOTOR CO LTD | G26: NOSHEEN ZAIB | H26: Karachi | I26: 42201-5090754-0 | K26: 03333054485 | L26: 02135144108 | M26: PLOT NO CIB-17 SECTOR 16 KORANGI INDUSTRIAL AREA VITA CHORANGI KARACHI | N26: 60500 | O26: 1999000 | P26: 01-1710-PO-MTR-PCCM-D-002936 | Q26: 45592 | R26: K14BS139751 | S26: MMSCVC41S00101292 | T26: NEW | U26: BKT-508 | V26: CIAZ | W26: 2017 | X26: 19-APR-2017 | Y26: 03-NOV-2017 | Z26: 03-Nov-2024 | AA26: POAKHI300021084 | AB26: 7 | AC26: CTRK | AD26: DIB0022522 | AE26: 17-OCT-2017 | AF26: 3.1% | AG26: 1599200 | AH26: 0 | AL26: #N/A | AM26: 0
A27: 404 | B27: NORM | C27: 9976AP1193030006 | D27: Closed | E27: T-PAK | F27: TOYOTA SHAHRA MOTORS | G27: ZAIN UL ABIDEEN | H27: Faisalabad | I27: 33301-5773163-9 | J27: 03004221627 | K27: 03004221627, 03004221627 | L27: 041-2422627 | M27: P-97 JHANG ROAD ABDUL HAQ COLONY FSD. FAISALABAD PK | N27: 106362 | O27: 2783000 | P27: 51244/00070/10/2019 | Q27: 45592 | R27: Z569602 | S27: NZE170R-4195016 | T27: NEW | U27: LEA-19A-1649 | V27: COROLLA GLI M/T | W27: 2019 | X27: 30-OCT-2019 | Y27: 03-NOV-2019 | Z27: 03-Nov-2024 | AA27: PODFSD300050265 | AB27: 5 | AC27: ITFM | AD27: 1942/10/2019/ITFM | AE27: 28-OCT-2019 | AF27: 2.5% | AG27: 2226400 | AH27: 0 | AL27: #N/A | AM27: 0
A28: 405 | B28: NORM | C28: 9976AP1182990012 | D28: Closed | E28: T-PAK | F28: ZAFAR MOTORS-LHR | G28: FAZAL ELAHI | H28: Lahore | I28: 35202-3445010-9 | J28: 033410471248 | K28: 03341047248 | L28: 37355173 | M28: OFF# 54 LAKE ROAD DOONI STREET CHAN OLD ANARKALI NEAR ROUND ABOUT JAN E MANDAR LAHORE | N28: 21862 | O28: 1234000 | P28: 49889/00053/10/2018 | Q28: 45589 | R28: 172015 | S28: 10071984 | T28: NEW | U28: LEC-18A-8023 | V28: WAGONR VXL | W28: 2018 | X28: 26-OCT-2018 | Y28: 27-OCT-2018 | Z28: 27-Oct-2024 | AA28: PODLHR300039547 | AB28: 6 | AC28: CTRK | AD28: DIB0026143 | AE28: 26-OCT-2018 | AF28: 3.1% | AG28: 987200 | AH28: 0 | AL28: #N/A | AM28: 0
A29: 406 | B29: NORM | C29: 9976AP1173030008 | D29: Closed | E29: T-PAK | F29: NADEEM INTERNATIONAL | G29: ARSALAN RABBANI KHAN | H29: Karachi | I29: 42101-4752585-3 | J29: 03212101005 | K29: 03212101005 | L29: 35839623 | M29: C-77 BLOCK A NORTH NAZIMBAD NEAR OP P SBP GROUND KARACHI PK | N29: 34564 | O29: 1094000 | P29: DIB/T/18435/KHI/1017 | Q29: 45589 | R29: 143670 | S29: 10043579 | T29: NEW | U29: BKX-718 | V29: SUZUKI WAGONR VXL | W29: 2017 | X29: 30-OCT-2017 | Y29: 03-NOV-2017 | Z29: 03-Nov-2024 | AA29: PODKHI300026607 | AB29: 7 | AC29: FLCN | AD29: 13558/10/2017 | AE29: 26-OCT-2017 | AF29: 3.2% | AG29: 875200 | AH29: 0 | AL29: #N/A | AM29: 0
A30: 407 | B30: NORM | C30: 9976AD2192120006 | D30: Closed | E30: T-PAK | F30: TOYOTA WALTON MOTORS | G30: NAILA HAFEEZ | H30: Lahore | I30: 35201-3276405-2 | J30: 03014189979 | K30: 04235724131, 03014189979 | L30: 04236560937 | M30: H NO 449 SECTOR S PHASE 2 ST NO 28 DHA LAHORE | N30: 55288 | O30: 3183000 | P30: 51244/00057/10/2019 | Q30: 45588 | R30: Q062216 | S30: ZRE171R-6039719 | T30: NEW | U30: LE-19A-5760 | V30: COROLLA ALTIS A/T | W30: 2019 | X30: 31-JUL-2019 | Y30: 27-OCT-2019 | Z30: 27-Oct-2024 | AA30: POALHR300048072 | AB30: 5 | AC30: CTRK | AD30: DIB0027920 | AE30: 24-OCT-2019 | AF30: 2% | AG30: 2546400 | AH30: 0 | AL30: #N/A | AM30: 0
A31: 408 | B31: NORM | C31: 9976AD2172400003 | D31: Closed | E31: T-PAK | F31: HONDA CENTRE | G31: AHSAN MAHMOOD KHAN GHAURI | H31: Lahore | I31: 35201-0243649-1 | J31: 03037771565 | K31: 03037771565 | L31: 35905704 | M31: H# 215 H 3 BLOCK JOHAR TOWN LAHORE PK | N31: 57927 | O31: 2333000 | P31: DIB/T/18420/LHR/1017 | Q31: 45588 | R31: 13504600 | S31: HR004609 | T31: NEW | U31: LEB-17A-3052 | V31: BR-V IVTEC-S | W31: 2017 | X31: 28-AUG-2017 | Y31: 03-NOV-2017 | Z31: 03-Nov-2024 | AA31: POALHR300025113 | AB31: 7 | AC31: FLCN | AD31: 13522/10/2017 | AE31: 24-OCT-2017 | AF31: 3.1% | AG31: 1866400 | AH31: 0 | AL31: #N/A | AM31: 0
A32: 409 | B32: NORM | C32: 9976AD1171190009 | D32: Closed | E32: T-PAK | F32: PAK SUZUKI MOTOR CO LTD | G32: SAJJAD SULAIMAN MALIK | H32: Lahore | I32: 35201-5529234-1 | K32: 03334217015 | L32: 04236367841 | M32: HOUSE NO.11-A MOHALLAH ASAD JAN ROAD LAHORE CANTT | N32: 35180 | O32: 1094000 | P32: DIB/T/18284/LHR/1017 | Q32: 45583 | R32: 143249 | S32: 10043218 | T32: NEW | U32: LEB-17A-1109 | V32: WAGON R VXL | W32: 2017 | X32: 29-APR-2017 | Y32: 03-NOV-2017 | Z32: 03-Nov-2024 | AA32: POALHR300021598 | AB32: 7 | AC32: CTRK | AD32: TDIDIB0021186 | AE32: 20-OCT-2017 | AF32: 3.1% | AG32: 875200 | AH32: 0 | AL32: #N/A | AM32: 0
A33: 410 | B33: NORM | C33: 9976AP1172930006 | D33: Closed | E33: T-PAK | F33: CAR CAPITAL | G33: RABIA SAQIB | H33: Karachi | I33: 42201-9419454-8 | J33: 03333322188 | K33: 03333322188 | L33: 0 | M33: E-9/10 A-1 RIZWAN APP MENTS BLOCK 1 4 GULSHAN-E-IQBAL NEAR CIVIC CENTRE KARACHI PK | N33: 21248 | O33: 2000000 | P33: DIB/T/18189/KHI/1017 | Q33: 45581 | R33: Z479524 | S33: 4105220 | T33: USD | U33: BHT-444 | V33: COROLLA GLI A/T | W33: 2017 | X33: 20-OCT-2017 | Y33: 21-OCT-2017 | Z33: 21-Oct-2024 | AA33: POUKHI300026399 | AB33: 7 | AC33: CTRK | AD33: TDIDIB0021179 | AE33: 18-OCT-2017 | AF33: 3.2% | AG33: 1600000 | AH33: 0 | AL33: #N/A | AM33: 0
A34: 411 | B34: NORM | C34: 9976AD1192730003 | D34: Closed | E34: T-PAK | F34: KIA MOTORS CANAL ROAD | G34: SYED ALI AHSAN | H34: Rawalpindi | I34: 37405-6968319-9 | J34: 5766325 | K34: 03222009148 | L34: 5120776 | M34: H NO 719 STREET NO 10 CHAKLALA SCHEME 3 RAWALPINDI | N34: 100474 | O34: 5399000 | P34: DIB/T/BT/25521/ISB/1019 | Q34: 45580 | R34: 030468 | S34: 500757 | T34: NEW | U34: ANS-747 | V34: SPORTAGE AWD | W34: 2019 | X34: 30-SEP-2019 | Y34: 27-OCT-2019 | Z34: 27-Oct-2024 | AA34: POARWP300049501 | AB34: 5 | AF34: 3.1% | AG34: 4319200 | AH34: 0 | AL34: #N/A | AM34: 0
A35: 412 | B35: NORM | C35: 9976AD1192120002 | D35: Closed | E35: T-PAK | F35: CENTRAL MOTORS | G35: MUHAMMAD JAVED MIRZA | H35: Rawalpindi | I35: 37405-3384468-3 | K35: 03215178453 | L35: 0514412492 | M35: OFFICE NO 1 2ND FLOOR CENTER POINT PLAZA PHASE 7 BAHRIA TOWN RAWALPINDI | N35: 37845 | O35: 1295000 | P35: 51244/00034/10/2019 | Q35: 45580 | R35: 112133 | S35: 1012080 | T35: NEW | U35: APT-289 | V35: ALTO VXL AGS EURO-II | W35: 2019 | X35: 31-JUL-2019 | Y35: 21-OCT-2019 | Z35: 21-Oct-2024 | AA35: POARWP300048019 | AB35: 5 | AC35: ITFM | AD35: 1902/10/2019/ITFM | AE35: 16-OCT-2019 | AF35: 2.5% | AG35: 1036000 | AH35: 0 | AL35: #N/A | AM35: 0
A36: 413 | B36: NORM | C36: 9976AD1172100002 | D36: Closed | E36: T-PAK | F36: HONDA CENTRE | G36: FAIZAN FAISAL | H36: Lahore | I36: 35200-7654710-3 | J36: 03334371680 | K36: 03334371680 | L36: 35941081 | M36: H# 105 A FAISAL TOWN LAHORE PK | N36: 44426 | O36: 2577500 | P36: DIB/T/18035/LHR/1017 | Q36: 45576 | R36: 12922975 | S36: HR026341 | T36: NEW | U36: LEB-17A-9500 | V36: CIVIC IVTEC ORIEL P/T WITH NAV | W36: 2017 | X36: 29-JUL-2017 | Y36: 21-OCT-2017 | Z36: 21-Oct-2024 | AA36: POALHR300024234 | AB36: 7 | AC36: FLCN | AD36: 13464/10/2017 | AE36: 16-OCT-2017 | AF36: 3.1% | AG36: 2062000 | AH36: 0 | AL36: #N/A | AM36: 0
A37: 414 | B37: NORM | C37: 9976AP1192880005 | D37: Closed | E37: T-PAK | F37: SUZUKI GUJRANWALA MOTOR | G37: AMANAT ALI | H37: Gujranwala | I37: 34101-0333984-3 | J37: 03017220074 | K37: 03017220074 | L37: 03017220074 | M37: GULAB PURA DAK KHANA CANTT GUJRANWALA PK | N37: 21034 | O37: 1050000 | P37: 01-1910-PO-MTR-PCCM-D-002686 | Q37: 45574 | R37: PKT1001263 | S37: SV308PK01117770 | T37: NEW | U37: LEA-19A-1046 | V37: BOLAN VX EURO-II | W37: 2019 | X37: 15-OCT-2019 | Y37: 21-OCT-2019 | Z37: 21-Oct-2024 | AA37: PODGWL300049772 | AB37: 5 | AC37: ITFM | AD37: 1886/10/2019/ITFM | AE37: 11-OCT-2019 | AF37: 2.5% | AG37: 840000 | AH37: 0 | AL37: #N/A | AM37: 0
A38: 415 | B38: NORM | C38: 9976AD2172120011 | D38: Closed | E38: T-PAK | F38: PAK SUZUKI MOTOR CO LTD | G38: AZRA YASMEEN | H38: Karachi | I38: 42301-2866781-6 | J38: 03462712365 | K38: 03462712365 | L38: 0 | M38: L-65 SHEERIN JINNAH COLONY CLIFTON NEAR CLIFTON MEDICAL CENTRE KARACHI PK | N38: 32926 | O38: 1375000 | P38: DIB/T/17960/KHI/1017 | Q38: 45570 | R38: 13037726 | S38: 10037687 | T38: NEW | U38: BKP-069 | V38: SWIFT DLX ABS WITH EBD | W38: 2017 | X38: 31-JUL-2017 | Y38: 11-OCT-2017 | Z38: 11-Oct-2024 | AA38: POAKHI300024188 | AB38: 7 | AC38: FLCN | AD38: 13379/10/2017 | AE38: 03-OCT-2017 | AF38: 3.1% | AG38: 1100000 | AH38: 0 | AL38: #N/A | AM38: 0
A39: 416 | B39: NORM | C39: 9976AP1233050001 | D39: Closed | E39: T-PAK | F39: SUZUKI BURJ MOTORS | G39: MUHAMMAD UMAIR KHAN | H39: Faisalabad | I39: 33100-6836729-5 | J39: 03216650501 | K39: 03216650501, 03216650501 | L39: 03216650501 | M39: P-134 SAFRON BLOCK SAMUNDARI ROAD F OUR SEASON PHASE 1 COLONY FAISALABAD | N39: 1678685 | O39: 2935000 | P39: 76078/00017/10/2023 | Q39: 30-OCT-2024 | R39: 6R286282 | S39: 1186252 | T39: NEW | V39: SUZUKI ALTO VXL AGS EURO II | W39: 2023 | X39: 45231 | Y39: 03-NOV-2023 | Z39: 03-Nov-2026 | AA39: OLDFSD300097682 | AB39: 3 | AC39: ITFT | AD39: 10581/10/2023/ITFM | AE39: 31-OCT-2023 | AF39: 1.75% | AG39: 2641500 | AH39: 0 | AL39: KHI/HO/D/MO/PC COMP/C/99821/220/10/2024 | AM39: 46226.25
A40: 417 | B40: NORM | C40: 9976AD2212520010 | D40: Closed | E40: T-PAK | F40: TOYOTA FAISALABAD | G40: NOSHEEN HAIDER | H40: Faisalabad | I40: 33100-0919528-6 | M40: EDUCATIONAL SERVICES PVT LTD 10-11 GURUMANGAT ROAD INDUSTRIAL AREA GULBERG 3 LAHORE. | N40: 100326 | O40: 2703000 | P40: 2021-10-205-V01501DP0002539 | Q40: 45594 | R40: 2A39172 | S40: 7024512 | T40: NEW | V40: TOYOTA YARIS ATIV | W40: 2021 | X40: 09-SEP-2021 | Y40: 03-NOV-2021 | Z40: 03-Nov-2024 | AA40: OLAFSD300073274 | AB40: 3 | AC40: CTRK | AD40: DIB0032270 | AE40: 29-OCT-2021 | AF40: 2% | AG40: 2162400 | AH40: 0 | AL40: #N/A | AM40: 0
A41: 418 | B41: NORM | C41: 9976AP1213030061 | D41: Closed | E41: T-PAK | F41: NEW CAR COMPLEX | G41: BILAL MUHAMMAD | H41: Karachi | I41: 42201-9642820-7 | J41: 0300-8929280/021-34693099 | K41: 03212744484 | L41: 34833074 75 | M41: HAIDERY PILGRIMS SHOP NO 3 PLOT SB 87 SALEEM HEIGHTS BLOCK 13/C GULSHAN E IQBAL KHI | N41: 89707 | O41: 1521000 | P41: 2524/02692/00133/10/2021 | Q41: 45594 | R41: 6R190641 | S41: NF1AET306H1090646 | T41: NEW | V41: SUZUKI ALTO VXL AGS EURO II | W41: 2021 | X41: 30-OCT-2021 | Y41: 03-NOV-2021 | Z41: 03-Nov-2024 | AA41: OLDKHI300077881 | AB41: 3 | AC41: FLCN | AD41: 108591/10/2021 | AE41: 30-OCT-2021 | AF41: 2% | AG41: 1216800 | AH41: 0 | AL41: #N/A | AM41: 0
A42: 419 | B42: NORM | C42: 9976AP2213030003 | D42: Closed | E42: T-PAK | F42: DANISH MOTORS | G42: WAQAS AHMED USMANI | H42: Karachi | I42: 42201-1219324-3 | J42: 03452083404 | K42: 03452083404, 03452083404 | L42: 03452083404 | M42: PLOT # E-63 SECTOR 10 BAGH-E-KORANG I NEAR JAMA MASJID REHMAT UL ALAMEE KARACHI PK | N42: 672804 | O42: 1700000 | P42: 2524/02692/00113/10/2021 | Q42: 45593 | R42: 127872 | S42: 1027921 | T42: USD | U42: BRY-910 | V42: SUZUKI ALTO VXL AGS EURO II | W42: 2020 | X42: 30-OCT-2021 | Y42: 03-NOV-2021 | Z42: 03-Nov-2026 | AA42: OLUKHI300077598 | AB42: 5 | AC42: CTRK | AD42: DIB0032320 | AE42: 30-OCT-2021 | AF42: 2% | AG42: 1360000 | AH42: 0 | AL42: KHI/HO/D/MO/PC COMP/C/99821/277/10/2024 | AM42: 27200
A43: 420 | B43: NORM | C43: 9976AD2221190009 | D43: Closed | E43: T-PAK | F43: PAK SUZUKI MOTOR CO LTD | G43: FARIHA SAHRISH | H43: Lahore | I43: 35202-0522461-6 | J43: 03236578028 | K43: 03236578028 | L43: 03236578028 | M43: HOUSE NO 4 STREET NO 38 AZIZ ROAD M ISRI SHAH NEAR AL AZIZ PHARMACY LAHORE PK | N43: 87195 | O43: 1886000 | P43: 64081/00069/10/2022 | Q43: 45592 | R43: 6R252132 | S43: 1152143 | T43: NEW | V43: SUZUKI ALTO VXL AGS EURO II | W43: 2022 | X43: 29-APR-2022 | Y43: 03-NOV-2022 | Z43: 03-Nov-2024 | AA43: OLALHR300086947 | AB43: 2 | AC43: ITFM | AD43: 9207/10/2022/ITFM | AE43: 28-OCT-2022 | AF43: 1.5% | AG43: 1508800 | AH43: 0 | AL43: #N/A | AM43: 0
A44: 421 | B44: NORM | C44: 9976AD1212120091 | D44: Closed | E44: T-PAK | F44: SUZUKI RACECOURSE MOTORS | G44: ASAD MEHMOOD ABBASI | H44: Rawalpindi | I44: 37405-0647353-9 | J44: 03215181178 | L44: 0519292754 | M44: H # 235 ST # 09 RAJA SHER KHAN STRE ET CHUNGI # 22 DHAMIAL ROAD OPP OFF RAWALPINDI PK | N44: 67247 | O44: 1521000 | P44: 01-2110-PO-MTR-PCCM-D-001469 | Q44: 45592 | R44: 189969 | S44: 1089914 | T44: NEW | V44: SUZUKI ALTO VXL AGS EURO II | W44: 2021 | X44: 31-JUL-2021 | Y44: 03-NOV-2021 | Z44: 03-Nov-2024 | AA44: OLAEWP300071428 | AB44: 3 | AC44: ITECL | AD44: 5563/10/2021 | AE44: 28-OCT-2021 | AF44: 2% | AG44: 1216800 | AH44: 0 | AL44: #N/A | AM44: 0
A45: 422 | B45: NORM | C45: 9976AD2210690010 | D45: Closed | E45: T-PAK | F45: TOYOTA CENTRAL MOTORS | G45: MUHAMMAD RIZWAN | H45: Karachi | I45: 13302-1255611-1 | K45: 03223333166 | L45: 02134573166 | M45: GALAXY INN GUEST HOUSE H NO A-46 BLOCK C GULSHAN E JAMAL OPP SAIMA SQ MALL | N45: 165952 | O45: 3255000 | P45: DIB/T/BT/34220/KHI/1021 | Q45: 45591 | R45: Q081395 | S45: ZRE171R-6058870 | T45: NEW | V45: COROLLA ALTIS A/T | W45: 2021 | X45: 10-MAR-2021 | Y45: 03-NOV-2021 | Z45: 03-Nov-2024 | AA45: OLAKHI300066576 | AB45: 3 | AC45: FLCN | AD45: 108586/10/2021 | AE45: 14-OCT-2021 | AF45: 2% | AG45: 2604000 | AH45: 0 | AL45: #N/A | AM45: 0
A46: 423 | B46: NORM | C46: 9976AP1223000073 | D46: Closed | E46: T-PAK | F46: AL JANAT MOTORS | G46: MUHAMMAD KHURSHID | H46: Lahore | I46: 35202-7697513-3 | J46: 03219473935 | K46: 03219473935 | L46: 03219473935 | M46: H# 325 A 2 BOR JOHAR TOWN LAHORE PK | N46: 161610 | O46: 3500000 | P46: 64081/00059/10/2022 | Q46: 45590 | R46: Q039920 | S46: R-6017396 | T46: USD | U46: LEA-17A-220 | V46: TOYOTA COROLLA ALTIS | W46: 2017 | X46: 27-OCT-2022 | Y46: 27-OCT-2022 | Z46: 27-Oct-2024 | AA46: OLULHR300090472 | AB46: 2 | AC46: ITFT | AD46: 9168/10/2022/ITFM | AE46: 26-OCT-2022 | AF46: 1.75% | AG46: 2800000 | AH46: 0 | AL46: N/A | AM46: 0
A47: 424 | B47: NORM | C47: 9976AP2213020002 | D47: Closed | E47: T-PAK | F47: HONDA EXPRESS PVT LTD | G47: ASIM ALI | H47: Rawalpindi | I47: 33104-0579871-3 | J47: 03219972912 | L47: 0512711447 | M47: H # 20 ST # 4 CHAKLALA SCHEME 2 RAWALPINDI PK | N47: 1098166 | O47: 2815000 | P47: 56038/00062/10/2021 | Q47: 45590 | R47: 1002592 | S47: MR003391 | T47: NEW | V47: HONDA CITY I-VTEC | W47: 2021 | X47: 29-OCT-2021 | Y47: 03-NOV-2021 | Z47: 03-Nov-2026 | AA47: OLDRWP300076563 | AB47: 5 | AC47: CTRK | AD47: DIB0032253 | AE47: 26-OCT-2021 | AF47: 2% | AG47: 2252000 | AH47: 0 | AL47: KHI/HO/D/MO/PC COMP/C/99821/345/10/2024 | AM47: 45040
A48: 425 | B48: NORM | C48: 9976AD2212430041 | D48: Closed | E48: T-PAK | F48: TOYOTA FAISALABAD | G48: MUHAMMAD FAROOQ | H48: Faisalabad | I48: 33102-6198041-7 | K48: 03006556565 | M48: H NO 180 D GULIFSHAAN COLONY 03006556565 FAISALABAD | N48: 150500 | O48: 2703000 | P48: DIB/T/BT/33973/LHR/1021 | Q48: 45589 | R48: ZA38879 | S48: 7024344 | T48: NEW | V48: TOYOTA YARIS ATIV CVT 1.3 | W48: 2021 | X48: 31-AUG-2021 | Y48: 11-NOV-2021 | Z48: 11-Nov-2024 | AA48: OLAFSD300072840 | AB48: 3 | AC48: CTRK | AD48: DIB0032192 | AE48: 25-OCT-2021 | AF48: 2% | AG48: 2162400 | AH48: 0 | AL48: #N/A | AM48: 0
A49: 426 | B49: NORM | C49: 9976AD2212370001 | D49: Closed | E49: T-PAK | F49: KIA MOTORS KINGS GATE | G49: HASSAN RASHEED | H49: Lahore | I49: 35202-6966280-1 | K49: 03334334681 | M49: HOUSE NO 7 A CANAL VIEW HOUSING SOCIETY LAHORE | N49: 37495 | O49: 1806000 | P49: 2524/02692/000089/10/2021 | Q49: 45589 | R49: 150526 | S49: 502573 | T49: NEW | V49: KIA PICANTO 1.0 L | W49: 2021 | X49: 25-AUG-2021 | Y49: 03-NOV-2021 | Z49: 03-Nov-2024 | AA49: OLALHR300072354 | AB49: 3 | AC49: CTRK | AD49: DIB0032240 | AE49: 25-OCT-2021 | AF49: 2% | AG49: 1444800 | AH49: 0 | AL49: #N/A | AM49: 0
A50: 427 | B50: NORM | C50: 9976AP1232980003 | D50: Closed | E50: T-PAK | F50: MANDVIWALA MOTORS | G50: SALEHA WAJAHAT | H50: Karachi | I50: 42201-5538754-0 | J50: 03343303808 | K50: 03343303808 | L50: 03343303808 | M50: D-06 STREET 3 PHASE 3 NHS DALMIA RO AD KARACHI PK | N50: 457129 | O50: 4960000 | P50: 76078/0008/10/2023 | Q50: 23-OCT-2024 | R50: 1017053 | S50: 0117018 | T50: NEW | V50: SUZUKI SWIFT GLX | W50: 2023 | X50: 45224 | Y50: 27-OCT-2023 | Z50: 27-Oct-2024 | AA50: OLDKHI300097557 | AB50: 1 | AC50: ITFT | AD50: 10546/10/2023 | AE50: 24-OCT-2023 | AF50: 1.5% | AG50: 3968000 | AH50: 0 | AL50: #N/A | AM50: 0
A51: 428 | B51: NORM | C51: 9976AD2211810015 | D51: Closed | E51: T-PAK | F51: TOYOTA AIRPORT MOTOR | G51: IJAZ AHMED QURESHI | H51: Lahore | I51: 35201-2588151-9 | K51: 03334237570 | M51: HOUSE NO 233 Y BLOCK STREET 14 PHASE III DHA LAHORE | N51: 296726 | O51: 3903000 | P51: 2524/02692/00080/10/2021 | Q51: 45586 | R51: Q353284 | S51: ZRE172R-7052456 | T51: NEW | V51: COROLLA GRANDE X | W51: 2021 | X51: 30-JUN-2021 | Y51: 03-NOV-2021 | Z51: 03-Nov-2024 | AA51: OLALHR300070156 | AB51: 3 | AC51: CTRK | AD51: DIB0032218 | AE51: 22-OCT-2021 | AF51: 2% | AG51: 3122400 | AH51: 0 | AL51: #N/A | AM51: 0
A52: 429 | B52: NORM | C52: 9976AD1211200057 | D52: Closed | E52: T-PAK | F52: PREMIER SYSTEMS (PVT) LTD | G52: MUDASSAR MAQBOOL | H52: Faisalabad | I52: 33100-0989371-7 | K52: 03008662113 | L52: 041242408185 | M52: MUBEEN MAQBOOL INDUSTRIES 3KM JARRANWALA ROAD FAISLABAD | N52: 1957507 | O52: 40800000 | P52: 2021/10/CLFTTPCD01145 | Q52: 45586 | R52: DCB323989 | S52: MD020951 | T52: NEW | V52: AUDI Q7 3.0 TFSI | W52: 2021 | X52: 30-APR-2021 | Y52: 11-NOV-2021 | Z52: 11-Nov-2024 | AA52: OLAFSD300068455 | AB52: 3 | AF52: 1.75% | AG52: 32640000 | AH52: 0 | AL52: #N/A | AM52: 0
A53: 430 | B53: NORM | C53: 9976AD1211200024 | D53: Closed | E53: T-PAK | F53: TOYOTA UNIVERSITY MOTORS | G53: MUHAMMAD FAROOQ | H53: Karachi | I53: 42201-0743428-1 | K53: 03028223007 | L53: 35032590 | M53: SULTAN OXYGEN PVT LTD PLOT NO 73 SECTOR 27 KORANGI INDUSTRIAL AREA KARACHI | N53: 505366 | O53: 9278000 | P53: DIB/T/BT/34147/KHI/1021 | Q53: 45586 | R53: 1GD5074902 | S53: GUN156R-1096761 | T53: NEW | V53: FORTUNER 4*4 SPORTIVO | W53: 2021 | X53: 30-APR-2021 | Y53: 03-NOV-2021 | Z53: 03-Nov-2024 | AA53: OLAKHI300068380 | AB53: 3 | AC53: FLCN | AD53: 108589/10/2021 | AE53: 21-OCT-2021 | AF53: 1.75% | AG53: 7422400 | AH53: 0 | AL53: #N/A | AM53: 0
A54: 431 | B54: NORM | C54: 9976AD2210570016 | D54: Closed | E54: T-PAK | F54: AL-HAJ AUTOMOTIVE PVT LTD | G54: MUHAMMAD ANWAR MUGHAL | H54: Lahore | I54: 34601-9841981-3 | J54: 03214782040 04235693698 | K54: 03214782040 04235693698 | L54: 04239902490 | M54: SPARCO OFFICE SAMSANI ROAD CANAL RO AD LAHORE | N54: 239319 | O54: 5390000 | P54: DIB/T/BT/34152/LHR/1021 | Q54: 45586 | R54: 3G15TDM3UA3101350 | S54: PL1NL2EVRMG028165 | T54: NEW | V54: PROTON X 70 PREMIUM 2WD | W54: 2021 | X54: 26-FEB-2021 | Y54: 03-NOV-2021 | Z54: 03-Nov-2024 | AA54: OLALHR300066171 | AB54: 3 | AC54: ITFT | AD54: 5544/10/2021/ITFM | AE54: 22-OCT-2021 | AF54: 1.75% | AG54: 4312000 | AH54: 0 | AL54: #N/A | AM54: 0
A55: 432 | B55: NORM | C55: 9976AD2210580043 | D55: Closed | E55: T-PAK | F55: AL-HAJ AUTOMOTIVE PVT LTD | G55: SHAHABUDDIN | H55: Karachi | I55: 42301-1049299-5 | K55: 03219229566 | L55: 32416279 | M55: HOUSE NO 115 KHY E GHAZI PHASE 6 DHA KARACHI | N55: 219056 | O55: 5390000 | P55: DIB/T/BT/34130/KHI/1021 | Q55: 45586 | R55: 2UA3100868 | S55: 2EVRMG028219 | T55: NEW | V55: PROTON X70 PREMIUM 2WD | W55: 2021 | X55: 27-FEB-2021 | Y55: 27-OCT-2021 | Z55: 27-Oct-2024 | AA55: OLAKHI300066052 | AB55: 3 | AC55: CTRK | AD55: TDIDIB0029729 | AE55: 25-OCT-2021 | AF55: 1.75% | AG55: 4312000 | AH55: 0 | AL55: #N/A | AM55: 0
A56: 433 | B56: NORM | C56: 9976AP1222970054 | D56: Closed | E56: T-PAK | F56: CAR DEALS | G56: SHEHZAD ANJUM | H56: Karachi | I56: 42101-8385994-9 | K56: 03008282037 | L56: 32580151 | M56: GHULAM RASOOL ENGINEERING E 80 E 81 E82 ADNAN CENTER D/11 A AGS BATTERY SITE KHI | N56: 97508 | O56: 4700000 | P56: 64081/00048/10/2022 | Q56: 45585 | R56: 888965 | S56: 9611427 | T56: USD | U56: KY-0922 | V56: TOYOTA VIGO | W56: 2016 | X56: 24-OCT-2022 | Y56: 27-OCT-2022 | Z56: 27-Oct-2024 | AA56: OLUKHI300090427 | AB56: 2 | AC56: ITFT | AD56: 9122/10/2022/ITFM | AE56: 21-OCT-2022 | AF56: 1.75% | AG56: 3760000 | AH56: 0 | AL56: #N/A | AM56: 0
A57: 434 | B57: NORM | C57: 9976AD2210580020 | D57: Closed | E57: T-PAK | F57: TOYOTA SHAHRA-E-FAISAL MOTORS | G57: ABDUL HAIE | H57: Karachi | I57: 42501-1602929-7 | J57: 021-34496725 | K57: 0300-8205329 | L57: 021-34594533 | M57: H NO IH-25 STREET NO 04 AFOHS NEW FALCON COMPLEX CHOHTA MALIR CNATT CP 5 KARACHI | N57: 434908 | O57: 8408000 | P57: DIB/T/BT/34035/KHI/1021 | Q57: 45585 | R57: 2TRA896067 | S57: 0443989 | T57: NEW | V57: TOYOTA FORTUNER A/T | W57: 2021 | X57: 27-FEB-2021 | Y57: 27-OCT-2021 | Z57: 27-Oct-2024 | AA57: OLAKHI300066347 | AB57: 3 | AC57: CTRK | AD57: TDIDIB0029711 | AE57: 20-OCT-2021 | AF57: 1.75% | AG57: 6726400 | AH57: 0 | AL57: #N/A | AM57: 0
A58: 435 | B58: NORM | C58: 9976AD1212640024 | D58: Closed | E58: T-PAK | F58: TOYOTA SOUTHERN MOTORS | G58: SAIRA BANO | H58: Karachi | I58: 42000-0496051-4 | J58: 02134152916, 0331-2443763 | K58: 03312443763 03353025474 | L58: 34174271 | M58: PLOT # FL-18/3 GROUND FLOOR MEZZAIN INE FLOOR GULSHAN-E-IQBAL BLOCK 3 K DA MARKET NEAR GPO GULSHAN KARACHI | N58: 192534 | O58: 7386500 | P58: 2021/10/CLFTTPCDP01146 | Q58: 45585 | R58: 1GD5062344 | S58: GUN126R-5548739 | T58: NEW | V58: TOYOTA HILUX REVO V DC A/T 4*4 | W58: 2021 | X58: 21-SEP-2021 | Y58: 27-OCT-2021 | Z58: 27-Oct-2024 | AA58: OLAKHI300073792 | AB58: 3 | AC58: CTRK | AD58: DIB0032155 | AE58: 20-OCT-2021 | AF58: 1.75% | AG58: 5909200 | AH58: 0 | AL58: #N/A | AM58: 0
A59: 436 | B59: NORM | C59: 9976AP1212990006 | D59: Closed | E59: T-PAK | F59: NEW S.S MOTORS | G59: NADEEM AKRAM | H59: Faisalabad | I59: 33100-3017612-5 | J59: 03235850000 | K59: 03235850000, 03009661042 | L59: 03235850000 | M59: H NO P-5 ALI BLOCK SITARA GOLD CITY SATYANA ROAD FAISALABAD PK | N59: 130119 | O59: 2525000 | P59: 56038/00055/10/2021 | Q59: 45585 | R59: L13Z17528136 | S59: NFBGM1647KR246040 | T59: USD | U59: ALJ-061 | V59: HONDA CITY I-VTEC P/T | W59: 2019 | X59: 26-OCT-2021 | Y59: 27-OCT-2021 | Z59: 27-Oct-2024 | AA59: OLUFSD300075992 | AB59: 3 | AC59: CTRK | AD59: DIB0032224 | AE59: 25-OCT-2021 | AF59: 2% | AG59: 2020000 | AH59: 0 | AL59: #N/A | AM59: 0
A60: 437 | B60: NORM | C60: 9976AP2232970009 | D60: Closed | E60: T-PAK | F60: SUZUKI ISLAMABAD MOTORS | G60: HAFIZ ASHRAF ALI | H60: Islamabad | I60: 21702-9776700-5 | K60: 0097439931586 | M60: AREA ABUHAMOUR ZONE 56? ST 492? BUILDING 4 DOHA 1930 QATAR | N60: 162627 | O60: 2935000 | P60: 76078/0006/10/2023 | Q60: 19-OCT-2024 | R60: 285494 | S60: 1185580 | T60: RDA | V60: SUZUKI ALTO VXL AGS EURO II | W60: 2023 | X60: 45223 | Y60: 27-OCT-2023 | Z60: 27-Oct-2024 | AA60: OLDISD300097534 | AB60: 1 | AC60: CTRK | AD60: DIB0035389 | AE60: 23-OCT-2023 | AF60: 1.4% | AG60: 2348000 | AH60: 0 | AL60: #N/A | AM60: 0
A61: 438 | B61: NORM | C61: 9976AD1211230088 | D61: Closed | E61: T-PAK | F61: TOYOTA WALTON MOTORS | G61: SHER ZAMAN KHAN | H61: Lahore | I61: 35201-1316887-3 | J61: 03400127073 | K61: 03400127073 | L61: 03400127073 | M61: NEW BHOGIWAL CHOWK GUJJAR PURA CHIN A SCHEME LAHORE | N61: 166563 | O61: 3283000 | P61: 2021-10-205-V01501OP0002461 | Q61: 45584 | R61: Q081602 | S61: 6059085 | T61: NEW | V61: TOYOTA COROLLA ALTIS A/T | W61: 2021 | X61: 03-MAY-2021 | Y61: 03-NOV-2021 | Z61: 03-Nov-2024 | AA61: OLALHR300068635 | AB61: 3 | AC61: CTRK | AD61: DIB0032181 | AE61: 20-OCT-2021 | AF61: 2% | AG61: 2626400 | AH61: 0 | AL61: #N/A | AM61: 0
A62: 439 | B62: NORM | C62: 9976AD1211090002 | D62: Closed | E62: T-PAK | F62: TOYOTA FAISALABAD | G62: MUHAMMAD RAHMAN | H62: Faisalabad | I62: 33100-2620492-1 | J62: 8726303 | K62: 8726303, 8726303 | L62: 2611993 | M62: P-128 C BLOCK PEOPLES COLONY 01 FSD FAISALABAD PK | N62: 120866 | O62: 3283000 | P62: DIB/T/BT/33853/LHR/1021 | Q62: 45584 | R62: Q082061 | S62: 6059566 | T62: NEW | V62: TOYOTA COROLLA ALTIS A/T | W62: 2021 | X62: 19-APR-2021 | Y62: 03-NOV-2021 | Z62: 03-Nov-2024 | AA62: OLAFSD300067873 | AB62: 3 | AC62: CTRK | AD62: TDIDIB0029713 | AE62: 20-OCT-2021 | AF62: 2% | AG62: 2626400 | AH62: 0 | AL62: #N/A | AM62: 0
A63: 440 | B63: NORM | C63: 9976AD2212170066 | D63: Closed | E63: T-PAK | F63: PAK SUZUKI MOTOR CO LTD | G63: SYED ARSALAN QAMAR | H63: Islamabad | I63: 31202-4797210-1 | J63: 03005552275 | L63: 0 | M63: H # 536 UPER PORTION ST # 5 G-11/1 ISLAMABAD PK | N63: 108755 | O63: 1521000 | P63: 01-2110-PO-MTR-PCCM-D-001443 | Q63: 45584 | R63: 188310 | S63: 1088308 | T63: NEW | V63: SUZUKI ALTO VXL AGS EURO II | W63: 2021 | X63: 05-AUG-2021 | Y63: 03-NOV-2021 | Z63: 03-Nov-2024 | AA63: OLAISD300071644 | AB63: 3 | AC63: CTRK | AD63: DIB0032230 | AE63: 27-OCT-2021 | AF63: 2% | AG63: 1216800 | AH63: 0 | AL63: #N/A | AM63: 0
A64: 441 | B64: NORM | C64: 9976AD1221030006 | D64: Closed | E64: T-PAK | F64: PAK SUZUKI MOTOR CO LTD | G64: HAMAD ALI | H64: Rawalpindi | I64: 17201-3414186-3 | J64: 03339418668 | L64: 0512746070 | M64: H # CB-825/1 MISRIAL ROAD PIA COLON Y CHORR CHOWK NEAR HAKIM PLAZA RAWALPINDI PK | N64: 52577 | O64: 1675000 | P64: 64081/00040/10/2022 | Q64: 45583 | R64: 251339 | S64: 1151343 | T64: NEW | V64: SUZUKI ALTO VXR EURO-II | W64: 2022 | X64: 13-APR-2022 | Y64: 27-OCT-2022 | Z64: 27-Oct-2024 | AA64: OLARWP300086422 | AB64: 2 | AC64: ITECL | AD64: 9097/10/2022 | AE64: 20-OCT-2022 | AF64: 2% | AG64: 1340000 | AH64: 0 | AL64: #N/A | AM64: 0
A65: 442 | B65: NORM | C65: 9976AP1222930037 | D65: Closed | E65: T-PAK | F65: CAR CAPITAL | G65: HAMZA | H65: Karachi | I65: 42201-6900403-5 | K65: 03009225864 | M65: HNO: D-53 BLOCK 08 GULSHAN-E-IQBAL KARACHI PK | N65: 103732 | O65: 5000000 | P65: 64081/000037/10/2022 | Q65: 45583 | R65: Z16929393 | S65: MR081980 | T65: USD | U65: BVU-671 | V65: HONDA CIVIC 1.8 ORIEL | W65: 2021 | X65: 20-OCT-2022 | Y65: 21-OCT-2022 | Z65: 21-Oct-2024 | AA65: OLUKHI300090371 | AB65: 2 | AC65: ITFM | AD65: 9078/10/2022/ITFM | AE65: 19-OCT-2022 | AF65: 1.75% | AG65: 4000000 | AH65: 0 | AL65: #N/A | AM65: 0
A66: 443 | B66: WACH | C66: 9976AP1212950003 | D66: Closed | E66: T-PAK | F66: FAROOQ MOTORS | G66: MUHAMMAD IRFAN WARRAICH | H66: Lahore | I66: 35202-2427281-3 | J66: 03064390200 | K66: 03064390200 | L66: 03064390200 | M66: BHATTA NO 14 NEAR PARADISE BAKERY N AWAN PIND HARBANSPURA LAHORE | N66: 104469 | O66: 4010000 | P66: 2524/02692/00061/10/2021 | Q66: 45582 | R66: 16913721 | S66: 065597 | T66: USD | U66: AEZ-443 | V66: HONDA CIVIC VTI ORIEL P/T | W66: 2020 | X66: 22-OCT-2021 | Y66: 27-OCT-2021 | Z66: 27-Oct-2024 | AA66: OLULHR300075503 | AB66: 3 | AC66: CTRK | AD66: DIB0032159 | AE66: 18-OCT-2021 | AF66: 2% | AG66: 3208000 | AH66: 0 | AL66: #N/A | AM66: 0
A67: 444 | B67: NORM | C67: 9976AP1222920030 | D67: Closed | E67: T-PAK | F67: NEW CAR COMPLEX | G67: MUHAMMAD ABBAS | H67: Karachi | I67: 42000-0534907-5 | J67: 03003638496 | K67: 03003638496 | L67: 35386639 | M67: HOUSE # 27 SECTOR-A BHITTAI COLONY KORANGI CREEK NEAR KARACHI PUBLIC S KARACHI PK | N67: 101656 | O67: 2800000 | P67: 64081/000036/10/2022 | Q67: 45582 | R67: WR-0761 | S67: NP000331 | T67: USD | U67: BVV-764 | V67: PROTON SAGA A/T | W67: 2022 | X67: 19-OCT-2022 | Y67: 21-OCT-2022 | Z67: 21-Oct-2024 | AA67: OLUKHI300090370 | AB67: 2 | AC67: ITFM | AD67: 9062/10/2022/ITFM | AE67: 19-OCT-2022 | AF67: 1.75% | AG67: 2240000 | AH67: 0 | AL67: #N/A | AM67: 0
A68: 445 | B68: NORM | C68: 9976AD1212430050 | D68: Closed | E68: T-PAK | F68: TOYOTA FAISALABAD | G68: HAFIZ NAYYAR KHURSHID | H68: Faisalabad | I68: 35202-1628693-5 | J68: 03122520001 | K68: 03122520001, 03122520001 | L68: 03122520001 | M68: P-767/54 ST NO 01 BAZAR STREET NO 2 1 RAZA ABAD FSD FAISALABAD PK | N68: 838473 | O68: 2703000 | P68: 2021-10-205-V01501OP0002451 | Q68: 45582 | R68: 2A38708 | S68: 7024228 | T68: NEW | V68: TOYOTA YARIS ATIV | W68: 2021 | X68: 31-AUG-2021 | Y68: 27-OCT-2021 | Z68: 27-Oct-2026 | AA68: OLAFSD300072644 | AB68: 5 | AC68: CTRK | AD68: DIB0032157 | AE68: 18-OCT-2021 | AF68: 2% | AG68: 2162400 | AH68: 0 | AL68: KHI/HO/D/MO/PC COMP/C/99821/232/10/2024 | AM68: 43248
A69: 446 | B69: NORM | C69: 9976AP1212940026 | D69: Closed | E69: T-PAK | F69: SHADOW MOTORS | G69: IMRAN ALI | H69: Karachi | I69: 41303-4831051-1 | J69: 03008372607 | K69: 03008372607 | L69: 03008372607 | M69: FLAT # 202 KHURASAN VIEW APT NOMAIS H KARACHI PK | N69: 33786 | O69: 1521000 | P69: 56038/00040/10/2021 | Q69: 45582 | R69: 6R171970 | S69: NF1AET306H1071952 | T69: USD | V69: SUZUKI ALTO VXL AGS EURO II | W69: 2021 | X69: 21-OCT-2021 | Y69: 21-OCT-2021 | Z69: 21-Oct-2024 | AA69: OLUKHI300075614 | AB69: 3 | AC69: CTRK | AD69: DIB0032180 | AE69: 20-OCT-2021 | AF69: 2% | AG69: 1216800 | AH69: 0 | AL69: #N/A | AM69: 0
A70: 447 | B70: NORM | C70: 9976AD2210580013 | D70: Closed | E70: T-PAK | F70: AL-HAJ AUTOMOTIVE PVT LTD | G70: KHURRAM AFZAL | H70: Lahore | I70: 35202-7463007-3 | J70: 03214748127 | K70: 03214748127 | L70: 03233451111 | M70: 4TH FLOOR 124-MB PHASE 6 DHA NEAR 4 TH FLOOR HBL LAHORE | N70: 199435 | O70: 5390000 | P70: DIB/T/BT/33849/LHR/1021 | Q70: 45579 | R70: 3101316 | S70: 028186 | T70: NEW | V70: PROTON X70 PREMIUM 2WD | W70: 2021 | X70: 27-FEB-2021 | Y70: 03-NOV-2021 | Z70: 03-Nov-2024 | AA70: OLALHR300066372 | AB70: 3 | AC70: CTRK | AD70: TDIDIB0029708 | AE70: 18-OCT-2021 | AF70: 1.75% | AG70: 4312000 | AH70: 0 | AL70: #N/A | AM70: 0
A71: 448 | B71: NORM | C71: 9976AD1212110058 | D71: Closed | E71: T-PAK | F71: KIA CLIFTON | G71: MIRZA MUHAMMAD KASHIF | H71: Faisalabad | I71: 33100-0590412-9 | J71: 0300-8664402 | K71: 03008664402 | L71: 041-2657397 | M71: H NO P-640 ST NO 11 NISAR COLONY FAISALABAD | N71: 147675 | O71: 5270000 | P71: DIB/T/BT/33721/LHR/0921 | Q71: 45577 | R71: 314355 | S71: 512786 | T71: NEW | V71: SPORTAGE AWD | W71: 2021 | X71: 30-JUL-2021 | Y71: 27-OCT-2021 | Z71: 27-Oct-2024 | AA71: OLAFSD300071287 | AB71: 3 | AF71: 1.75% | AG71: 4216000 | AH71: 0 | AL71: #N/A | AM71: 0
A72: 449 | B72: NORM | C72: 9976AD2212250009 | D72: Closed | E72: T-PAK | F72: TOYOTA GARDEN MOTORS | G72: DANISH | H72: Lahore | I72: 35202-9259545-5 | K72: 03220285261 | M72: HOUSE NO 65 - P MOHALLA MARGAZAR COLONY MULTAN ROAD LAHORE | N72: 136149 | O72: 2623000 | P72: 2524/02692/00047/10/2021 | Q72: 45577 | R72: 2A37215 | S72: NSP150R-7023420 | T72: NEW | V72: TOYATA YARIS GLI CVT 1.3 | W72: 2021 | X72: 13-AUG-2021 | Y72: 03-NOV-2021 | Z72: 03-Nov-2024 | AA72: OLALHR300071887 | AB72: 3 | AC72: CTRK | AD72: DIB032107 | AE72: 14-OCT-2021 | AF72: 2% | AG72: 2098400 | AH72: 0 | AL72: #N/A | AM72: 0
A73: 450 | B73: NORM | C73: 9976AD1221160028 | D73: Closed | E73: T-PAK | F73: PAK SUZUKI MOTOR CO LTD | G73: SAJID SAEED | H73: Wah Cantt | I73: 37406-8699959-5 | J73: 03450091506 | L73: 0519217728 | M73: H # 214/9 ST # 8 OFFICER COLONY PHA SE 2 TAXILA WAH CANT TAXILA PK | N73: 1401765 | O73: 1886000 | P73: 64081/00020/10/2022 | Q73: 45576 | R73: 251506 | S73: 1151514 | T73: NEW | V73: SUZUKI ALTO VXL AGS EURO-II | W73: 2022 | X73: 26-APR-2022 | Y73: 21-OCT-2022 | Z73: 21-Oct-2029 | AA73: OLAWAH300086845 | AB73: 7 | AC73: ITFM | AD73: 9004/10/2022/ITFM | AE73: 12-OCT-2022 | AF73: 1.75% | AG73: 1603100 | AH73: 0 | AL73: KHI/HO/D/MO/PC COMP/C/99821/157/10/2024 | AM73: 28054.25
A74: 451 | B74: NORM | C74: 9976AD1210580093 | D74: Closed | E74: T-PAK | F74: AL-HAJ AUTOMOTIVE PVT LTD | G74: FURQAN HAMEED | H74: Lahore | I74: 35201-1145817-1 | J74: 03214049091 | K74: 03214049091 | L74: 03214049091 | M74: LIDHER ROAD KAMAHAN BEDIAN ROAD NEA R DERA HAJI NAZIR MYO LAHORE | N74: 279206 | O74: 5390000 | P74: DIB/T/BT/33834/LHR/1021 | Q74: 45576 | R74: 3101384 | S74: 028163 | T74: NEW | V74: PROTON X70 PREMIUM 2WD | W74: 2021 | X74: 27-FEB-2021 | Y74: 03-NOV-2021 | Z74: 03-Nov-2024 | AA74: OLALHR300066480 | AB74: 3 | AC74: CTRK | AD74: TDIDIB0029699 | AE74: 12-OCT-2021 | AF74: 1.75% | AG74: 4312000 | AH74: 0 | AL74: #N/A | AM74: 0
A75: 452 | B75: NORM | C75: 9976AD1212350007 | D75: Closed | E75: T-PAK | F75: TOYOTA AIRPORT MOTOR | G75: ASIM AJMAL HUSSAIN | H75: Sialkot | I75: 34603-7832613-1 | J75: 03107217130 | K75: 03107217130 | L75: 03107217130 | M75: MOH MADINA MASJID BONKAN ROAD PACCA GARHA SIALKOT PK | N75: 75306 | O75: 2703000 | P75: PL-1021-1101010102-V14-D-00477 | Q75: 45576 | R75: 2A38424 | S75: NSP150R-7024025 | T75: NEW | V75: TOYOTA YARIS ATIV CVT 1.3 | W75: 2021 | X75: 23-AUG-2021 | Y75: 21-OCT-2021 | Z75: 21-Oct-2024 | AA75: OLASKT300072009 | AB75: 3 | AC75: CTRK | AD75: DIB0032100 | AE75: 13-OCT-2021 | AF75: 2% | AG75: 2162400 | AH75: 0 | AL75: #N/A | AM75: 0
A76: 453 | B76: NORM | C76: 9976AD1211480039 | D76: Closed | E76: T-PAK | F76: PRINCE SAJJAD MOTORS | G76: FARIHA SAJID | H76: Chakwal | I76: 37201-9547359-2 | K76: 03315005535 | M76: SAJID HOUSE NEAR CHAKWAL CNG KHAYABAN E ABU BAKAR SIDDIQUE JAHANGIR TOWN BHOUN ROAD CHAKWAL | N76: 133999 | O76: 4549000 | P76: DIB/T/BT/33828/ISB/1021 | Q76: 45576 | R76: 21026235 | S76: R21H1786 | T76: NEW | V76: PRINCE GLORY 580 PRO | W76: 2021 | X76: 28-MAY-2021 | Y76: 03-NOV-2021 | Z76: 03-Nov-2024 | AA76: OLACHW300069007 | AB76: 3 | AC76: CTRK | AD76: TDIDIB0029697 | AE76: 30-OCT-2021 | AF76: 2% | AG76: 3639200 | AH76: 0 | AL76: #N/A | AM76: 0
A77: 454 | B77: NORM | C77: 9976AD1212080037 | D77: Closed | E77: T-PAK | F77: PAK SUZUKI MOTOR CO LTD | G77: SHAHID WALI | H77: Faisalabad | I77: 33100-9354205-3 | J77: 03057703270 | K77: 03057703270, 03057703270 | L77: 03057703270 | M77: P- 127 D-BLOCK MOHALLAH MISTRIAN GM ABAD FAISALABAD PK | N77: 45733 | O77: 1760000 | P77: 01-2110-PO-MTR-PCCM-D-001370 | Q77: 45576 | R77: PK10B221649 | S77: A1J310PK10121680 | T77: NEW | V77: SUZUKI WAGON R VXL AGS | W77: 2021 | X77: 27-JUL-2021 | Y77: 21-OCT-2021 | Z77: 21-Oct-2024 | AA77: OLAFSD300070991 | AB77: 3 | AC77: CTRK | AD77: DIB0032046 | AE77: 12-OCT-2021 | AF77: 2% | AG77: 1408000 | AH77: 0 | AL77: #N/A | AM77: 0
A78: 455 | B78: NORM | C78: 9976AD2212120040 | D78: Closed | E78: T-PAK | F78: FEDERAL MOTORS | G78: IMRAN KHAN | H78: Islamabad | I78: 42000-0537301-7 | J78: 03458281721 | L78: 0 | M78: H # 211-C ST # 31 BLOCK -C PWD NEAR LONDON BAKERY ISLAMABAD PK | N78: 28431 | O78: 1521000 | P78: 01-2110-PO-MTR-PCCM-D-001389 | Q78: 45576 | R78: 186066 | S78: 1085984 | T78: NEW | V78: SUZUKI ALTO VXL AGS EURO II | W78: 2021 | X78: 31-JUL-2021 | Y78: 21-OCT-2021 | Z78: 21-Oct-2024 | AA78: OLAISD300071505 | AB78: 3 | AC78: ITECL | AD78: 5513/10/2021 | AE78: 12-OCT-2021 | AF78: 2% | AG78: 1216800 | AH78: 0 | AL78: #N/A | AM78: 0
A79: 456 | B79: NORM | C79: 9976AD1211940009 | D79: Closed | E79: T-PAK | F79: PAK SUZUKI MOTOR CO LTD | G79: MUHAMMAD ALMAS DILAWAR | H79: Lahore | I79: 35202-2363890-1 | J79: 03124423213 | K79: 03124423213 | L79: 04235916352 | M79: 53-A Q-BLOCK MODEL TOWN COLONY MODE L TOWN NEAR BANDU KHAN BAKERY LAHORE | N79: 29777 | O79: 1335000 | P79: 2021-10-205-V01501OP0002420 | Q79: 45575 | R79: 184920 | S79: 1084837 | T79: NEW | V79: ALTO VXR EURO II | W79: 2021 | X79: 13-JUL-2021 | Y79: 27-OCT-2021 | Z79: 27-Oct-2024 | AA79: OLALHR300070543 | AB79: 3 | AC79: CTRK | AD79: DIB0032079 | AE79: 12-OCT-2021 | AF79: 2% | AG79: 1068000 | AH79: 0 | AL79: #N/A | AM79: 0
A80: 457 | B80: NORM | C80: 9976AD1211940004 | D80: Closed | E80: T-PAK | F80: PAK SUZUKI MOTOR CO LTD | G80: MUHAMMAD ALMAS DILAWAR | H80: Lahore | I80: 35202-2363890-1 | J80: 03124423213 | K80: 03124423213 | L80: 04235916352 | M80: 53-A Q-BLOCK MODEL TOWN COLONY MODE L TOWN NEAR BANDU KHAN BAKERY LAHORE | N80: 27293 | O80: 1335000 | P80: 2021-10-205-V01501OP0002421 | Q80: 45575 | R80: 184772 | S80: 1084770 | T80: NEW | V80: ALTO VXR EURO II | W80: 2021 | X80: 13-JUL-2021 | Y80: 27-OCT-2021 | Z80: 27-Oct-2024 | AA80: OLALHR300070544 | AB80: 3 | AC80: CTRK | AD80: DIB0032080 | AE80: 12-OCT-2021 | AF80: 2% | AG80: 1068000 | AH80: 0 | AL80: #N/A | AM80: 0
A81: 458 | B81: NORM | C81: 9976AD1210150004 | D81: Closed | E81: T-PAK | F81: HYUNDAI D GROUND MOTORS | G81: MUHAMMAD AMJID | H81: Faisalabad | I81: 33100-5543898-1 | J81: 03008650974 | K81: 03008650974, 03008650974 | L81: 0412656436 | M81: H NO P-195-A ST NO 5 NEAR A PLUS AC ADEMY GARDENS COLONY FAISALABAD PK | N81: 101438 | O81: 5473000 | P81: 01-2109-PO-MTR-PCCM-D-001349 | Q81: 45572 | R81: G4NAMU107266 | S81: PHMJ2813SMN204540 | T81: NEW | V81: TUCSON AWD | W81: 2021 | X81: 15-JAN-2021 | Y81: 21-OCT-2021 | Z81: 21-Oct-2024 | AA81: OLAFSD300065032 | AB81: 3 | AC81: CTRK | AD81: DIB0032000 | AE81: 08-OCT-2021 | AF81: 2% | AG81: 4378400 | AH81: 0 | AL81: #N/A | AM81: 0
A82: 459 | B82: NORM | C82: 9976AP1212840005 | D82: Closed | E82: T-PAK | F82: SAEED AUTOS | G82: MUHAMMAD ASIM | H82: Faisalabad | I82: 33100-0858573-7 | J82: 03143110308 | K82: 03143110308, 03143110308 | L82: 03143110308 | M82: P-70 KHALID BIN WALEED ROAD DAWOO R OAD RIAZ UL JINNAH FAISALABAD PK | N82: 95882 | O82: 1860000 | P82: 56038/00022/10/2021 | Q82: 45572 | R82: 145385 | S82: 10045359 | T82: USD | U82: ADZ-372 | V82: SUZUKI CULTUS VXL EURO II | W82: 2019 | X82: 11-OCT-2021 | Y82: 11-OCT-2021 | Z82: 11-Oct-2024 | AA82: OLUFSD300074826 | AB82: 3 | AC82: CTRK | AD82: DIB0032064 | AE82: 08-OCT-2021 | AF82: 2% | AG82: 1488000 | AH82: 0 | AL82: #N/A | AM82: 0
A83: 460 | B83: NORM | C83: 9976AP1212840006 | D83: Closed | E83: T-PAK | F83: SAEED AUTOS | G83: MUHAMMAD NABEEL SALEEM | H83: Faisalabad | I83: 33102-7404256-5 | J83: 03067110060 | K83: 03067110060, 03067110060 | L83: 03067110060 | M83: P-48 ST NO 17 ABDULLAH PUR FSD NEAR DR SHAHZAD NAWAR FAISALABAD PK | N83: 37975 | O83: 1700000 | P83: 56038/00021/10/2021 | Q83: 45572 | R83: 124726 | S83: 10024700 | T83: USD | U83: LE-18A-9217 | V83: SUZUKI WAGONR VXL | W83: 2018 | X83: 11-OCT-2021 | Y83: 11-OCT-2021 | Z83: 11-Oct-2024 | AA83: OLUFSD300074825 | AB83: 3 | AC83: CTRK | AD83: DIB0032058 | AE83: 11-OCT-2021 | AF83: 2% | AG83: 1360000 | AH83: 0 | AL83: #N/A | AM83: 0
A84: 461 | B84: NORM | C84: 9976AD1212100027 | D84: Closed | E84: T-PAK | F84: KIA CLIFTON | G84: FAISAL MEHMOOD | H84: Faisalabad | I84: 33100-9451697-5 | J84: 03219668372 | K84: 03219668372, 03219668372 | L84: 0412634708 | M84: P-206-C SITARA GOLD CITY FAISALABAD PK | N84: 98129 | O84: 4782000 | P84: DIB/T/33732/LHR/0921 | Q84: 45570 | R84: 306850 | S84: 306334 | T84: NEW | V84: KIA SPORTGE FWD | W84: 2021 | X84: 29-JUL-2021 | Y84: 21-OCT-2021 | Z84: 21-Oct-2024 | AA84: OLASFSD300071292 | AB84: 3 | AF84: 1.75% | AG84: 3825600 | AH84: 0 | AL84: #N/A | AM84: 0
A85: 462 | B85: NORM | C85: 9976AD2211970001 | D85: Closed | E85: T-PAK | F85: PAK SUZUKI MOTOR CO LTD | G85: MUHAMMAD HAMID SAEED | H85: Faisalabad | I85: 33100-5900695-9 | J85: 03218664472 | K85: 03218664472, 03218664472 | L85: 03218664472 | M85: H NO 70-A PEOPLES COLONY FSD FAISALABAD PK | N85: 99478 | O85: 1830000 | P85: DIB/T/BT/33718/LHR/0921 | Q85: 45570 | R85: PK10K185546 | S85: NF1AVK31H10085544 | T85: NEW | V85: SUZUKI CULTUS VXL EURO-II | W85: 2021 | X85: 16-JUL-2021 | Y85: 21-OCT-2021 | Z85: 21-Oct-2024 | AA85: OLAFSD300070803 | AB85: 3 | AC85: CTRK | AD85: DIB0031914 | AE85: 06-OCT-2021 | AF85: 2% | AG85: 1464000 | AH85: 0 | AL85: #N/A | AM85: 0
A86: 463 | B86: NORM | C86: 9976AD1211960005 | D86: Closed | E86: T-PAK | F86: PAK SUZUKI MOTOR CO LTD | G86: MOHSIN PERVEZ | H86: Lahore | I86: 35202-7757033-3 | J86: 03238666682 | K86: 03238666682 | L86: 37380496 | M86: EME SOCIETY HOUSE NO 203 E STREET NO 14 MOHALLA DHA MULTAN ROAD LAHORE | N86: 58900 | O86: 1335000 | P86: 2021-10-205-V01501OP0002397 | Q86: 45570 | R86: 186484 | S86: 1086406 | T86: NEW | V86: ALTO VXR EURO II | W86: 2021 | X86: 15-JUL-2021 | Y86: 27-OCT-2021 | Z86: 27-Oct-2024 | AA86: OLALHR300070812 | AB86: 3 | AC86: ITECL | AD86: 5497/10/2021 | AE86: 06-OCT-2021 | AF86: 2% | AG86: 1068000 | AH86: 0 | AL86: #N/A | AM86: 0
A87: 464 | B87: NORM | C87: 9976AD1212070013 | D87: Closed | E87: T-PAK | F87: ALI JAN MOTORS | G87: ASIF BHATTI | H87: Gujranwala | I87: 34101-6712641-3 | J87: 03422989070 | K87: 03422989070 | L87: 03422989070 | M87: SIALKOT ROAD ST NO 6 BLOCK C RAJA C OLONY GUJRANWALA PK | N87: 900877 | O87: 1610000 | P87: 56038/00009/10/2021 | Q87: 45569 | R87: 21643 | S87: 10121651 | T87: NEW | V87: WAGONR VXL | W87: 2021 | X87: 26-JUL-2021 | Y87: 03-NOV-2021 | Z87: 03-Nov-2028 | AA87: OLAGWL300070925 | AB87: 7 | AC87: ITECL | AD87: 5489/10/2021 | AE87: 05-OCT-2021 | AF87: 2% | AG87: 1288000 | AH87: 0 | AL87: KHI/HO/D/MO/PC COMP/C/99821/31/10/2024 | AM87: 25760
A88: 465 | B88: NORM | C88: 9976AD1211960004 | D88: Closed | E88: T-PAK | F88: SUZUKI SUMMIT MOTORS PVT LTD. | G88: SALMAN RIAZ | H88: Gujranwala | I88: 34101-7698201-7 | J88: 03216421603 | K88: 03216421603 | L88: 03216421603 | M88: US MOBILE ANDRON SIALKOTI GATE GUJRANWALA | N88: 39525 | O88: 1521000 | P88: DIB/T/BT/33761/LHR/1021 | Q88: 45569 | R88: 185931 | S88: 1085979 | T88: NEW | V88: ALTO VXL AGS EURO II | W88: 2021 | X88: 15-JUL-2021 | Y88: 21-OCT-2021 | Z88: 21-Oct-2024 | AA88: OLAGWL300070712 | AB88: 3 | AC88: ITFM | AD88: 5490/10/2021/ITFM | AE88: 05-OCT-2021 | AF88: 1.75% | AG88: 1216800 | AH88: 0 | AL88: #N/A | AM88: 0
A89: 466 | B89: NORM | C89: 9976AD1211940003 | D89: Closed | E89: T-PAK | F89: KIA MOTORS CANAL ROAD | G89: MUHAMMAD BILAL | H89: Faisalabad | I89: 33100-0319492-9 | J89: 041-2657744 | K89: 03218664046 | L89: 0412656053 | M89: C-52 LIAQAT TOWN NEAR MUHAMMADI PARK FAISALABAD | N89: 105274 | O89: 4327000 | P89: 2021/09/CLFTTPCDP01070 | Q89: 45568 | R89: G4NAMH319006 | S89: NNAQL51AZLP102241 | T89: NEW | V89: SPORTAGE ALPHA | W89: 2021 | X89: 13-JUL-2021 | Y89: 11-OCT-2021 | Z89: 11-Oct-2024 | AA89: OLAFSD300070578 | AB89: 3 | AF89: 2% | AG89: 3461600 | AH89: 0 | AL89: #N/A | AM89: 0
A90: 467 | B90: NORM | C90: 9976AD2212250016 | D90: Closed | E90: T-PAK | F90: TOYOTA SOUTHERN MOTORS | G90: MUHAMMAD ALI SHAHZADA | H90: Karachi | I90: 42201-5958122-7 | J90: 34523930 | K90: 0300-8278770 | L90: 356670609 35662609 | M90: H# R-87 ST# 20 KHAYABAN-E-ROOMI PHASE-8 NEAR KHAYABAN-E-TARIQ KARACHI | N90: 74872 | O90: 2675000 | P90: 2524/02692/00001/10/2021 | Q90: 45568 | R90: 2A37438 | S90: 7023514 | T90: NEW | V90: TOYOTA YARIS ATIV CVT 1.3 | W90: 2021 | X90: 13-AUG-2021 | Y90: 03-OCT-2021 | Z90: 03-Oct-2024 | AA90: OLAKHI300071929 | AB90: 3 | AC90: ITECL | AD90: 5465/09/2021 | AE90: 27-SEP-2021 | AF90: 2% | AG90: 2140000 | AH90: 0 | AL90: N/A | AM90: 0
A91: 468 | B91: NORM | C91: 9976AD1212140142 | D91: Closed | E91: T-PAK | F91: PAK SUZUKI MOTOR CO LTD | G91: SAIMA BATOOL | H91: Haripur | I91: 45303-8958540-2 | J91: 03317322274 | L91: 0 | M91: H # D-79 TandT COLONY NEAR NRTC HARIPUR PK | N91: 55023 | O91: 1975000 | P91: 2021/09/CLFTTPCDP01111 | Q91: 45568 | R91: PK10K186453 | S91: NF1AVK31H10086470 | T91: NEW | V91: SUZUKI CULTUS VXL AGS EURO II | W91: 2021 | X91: 02-AUG-2021 | Y91: 21-OCT-2021 | Z91: 21-Oct-2024 | AA91: OLALHR300071446 | AB91: 3 | AC91: ITECL | AD91: 5481/10/2021 | AE91: 04-OCT-2021 | AF91: 2% | AG91: 1580000 | AH91: 0 | AL91: #N/A | AM91: 0
A92: 469 | B92: NORM | C92: 9976AD1232380001 | D92: Closed | E92: T-PAK | F92: HYUNDAI SHAHRAH E FAISAL | G92: WAQAS AMIN | H92: Karachi | I92: 42201-8971878-5 | J92: 03323050235 | K92: 03323050235 | L92: 0 | M92: FLAT # G-2 C-174 GULISTAN E JOHAR B LOCK 14 KHI KARACHI PK | N92: 216438 | O92: 8230000 | P92: 76078/00001/10/2023 | Q92: 01-OCT-2024 | R92: 362428 | S92: 214957 | T92: NEW | V92: HYUNDAI TUCSON FWD | W92: 2023 | X92: 45164 | Y92: 11-OCT-2023 | Z92: 11-Oct-2024 | AA92: OLAKHI300096468 | AB92: 1 | AC92: CTRK | AD92: DIB0035331 | AE92: 28-SEP-2023 | AF92: 1.75% | AG92: 6584000 | AH92: 0 | AL92: #N/A | AM92: 0
A93: 9 | B93: NORM | C93: 9976AD1211740033 | D93: Active | E93: T-PAK | F93: HONDA FALCON SIALKOT | G93: AKIF ABBAS | H93: Sialkot | I93: 34602-5004905-9 | J93: 03219408040 | K93: 03219408040 | L93: 03219408040 | M93: ZIANA INDUSTRIES ISLAM NAGAR ROAD P ACCA GARH SIALKOT | N93: 174347 | O93: 2455000 | P93: PL-1021-1101010102-V14-D-00462 | Q93: 45568 | R93: L12B51002080 | S93: NFBGN8523MR002765 | T93: NEW | V93: HONDA CITY I-VTEC M/T | W93: 2021 | X93: 23-JUN-2021 | Y93: 03-NOV-2021 | Z93: 03-Nov-2024 | AA93: OLASKT300069693 | AB93: 3 | AC93: CTRK | AD93: DIB0032007 | AE93: 06-OCT-2021 | AF93: 2% | AG93: 1964000 | AH93: 0 | AL93: #N/A | AM93: 0
A94: 13 | B94: NORM | C94: 9976AD1211110019 | D94: Active | E94: T-PAK | F94: HONDA GUJRANWALA | G94: JAVED IQBAL | H94: Gujranwala | I94: 38402-4769167-5 | J94: 03215912021 | K94: 03215912021 | L94: 03215912021 | M94: AUTO MKT SIALKOT ROAD LINK TEHSIL R OAD NEAR TEHSIL OFFICE GUJRANWALA | N94: 49084 | O94: 2645000 | P94: 2021-10-205-V01501OP0002385 | Q94: 45569 | R94: L12B51002904 | S94: NFBGN8625MR003933 | T94: NEW | V94: HONDA CITY IVTEC P/T | W94: 2021 | X94: 21-APR-2021 | Y94: 21-OCT-2021 | Z94: 21-Oct-2024 | AA94: OLAGWL300068050 | AB94: 3 | AC94: CTRK | AD94: DIB0032017 | AE94: 06-OCT-2021 | AF94: 2% | AG94: 2116000 | AH94: 0 | AL94: #N/A | AM94: 0
A95: 16 | B95: NORM | C95: 9976AD1212390014 | D95: Active | E95: T-PAK | F95: TOYOTA FAISALABAD | G95: MUHAMMAD AKRAM | H95: Faisalabad | I95: 33100-2251475-3 | J95: 03237676483 | K95: 03237676483, 03237676483 | L95: 03237676483 | M95: H NO 131 B BLOCK LIAQAT TOWN FAISALABAD PK | N95: 161919 | O95: 2933000 | P95: DIB/T/BT/33757/LHR/1021 | Q95: 45569 | R95: 2A37797 | S95: 9514013 | T95: NEW | V95: TOYOTA YARIS ATIV X CVT | W95: 2021 | X95: 27-AUG-2021 | Y95: 11-OCT-2021 | Z95: 11-Oct-2024 | AA95: OLAFSD300072458 | AB95: 3 | AC95: CTRK | AD95: DIB0032001 | AE95: 05-OCT-2021 | AF95: 2% | AG95: 2346400 | AH95: 0 | AL95: #N/A | AM95: 0
A96: 26 | B96: NORM | C96: 9976AD2212230007 | D96: Active | E96: T-PAK | F96: TOYOTA CAPITAL MOTORS | G96: SHAHZAD NAVEED | H96: Islamabad | I96: 13101-0883937-7 | K96: 03008505212 | M96: PLOT NO 395 396 INDUSTRIAL AREA I-9/3 ISLAMABAD | N96: 190306 | O96: 2669000 | P96: 01-2110-PO-MTR-PCCM-D-001360 | Q96: 45570 | R96: 2A38092 | S96: R-7023894 | T96: NEW | V96: TOYOTA YARIS ATIV CVT 1.3 | W96: 2021 | X96: 11-AUG-2021 | Y96: 21-OCT-2021 | Z96: 21-Oct-2024 | AA96: OLAISB300071642 | AB96: 3 | AC96: CTRK | AD96: DIB0032027 | AE96: 06-OCT-2021 | AF96: 2% | AG96: 2135200 | AH96: 0 | AL96: #N/A | AM96: 0
A97: 40 | B97: NORM | C97: 9976AD2212070001 | D97: Active | E97: T-PAK | F97: TOYOTA AIRPORT MOTOR | G97: SUFYAN | H97: Gujranwala | I97: 34601-8191304-5 | J97: 03206866952 | K97: 03206866952 | L97: 03206866952 | M97: STREET NO 2 HASHMI COLONY MUHAMMADI PARK GUJRANWALA | N97: 137113 | O97: 2703000 | P97: 56038/00014/10/2021 | Q97: 45571 | R97: 2A37897 | S97: R-7023788 | T97: NEW | V97: YARIS GLI CVT 1.3 | W97: 2021 | X97: 26-JUL-2021 | Y97: 21-OCT-2021 | Z97: 21-Oct-2024 | AA97: OLAGWL300070945 | AB97: 3 | AC97: ITECL | AD97: 5500/10/2021 | AE97: 07-OCT-2021 | AF97: 2% | AG97: 2162400 | AH97: 0 | AL97: #N/A | AM97: 0
A98: 45 | B98: NORM | C98: 9976AP1222850015 | D98: Active | E98: T-PAK | F98: AL JANAT MOTORS | G98: MUHAMMAD BASHIR AHMAD | H98: Lahore | I98: 35202-2945108-9 | J98: 03234570218 | K98: 03234570218 | L98: 03234570218 | M98: 58-A NESPAK PHASE 2 CANAL ROAD NEAR IZMIR TOWN LAHORE | N98: 447729 | O98: 4200000 | P98: 64081/00008/10/2022 | Q98: 45571 | R98: 082806 | S98: 6060283 | T98: USD | U98: AHK-714 | V98: TOYOTA COROLLA ALTIS A/T | W98: 2021 | X98: 12-OCT-2022 | Y98: 21-OCT-2022 | Z98: 21-Oct-2024 | AA98: OLULHR300090273 | AB98: 2 | AC98: ITFM | AD98: 8961/10/2022/ITFM | AE98: 08-OCT-2022 | AF98: 1.75% | AG98: 3360000 | AH98: 0 | AL98: #N/A | AM98: 0
A99: 61 | B99: NORM | C99: 9976AD1212320017 | D99: Active | E99: T-PAK | F99: HONDA CENTRE | G99: TAIMOOR ALI | H99: Islamabad | I99: 34101-6364661-1 | J99: 03215222518 | L99: 0512745845 | M99: H # 8 JINNAH BOVLEVARD SECTOR E DHA -2 ISLAMABAD PK | N99: 148116 | O99: 4022000 | P99: DIB/T/BT/33819/ISB/1021 | Q99: 45575 | R99: 6926803 | S99: MR079340 | T99: NEW | V99: CIVIC VTI ORIEL P/T | W99: 2021 | X99: 20-AUG-2021 | Y99: 27-OCT-2021 | Z99: 27-Oct-2024 | AA99: OLAISD300072088 | AB99: 3 | AC99: CTRK | AD99: TDIDIB0029692 | AE99: 12-OCT-2021 | AF99: 1.5% | AG99: 3217600 | AH99: 0 | AL99: #N/A | AM99: 0
A100: 74 | B100: NORM | C100: 997APD1201320001 | D100: Active | E100: T-PAK | F100: SUZUKI CANAL MOTORS | G100: MUHAMMAD AWAIS QAISER | H100: Faisalabad | I100: 33100-4014715-5 | K100: 03018661616 | L100: 0418530616 | M100: H NO 170-B TECH TOWN EXTENTION BLOCK SATYAN ROAD FSD FAISALABAD 03018661616 | N100: 79624 | O100: 1461000 | P100: 49889/00063/10/2018 | Q100: 45591 | R100: 130889 | S100: 10030894 | T100: NEW | U100: LEC-18A-8880 | V100: SUZUKI CULTUS VXL | W100: 2018 | X100: 11-MAY-2020 | Y100: 27-OCT-2018 | Z100: 01-Aug-2039 | AA100: PODFSD300039647 | AB100: 4 | AC100: FSPT | AD100: 16614/10/2018/SPD | AE100: 27-OCT-2018 | AF100: 3.1% | AG100: 1168800 | AH100: 0 | AI100: 997APD1183020007 | AJ100: CO19 Relief Principal Deferment Cases | AL100: #N/A | AM100: 0
...
