Workbook

Sheet Direct Agency Outstanding
B1: MUL/MUL/F/FR/D/P/12471/09/2021 | C1: -6
B2: KHI/HO/D/MO/PC COMP/P/73118/07/2023 | C2: -4
B3: MUL/MUL/F/FR/D/P/13574/12/2021 | C3: -3
B4: MUL/MUL/F/FR/ND/P/13059/11/2021 | C4: -3
B5: MUL/MUL/F/FR/ND/P/13084/11/2021 | C5: -3
B6: MUL/MUL/F/FR/ND/P/13122/11/2021 | C6: -3
B7: KHI/HO/D/MO/PC COMP/P/69597/04/2023 | C7: -2
B8: MUL/MUL/F/FR/ND/P/12988/11/2021 | C8: -2
B9: MUL/MUL/F/FR/ND/P/13081/11/2021 | C9: -2
B10: MUL/MUL/F/FR/ND/P/13116/11/2021 | C10: -2
B11: MUL/MUL/F/FR/ND/P/13567/12/2021 | C11: -2
B12: ISD/ISD/F/MR/IMPORTS/P/38010/11/2022 | C12: -1
... B2209: KHI/HO/D/MI/TRI/P/6533/11/2022 | C2209: 590
B2210: KHI/HO/D/MI/TRI/P/6534/11/2022 | C2210: 590 | E2210: =SUM(C1:C2210) -> 101021.82
B2211: KHI/HO/D/MI/TRI/P/6535/11/2022 | C2211: 590
B2212: MUL/MUL/F/FR/ND/P/12610/10/2021 | C2212: 592
B2213: KHI/HO/D/MI/MP/P/2514/01/2023 | C2213: 593
B2214: KHI/HO/D/MO/PD COMP/P/78292/11/2023 | C2214: 593
B2215: MUL/MUL/F/MI/FG/P/1797/09/2021 | C2215: 596
B2216: KHI/HO/D/MR/IMPORTS/C/18700/10/2023 | C2216: 598
B2217: KHI/HO/D/FR/ND/P/14909/06/2022 | C2217: 600
B2218: KHI/HO/D/MO/PC COMP/C/77027/346/10/2023 | C2218: 605
B2219: KHI/HO/D/MR/IMPORTS/C/18891/11/2023 | C2219: 605
B2220: KHI/HO/D/MO/PD COMP/P/75790/09/2023 | C2220: 606
B2221: MUL/MUL/F/EG/MBD/P/714/01/2022 | C2221: 613
B2222: KHI/HO/D/MO/PD COMP/P/58016/01/2022 | C2222: 614
... B2636: KHI/HO/D/MR/IMPORTS/P/41520/12/2023 | C2636: 1000
B2637: Policy No | C2637: Total
C2638: =SUM(C1:C2636) -> 410970.57

Sheet Advance Amount Knock Off Detail
A1: Type | B1: Vcher No. | C1: Cheque No. | D1: Date | E1: Rec From | F1: Amount
A2: RV | B2: 24-01-0436 | C2: 74824889 | D2: 45300 | E2: Zeeshan Ahmed | F2: 0.1
A3: RV | B3: 24-07-0171 | C3: 770736 | D3: 45478 | E3: Syed Muzafar Ali Shah | F3: 0.2
A4: RV | B4: 24-04-1377 | C4: 1519758 | D4: 45412 | E4: Imaan Hussain | F4: 0.3
A5: RV | B5: 24-05-0245 | C5: 416992 | D5: 45419 | E5: Jehangir Abbas Awan | F5: 0.3
A6: RV | B6: 24-04-0432 | C6: 2 on line transfer | D6: 45397 | E6: Mr. Syed Misbah Uddin CNIC: 4220116890503 Cell: 0301-3384728 | F6: 0.5
A7: RV | B7: 24-07-0398 | C7: 5758397 6460 | D7: 45484 | E7: Bank Of Punjab A/c. M/s. Security Organizing System Pakistan Pvt. Ltd. | F7: 0.71
A8: RV | B8: 24-05-1519 | C8: ON LINE | D8: 45442 | E8: M/s Bank Alfalah Limited Islamic A/c Various User | F8: 0.86
A9: RV | B9: 24-05-0153 | C9: 31930811 | D9: 45418 | E9: TAPAL TEX (PRIVATE) LIMITED | F9: 0.93
A10: RV | B10: 24-09-0594 | C10: 439373 | D10: 45547 | E10: Sabina Rana | F10: 0.95
A11: RV | B11: 24-02-0213 | C11: 71572932 | D11: 45331 | E11: Security General Insurance Co. Ltd. | F11: 1
A12: RV | B12: 24-03-1138 | C12: 59877482 | D12: 45378 | E12: EFU GENRAL INSURANCE LIMITED | F12: 1
A13: RV | B13: 24-01-1047 | C13: 928665 | D13: 45309 | E13: M/S. DUBAI ISLAMIC BANK PAKISTAN LIMITED A/C M/S. SAFA HEALTHCSARE | F13: 1
A14: RV | B14: 24-01-1071 | C14: 30299826 | D14: 45310 | E14: EFU GENRAL INSURANCE LIMITED (Soorthy Enterprises) | F14: 1
A15: RV | B15: 24-01-0190 | C15: 11 | D15: 45295 | E15: M/s Meezan Bank Limited A/c Various User | F15: 1
A16: RV | B16: 24-01-0304 | C16: 381289 | D16: 45296 | E16: PAID BY HAMMAD | F16: 1
A17: RV | B17: 24-01-0491 | C17: 356785 | D17: 45300 | E17: Imran Ali | F17: 1
A18: RV | B18: 24-01-0537 | C18: 146664 | D18: 45300 | E18: Nextbridge Private Limited. | F18: 1
A19: RV | B19: 24-01-0675 | C19: 295473 | D19: 45302 | E19: Muhammad Jawad Azam | F19: 1
A20: RV | B20: 24-01-0702 | C20: 241040 | D20: 45302 | E20: Naveed Iqbal | F20: 1
A21: RV | B21: 24-01-0775 | C21: 9976AFR2332 | D21: 45303 | E21: M/s. M/s. Nobel Cotton Waste HPA M/s Dubai Islamic Bank (Pakistan) Limited User Mr. Mr. Zeeshan Aziz Malik | F21: 1
A22: RV | B22: 24-01-0744 | C22: 107709 | D22: 45305 | E22: Aftab Iqbal Qureshi | F22: 1
A23: RV | B23: 24-01-0764 | C23: 102798 | D23: 45305 | E23: Muhammad Bashir | F23: 1
A24: RV | B24: 24-01-0872 | C24: 464975 | D24: 45306 | E24: Akhlas Ahmad | F24: 1
A25: RV | B25: 24-01-0979 | C25: 453244 | D25: 45308 | E25: Hafiz Asad Ali | F25: 1
A26: RV | B26: 24-01-1033 | C26: 578913 | D26: 45308 | E26: Farrkhanda Akhtar | F26: 1
A27: RV | B27: 24-01-1006 | C27: 534198 | D27: 45309 | E27: M/s Meezan Bank Limited A/c ARY Jewellers | F27: 1
A28: RV | B28: 24-01-1328 | C28: 2 Pay Orders | D28: 45315 | E28: M/s Al Baraka Bank A/c Various User (Fresh And Renewal) | F28: 1
A29: RV | B29: 24-01-1364 | C29: 209156 | D29: 45315 | E29: Abdul Basit Aziz | F29: 1
A30: RV | B30: 24-01-1419 | C30: 11 | D30: 45316 | E30: M/s Meezan Bank Limited Multan HubA/c Various User | F30: 1
A31: RV | B31: 24-01-1453 | D31: 45316 | E31: VARIOUS PAYD CUSTOMER | F31: 1
A32: RV | B32: 24-01-1865 | C32: 240310 | D32: 45322 | E32: Shah Rukh Shahid | F32: 1
A33: RV | B33: 24-02-0216 | C33: ON LINE | D33: 45329 | E33: M/S Dubai Islamic Bank Limited User A/c Various User | F33: 1
A34: RV | B34: 24-02-0294 | C34: 96045798 | D34: 45329 | E34: Mystic Tours Pvt Limited 1st Inst Plan | F34: 1
A35: RV | B35: 24-02-0716 | C35: 531498 | D35: 45329 | E35: M/S. Dubai Islamic Bank Pakistan Limited User: Saleem Ullah Butt | F35: 1
A36: RV | B36: 24-02-0330 | C36: 31162050973 | D36: 45331 | E36: M/s. Bank Alfalah Limited Islamic Banking Division (Dhoraji Branch Karachi ) as Lessor & Owner And Mr. Muhammad Pervaiz | F36: 1
A37: RV | B37: 24-02-0780 | C37: ON LINE | D37: 45341 | E37: M/S Dubai Islamic Bank Limited User A/c Various User | F37: 1
A38: RV | B38: 24-02-0943 | C38: 6502154 | D38: 45342 | E38: Sarfaraz Ali Shah | F38: 1
A39: RV | B39: 24-02-0986 | C39: 958801 | D39: 45344 | E39: M/S OCEAN NETWORK EXPRESS PAKISTAN PVT LTD | F39: 1
A40: RV | B40: 24-02-1395 | C40: 424463 | D40: 45350 | E40: Siraj Tanoli | F40: 1
A41: RV | B41: 24-02-1400 | C41: 2 Pay Orders | D41: 45350 | E41: M/s Al Baraka Bank A/c Various User | F41: 1
A42: RV | B42: 24-03-0176 | C42: 255595 | D42: 45355 | E42: Mr. Muhammad Maaz Ahmed Nomani CNIC: 4210128882209 Cell: 03018294032 | F42: 1
A43: RV | B43: 24-03-0236 | C43: 864633 | D43: 45357 | E43: Muhammad Atif Qureshi | F43: 1
A44: RV | B44: 24-03-0320 | C44: 2896029 | D44: 45357 | E44: Muhammad Younus Agha | F44: 1
A45: RV | B45: 24-03-0317 | C45: 677014 | D45: 45358 | E45: Mufti Ehsan Waqar-ESAAC | F45: 1
A46: RV | B46: 24-03-0468 | C46: 182 | D46: 45362 | E46: Ajeet Kumar | F46: 1
A47: RV | B47: 24-03-0743 | C47: 990649 | D47: 45369 | E47: Zia Ullah Nagra | F47: 1
A48: RV | B48: 24-03-0881 | C48: 840997 | D48: 45371 | E48: Muhammad Ahmed Khalid | F48: 1
A49: RV | B49: 24-03-1015 | C49: 799462 | D49: 45375 | E49: Abdullah Ghaffar | F49: 1
A50: RV | B50: 24-03-1202 | D50: 45378 | E50: VARIOUS PAYD CUSTOMERS | F50: 1
A51: RV | B51: 24-03-1364 | C51: 834647 | D51: 45382 | E51: Muhammad Irfan | F51: 1
A52: RV | B52: 24-01-0261 | C52: 12055295 | D52: 45297 | E52: A ONE TECHNIQUES (PVT) LTD | F52: 1
A53: RV | B53: 24-01-0467 | C53: 2 BANK TRF | D53: 45300 | E53: Al-Ghazi Tractors Limited | F53: 1
A54: RV | B54: 24-01-1270 | C54: 10311236 | D54: 45313 | E54: ECHO DIGITAL (PVT) LTD | F54: 1
A55: RV | B55: 24-02-0628 | C55: 101 | D55: 45336 | E55: PHARMEVO (PRIVATE) LIMITED | F55: 1
A56: RV | B56: 24-02-0524 | C56: 12951865 | D56: 45337 | E56: LE Mendoza Pharmaceutical (Private) Limited | F56: 1
A57: RV | B57: 24-02-0525 | C57: 10797642 | D57: 45337 | E57: Woodward Herbal Laboratories Private Limited | F57: 1
A58: RV | B58: 24-02-0526 | C58: 60491165 | D58: 45337 | E58: W. Woodward Pakistan (Private) Limited | F58: 1
A59: RV | B59: 29610 | C59: STAN(983288) | D59: 45322 | E59: Advance Cont Received against MBL 41719 JAN 2024 | F59: 1
A60: RV | B60: 24-03-1460 | C60: 929726 | D60: 45352 | E60: MBL 41719 | F60: 1
A61: RV | B61: 24-03-1462 | C61: 747721 | D61: 45382 | E61: BI 30190 | F61: 1
A62: RV | B62: 24-04-0982 | C62: 4 chqs | D62: 45406 | E62: TOYOTA SOCIETY MOTORS | F62: 1
A63: RV | B63: 24-05-0447 | C63: 80091166 | D63: 45422 | E63: THE UNITED INSURANCE CO OF PAKISTAN | F63: 1
A64: RV | B64: 24-05-0647 | C64: 11292215 | D64: 45428 | E64: Pioneer Cement Ltd | F64: 1
A65: RV | B65: 24-06-0119 | C65: 30164310 | D65: 45448 | E65: Solar Fresh Billing | F65: 1
A66: RV | B66: 24-06-0762 | C66: 67360102 | D66: 45467 | E66: M/s. Pakistan International Bulk Terminal Limited | F66: 1
A67: RV | B67: 24-04-0086 | C67: 2323951 | D67: 45385 | E67: Progressive International | F67: 1
A68: RV | B68: 24-05-0168 | C68: 2900581 | D68: 45418 | E68: PROGRESSIVE INTERNATIONAL | F68: 1
A69: RV | B69: 24-05-0765 | C69: 2323953 | D69: 45429 | E69: M/S.PROGRESSIVE INTERNATIONAL. | F69: 1
A70: RV | B70: 24-06-0506 | C70: 45584601 | D70: 45457 | E70: M/S.A.AMAR FOOD INDUSTRIES | F70: 1
A71: RV | B71: 24-04-1289 | C71: 418639 | D71: 45407 | E71: Mr. Habib Akhtar | F71: 1
A72: RV | B72: 24-04-1463 | C72: 7459090 | D72: 45412 | E72: Abdul Malik | F72: 1
A73: RV | B73: 24-04-1473 | C73: 592150 | D73: 45412 | E73: Syed Rizwan Ali | F73: 1
A74: RV | B74: 24-05-0173 | C74: 208434 | D74: 45418 | E74: Muhammad Mubashir Rafiq | F74: 1
... A76: RV | B76: 24-05-0924 | C76: 537338 | D76: 45433 | E76: Touseef Khan | F76: 1
A77: RV | B77: 24-05-1508 | D77: 45443 | E77: VARIOUS PAYD CUSTOMER | F77: 1
A78: RV | B78: 24-06-0093 | C78: 7016816 | D78: 45447 | E78: Muhammad Alam | F78: 1
A79: RV | B79: 24-06-0191 | C79: 369915 | D79: 45448 | E79: Shahbaz Khan - | F79: 1
A80: RV | B80: 24-06-0333 | C80: 5162648 | D80: 45453 | E80: Fareeha Shah | F80: 1
A81: RV | B81: 24-06-0573 | C81: 744989 | D81: 45457 | E81: VARIOUS PAYD CUSTOMERS | F81: 1
A82: RV | B82: 24-06-1081 | C82: 540934 | D82: 45467 | E82: STRATEGIC VISION INSTITUTE | F82: 1
A83: RV | B83: 24-04-1194 | C83: 1947915564 & 8313009 | D83: 45411 | E83: Mr. Musa Khan Durrani Owner of M/s. Al Hameed Farms | F83: 1
A84: RV | B84: 24-05-0445 | C84: 798820319 | D84: 45422 | E84: ADAMJEE INSURANCE COMPANY LIMITED | F84: 1
A85: RV | B85: 24-04-0110 | C85: 844351 | D85: 45384 | E85: NKC (SMC - PVT) LTD | F85: 1
A86: RV | B86: 24-05-0004 | C86: 61681549 | D86: 45413 | E86: TRANSKARACHI | F86: 1
A87: RV | B87: 24-05-1619 | C87: 50754 | D87: 45443 | E87: BI 190 | F87: 1
A88: RV | B88: 24-06-1237 | C88: 405144 | D88: 45473 | E88: BANK ISLAMI 190 | F88: 1
A89: RV | B89: 24-07-0280 | C89: 30275639 | D89: 45481 | E89: M/s Bank Islami Pakistan Limited A/c Roshni Asaan Renewable Energy Product | F89: 1
A90: RV | B90: 24-08-1348 | C90: 558409 34024248 | D90: 45534 | E90: SITARA CHEMICAL INDUSTRIES (TEXTILE DIVISION) | F90: 1
A91: RV | B91: 24-07-0333 | C91: 95463853 | D91: 45482 | E91: DHEDHI BROTHERS | F91: 1
A92: RV | B92: 24-07-1219 | C92: 57045336 | D92: 45503 | E92: M/s Meezan Bank Ltd A/c M/s Insaf Textile Printing Mills Pvt. Ltd. | F92: 1
A93: RV | B93: 24-08-1370 | C93: 651506 | D93: 45534 | E93: Noori international | F93: 1
A94: RV | B94: 24-09-0009 | C94: 11053171 | D94: 45537 | E94: M/S ASKARI BANK LIMITED A/C AWAN TRADING COMPANY (PVT) | F94: 1
A95: RV | B95: 24-10-0324 | C95: 253256 | D95: 45572 | E95: PROGRESSIVE INTERNATIONA | F95: 1
A96: RV | B96: 24-07-0168 | C96: 5446767 | D96: 45478 | E96: Ahmedalisiddiqui | F96: 1
A97: RV | B97: 24-07-0626 | C97: 1198485 | D97: 45488 | E97: Mr. Zafar Khalil Khan | F97: 1
A98: RV | B98: 24-07-0741 | C98: 71914336408 | D98: 45492 | E98: Taimoorsaleemqureshi | F98: 1
A99: RV | B99: 24-07-0850 | C99: ONLINE | D99: 45495 | E99: MS Dubai Islamic Bank A/C Various User | F99: 1
A100: RV | B100: 24-07-1431 | C100: 90039150 | D100: 45497 | E100: Abdul Malik | F100: 1
A101: RV | B101: 24-07-1214 | C101: 702861 | D101: 45501 | E101: Sohail Iqbal | F101: 1
...

Sheet working
A1: POLICY NO. | B1: Assorted_code | D1: Premium | E1: 13Nov240062
A2: MUL/MUL/F/FR/D/P/12471/09/2021 | B2: =VLOOKUP(A2,policy!B:C,2,0) -> 040000106339 | C2: -6 | D2: -6 | E2: 13Nov240062 | F2: ="insert into ins_premium_det (premium_rcv_code,assorted_code, rec_amount,premium_rcv_detail_code,remaining_amt, payrec, mode_code,coinsurance_code,class_cd,it_remarks) values" -> insert into ins_premium_det (premium_rcv_code,assorted_code, rec_amount,premium_rcv_detail_code,remaining_amt, payrec, mode_code,coinsurance_code,class_cd,it_remarks) values | G2: ="('"&E2&"','"&B2&"','"&D2&"',(select max(to_number(i.premium_rcv_detail_code))+1 from ins_premium_det i),'"&D2&"','"&D2&"','02', '11000003','00','Request by Mr. Raheel Malik 15-Nov-2024');" -> ('13Nov240062','040000106339','-6',(select max(to_number(i.premium_rcv_detail_code))+1 from ins_premium_det i),'-6','-6','02', '11000003','00','Request by Mr. Raheel Malik 15-Nov-2024'); | H2: =F2&G2 -> insert into ins_premium_det (premium_rcv_code,assorted_code, rec_amount,premium_rcv_detail_code,remaining_amt, payrec, mode_code,coinsurance_code,class_cd,it_remarks) values('13Nov240062','040000106339','-6',(select max(to_number(i.premium_rcv_detail_code))+1 from ins_premium_det i),'-6','-6','02', '11000003','00','Request by Mr. Raheel Malik 15-Nov-2024');
A3: KHI/HO/D/MO/PC COMP/P/73118/07/2023 | B3: =VLOOKUP(A3,policy!B:C,2,0) -> 040000149022 | C3: -4 | D3: -4 | E3: 13Nov240062 | F3: ="insert into ins_premium_det (premium_rcv_code,assorted_code, rec_amount,premium_rcv_detail_code,remaining_amt, payrec, mode_code,coinsurance_code,class_cd,it_remarks) values" -> insert into ins_premium_det (premium_rcv_code,assorted_code, rec_amount,premium_rcv_detail_code,remaining_amt, payrec, mode_code,coinsurance_code,class_cd,it_remarks) values | G3: ="('"&E3&"','"&B3&"','"&D3&"',(select max(to_number(i.premium_rcv_detail_code))+1 from ins_premium_det i),'"&D3&"','"&D3&"','02', '11000003','00','Request by Mr. Raheel Malik 15-Nov-2024');" -> ('13Nov240062','040000149022','-4',(select max(to_number(i.premium_rcv_detail_code))+1 from ins_premium_det i),'-4','-4','02', '11000003','00','Request by Mr. Raheel Malik 15-Nov-2024'); | H3: =F3&G3 -> insert into ins_premium_det (premium_rcv_code,assorted_code, rec_amount,premium_rcv_detail_code,remaining_amt, payrec, mode_code,coinsurance_code,class_cd,it_remarks) values('13Nov240062','040000149022','-4',(select max(to_number(i.premium_rcv_detail_code))+1 from ins_premium_det i),'-4','-4','02', '11000003','00','Request by Mr. Raheel Malik 15-Nov-2024');
A4: MUL/MUL/F/FR/D/P/13574/12/2021 | B4: =VLOOKUP(A4,policy!B:C,2,0) -> 040000110713 | C4: -3 | D4: -3 | E4: 13Nov240062 | F4: ="insert into ins_premium_det (premium_rcv_code,assorted_code, rec_amount,premium_rcv_detail_code,remaining_amt, payrec, mode_code,coinsurance_code,class_cd,it_remarks) values" -> insert into ins_premium_det (premium_rcv_code,assorted_code, rec_amount,premium_rcv_detail_code,remaining_amt, payrec, mode_code,coinsurance_code,class_cd,it_remarks) values | G4: ="('"&E4&"','"&B4&"','"&D4&"',(select max(to_number(i.premium_rcv_detail_code))+1 from ins_premium_det i),'"&D4&"','"&D4&"','02', '11000003','00','Request by Mr. Raheel Malik 15-Nov-2024');" -> ('13Nov240062','040000110713','-3',(select max(to_number(i.premium_rcv_detail_code))+1 from ins_premium_det i),'-3','-3','02', '11000003','00','Request by Mr. Raheel Malik 15-Nov-2024'); | H4: =F4&G4 -> insert into ins_premium_det (premium_rcv_code,assorted_code, rec_amount,premium_rcv_detail_code,remaining_amt, payrec, mode_code,coinsurance_code,class_cd,it_remarks) values('13Nov240062','040000110713','-3',(select max(to_number(i.premium_rcv_detail_code))+1 from ins_premium_det i),'-3','-3','02', '11000003','00','Request by Mr. Raheel Malik 15-Nov-2024');
A5: MUL/MUL/F/FR/ND/P/13059/11/2021 | B5: =VLOOKUP(A5,policy!B:C,2,0) -> 040000108658 | C5: -3 | D5: -3 | E5: 13Nov240062 | F5: ="insert into ins_premium_det (premium_rcv_code,assorted_code, rec_amount,premium_rcv_detail_code,remaining_amt, payrec, mode_code,coinsurance_code,class_cd,it_remarks) values" -> insert into ins_premium_det (premium_rcv_code,assorted_code, rec_amount,premium_rcv_detail_code,remaining_amt, payrec, mode_code,coinsurance_code,class_cd,it_remarks) values | G5: ="('"&E5&"','"&B5&"','"&D5&"',(select max(to_number(i.premium_rcv_detail_code))+1 from ins_premium_det i),'"&D5&"','"&D5&"','02', '11000003','00','Request by Mr. Raheel Malik 15-Nov-2024');" -> ('13Nov240062','040000108658','-3',(select max(to_number(i.premium_rcv_detail_code))+1 from ins_premium_det i),'-3','-3','02', '11000003','00','Request by Mr. Raheel Malik 15-Nov-2024'); | H5: =F5&G5 -> insert into ins_premium_det (premium_rcv_code,assorted_code, rec_amount,premium_rcv_detail_code,remaining_amt, payrec, mode_code,coinsurance_code,class_cd,it_remarks) values('13Nov240062','040000108658','-3',(select max(to_number(i.premium_rcv_detail_code))+1 from ins_premium_det i),'-3','-3','02', '11000003','00','Request by Mr. Raheel Malik 15-Nov-2024');
A6: MUL/MUL/F/FR/ND/P/13084/11/2021 | B6: =VLOOKUP(A6,policy!B:C,2,0) -> 040000108917 | C6: -3 | D6: -3 | E6: 13Nov240062 | F6: ="insert into ins_premium_det (premium_rcv_code,assorted_code, rec_amount,premium_rcv_detail_code,remaining_amt, payrec, mode_code,coinsurance_code,class_cd,it_remarks) values" -> insert into ins_premium_det (premium_rcv_code,assorted_code, rec_amount,premium_rcv_detail_code,remaining_amt, payrec, mode_code,coinsurance_code,class_cd,it_remarks) values | G6: ="('"&E6&"','"&B6&"','"&D6&"',(select max(to_number(i.premium_rcv_detail_code))+1 from ins_premium_det i),'"&D6&"','"&D6&"','02', '11000003','00','Request by Mr. Raheel Malik 15-Nov-2024');" -> ('13Nov240062','040000108917','-3',(select max(to_number(i.premium_rcv_detail_code))+1 from ins_premium_det i),'-3','-3','02', '11000003','00','Request by Mr. Raheel Malik 15-Nov-2024'); | H6: =F6&G6 -> insert into ins_premium_det (premium_rcv_code,assorted_code, rec_amount,premium_rcv_detail_code,remaining_amt, payrec, mode_code,coinsurance_code,class_cd,it_remarks) values('13Nov240062','040000108917','-3',(select max(to_number(i.premium_rcv_detail_code))+1 from ins_premium_det i),'-3','-3','02', '11000003','00','Request by Mr. Raheel Malik 15-Nov-2024');
A7: MUL/MUL/F/FR/ND/P/13122/11/2021 | B7: =VLOOKUP(A7,policy!B:C,2,0) -> 040000109079 | C7: -3 | D7: -3 | E7: 13Nov240062 | F7: ="insert into ins_premium_det (premium_rcv_code,assorted_code, rec_amount,premium_rcv_detail_code,remaining_amt, payrec, mode_code,coinsurance_code,class_cd,it_remarks) values" -> insert into ins_premium_det (premium_rcv_code,assorted_code, rec_amount,premium_rcv_detail_code,remaining_amt, payrec, mode_code,coinsurance_code,class_cd,it_remarks) values | G7: ="('"&E7&"','"&B7&"','"&D7&"',(select max(to_number(i.premium_rcv_detail_code))+1 from ins_premium_det i),'"&D7&"','"&D7&"','02', '11000003','00','Request by Mr. Raheel Malik 15-Nov-2024');" -> ('13Nov240062','040000109079','-3',(select max(to_number(i.premium_rcv_detail_code))+1 from ins_premium_det i),'-3','-3','02', '11000003','00','Request by Mr. Raheel Malik 15-Nov-2024'); | H7: =F7&G7 -> insert into ins_premium_det (premium_rcv_code,assorted_code, rec_amount,premium_rcv_detail_code,remaining_amt, payrec, mode_code,coinsurance_code,class_cd,it_remarks) values('13Nov240062','040000109079','-3',(select max(to_number(i.premium_rcv_detail_code))+1 from ins_premium_det i),'-3','-3','02', '11000003','00','Request by Mr. Raheel Malik 15-Nov-2024');
A8: KHI/HO/D/MO/PC COMP/P/69597/04/2023 | B8: =VLOOKUP(A8,policy!B:C,2,0) -> 040000143001 | C8: -2 | D8: -2 | E8: 13Nov240062 | F8: ="insert into ins_premium_det (premium_rcv_code,assorted_code, rec_amount,premium_rcv_detail_code,remaining_amt, payrec, mode_code,coinsurance_code,class_cd,it_remarks) values" -> insert into ins_premium_det (premium_rcv_code,assorted_code, rec_amount,premium_rcv_detail_code,remaining_amt, payrec, mode_code,coinsurance_code,class_cd,it_remarks) values | G8: ="('"&E8&"','"&B8&"','"&D8&"',(select max(to_number(i.premium_rcv_detail_code))+1 from ins_premium_det i),'"&D8&"','"&D8&"','02', '11000003','00','Request by Mr. Raheel Malik 15-Nov-2024');" -> ('13Nov240062','040000143001','-2',(select max(to_number(i.premium_rcv_detail_code))+1 from ins_premium_det i),'-2','-2','02', '11000003','00','Request by Mr. Raheel Malik 15-Nov-2024'); | H8: =F8&G8 -> insert into ins_premium_det (premium_rcv_code,assorted_code, rec_amount,premium_rcv_detail_code,remaining_amt, payrec, mode_code,coinsurance_code,class_cd,it_remarks) values('13Nov240062','040000143001','-2',(select max(to_number(i.premium_rcv_detail_code))+1 from ins_premium_det i),'-2','-2','02', '11000003','00','Request by Mr. Raheel Malik 15-Nov-2024');
A9: MUL/MUL/F/FR/ND/P/12988/11/2021 | B9: =VLOOKUP(A9,policy!B:C,2,0) -> 040000108330 | C9: -2 | D9: -2 | E9: 13Nov240062 | F9: ="insert into ins_premium_det (premium_rcv_code,assorted_code, rec_amount,premium_rcv_detail_code,remaining_amt, payrec, mode_code,coinsurance_code,class_cd,it_remarks) values" -> insert into ins_premium_det (premium_rcv_code,assorted_code, rec_amount,premium_rcv_detail_code,remaining_amt, payrec, mode_code,coinsurance_code,class_cd,it_remarks) values | G9: ="('"&E9&"','"&B9&"','"&D9&"',(select max(to_number(i.premium_rcv_detail_code))+1 from ins_premium_det i),'"&D9&"','"&D9&"','02', '11000003','00','Request by Mr. Raheel Malik 15-Nov-2024');" -> ('13Nov240062','040000108330','-2',(select max(to_number(i.premium_rcv_detail_code))+1 from ins_premium_det i),'-2','-2','02', '11000003','00','Request by Mr. Raheel Malik 15-Nov-2024'); | H9: =F9&G9 -> insert into ins_premium_det (premium_rcv_code,assorted_code, rec_amount,premium_rcv_detail_code,remaining_amt, payrec, mode_code,coinsurance_code,class_cd,it_remarks) values('13Nov240062','040000108330','-2',(select max(to_number(i.premium_rcv_detail_code))+1 from ins_premium_det i),'-2','-2','02', '11000003','00','Request by Mr. Raheel Malik 15-Nov-2024');
A10: MUL/MUL/F/FR/ND/P/13081/11/2021 | B10: =VLOOKUP(A10,policy!B:C,2,0) -> 040000108904 | C10: -2 | D10: -2 | E10: 13Nov240062 | F10: ="insert into ins_premium_det (premium_rcv_code,assorted_code, rec_amount,premium_rcv_detail_code,remaining_amt, payrec, mode_code,coinsurance_code,class_cd,it_remarks) values" -> insert into ins_premium_det (premium_rcv_code,assorted_code, rec_amount,premium_rcv_detail_code,remaining_amt, payrec, mode_code,coinsurance_code,class_cd,it_remarks) values | G10: ="('"&E10&"','"&B10&"','"&D10&"',(select max(to_number(i.premium_rcv_detail_code))+1 from ins_premium_det i),'"&D10&"','"&D10&"','02', '11000003','00','Request by Mr. Raheel Malik 15-Nov-2024');" -> ('13Nov240062','040000108904','-2',(select max(to_number(i.premium_rcv_detail_code))+1 from ins_premium_det i),'-2','-2','02', '11000003','00','Request by Mr. Raheel Malik 15-Nov-2024'); | H10: =F10&G10 -> insert into ins_premium_det (premium_rcv_code,assorted_code, rec_amount,premium_rcv_detail_code,remaining_amt, payrec, mode_code,coinsurance_code,class_cd,it_remarks) values('13Nov240062','040000108904','-2',(select max(to_number(i.premium_rcv_detail_code))+1 from ins_premium_det i),'-2','-2','02', '11000003','00','Request by Mr. Raheel Malik 15-Nov-2024');
A11: MUL/MUL/F/FR/ND/P/13116/11/2021 | B11: =VLOOKUP(A11,policy!B:C,2,0) -> 040000109068 | C11: -2 | D11: -2 | E11: 13Nov240062 | F11: ="insert into ins_premium_det (premium_rcv_code,assorted_code, rec_amount,premium_rcv_detail_code,remaining_amt, payrec, mode_code,coinsurance_code,class_cd,it_remarks) values" -> insert into ins_premium_det (premium_rcv_code,assorted_code, rec_amount,premium_rcv_detail_code,remaining_amt, payrec, mode_code,coinsurance_code,class_cd,it_remarks) values | G11: ="('"&E11&"','"&B11&"','"&D11&"',(select max(to_number(i.premium_rcv_detail_code))+1 from ins_premium_det i),'"&D11&"','"&D11&"','02', '11000003','00','Request by Mr. Raheel Malik 15-Nov-2024');" -> ('13Nov240062','040000109068','-2',(select max(to_number(i.premium_rcv_detail_code))+1 from ins_premium_det i),'-2','-2','02', '11000003','00','Request by Mr. Raheel Malik 15-Nov-2024'); | H11: =F11&G11 -> insert into ins_premium_det (premium_rcv_code,assorted_code, rec_amount,premium_rcv_detail_code,remaining_amt, payrec, mode_code,coinsurance_code,class_cd,it_remarks) values('13Nov240062','040000109068','-2',(select max(to_number(i.premium_rcv_detail_code))+1 from ins_premium_det i),'-2','-2','02', '11000003','00','Request by Mr. Raheel Malik 15-Nov-2024');
A12: MUL/MUL/F/FR/ND/P/13567/12/2021 | B12: =VLOOKUP(A12,policy!B:C,2,0) -> 040000110701 | C12: -2 | D12: -2 | E12: 13Nov240062 | F12: ="insert into ins_premium_det (premium_rcv_code,assorted_code, rec_amount,premium_rcv_detail_code,remaining_amt, payrec, mode_code,coinsurance_code,class_cd,it_remarks) values" -> insert into ins_premium_det (premium_rcv_code,assorted_code, rec_amount,premium_rcv_detail_code,remaining_amt, payrec, mode_code,coinsurance_code,class_cd,it_remarks) values | G12: ="('"&E12&"','"&B12&"','"&D12&"',(select max(to_number(i.premium_rcv_detail_code))+1 from ins_premium_det i),'"&D12&"','"&D12&"','02', '11000003','00','Request by Mr. Raheel Malik 15-Nov-2024');" -> ('13Nov240062','040000110701','-2',(select max(to_number(i.premium_rcv_detail_code))+1 from ins_premium_det i),'-2','-2','02', '11000003','00','Request by Mr. Raheel Malik 15-Nov-2024'); | H12: =F12&G12 -> insert into ins_premium_det (premium_rcv_code,assorted_code, rec_amount,premium_rcv_detail_code,remaining_amt, payrec, mode_code,coinsurance_code,class_cd,it_remarks) values('13Nov240062','040000110701','-2',(select max(to_number(i.premium_rcv_detail_code))+1 from ins_premium_det i),'-2','-2','02', '11000003','00','Request by Mr. Raheel Malik 15-Nov-2024');
A13: ISD/ISD/F/MR/IMPORTS/P/38010/11/2022 | B13: =VLOOKUP(A13,policy!B:C,2,0) -> 040000131738 | C13: -1 | D13: -1 | E13: 13Nov240062 | F13: ="insert into ins_premium_det (premium_rcv_code,assorted_code, rec_amount,premium_rcv_detail_code,remaining_amt, payrec, mode_code,coinsurance_code,class_cd,it_remarks) values" -> insert into ins_premium_det (premium_rcv_code,assorted_code, rec_amount,premium_rcv_detail_code,remaining_amt, payrec, mode_code,coinsurance_code,class_cd,it_remarks) values | G13: ="('"&E13&"','"&B13&"','"&D13&"',(select max(to_number(i.premium_rcv_detail_code))+1 from ins_premium_det i),'"&D13&"','"&D13&"','02', '11000003','00','Request by Mr. Raheel Malik 15-Nov-2024');" -> ('13Nov240062','040000131738','-1',(select max(to_number(i.premium_rcv_detail_code))+1 from ins_premium_det i),'-1','-1','02', '11000003','00','Request by Mr. Raheel Malik 15-Nov-2024'); | H13: =F13&G13 -> insert into ins_premium_det (premium_rcv_code,assorted_code, rec_amount,premium_rcv_detail_code,remaining_amt, payrec, mode_code,coinsurance_code,class_cd,it_remarks) values('13Nov240062','040000131738','-1',(select max(to_number(i.premium_rcv_detail_code))+1 from ins_premium_det i),'-1','-1','02', '11000003','00','Request by Mr. Raheel Malik 15-Nov-2024');
... A2211: KHI/HO/D/MI/TRI/P/6534/11/2022 | B2211: =VLOOKUP(A2211,policy!B:C,2,0) -> 040000130891 | C2211: 590 | D2211: 590 | E2211: 13Nov240062 | F2211: ="insert into ins_premium_det (premium_rcv_code,assorted_code, rec_amount,premium_rcv_detail_code,remaining_amt, payrec, mode_code,coinsurance_code,class_cd,it_remarks) values" -> insert into ins_premium_det (premium_rcv_code,assorted_code, rec_amount,premium_rcv_detail_code,remaining_amt, payrec, mode_code,coinsurance_code,class_cd,it_remarks) values | G2211: ="('"&E2211&"','"&B2211&"','"&D2211&"',(select max(to_number(i.premium_rcv_detail_code))+1 from ins_premium_det i),'"&D2211&"','"&D2211&"','02', '11000003','00','Request by Mr. Raheel Malik 15-Nov-2024');" -> ('13Nov240062','040000130891','590',(select max(to_number(i.premium_rcv_detail_code))+1 from ins_premium_det i),'590','590','02', '11000003','00','Request by Mr. Raheel Malik 15-Nov-2024'); | H2211: =F2211&G2211 -> insert into ins_premium_det (premium_rcv_code,assorted_code, rec_amount,premium_rcv_detail_code,remaining_amt, payrec, mode_code,coinsurance_code,class_cd,it_remarks) values('13Nov240062','040000130891','590',(select max(to_number(i.premium_rcv_detail_code))+1 from ins_premium_det i),'590','590','02', '11000003','00','Request by Mr. Raheel Malik 15-Nov-2024');
A2212: KHI/HO/D/MI/TRI/P/6535/11/2022 | B2212: 040000130892 | C2212: 590 | D2212: 590 | E2212: 13Nov240062 | F2212: ="insert into ins_premium_det (premium_rcv_code,assorted_code, rec_amount,premium_rcv_detail_code,remaining_amt, payrec, mode_code,coinsurance_code,class_cd,it_remarks) values" -> insert into ins_premium_det (premium_rcv_code,assorted_code, rec_amount,premium_rcv_detail_code,remaining_amt, payrec, mode_code,coinsurance_code,class_cd,it_remarks) values | G2212: ="('"&E2212&"','"&B2212&"','"&D2212&"',(select max(to_number(i.premium_rcv_detail_code))+1 from ins_premium_det i),'"&D2212&"','"&D2212&"','02', '11000003','00','Request by Mr. Raheel Malik 15-Nov-2024');" -> ('13Nov240062','040000130892','590',(select max(to_number(i.premium_rcv_detail_code))+1 from ins_premium_det i),'590','590','02', '11000003','00','Request by Mr. Raheel Malik 15-Nov-2024'); | H2212: =F2212&G2212 -> insert into ins_premium_det (premium_rcv_code,assorted_code, rec_amount,premium_rcv_detail_code,remaining_amt, payrec, mode_code,coinsurance_code,class_cd,it_remarks) values('13Nov240062','040000130892','590',(select max(to_number(i.premium_rcv_detail_code))+1 from ins_premium_det i),'590','590','02', '11000003','00','Request by Mr. Raheel Malik 15-Nov-2024');
A2213: MUL/MUL/F/FR/ND/P/12610/10/2021 | B2213: 040000107624 | C2213: 592 | D2213: 592 | E2213: 13Nov240062 | F2213: ="insert into ins_premium_det (premium_rcv_code,assorted_code, rec_amount,premium_rcv_detail_code,remaining_amt, payrec, mode_code,coinsurance_code,class_cd,it_remarks) values" -> insert into ins_premium_det (premium_rcv_code,assorted_code, rec_amount,premium_rcv_detail_code,remaining_amt, payrec, mode_code,coinsurance_code,class_cd,it_remarks) values | G2213: ="('"&E2213&"','"&B2213&"','"&D2213&"',(select max(to_number(i.premium_rcv_detail_code))+1 from ins_premium_det i),'"&D2213&"','"&D2213&"','02', '11000003','00','Request by Mr. Raheel Malik 15-Nov-2024');" -> ('13Nov240062','040000107624','592',(select max(to_number(i.premium_rcv_detail_code))+1 from ins_premium_det i),'592','592','02', '11000003','00','Request by Mr. Raheel Malik 15-Nov-2024'); | H2213: =F2213&G2213 -> insert into ins_premium_det (premium_rcv_code,assorted_code, rec_amount,premium_rcv_detail_code,remaining_amt, payrec, mode_code,coinsurance_code,class_cd,it_remarks) values('13Nov240062','040000107624','592',(select max(to_number(i.premium_rcv_detail_code))+1 from ins_premium_det i),'592','592','02', '11000003','00','Request by Mr. Raheel Malik 15-Nov-2024');
A2214: KHI/HO/D/MI/MP/P/2514/01/2023 | B2214: 040000138279 | C2214: 593 | D2214: 593 | E2214: 13Nov240062 | F2214: ="insert into ins_premium_det (premium_rcv_code,assorted_code, rec_amount,premium_rcv_detail_code,remaining_amt, payrec, mode_code,coinsurance_code,class_cd,it_remarks) values" -> insert into ins_premium_det (premium_rcv_code,assorted_code, rec_amount,premium_rcv_detail_code,remaining_amt, payrec, mode_code,coinsurance_code,class_cd,it_remarks) values | G2214: ="('"&E2214&"','"&B2214&"','"&D2214&"',(select max(to_number(i.premium_rcv_detail_code))+1 from ins_premium_det i),'"&D2214&"','"&D2214&"','02', '11000003','00','Request by Mr. Raheel Malik 15-Nov-2024');" -> ('13Nov240062','040000138279','593',(select max(to_number(i.premium_rcv_detail_code))+1 from ins_premium_det i),'593','593','02', '11000003','00','Request by Mr. Raheel Malik 15-Nov-2024'); | H2214: =F2214&G2214 -> insert into ins_premium_det (premium_rcv_code,assorted_code, rec_amount,premium_rcv_detail_code,remaining_amt, payrec, mode_code,coinsurance_code,class_cd,it_remarks) values('13Nov240062','040000138279','593',(select max(to_number(i.premium_rcv_detail_code))+1 from ins_premium_det i),'593','593','02', '11000003','00','Request by Mr. Raheel Malik 15-Nov-2024');
A2215: KHI/HO/D/MO/PD COMP/P/78292/11/2023 | B2215: 040000157961 | C2215: 593 | D2215: 593 | E2215: 13Nov240062 | F2215: ="insert into ins_premium_det (premium_rcv_code,assorted_code, rec_amount,premium_rcv_detail_code,remaining_amt, payrec, mode_code,coinsurance_code,class_cd,it_remarks) values" -> insert into ins_premium_det (premium_rcv_code,assorted_code, rec_amount,premium_rcv_detail_code,remaining_amt, payrec, mode_code,coinsurance_code,class_cd,it_remarks) values | G2215: ="('"&E2215&"','"&B2215&"','"&D2215&"',(select max(to_number(i.premium_rcv_detail_code))+1 from ins_premium_det i),'"&D2215&"','"&D2215&"','02', '11000003','00','Request by Mr. Raheel Malik 15-Nov-2024');" -> ('13Nov240062','040000157961','593',(select max(to_number(i.premium_rcv_detail_code))+1 from ins_premium_det i),'593','593','02', '11000003','00','Request by Mr. Raheel Malik 15-Nov-2024'); | H2215: =F2215&G2215 -> insert into ins_premium_det (premium_rcv_code,assorted_code, rec_amount,premium_rcv_detail_code,remaining_amt, payrec, mode_code,coinsurance_code,class_cd,it_remarks) values('13Nov240062','040000157961','593',(select max(to_number(i.premium_rcv_detail_code))+1 from ins_premium_det i),'593','593','02', '11000003','00','Request by Mr. Raheel Malik 15-Nov-2024');
A2216: MUL/MUL/F/MI/FG/P/1797/09/2021 | B2216: 040000106538 | C2216: 596 | D2216: 596 | E2216: 13Nov240062 | F2216: ="insert into ins_premium_det (premium_rcv_code,assorted_code, rec_amount,premium_rcv_detail_code,remaining_amt, payrec, mode_code,coinsurance_code,class_cd,it_remarks) values" -> insert into ins_premium_det (premium_rcv_code,assorted_code, rec_amount,premium_rcv_detail_code,remaining_amt, payrec, mode_code,coinsurance_code,class_cd,it_remarks) values | G2216: ="('"&E2216&"','"&B2216&"','"&D2216&"',(select max(to_number(i.premium_rcv_detail_code))+1 from ins_premium_det i),'"&D2216&"','"&D2216&"','02', '11000003','00','Request by Mr. Raheel Malik 15-Nov-2024');" -> ('13Nov240062','040000106538','596',(select max(to_number(i.premium_rcv_detail_code))+1 from ins_premium_det i),'596','596','02', '11000003','00','Request by Mr. Raheel Malik 15-Nov-2024'); | H2216: =F2216&G2216 -> insert into ins_premium_det (premium_rcv_code,assorted_code, rec_amount,premium_rcv_detail_code,remaining_amt, payrec, mode_code,coinsurance_code,class_cd,it_remarks) values('13Nov240062','040000106538','596',(select max(to_number(i.premium_rcv_detail_code))+1 from ins_premium_det i),'596','596','02', '11000003','00','Request by Mr. Raheel Malik 15-Nov-2024');
A2217: KHI/HO/D/MR/IMPORTS/C/18700/10/2023 | B2217: 070000140167 | C2217: 598 | D2217: 598 | E2217: 13Nov240062 | F2217: ="insert into ins_premium_det (premium_rcv_code,assorted_code, rec_amount,premium_rcv_detail_code,remaining_amt, payrec, mode_code,coinsurance_code,class_cd,it_remarks) values" -> insert into ins_premium_det (premium_rcv_code,assorted_code, rec_amount,premium_rcv_detail_code,remaining_amt, payrec, mode_code,coinsurance_code,class_cd,it_remarks) values | G2217: ="('"&E2217&"','"&B2217&"','"&D2217&"',(select max(to_number(i.premium_rcv_detail_code))+1 from ins_premium_det i),'"&D2217&"','"&D2217&"','02', '11000003','00','Request by Mr. Raheel Malik 15-Nov-2024');" -> ('13Nov240062','070000140167','598',(select max(to_number(i.premium_rcv_detail_code))+1 from ins_premium_det i),'598','598','02', '11000003','00','Request by Mr. Raheel Malik 15-Nov-2024'); | H2217: =F2217&G2217 -> insert into ins_premium_det (premium_rcv_code,assorted_code, rec_amount,premium_rcv_detail_code,remaining_amt, payrec, mode_code,coinsurance_code,class_cd,it_remarks) values('13Nov240062','070000140167','598',(select max(to_number(i.premium_rcv_detail_code))+1 from ins_premium_det i),'598','598','02', '11000003','00','Request by Mr. Raheel Malik 15-Nov-2024');
A2218: KHI/HO/D/FR/ND/P/14909/06/2022 | B2218: 040000120596 | C2218: 600 | D2218: 600 | E2218: 13Nov240062 | F2218: ="insert into ins_premium_det (premium_rcv_code,assorted_code, rec_amount,premium_rcv_detail_code,remaining_amt, payrec, mode_code,coinsurance_code,class_cd,it_remarks) values" -> insert into ins_premium_det (premium_rcv_code,assorted_code, rec_amount,premium_rcv_detail_code,remaining_amt, payrec, mode_code,coinsurance_code,class_cd,it_remarks) values | G2218: ="('"&E2218&"','"&B2218&"','"&D2218&"',(select max(to_number(i.premium_rcv_detail_code))+1 from ins_premium_det i),'"&D2218&"','"&D2218&"','02', '11000003','00','Request by Mr. Raheel Malik 15-Nov-2024');" -> ('13Nov240062','040000120596','600',(select max(to_number(i.premium_rcv_detail_code))+1 from ins_premium_det i),'600','600','02', '11000003','00','Request by Mr. Raheel Malik 15-Nov-2024'); | H2218: =F2218&G2218 -> insert into ins_premium_det (premium_rcv_code,assorted_code, rec_amount,premium_rcv_detail_code,remaining_amt, payrec, mode_code,coinsurance_code,class_cd,it_remarks) values('13Nov240062','040000120596','600',(select max(to_number(i.premium_rcv_detail_code))+1 from ins_premium_det i),'600','600','02', '11000003','00','Request by Mr. Raheel Malik 15-Nov-2024');
A2219: KHI/HO/D/MO/PC COMP/C/77027/346/10/2023 | B2219: 070000142596 | C2219: 605 | D2219: 605 | E2219: 13Nov240062 | F2219: ="insert into ins_premium_det (premium_rcv_code,assorted_code, rec_amount,premium_rcv_detail_code,remaining_amt, payrec, mode_code,coinsurance_code,class_cd,it_remarks) values" -> insert into ins_premium_det (premium_rcv_code,assorted_code, rec_amount,premium_rcv_detail_code,remaining_amt, payrec, mode_code,coinsurance_code,class_cd,it_remarks) values | G2219: ="('"&E2219&"','"&B2219&"','"&D2219&"',(select max(to_number(i.premium_rcv_detail_code))+1 from ins_premium_det i),'"&D2219&"','"&D2219&"','02', '11000003','00','Request by Mr. Raheel Malik 15-Nov-2024');" -> ('13Nov240062','070000142596','605',(select max(to_number(i.premium_rcv_detail_code))+1 from ins_premium_det i),'605','605','02', '11000003','00','Request by Mr. Raheel Malik 15-Nov-2024'); | H2219: =F2219&G2219 -> insert into ins_premium_det (premium_rcv_code,assorted_code, rec_amount,premium_rcv_detail_code,remaining_amt, payrec, mode_code,coinsurance_code,class_cd,it_remarks) values('13Nov240062','070000142596','605',(select max(to_number(i.premium_rcv_detail_code))+1 from ins_premium_det i),'605','605','02', '11000003','00','Request by Mr. Raheel Malik 15-Nov-2024');
A2220: KHI/HO/D/MR/IMPORTS/C/18891/11/2023 | B2220: 070000146417 | C2220: 605 | D2220: 605 | E2220: 13Nov240062 | F2220: ="insert into ins_premium_det (premium_rcv_code,assorted_code, rec_amount,premium_rcv_detail_code,remaining_amt, payrec, mode_code,coinsurance_code,class_cd,it_remarks) values" -> insert into ins_premium_det (premium_rcv_code,assorted_code, rec_amount,premium_rcv_detail_code,remaining_amt, payrec, mode_code,coinsurance_code,class_cd,it_remarks) values | G2220: ="('"&E2220&"','"&B2220&"','"&D2220&"',(select max(to_number(i.premium_rcv_detail_code))+1 from ins_premium_det i),'"&D2220&"','"&D2220&"','02', '11000003','00','Request by Mr. Raheel Malik 15-Nov-2024');" -> ('13Nov240062','070000146417','605',(select max(to_number(i.premium_rcv_detail_code))+1 from ins_premium_det i),'605','605','02', '11000003','00','Request by Mr. Raheel Malik 15-Nov-2024'); | H2220: =F2220&G2220 -> insert into ins_premium_det (premium_rcv_code,assorted_code, rec_amount,premium_rcv_detail_code,remaining_amt, payrec, mode_code,coinsurance_code,class_cd,it_remarks) values('13Nov240062','070000146417','605',(select max(to_number(i.premium_rcv_detail_code))+1 from ins_premium_det i),'605','605','02', '11000003','00','Request by Mr. Raheel Malik 15-Nov-2024');
A2221: KHI/HO/D/MO/PD COMP/P/75790/09/2023 | B2221: 040000153863 | C2221: 606 | D2221: 606 | E2221: 13Nov240062 | F2221: ="insert into ins_premium_det (premium_rcv_code,assorted_code, rec_amount,premium_rcv_detail_code,remaining_amt, payrec, mode_code,coinsurance_code,class_cd,it_remarks) values" -> insert into ins_premium_det (premium_rcv_code,assorted_code, rec_amount,premium_rcv_detail_code,remaining_amt, payrec, mode_code,coinsurance_code,class_cd,it_remarks) values | G2221: ="('"&E2221&"','"&B2221&"','"&D2221&"',(select max(to_number(i.premium_rcv_detail_code))+1 from ins_premium_det i),'"&D2221&"','"&D2221&"','02', '11000003','00','Request by Mr. Raheel Malik 15-Nov-2024');" -> ('13Nov240062','040000153863','606',(select max(to_number(i.premium_rcv_detail_code))+1 from ins_premium_det i),'606','606','02', '11000003','00','Request by Mr. Raheel Malik 15-Nov-2024'); | H2221: =F2221&G2221 -> insert into ins_premium_det (premium_rcv_code,assorted_code, rec_amount,premium_rcv_detail_code,remaining_amt, payrec, mode_code,coinsurance_code,class_cd,it_remarks) values('13Nov240062','040000153863','606',(select max(to_number(i.premium_rcv_detail_code))+1 from ins_premium_det i),'606','606','02', '11000003','00','Request by Mr. Raheel Malik 15-Nov-2024');
A2222: MUL/MUL/F/EG/MBD/P/714/01/2022 | B2222: 040000111316 | C2222: 613 | D2222: 613 | E2222: 13Nov240062 | F2222: ="insert into ins_premium_det (premium_rcv_code,assorted_code, rec_amount,premium_rcv_detail_code,remaining_amt, payrec, mode_code,coinsurance_code,class_cd,it_remarks) values" -> insert into ins_premium_det (premium_rcv_code,assorted_code, rec_amount,premium_rcv_detail_code,remaining_amt, payrec, mode_code,coinsurance_code,class_cd,it_remarks) values | G2222: ="('"&E2222&"','"&B2222&"','"&D2222&"',(select max(to_number(i.premium_rcv_detail_code))+1 from ins_premium_det i),'"&D2222&"','"&D2222&"','02', '11000003','00','Request by Mr. Raheel Malik 15-Nov-2024');" -> ('13Nov240062','040000111316','613',(select max(to_number(i.premium_rcv_detail_code))+1 from ins_premium_det i),'613','613','02', '11000003','00','Request by Mr. Raheel Malik 15-Nov-2024'); | H2222: =F2222&G2222 -> insert into ins_premium_det (premium_rcv_code,assorted_code, rec_amount,premium_rcv_detail_code,remaining_amt, payrec, mode_code,coinsurance_code,class_cd,it_remarks) values('13Nov240062','040000111316','613',(select max(to_number(i.premium_rcv_detail_code))+1 from ins_premium_det i),'613','613','02', '11000003','00','Request by Mr. Raheel Malik 15-Nov-2024');
A2223: KHI/HO/D/MO/PD COMP/P/58016/01/2022 | B2223: 040000111178 | C2223: 614 | D2223: 614 | E2223: 13Nov240062 | F2223: ="insert into ins_premium_det (premium_rcv_code,assorted_code, rec_amount,premium_rcv_detail_code,remaining_amt, payrec, mode_code,coinsurance_code,class_cd,it_remarks) values" -> insert into ins_premium_det (premium_rcv_code,assorted_code, rec_amount,premium_rcv_detail_code,remaining_amt, payrec, mode_code,coinsurance_code,class_cd,it_remarks) values | G2223: ="('"&E2223&"','"&B2223&"','"&D2223&"',(select max(to_number(i.premium_rcv_detail_code))+1 from ins_premium_det i),'"&D2223&"','"&D2223&"','02', '11000003','00','Request by Mr. Raheel Malik 15-Nov-2024');" -> ('13Nov240062','040000111178','614',(select max(to_number(i.premium_rcv_detail_code))+1 from ins_premium_det i),'614','614','02', '11000003','00','Request by Mr. Raheel Malik 15-Nov-2024'); | H2223: =F2223&G2223 -> insert into ins_premium_det (premium_rcv_code,assorted_code, rec_amount,premium_rcv_detail_code,remaining_amt, payrec, mode_code,coinsurance_code,class_cd,it_remarks) values('13Nov240062','040000111178','614',(select max(to_number(i.premium_rcv_detail_code))+1 from ins_premium_det i),'614','614','02', '11000003','00','Request by Mr. Raheel Malik 15-Nov-2024');
... A2637: KHI/HO/D/MR/IMPORTS/P/41520/12/2023 | B2637: 040000161493 | C2637: 1000 | D2637: 1000 | E2637: 13Nov240062 | F2637: ="insert into ins_premium_det (premium_rcv_code,assorted_code, rec_amount,premium_rcv_detail_code,remaining_amt, payrec, mode_code,coinsurance_code,class_cd,it_remarks) values" -> insert into ins_premium_det (premium_rcv_code,assorted_code, rec_amount,premium_rcv_detail_code,remaining_amt, payrec, mode_code,coinsurance_code,class_cd,it_remarks) values | G2637: ="('"&E2637&"','"&B2637&"','"&D2637&"',(select max(to_number(i.premium_rcv_detail_code))+1 from ins_premium_det i),'"&D2637&"','"&D2637&"','02', '11000003','00','Request by Mr. Raheel Malik 15-Nov-2024');" -> ('13Nov240062','040000161493','1000',(select max(to_number(i.premium_rcv_detail_code))+1 from ins_premium_det i),'1000','1000','02', '11000003','00','Request by Mr. Raheel Malik 15-Nov-2024'); | H2637: =F2637&G2637 -> insert into ins_premium_det (premium_rcv_code,assorted_code, rec_amount,premium_rcv_detail_code,remaining_amt, payrec, mode_code,coinsurance_code,class_cd,it_remarks) values('13Nov240062','040000161493','1000',(select max(to_number(i.premium_rcv_detail_code))+1 from ins_premium_det i),'1000','1000','02', '11000003','00','Request by Mr. Raheel Malik 15-Nov-2024');
C2639: =SUM(C2:C2637) -> 410970.57 | D2639: =SUM(D2:D2637) -> 410970.57

Sheet Remove
A1: 040000130892 | B1: '040000130892',
A2: 040000107624 | B2: '040000107624',
A3: 040000138279 | B3: '040000138279',
A4: 040000157961 | B4: '040000157961',
A5: 040000106538 | B5: '040000106538',
A6: 070000140167 | B6: '070000140167',
A7: 040000120596 | B7: '040000120596',
A8: 070000142596 | B8: '070000142596',
A9: 070000146417 | B9: '070000146417',
A10: 040000153863 | B10: '040000153863',
A11: 040000111316 | B11: '040000111316',
A12: 040000111178 | B12: '040000111178',
... A426: 040000161493 | B426: '040000161493',
D427: total | E427: remove
D428: 2636 | E428: 426 | F428: =D428-E428 -> 2210

Sheet Sheet3
C1: PC | E1: E
A2: MUL/MUL/F/FR/D/P/12471/09/2021 | B2: -09-2021 | C2: P | D2: 12471 | E2: ="ia.assorted_string like '%"&D2&B2&"%' or" -> ia.assorted_string like '%12471-09-2021%' or
A3: KHI/HO/D/MO/PC COMP/P/73118/07/2023 | B3: -07-2023 | C3: P | D3: 73118 | E3: ="ia.assorted_string like '%"&D3&B3&"%' or" -> ia.assorted_string like '%73118-07-2023%' or
A4: MUL/MUL/F/FR/D/P/13574/12/2021 | B4: -12-2021 | C4: P | D4: 13574 | E4: ="ia.assorted_string like '%"&D4&B4&"%' or" -> ia.assorted_string like '%13574-12-2021%' or
A5: MUL/MUL/F/FR/ND/P/13059/11/2021 | B5: -11-2021 | C5: P | D5: 13059 | E5: ="ia.assorted_string like '%"&D5&B5&"%' or" -> ia.assorted_string like '%13059-11-2021%' or
A6: MUL/MUL/F/FR/ND/P/13084/11/2021 | B6: -11-2021 | C6: P | D6: 13084 | E6: ="ia.assorted_string like '%"&D6&B6&"%' or" -> ia.assorted_string like '%13084-11-2021%' or
A7: MUL/MUL/F/FR/ND/P/13122/11/2021 | B7: -11-2021 | C7: P | D7: 13122 | E7: ="ia.assorted_string like '%"&D7&B7&"%' or" -> ia.assorted_string like '%13122-11-2021%' or
A8: KHI/HO/D/MO/PC COMP/P/69597/04/2023 | B8: -04-2023 | C8: P | D8: 69597 | E8: ="ia.assorted_string like '%"&D8&B8&"%' or" -> ia.assorted_string like '%69597-04-2023%' or
A9: MUL/MUL/F/FR/ND/P/12988/11/2021 | B9: -11-2021 | C9: P | D9: 12988 | E9: ="ia.assorted_string like '%"&D9&B9&"%' or" -> ia.assorted_string like '%12988-11-2021%' or
A10: MUL/MUL/F/FR/ND/P/13081/11/2021 | B10: -11-2021 | C10: P | D10: 13081 | E10: ="ia.assorted_string like '%"&D10&B10&"%' or" -> ia.assorted_string like '%13081-11-2021%' or
A11: MUL/MUL/F/FR/ND/P/13116/11/2021 | B11: -11-2021 | C11: P | D11: 13116 | E11: ="ia.assorted_string like '%"&D11&B11&"%' or" -> ia.assorted_string like '%13116-11-2021%' or
A12: MUL/MUL/F/FR/ND/P/13567/12/2021 | B12: -12-2021 | C12: P | D12: 13567 | E12: ="ia.assorted_string like '%"&D12&B12&"%' or" -> ia.assorted_string like '%13567-12-2021%' or
A13: ISD/ISD/F/MR/IMPORTS/P/38010/11/2022 | B13: -11-2022 | C13: P | D13: 38010 | E13: ="ia.assorted_string like '%"&D13&B13&"%' or" -> ia.assorted_string like '%38010-11-2022%' or
A14: ISD/ISD/F/MR/IMPORTS/P/38026/11/2022 | B14: -11-2022 | C14: P | D14: 38026 | E14: ="ia.assorted_string like '%"&D14&B14&"%' or" -> ia.assorted_string like '%38026-11-2022%' or
A15: KHI/HO/D/MO/PC COMP/C/63286/34/09/2022 | B15: -09-2022 | C15: C | D15: 63286 | E15: 00034 | F15: ="ia.assorted_string like '%"&D15&"-"&E15&B15&"%' or" -> ia.assorted_string like '%63286-00034-09-2022%' or
A16: KHI/HO/D/MO/PC COMP/C/64350/1/10/2022 | B16: -10-2022 | C16: C | D16: 64350 | E16: 00001 | F16: ="ia.assorted_string like '%"&D16&"-"&E16&B16&"%' or" -> ia.assorted_string like '%64350-00001-10-2022%' or
A17: KHI/HO/D/MO/PC COMP/C/64383/1/10/2022 | B17: -10-2022 | C17: C | D17: 64383 | E17: 00001 | F17: ="ia.assorted_string like '%"&D17&"-"&E17&B17&"%' or" -> ia.assorted_string like '%64383-00001-10-2022%' or
A18: KHI/HO/D/MO/PC COMP/C/64389/1/10/2022 | B18: -10-2022 | C18: C | D18: 64389 | E18: 00001 | F18: ="ia.assorted_string like '%"&D18&"-"&E18&B18&"%' or" -> ia.assorted_string like '%64389-00001-10-2022%' or
A19: KHI/HO/D/MO/PC COMP/C/64794/68/11/2022 | B19: -11-2022 | C19: C | D19: 64794 | E19: 00068 | F19: ="ia.assorted_string like '%"&D19&"-"&E19&B19&"%' or" -> ia.assorted_string like '%64794-00068-11-2022%' or
A20: KHI/HO/D/MO/PC COMP/C/65057/1/11/2022 | B20: -11-2022 | C20: C | D20: 65057 | E20: 00001 | F20: ="ia.assorted_string like '%"&D20&"-"&E20&B20&"%' or" -> ia.assorted_string like '%65057-00001-11-2022%' or
A21: KHI/HO/D/MO/PC COMP/C/65057/139/11/2022 | B21: -11-2022 | C21: C | D21: 65057 | E21: 00139 | F21: ="ia.assorted_string like '%"&D21&"-"&E21&B21&"%' or" -> ia.assorted_string like '%65057-00139-11-2022%' or
A22: KHI/HO/D/MO/PC COMP/C/65057/172/11/2022 | B22: -11-2022 | C22: C | D22: 65057 | E22: 00172 | F22: ="ia.assorted_string like '%"&D22&"-"&E22&B22&"%' or" -> ia.assorted_string like '%65057-00172-11-2022%' or
A23: KHI/HO/D/MO/PC COMP/C/65057/190/11/2022 | B23: -11-2022 | C23: C | D23: 65057 | E23: 00190 | F23: ="ia.assorted_string like '%"&D23&"-"&E23&B23&"%' or" -> ia.assorted_string like '%65057-00190-11-2022%' or
A24: KHI/HO/D/MO/PC COMP/C/65057/21/11/2022 | B24: -11-2022 | C24: C | D24: 65057 | E24: 00021 | F24: ="ia.assorted_string like '%"&D24&"-"&E24&B24&"%' or" -> ia.assorted_string like '%65057-00021-11-2022%' or
A25: KHI/HO/D/MO/PC COMP/C/65057/250/11/2022 | B25: -11-2022 | C25: C | D25: 65057 | E25: 00250 | F25: ="ia.assorted_string like '%"&D25&"-"&E25&B25&"%' or" -> ia.assorted_string like '%65057-00250-11-2022%' or
A26: KHI/HO/D/MO/PC COMP/C/65057/325/11/2022 | B26: -11-2022 | C26: C | D26: 65057 | E26: 00325 | F26: ="ia.assorted_string like '%"&D26&"-"&E26&B26&"%' or" -> ia.assorted_string like '%65057-00325-11-2022%' or
... A69: KHI/HO/D/MO/PC COMP/C/68699/99/03/2023 | B69: -03-2023 | C69: C | D69: 68699 | E69: 00099 | F69: ="ia.assorted_string like '%"&D69&"-"&E69&B69&"%' or" -> ia.assorted_string like '%68699-00099-03-2023%' or
A70: KHI/HO/D/MO/PC COMP/P/64394/10/2022 | B70: -10-2022 | C70: P | D70: 64394 | E70: ="ia.assorted_string like '%"&D70&B70&"%' or" -> ia.assorted_string like '%64394-10-2022%' or
A71: KHI/HO/D/MO/PC COMP/P/66872/01/2023 | B71: -01-2023 | C71: P | D71: 66872 | E71: ="ia.assorted_string like '%"&D71&B71&"%' or" -> ia.assorted_string like '%66872-01-2023%' or
A72: KHI/HO/D/MO/PC COMP/P/75915/09/2023 | B72: -09-2023 | C72: P | D72: 75915 | E72: ="ia.assorted_string like '%"&D72&B72&"%' or" -> ia.assorted_string like '%75915-09-2023%' or
A73: KHI/HO/D/MO/PC COMP/P/77977/11/2023 | B73: -11-2023 | C73: P | D73: 77977 | E73: ="ia.assorted_string like '%"&D73&B73&"%' or" -> ia.assorted_string like '%77977-11-2023%' or
A74: KHI/HO/F/FR/ND/P/13179/12/2021 | B74: -12-2021 | C74: P | D74: 13179 | E74: ="ia.assorted_string like '%"&D74&B74&"%' or" -> ia.assorted_string like '%13179-12-2021%' or
A75: LHR/LHR/D/MO/PC COMP/P/60625/05/2022 | B75: -05-2022 | C75: P | D75: 60625 | E75: ="ia.assorted_string like '%"&D75&B75&"%' or" -> ia.assorted_string like '%60625-05-2022%' or
A76: MUL/MUL/F/FR/D/P/13120/11/2021 | B76: -11-2021 | C76: P | D76: 13120 | E76: ="ia.assorted_string like '%"&D76&B76&"%' or" -> ia.assorted_string like '%13120-11-2021%' or
A77: MUL/MUL/F/FR/ND/P/12524/09/2021 | B77: -09-2021 | C77: P | D77: 12524 | E77: ="ia.assorted_string like '%"&D77&B77&"%' or" -> ia.assorted_string like '%12524-09-2021%' or
A78: MUL/MUL/F/FR/ND/P/12611/10/2021 | B78: -10-2021 | C78: P | D78: 12611 | E78: ="ia.assorted_string like '%"&D78&B78&"%' or" -> ia.assorted_string like '%12611-10-2021%' or
A79: MUL/MUL/F/FR/ND/P/12983/11/2021 | B79: -11-2021 | C79: P | D79: 12983 | E79: ="ia.assorted_string like '%"&D79&B79&"%' or" -> ia.assorted_string like '%12983-11-2021%' or
A80: MUL/MUL/F/FR/ND/P/13025/11/2021 | B80: -11-2021 | C80: P | D80: 13025 | E80: ="ia.assorted_string like '%"&D80&B80&"%' or" -> ia.assorted_string like '%13025-11-2021%' or
A81: MUL/MUL/F/FR/ND/P/13060/11/2021 | B81: -11-2021 | C81: P | D81: 13060 | E81: ="ia.assorted_string like '%"&D81&B81&"%' or" -> ia.assorted_string like '%13060-11-2021%' or
... A255: KHI/HO/D/MI/TRI/P/5801/10/2022 | B255: -10-2022 | C255: P | D255: 5801 | E255: ="ia.assorted_string like '%"&D255&B255&"%' or" -> ia.assorted_string like '%5801-10-2022%' or
A256: KHI/HO/D/MI/TRI/P/5914/10/2022 | B256: -10-2022 | C256: P | D256: 5914 | E256: ="ia.assorted_string like '%"&D256&B256&"%' or" -> ia.assorted_string like '%5914-10-2022%' or | J256: OK
A257: KHI/HO/D/MI/TRI/P/6003/10/2022 | B257: -10-2022 | C257: P | D257: 6003 | E257: ="ia.assorted_string like '%"&D257&B257&"%' or" -> ia.assorted_string like '%6003-10-2022%' or
A258: KHI/HO/D/MI/TRI/P/6076/10/2022 | B258: -10-2022 | C258: P | D258: 6076 | E258: ="ia.assorted_string like '%"&D258&B258&"%' or" -> ia.assorted_string like '%6076-10-2022%' or
A259: KHI/HO/D/MI/TRI/P/6083/10/2022 | B259: -10-2022 | C259: P | D259: 6083 | E259: ="ia.assorted_string like '%"&D259&B259&"%' or" -> ia.assorted_string like '%6083-10-2022%' or
A260: KHI/HO/D/MI/TRI/P/6099/10/2022 | B260: -10-2022 | C260: P | D260: 6099 | E260: ="ia.assorted_string like '%"&D260&B260&"%' or" -> ia.assorted_string like '%6099-10-2022%' or
A261: KHI/HO/D/MI/TRI/P/6111/10/2022 | B261: -10-2022 | C261: P | D261: 6111 | E261: ="ia.assorted_string like '%"&D261&B261&"%' or" -> ia.assorted_string like '%6111-10-2022%' or
A262: KHI/HO/D/MI/TRI/P/6167/10/2022 | B262: -10-2022 | C262: P | D262: 6167 | E262: ="ia.assorted_string like '%"&D262&B262&"%' or" -> ia.assorted_string like '%6167-10-2022%' or
A263: KHI/HO/D/MI/TRI/P/6168/10/2022 | B263: -10-2022 | C263: P | D263: 6168 | E263: ="ia.assorted_string like '%"&D263&B263&"%' or" -> ia.assorted_string like '%6168-10-2022%' or
A264: KHI/HO/D/MI/TRI/P/6338/11/2022 | B264: -11-2022 | C264: P | D264: 6338 | E264: ="ia.assorted_string like '%"&D264&B264&"%' or" -> ia.assorted_string like '%6338-11-2022%' or
A265: KHI/HO/D/MI/TRI/P/6438/11/2022 | B265: -11-2022 | C265: P | D265: 6438 | E265: ="ia.assorted_string like '%"&D265&B265&"%' or" -> ia.assorted_string like '%6438-11-2022%' or
A266: KHI/HO/D/MI/TRI/P/6439/11/2022 | B266: -11-2022 | C266: P | D266: 6439 | E266: ="ia.assorted_string like '%"&D266&B266&"%' or" -> ia.assorted_string like '%6439-11-2022%' or
A267: KHI/HO/D/MI/TRI/P/6440/11/2022 | B267: -11-2022 | C267: P | D267: 6440 | E267: ="ia.assorted_string like '%"&D267&B267&"%' or" -> ia.assorted_string like '%6440-11-2022%' or
A268: KHI/HO/D/MI/TRI/P/6500/11/2022 | B268: -11-2022 | C268: P | D268: 6500 | E268: ="ia.assorted_string like '%"&D268&B268&"%' or" -> ia.assorted_string like '%6500-11-2022%' or
... A346: KHI/HO/D/MI/TRI/P/9785/05/2023 | B346: -05-2023 | C346: P | D346: 9785 | E346: ="ia.assorted_string like '%"&D346&B346&"%' or" -> ia.assorted_string like '%9785-05-2023%' or
A347: KHI/HO/D/MO/PC COMP/C/69943/130/04/2023 | B347: -04-2023 | C347: C | D347: 69943 | E347: 00130 | F347: ="ia.assorted_string like '%"&D347&"-"&E347&B347&"%' or" -> ia.assorted_string like '%69943-00130-04-2023%' or
A348: KHI/HO/D/MO/PC COMP/C/69943/161/04/2023 | B348: -04-2023 | C348: C | D348: 69943 | E348: 00161 | F348: ="ia.assorted_string like '%"&D348&"-"&E348&B348&"%' or" -> ia.assorted_string like '%69943-00161-04-2023%' or
A349: KHI/HO/D/MO/PC COMP/C/69943/175/04/2023 | B349: -04-2023 | C349: C | D349: 69943 | E349: 00175 | F349: ="ia.assorted_string like '%"&D349&"-"&E349&B349&"%' or" -> ia.assorted_string like '%69943-00175-04-2023%' or
A350: KHI/HO/D/MO/PC COMP/C/69943/256/04/2023 | B350: -04-2023 | C350: C | D350: 69943 | E350: 00256 | F350: ="ia.assorted_string like '%"&D350&"-"&E350&B350&"%' or" -> ia.assorted_string like '%69943-00256-04-2023%' or
A351: KHI/HO/D/MO/PC COMP/C/69943/269/04/2023 | B351: -04-2023 | C351: C | D351: 69943 | E351: 00269 | F351: ="ia.assorted_string like '%"&D351&"-"&E351&B351&"%' or" -> ia.assorted_string like '%69943-00269-04-2023%' or
A352: KHI/HO/D/MO/PC COMP/C/69943/280/04/2023 | B352: -04-2023 | C352: C | D352: 69943 | E352: 00280 | F352: ="ia.assorted_string like '%"&D352&"-"&E352&B352&"%' or" -> ia.assorted_string like '%69943-00280-04-2023%' or
A353: KHI/HO/D/MO/PC COMP/C/69943/40/04/2023 | B353: -04-2023 | C353: C | D353: 69943 | E353: 00040 | F353: ="ia.assorted_string like '%"&D353&"-"&E353&B353&"%' or" -> ia.assorted_string like '%69943-00040-04-2023%' or
A354: KHI/HO/D/MO/PC COMP/C/69943/48/04/2023 | B354: -04-2023 | C354: C | D354: 69943 | E354: 00048 | F354: ="ia.assorted_string like '%"&D354&"-"&E354&B354&"%' or" -> ia.assorted_string like '%69943-00048-04-2023%' or
A355: KHI/HO/D/MO/PC COMP/C/69943/51/04/2023 | B355: -04-2023 | C355: C | D355: 69943 | E355: 00051 | F355: ="ia.assorted_string like '%"&D355&"-"&E355&B355&"%' or" -> ia.assorted_string like '%69943-00051-04-2023%' or
A356: KHI/HO/D/MO/PC COMP/C/69943/55/04/2023 | B356: -04-2023 | C356: C | D356: 69943 | E356: 00055 | F356: ="ia.assorted_string like '%"&D356&"-"&E356&B356&"%' or" -> ia.assorted_string like '%69943-00055-04-2023%' or
A357: KHI/HO/D/MO/PC COMP/C/69943/56/04/2023 | B357: -04-2023 | C357: C | D357: 69943 | E357: 00056 | F357: ="ia.assorted_string like '%"&D357&"-"&E357&B357&"%' or" -> ia.assorted_string like '%69943-00056-04-2023%' or
A358: KHI/HO/D/MO/PC COMP/C/69943/59/04/2023 | B358: -04-2023 | C358: C | D358: 69943 | E358: 00059 | F358: ="ia.assorted_string like '%"&D358&"-"&E358&B358&"%' or" -> ia.assorted_string like '%69943-00059-04-2023%' or
A359: KHI/HO/D/MO/PC COMP/C/69943/81/04/2023 | B359: -04-2023 | C359: C | D359: 69943 | E359: 00081 | F359: ="ia.assorted_string like '%"&D359&"-"&E359&B359&"%' or" -> ia.assorted_string like '%69943-00081-04-2023%' or
A360: LHR/LHR/D/MO/PC COMP/P/65772/12/2022 | B360: -12-2022 | C360: P | D360: 65772 | E360: ="ia.assorted_string like '%"&D360&B360&"%' or" -> ia.assorted_string like '%65772-12-2022%' or
A361: KHI/HO/D/MI/TRI/P/5605/10/2022 | B361: -10-2022 | C361: P | D361: 5605 | E361: ="ia.assorted_string like '%"&D361&B361&"%' or" -> ia.assorted_string like '%5605-10-2022%' or
A362: KHI/HO/D/MI/TRI/P/5609/10/2022 | B362: -10-2022 | C362: P | D362: 5609 | E362: ="ia.assorted_string like '%"&D362&B362&"%' or" -> ia.assorted_string like '%5609-10-2022%' or
A363: KHI/HO/D/MI/TRI/P/5942/10/2022 | B363: -10-2022 | C363: P | D363: 5942 | E363: ="ia.assorted_string like '%"&D363&B363&"%' or" -> ia.assorted_string like '%5942-10-2022%' or
A364: KHI/HO/D/MI/TRI/P/7540/12/2022 | B364: -12-2022 | C364: P | D364: 7540 | E364: ="ia.assorted_string like '%"&D364&B364&"%' or" -> ia.assorted_string like '%7540-12-2022%' or
A365: KHI/HO/D/MI/TRI/P/9694/03/2023 | B365: -03-2023 | C365: P | D365: 9694 | E365: ="ia.assorted_string like '%"&D365&B365&"%' or" -> ia.assorted_string like '%9694-03-2023%' or
A366: KHI/HO/D/MI/TRI/P/9786/05/2023 | B366: -05-2023 | C366: P | D366: 9786 | E366: ="ia.assorted_string like '%"&D366&B366&"%' or" -> ia.assorted_string like '%9786-05-2023%' or
A367: KHI/HO/D/MI/TRI/P/6545/11/2022 | B367: -11-2022 | C367: P | D367: 6545 | E367: ="ia.assorted_string like '%"&D367&B367&"%' or" -> ia.assorted_string like '%6545-11-2022%' or
A368: KHI/HO/D/MI/TRI/P/6909/11/2022 | B368: -11-2022 | C368: P | D368: 6909 | E368: ="ia.assorted_string like '%"&D368&B368&"%' or" -> ia.assorted_string like '%6909-11-2022%' or
A369: KHI/HO/D/MI/TRI/P/8957/01/2023 | B369: -01-2023 | C369: P | D369: 8957 | E369: ="ia.assorted_string like '%"&D369&B369&"%' or" -> ia.assorted_string like '%8957-01-2023%' or
A370: KHI/HO/D/MI/TRI/P/8985/01/2023 | B370: -01-2023 | C370: P | D370: 8985 | E370: ="ia.assorted_string like '%"&D370&B370&"%' or" -> ia.assorted_string like '%8985-01-2023%' or
A371: KHI/HO/D/MI/TRI/P/9368/02/2023 | B371: -02-2023 | C371: P | D371: 9368 | E371: ="ia.assorted_string like '%"&D371&B371&"%' or" -> ia.assorted_string like '%9368-02-2023%' or
A372: KHI/HO/D/MI/TRI/P/9592/02/2023 | B372: -02-2023 | C372: P | D372: 9592 | E372: ="ia.assorted_string like '%"&D372&B372&"%' or" -> ia.assorted_string like '%9592-02-2023%' or
A373: KHI/HO/D/MO/PC COMP/C/70036/31/04/2023 | B373: -04-2023 | C373: C | D373: 70036 | E373: 00031 | F373: ="ia.assorted_string like '%"&D373&"-"&E373&B373&"%' or" -> ia.assorted_string like '%70036-00031-04-2023%' or
A374: KHI/HO/D/MI/TRI/P/8448/01/2023 | B374: -01-2023 | C374: P | D374: 8448 | E374: ="ia.assorted_string like '%"&D374&B374&"%' or" -> ia.assorted_string like '%8448-01-2023%' or
A375: KHI/HO/D/MI/TRI/P/9807/05/2023 | B375: -05-2023 | C375: P | D375: 9807 | E375: ="ia.assorted_string like '%"&D375&B375&"%' or" -> ia.assorted_string like '%9807-05-2023%' or
A376: KHI/HO/D/MI/TRI/P/9814/05/2023 | B376: -05-2023 | C376: P | D376: 9814 | E376: ="ia.assorted_string like '%"&D376&B376&"%' or" -> ia.assorted_string like '%9814-05-2023%' or
A377: KHI/HO/D/MI/TRI/P/7438/12/2022 | B377: -12-2022 | C377: P | D377: 7438 | E377: ="ia.assorted_string like '%"&D377&B377&"%' or" -> ia.assorted_string like '%7438-12-2022%' or
A378: KHI/HO/D/MI/TRI/P/9626/02/2023 | B378: -02-2023 | C378: P | D378: 9626 | E378: ="ia.assorted_string like '%"&D378&B378&"%' or" -> ia.assorted_string like '%9626-02-2023%' or
A379: KHI/HO/D/MI/TRI/P/7788/12/2022 | B379: -12-2022 | C379: P | D379: 7788 | E379: ="ia.assorted_string like '%"&D379&B379&"%' or" -> ia.assorted_string like '%7788-12-2022%' or
A380: KHI/HO/D/MI/TRI/P/7827/12/2022 | B380: -12-2022 | C380: P | D380: 7827 | E380: ="ia.assorted_string like '%"&D380&B380&"%' or" -> ia.assorted_string like '%7827-12-2022%' or
A381: KHI/HO/D/MI/TRI/P/8578/01/2023 | B381: -01-2023 | C381: P | D381: 8578 | E381: ="ia.assorted_string like '%"&D381&B381&"%' or" -> ia.assorted_string like '%8578-01-2023%' or
A382: KHI/HO/D/MI/TRI/P/8580/01/2023 | B382: -01-2023 | C382: P | D382: 8580 | E382: ="ia.assorted_string like '%"&D382&B382&"%' or" -> ia.assorted_string like '%8580-01-2023%' or
A383: KHI/HO/D/MO/PC COMP/C/69943/102/04/2023 | B383: -04-2023 | C383: C | D383: 69943 | E383: 00102 | F383: ="ia.assorted_string like '%"&D383&"-"&E383&B383&"%' or" -> ia.assorted_string like '%69943-00102-04-2023%' or
A384: KHI/HO/D/MI/TRI/P/4226/08/2022 | B384: -08-2022 | C384: P | D384: 4226 | E384: ="ia.assorted_string like '%"&D384&B384&"%' or" -> ia.assorted_string like '%4226-08-2022%' or
A385: KHI/HO/D/MI/TRI/P/5202/10/2022 | B385: -10-2022 | C385: P | D385: 5202 | E385: ="ia.assorted_string like '%"&D385&B385&"%' or" -> ia.assorted_string like '%5202-10-2022%' or
A386: KHI/HO/D/MI/TRI/P/5203/10/2022 | B386: -10-2022 | C386: P | D386: 5203 | E386: ="ia.assorted_string like '%"&D386&B386&"%' or" -> ia.assorted_string like '%5203-10-2022%' or
A387: KHI/HO/D/MI/TRI/P/6329/11/2022 | B387: -11-2022 | C387: P | D387: 6329 | E387: ="ia.assorted_string like '%"&D387&B387&"%' or" -> ia.assorted_string like '%6329-11-2022%' or
A388: KHI/HO/D/MI/TRI/P/6387/11/2022 | B388: -11-2022 | C388: P | D388: 6387 | E388: ="ia.assorted_string like '%"&D388&B388&"%' or" -> ia.assorted_string like '%6387-11-2022%' or
A389: KHI/HO/D/MI/TRI/P/6678/11/2022 | B389: -11-2022 | C389: P | D389: 6678 | E389: ="ia.assorted_string like '%"&D389&B389&"%' or" -> ia.assorted_string like '%6678-11-2022%' or
A390: KHI/HO/D/MI/TRI/P/7831/12/2022 | B390: -12-2022 | C390: P | D390: 7831 | E390: ="ia.assorted_string like '%"&D390&B390&"%' or" -> ia.assorted_string like '%7831-12-2022%' or
A391: KHI/HO/D/MI/TRI/P/7847/12/2022 | B391: -12-2022 | C391: P | D391: 7847 | E391: ="ia.assorted_string like '%"&D391&B391&"%' or" -> ia.assorted_string like '%7847-12-2022%' or
A392: KHI/HO/D/MI/TRI/P/7850/12/2022 | B392: -12-2022 | C392: P | D392: 7850 | E392: ="ia.assorted_string like '%"&D392&B392&"%' or" -> ia.assorted_string like '%7850-12-2022%' or
...

Sheet policy
B1: FUNC_ASSORTED_STRING(IA.ASSORTED_CODE) | C1: ASSORTED_CODE
A2: 1 | B2: KHI/HO/D/MO/PC COMP/C/58470/167/02/2022 | C2: 070000094004
A3: =A2+1 -> 2 | B3: KHI/HO/D/MO/PC COMP/C/5192/02/2022 | C3: 020000024176
A4: =A3+1 -> 3 | B4: MUL/MUL/F/FR/ND/P/13084/11/2021 | C4: 040000108917
A5: =A4+1 -> 4 | B5: KHI/HO/D/MO/PC COMP/C/59294/284/03/2022 | C5: 070000097302
A6: =A5+1 -> 5 | B6: KHI/HO/D/MI/TRI/P/116/02/2022 | C6: 040000112435
A7: =A6+1 -> 6 | B7: KHI/HO/D/MI/TRI/P/130/02/2022 | C7: 040000112531
A8: =A7+1 -> 7 | B8: KHI/HO/D/MO/PC COMP/C/58470/221/02/2022 | C8: 070000094835
A9: =A8+1 -> 8 | B9: KHI/HO/D/MR/EXPORTS/P/36116/02/2022 | C9: 040000112349
A10: =A9+1 -> 9 | B10: MUL/MUL/F/FR/ND/P/12983/11/2021 | C10: 040000108321
A11: =A10+1 -> 10 | B11: MUL/MUL/F/FR/ND/P/12611/10/2021 | C11: 040000107626
A12: =A11+1 -> 11 | B12: KHI/HO/D/MR/IMPORTS/P/36167/02/2022 | C12: 040000112768
A13: =A12+1 -> 12 | B13: LHR/LHR/D/MO/PC COMP/P/59222/02/2022 | C13: 040000113309
A14: =A13+1 -> 13 | B14: KHI/HO/D/MO/PC COMP/C/58935/113/02/2022 | C14: 070000093846
... A5692: =A5691+1 -> 5691 | B5692: KHI/HO/D/MO/PC COMP/C/71203/73/05/2023 | C5692: 070000130331
